Workbook

Sheet Summary - SFR - Global
A2: Sony France
A4: FY | B4: FY24 | Q4: FY | R4: FY23
A5: PO Status | B5: (Tous) | Q5: PO Status | R5: PO en attente
A7: Sum of Total Value | D7: Month | Q7: Sum of Total Value | T7: Month
A8: Team | B8: Contact | C8: Project | D8: 01-APR | E8: 02-MAY | F8: 03-JUN | G8: 04-JUL | H8: 05-AUG | I8: 06-SEP | J8: 07-OCT | K8: 08-NOV | L8: 10-JAN | M8: 11-FEB | N8: 12-MAR | O8: Total | Q8: Team | R8: Category | S8: Project | T8: Total
A9: (vide) | B9: Alice Mucke | I9: 120 | O9: 120 | Q9: Total
B10: Kenza Touili | I10: 215 | O10: 215
B11: Justine RODRIGUES | C11: SDLP - Leaflet Vlogging | I11: 180 | O11: 180
A12: CM | B12: Alice Mucke | D12: 605 | E12: 2120 | F12: 1210 | G12: 1245 | H12: 895 | I12: 70 | M12: 270 | N12: 825 | O12: 7240
B13: Lucia Alvaro | D13: 1295 | E13: 1170 | L13: 600 | O13: 3065
B14: Mylène Pellet | D14: 1410 | G14: 645 | O14: 2055
B15: Xanthi Ountzoudi | J15: 775 | O15: 775
A16: BA | B16: Anissa Azediou | D16: 3020 | E16: 440 | G16: 160 | H16: 2450 | I16: 405 | J16: 540 | N16: 495 | O16: 7510
B17: Astrid Jean-Baptiste | D17: 1860 | E17: 2765 | F17: 2270 | G17: 5490 | H17: 540 | N17: 1960 | O17: 14885
B18: Françoise Burgarella | D18: 70 | O18: 70
B19: Héloïse Leroy | C19: Stickers vitrines - Dealer Days 2024 | M19: 175 | O19: 175
C20: Mise au format visuel JPO FNAC Audio | E20: 40 | O20: 40
C21: Insertion pub | G21: 135 | O21: 135
C22: URGENT : Visuel pour stand Fnac | H22: 40 | O22: 40
B23: Ivet Rico | C23: BRIEF CREA_Magnet ZV 1II | I23: 180 | O23: 180
C24: Comparaison Table Xperia 5 V | I24: 135 | O24: 135
B25: Kenza Touili | D25: 6515 | E25: 1530 | F25: 1720 | G25: 635 | H25: 465 | I25: 315 | N25: 915 | O25: 12095
B26: Léa Novio | J26: 465 | O26: 465
B27: Sébastien Minaux | E27: 180 | K27: 105 | O27: 285
B28: Kenza Touilli | C28: AN1000 Award | E28: 70 | O28: 70
C29: TV SONY format demi-page | N29: 135 | O29: 135
B30: Antoine Cuvillier | C30: Visuels page produits S40R | D30: 315 | O30: 315
B31: Valentin Gibaud | C31: BRAVIA 8 BVB screenfill | F31: 35 | O31: 35
C32: Adaptations Header web | F32: 105 | O32: 105
B33: Orianne Hochweiker | C33: Visuel 800 x 418 - Lancement ZVE10M2B | G33: 70 | O33: 70
B34: Lisa Peron | C34: Panneau - Visuel pour un événement interne Sony | H34: 180 | O34: 180
B35: Justine RODRIGUES | C35: OP IP&S AOUT_Focales Fixes et TRADE IN | I35: 720 | O35: 720
C36: OP LENSES BACK TO SCHOOL | I36: 120 | O36: 120
C37: SDLP - LEAFLET MICROS | I37: 250 | O37: 250
A38: Total | D38: 15090 | E38: 8315 | F38: 5340 | G38: 8380 | H38: 4570 | I38: 2710 | J38: 1780 | K38: 105 | L38: 600 | M38: 445 | N38: 4330 | O38: 51665

Sheet Summary - SFR - CM
A2: Sony France - CM
A3: FY | B3: FY24
A4: Team | B4: (Tous)
A5: PO Status | B5: (Plusieurs éléments)
A7: Category | B7: Quarter | C7: PO | D7: Project | E7: Total
A8: Cross | B8: Q2 | C8: 4200670036 | D8: Panneau - Visuel pour un événement interne Sony | E8: 180
A9: DI | B9: Q1 | C9: (vide) | E9: 0
C10: 4200663622 | D10: BOULANGER OP AVRIL | E10: 70
C11: 4200665908 | D11: Visuel ZV E10-format FNAC | E11: 40
D12: Affiche A9M_ Decli Vitrine IP CHOLET | E12: 40
D13: Lancement nouvel Objectif_BANNERS | E13: 435
D14: OP LANDSCAPE_banners | E14: 540
C15: 4200665859 | D15: OP 500€ de remise_ KIT A7M4 ou A7M3 | E15: 235
C16: 4200663622 | D16: FRENCH DAYS | Adaptation des créas | E16: 70
D17: Fnac Darty - Brief Habillage & Bannières OP Photo | E17: 500
C18: 4200667507 | D18: DI | Brief 21x21 OPENEYE | E18: 120
D19: Print always on DI - Juin | E19: 120
D20: DI | FY24 Always ON DI - Flight 1 | E20: 400
C21: 4200667761 | D21: STUDENT CASHBACK France | E21: 670
B22: Q2 | C22: (vide) | E22: 960
C23: 4200668080 | D23: BOULANGER | Offres braderie | E23: 535
D24: BOULANGER | Opération de reprise Gaming | E24: 195
B25: Q3 | C25: (vide) | E25: 1240
B26: Q4 | C26: (vide) | E26: 775
C27: 4200665906 | D27: Newsletter PRT - Janvier 2024 | E27: 600
C28: 4200665859 | D28: OP SUMMER FY24 | E28: 1960
C29: 4200664144 | D29: XV500 Subtitles | E29: 240
A30: HAV | B30: Q1 | C30: 4200663723 | D30: Visuels page produits S40R | E30: 315
C31: 4200667872 | D31: BOULANGER | Newsletter 65BRAVIA7 + QUAD | E31: 120
A32: MDR | B32: Q1 | C32: 4200663610 | D32: BOULANGER | Offre XM4 | E32: 155
D33: BOULANGER | Offres sur la 1000X Family | E33: 155
D34: Brief Créa ULT - Megastar/Impulse Fnac Darty | E34: 275
D35: ULT WEAR - AMS bannières statiques | E35: 400
D36: ULT WEAR - REC AMAZON | E36: 410
D37: Nouveau format Megastar ULT | E37: 35
C38: 4200665082 | D38: BRIEF INLAYS ULT | E38: 215
C39: 4200665083 | D39: FICHES PRODUITS ULT FAMILY | E39: 1000
C40: 4200665081 | D40: ULT | Bannières | E40: 510
C41: 4200665074 | D41: ULT - CHALLENGE POS | E41: 810
C42: 4200665900 | D42: Assets Vidéos - Campagne Social Ads Fnac Darty | E42: 1020
C43: 4200665080 | D43: Créa Box magasin | E43: 350
C44: 4200667862 | D44: BOULANGER | Video SocialAds GAMME ULT | E44: 260
D45: BOULANGER | Offres Audio EURO | E45: 155
D46: Reformatage Asset ULT - Challenge Fnac Airport | E46: 615
D47: ULT bannières | E47: 155
D48: BOULANGER | ILV Magasins - CH720N | E48: 35
D49: BOULANGER | Vidéo magasins ULT | E49: 260
C50: 4270028664 | D50: Etiquette inlay | E50: 35
C51: 4200670851 | D51: BOULANGER | Adaptation bulles WFXM5 | E51: 405
B52: Q2 | C52: (vide) | E52: 1730
C53: 4200663610 | D53: Facture Complémentaire PO 4200663610 | E53: 120
C54: 4200667862 | D54: Simluation rayon casques TV | E54: 120
D55: CREA DSP WH1000XM5 | E55: 645
B56: Q3 | C56: 4200664132 | D56: FICHES PRODUITS LANCEMENT INZONE | E56: 540
B57: Q4 | C57: 4200663610 | D57: BOULANGER | ILV Magasins | E57: 270
D58: BOULANGER | Homepage sur l'Audio Coloré | E58: 190
D59: Audio Coloré adaptation Newsletter | E59: 35
C60: 4200664145 | D60: POS ULT | E60: 255
A61: MEDIA DI | E61: 1100
A62: MEDIA TV | E62: 355
A63: PAG | B63: Q1 | C63: 4200663623 | D63: ULT WEAR - REC AMAZON | E63: 600
A64: TV | B64: Q1 | C64: (vide) | E64: 250
C65: 4200663716 | D65: BOULANGER | BUNDLE A3000+SW3 | E65: 155
D66: BOULANGER | Offre 75X75WL | E66: 155
D67: BOULANGER | Showcase Criteo | E67: 190
D68: BOULANGER | Vidéo Magasin - Un été sportif avec Bravia | E68: 260
D69: Modification Assets Cashback TV & BDS | E69: 20
D70: BOULANGER | Vidéo Magasin - 2e vidéo TV | E70: 260
C71: 4200664137 | D71: HABILLAGE BOULANGER GENNEVILLIERS | E71: 135
C72: 4200667871 | D72: BOULANGER | Trigger TV BDS | E72: 720
D73: BOULANGER | Offre limitée sur les A80L | E73: 155
D74: BOULANGER | Mise à jour landing page TV | E74: 120
D75: Adaptations Header web | E75: 105
D76: BOULANGER | Synergie TV & BDS | E76: 120
D77: Affichages dynamiques - RELAY V1 | E77: 80
D78: BOULANGER | Habillage rayon casques TV | E78: 135
D79: Affichages dynamiques - RELAY V2 | E79: 150
C80: 4200669104 | D80: T&C Crunchyroll - update 2024 | E80: 40
B81: Q2 | C81: (vide) | E81: 895
B82: Q3 | C82: (vide) | E82: 105
A83: MARCOM TV | B83: Q1 | C83: 4200669114 | D83: HE | Cashback lancement HE 2024 | E83: 730
C84: 4200666286 | D84: HE | Adaptation POS Gamme 2024 | E84: 3800
C85: 4200665873 | D85: HE | POLO promoteurs Eurocup | E85: 175
D86: HE | Bannières & modalités SPC | E86: 285
D87: MARCOM HE | Screenfills BVB A80L & A95L | E87: 280
C88: 4200666278 | D88: Adaptation bannière A95L | E88: 175
D89: Lancement adaptation bannières BOULANGER | E89: 70
D90: BOULANGER | Nouveautés TV | E90: 105
D91: HE | screenfill X75WL | E91: 35
D92: Adaptation POS leaflet/upcale/TV guide | E92: 355
B93: Q4 | C93: 4200665873 | D93: TV x HAV - EuroCup & JO 2024 | E93: 915
A94: MARCOM HAV | B94: Q1 | C94: 4200669114 | D94: AN1000 Award | E94: 70
D95: HE | Traduction fiches produit HAV | E95: 300
B96: Q2 | C96: (vide) | E96: 270
A97: PSK | B97: Q2 | C97: (vide) | E97: 665
A98: GAM | B98: Q2 | C98: (vide) | E98: 200
A99: Total | E99: 36055

Sheet Sony France - CM
A1: Price File | Q1: Online | X1: Offline | AG1: Presentations | AH1: Web | AN1: Videos | AU1: Virtualization | AW1: Copy
A2: Project | E2: Details | Q2: Banner creation (static) | R2: Banner adaptation (static) | S2: Banner creation (animated) | T2: Banner adaptation (animated) | U2: Logo | V2: Lifestyle Picture | W2: Wallpapers | X2: Offline creation (standard) | Y2: Offline creation (adaptation) | Z2: Leaflet (1 page) | AA2: Leaflet (2 pages) | AB2: Packaging (box) | AC2: Merchandising Plan | AD2: Roll-up / Wall creation | AE2: Chart | AF2: Brochure (20 pages) | AG2: Slide | AH2: Newsletter (design only) | AI2: Newsletter (complete) | AJ2: Landing page (design only) | AK2: Landing page (complete) | AL2: Website (design only) | AM2: Website (complete) | AN2: Simple Edition | AO2: Longer Edition | AP2: Social Media Video (up to 30s) | AQ2: Social Media Video (up to 1 min) | AR2: Promotional | AS2: 2D Video (up to 3min) | AT2: 3D Video (up to 3min) | AU2: Virtual space | AV2: Virtual showroom | AW2: Translation (per word) | AX2: Copywrite (per word)
A3: Customer | B3: Division | C3: Date | D3: Project | E3: Contact | F3: Status | G3: Category | H3: Link | I3: Assets | J3: Total Value | K3: Quote | L3: PO | M3: Mois de paiement | N3: Invoice | O3: N° Invoice | P3: Status | Q3: 120 | R3: 35 | S3: 220 | T3: 60 | U3: 250 | V3: 500 | W3: 100 | X3: 135 | Y3: 40 | Z3: 180 | AA3: 250 | AB3: 200 | AC3: 250 | AD3: 180 | AE3: 400 | AF3: sa | AG3: 35 | AH3: 500 | AI3: 600 | AJ3: 500 | AK3: 1200 | AL3: 5000 | AM3: 7000 | AN3: 80 | AO3: 150 | AP3: 260 | AQ3: 360 | AR3: 5000 | AS3: 6500 | AT3: 10000 | AU3: 2500 | AV3: 10000 | AW3: 0.1 | AX3: 0.25
A4: Sony | B4: SFR | C4: 45013 | D4: Bannières de lancement A80L + ZV-E1 | E4: Alice Mucke | F4: Delivered | G4: TV | H4: https://saranistudio-my.sharepoint.com/:f:/g/personal/team_sarani_studio/EmtLIsoaTzxJnuMVqwFkEXEBRLxiJIn6Dx3sdurRJBv18Q?e=SUZpe2 | I4: =IF(SUM(Q4:AX4)=0,"-",SUM(Q4:AX4)) -> 6 | J4: =IF(SUMPRODUCT('Sony France - CM'!$Q$3:$AX$3,Q4:AX4)=0,"-",SUMPRODUCT('Sony France - CM'!$Q$3:$AX$3,Q4:AX4)) -> 210 | K4: 45023 | L4: 4200641929 | M4: Avril | R4: 6
A5: Sony | B5: SFR | C5: 45008 | D5: Adaptation Offres MEGASTAR | E5: Mylène Pellet | F5: Delivered | G5: TV | H5: https://saranistudio-my.sharepoint.com/:f:/g/personal/team_sarani_studio/Em9OAsLQ3rVAsCjuhjlyf9ABulvOo8C6xbY6ZkPMG8hkFQ?e=cTZegr | I5: =IF(SUM(Q5:AX5)=0,"-",SUM(Q5:AX5)) -> 3 | J5: =IF(SUMPRODUCT('Sony France - CM'!$Q$3:$AX$3,Q5:AX5)=0,"-",SUMPRODUCT('Sony France - CM'!$Q$3:$AX$3,Q5:AX5)) -> 105 | K5: 45071 | L5: 4200641929 | M5: Avril | N5: sent | R5: 3
A6: Sony | B6: SFR | C6: 45034 | D6: Habillages de site Lancement TV FY23 | E6: Maureen Masson | F6: Delivered | G6: TV | H6: https://saranistudio-my.sharepoint.com/:f:/g/personal/team_sarani_studio/ErYK9M-zOA5Hl_9y0WcmEwsBwd5R8qMMwATIAABc168MWQ?e=kSNAdo | I6: =IF(SUM(Q6:AX6)=0,"-",SUM(Q6:AX6)) -> 3 | J6: =IF(SUMPRODUCT('Sony France - CM'!$Q$3:$AX$3,Q6:AX6)=0,"-",SUMPRODUCT('Sony France - CM'!$Q$3:$AX$3,Q6:AX6)) -> 190 | K6: 45041 | L6: 4200641929 | M6: Mai | N6: sent | Q6: 1 | R6: 2
A7: Sony | B7: SFR | C7: 26/04/23 | D7: Adaptation Megastar Cashback TV HAV | E7: Mylène Pellet | F7: Delivered | G7: TV | H7: https://saranistudio-my.sharepoint.com/:f:/g/personal/team_sarani_studio/EryFOZSDujNAvnhAwzgHd6YBejy68T4VHXJZQ1QAcVGLmw?e=rKtkku | I7: =IF(SUM(Q7:AX7)=0,"-",SUM(Q7:AX7)) -> 1 | J7: =IF(SUMPRODUCT($Q$3:$AX$3,Q7:AX7)=0,"-",SUMPRODUCT($Q$3:$AX$3,Q7:AX7)) -> 35 | K7: 45047 | L7: 4200641929 | M7: Juin | N7: sent | R7: 1
A8: Sony | B8: SFR | C8: 26/04/23 | D8: Campagne TV launch FNAC DARTY | E8: Mylène Pellet | F8: Delivered | G8: TV | H8: https://saranistudio-my.sharepoint.com/:f:/g/personal/team_sarani_studio/Eq7SJAAGtLFPt3_OkqT-cAUBgqmFSKdaWA6Q3fjNYYyZLw?e=Kf8H76 | I8: =IF(SUM(Q8:AX8)=0,"-",SUM(Q8:AX8)) -> 7 | J8: =IF(SUMPRODUCT($Q$3:$AX$3,Q8:AX8)=0,"-",SUMPRODUCT($Q$3:$AX$3,Q8:AX8)) -> 245 | K8: 45047 | L8: 4200641929 | M8: Mai | N8: sent | R8: 7
A9: Sony | B9: SFR | C9: 28/04/23 | D9: Webpop TV FY23 | E9: Joelle Mechache | F9: Delivered | G9: TV | H9: https://saranistudio-my.sharepoint.com/:f:/g/personal/team_sarani_studio/EksaPdiWfxhMnbU7goZGW3wBNMdtyNVXPZFQGY1IHS_P8w?e=K0olFY | I9: =IF(SUM(Q9:AX9)=0,"-",SUM(Q9:AX9)) -> 1 | J9: =IF(SUMPRODUCT('Sony France - CM'!$Q$3:$AX$3,Q9:AX9)=0,"-",SUMPRODUCT('Sony France - CM'!$Q$3:$AX$3,Q9:AX9)) -> 120 | K9: 45061 | L9: 4200641929 | M9: Juin | N9: sent | Q9: 1
A10: Sony | B10: SFR | C10: 45054 | D10: Mockup Newsletter Micromania | E10: Alice Mucke | F10: Delivered | G10: TV | H10: https://saranistudio-my.sharepoint.com/:f:/g/personal/team_sarani_studio/EhXJcziQF1VOliqxaNrnlb0BfZuNE9G1FoVfA52_LbSH2A?e=KNakVW | I10: 0,5 | J10: 250 € | K10: 45064 | L10: 4200641929 | M10: Juin | N10: Sent | AH10: 0,5
A11: Sony | B11: SFR | C11: 45056 | D11: Cashback TV HAV - Adaptation Impulse | E11: Mylène Pellet | F11: Delivered | G11: TV | H11: https://saranistudio-my.sharepoint.com/:f:/g/personal/team_sarani_studio/Ekai1uZu5I1DjFQDqtNMglUB-a9khXEpgHVGO6Ehmq4loA?e=O64h2s | I11: =IF(SUM(Q11:AX11)=0,"-",SUM(Q11:AX11)) -> 4 | J11: =IF(SUMPRODUCT($Q$3:$AX$3,Q11:AX11)=0,"-",SUMPRODUCT($Q$3:$AX$3,Q11:AX11)) -> 140 | K11: 45082 | L11: 4200641929 | M11: Juin | N11: Sent | R11: 4
A12: Sony | B12: SFR | C12: 45057 | D12: Spiderman Micromania banners | E12: Alice Mucke | F12: Delivered | G12: TV | H12: https://saranistudio-my.sharepoint.com/:f:/g/personal/team_sarani_studio/Ej9SOLBtCcBHld_gbUxWxU4Bj5ZI1lZOhveurJhxJ-lshA?e=zgWyyk | I12: =IF(SUM(Q12:AX12)=0,"-",SUM(Q12:AX12)) -> 7 | J12: =IF(SUMPRODUCT($Q$3:$AX$3,Q12:AX12)=0,"-",SUMPRODUCT($Q$3:$AX$3,Q12:AX12)) -> 330 | K12: 45064 | L12: 4200641929 | M12: Juin | N12: Sent | Q12: 1 | R12: 6
A13: Sony | B13: SFR | C13: 17/05/23 | D13: HAV bundle - Réseaux sociaux | E13: Alice Mucke | F13: Delivered | G13: TV | H13: https://saranistudio-my.sharepoint.com/:f:/g/personal/team_sarani_studio/Eno1hTwc6CZOpOaDyfuFXzEBK3IEmmBUsIThhxjU7-HINg?e=eUPBG7 | I13: =IF(SUM(Q13:AX13)=0,"-",SUM(Q13:AX13)) -> 6 | J13: =IF(SUMPRODUCT($Q$3:$AX$3,Q13:AX13)=0,"-",SUMPRODUCT($Q$3:$AX$3,Q13:AX13)) -> 380 | K13: 45064 | L13: 4200641929 | M13: Juin | N13: Sent | Q13: 2 | R13: 4
A14: Sony | B14: SFR | C14: 30/05/23 | D14: Jeu Concours PS5 - Banners Boulanger | E14: Maureen Masson | F14: Delivered | G14: TV | H14: https://saranistudio-my.sharepoint.com/:f:/g/personal/team_sarani_studio/Et4JEQ0pJl5Kp_gFcv6IrzAB9iSZfuy0HfDvSRmUsm9szw?e=pEDdUu | I14: =IF(SUM(Q14:AX14)=0,"-",SUM(Q14:AX14)) -> 2 | J14: =IF(SUMPRODUCT($Q$3:$AX$3,Q14:AX14)=0,"-",SUMPRODUCT($Q$3:$AX$3,Q14:AX14)) -> 155 | K14: 45047 | L14: 4200641929 | M14: Juin | N14: Sent | Q14: 1 | R14: 1
A15: Sony | B15: SFR | C15: 30/05/23 | D15: Lancement TA-AN1000 - Banners Boulanger | E15: Maureen Masson | F15: Delivered | G15: HAV | H15: https://saranistudio-my.sharepoint.com/:f:/g/personal/team_sarani_studio/Ei_NmotrYflMp_lWmHZy990BpLoLZi4cDnXnEJa6yjOecw?e=dGyo9B | I15: =IF(SUM(Q15:AX15)=0,"-",SUM(Q15:AX15)) -> 2 | J15: =IF(SUMPRODUCT($Q$3:$AX$3,Q15:AX15)=0,"-",SUMPRODUCT($Q$3:$AX$3,Q15:AX15)) -> 155 | K15: 45047 | L15: 4200641929 | M15: Juin | N15: Sent | Q15: 1 | R15: 1
A16: Sony | B16: SFR | C16: 45019 | D16: New C700 Video - Short Video Editing | E16: Joelle Mechache | F16: Delivered | G16: MDR | H16: https://saranistudio-my.sharepoint.com/:f:/g/personal/team_sarani_studio/EkiROo65MdxOl4foCK_JnkMB7b1GqAM5JaGtE7NM2E563A?e=zgcdCi | I16: =IF(SUM(Q16:AX16)=0,"-",SUM(Q16:AX16)) -> 1 | J16: 260 | K16: 45023 | L16: 4200641950 | M16: Mai | N16: Sent | AQ16: 1
A17: Sony | B17: SFR | C17: 45089 | D17: Adaptations C700 / CH520 / XG300 | E17: Alice Mucke | F17: Delivered | G17: MDR | H17: https://saranistudio-my.sharepoint.com/:f:/g/personal/team_sarani_studio/EnY_cb3_b3FBkuyHMMgrIqABI3LhFTYtdKHZJVa7a7n45w?e=c3qr6G | I17: =IF(SUM(Q17:AX17)=0,"-",SUM(Q17:AX17)) -> 6 | J17: =IF(SUMPRODUCT($Q$3:$AX$3,Q17:AX17)=0,"-",SUMPRODUCT($Q$3:$AX$3,Q17:AX17)) -> 210 | L17: 4200647984 | M17: Juillet | N17: Sent | R17: 6
A18: Sony | B18: SFR | C18: 45103 | D18: Patacos nouveautés MDR | E18: Alice Mucke | F18: Delivered | G18: MDR | H18: https://saranistudio-my.sharepoint.com/:f:/g/personal/team_sarani_studio/EhWQhvikpjJAs9fRKuPWGgEBkfzxAmfMaaWw3wA91WzwdQ?e=0urtbw | I18: =IF(SUM(Q18:AX18)=0,"-",SUM(Q18:AX18)) -> 3 | J18: =IF(SUMPRODUCT($Q$3:$AX$3,Q18:AX18)=0,"-",SUMPRODUCT($Q$3:$AX$3,Q18:AX18)) -> 120 | L18: 4200641950 | M18: Aout | N18: Sent | Y18: 3
A19: Sony | B19: SFR | C19: 45012 | D19: Déclinaisons TV / DI | E19: Alice Mucke | F19: Delivered | G19: DI | H19: https://saranistudio-my.sharepoint.com/:f:/g/personal/team_sarani_studio/EmtLIsoaTzxJnuMVqwFkEXEBRLxiJIn6Dx3sdurRJBv18Q?e=g8c6h9 | I19: =IF(SUM(Q19:AX19)=0,"-",SUM(Q19:AX19)) -> 6 | J19: =IF(SUMPRODUCT('Sony France - CM'!$Q$3:$AX$3,Q19:AX19)=0,"-",SUMPRODUCT('Sony France - CM'!$Q$3:$AX$3,Q19:AX19)) -> 210 | K19: 45041 | L19: 4200641951 | M19: Avril | R19: 6
A20: Sony | B20: SFR | C20: 26/04/23 | D20: OP summer - Déclinaisons Photo Univers | E20: Alice Mucke | F20: Delivered | G20: DI | H20: https://saranistudio-my.sharepoint.com/:f:/g/personal/team_sarani_studio/ElqnG-FXH_tIjM-5CjehobkBI3iwiykX2wZsbbcXjP2u5Q?e=cTcTX3 | I20: =IF(SUM(Q20:AX20)=0,"-",SUM(Q20:AX20)) -> 3 | J20: =IF(SUMPRODUCT('Sony France - CM'!$Q$3:$AX$3,Q20:AX20)=0,"-",SUMPRODUCT('Sony France - CM'!$Q$3:$AX$3,Q20:AX20)) -> 105 | K20: 45043 | L20: 4200641951 | M20: Mai | N20: sent | R20: 3
A21: Sony | B21: SFR | C21: 45048 | D21: OP FX30 - Photo Univers | E21: Alice Mucke | F21: Delivered | G21: DI | H21: https://saranistudio-my.sharepoint.com/:f:/g/personal/team_sarani_studio/EmGsdIsbJgRJsHn18mqoDSQB5FuBnBna9S_58xG7MtztpQ?e=qp39eM | I21: =IF(SUM(Q21:AX21)=0,"-",SUM(Q21:AX21)) -> 4 | J21: =IF(SUMPRODUCT($Q$3:$AX$3,Q21:AX21)=0,"-",SUMPRODUCT($Q$3:$AX$3,Q21:AX21)) -> 140 | K21: 45047 | L21: 4200641951 | M21: Juin | N21: sent | R21: 4
A22: Sony | B22: SFR | C22: 23/05/23 | D22: CX64800 - Photo Univers | E22: Alice Mucke | F22: Delivered | G22: DI | H22: https://saranistudio-my.sharepoint.com/:f:/g/personal/team_sarani_studio/En4adQAwLLdMpS_-kswH4HYBlTRV8MD-w8jBUwACO_7rVA?e=59Phkd | I22: =IF(SUM(Q22:AX22)=0,"-",SUM(Q22:AX22)) -> 4 | J22: =IF(SUMPRODUCT($Q$3:$AX$3,Q22:AX22)=0,"-",SUMPRODUCT($Q$3:$AX$3,Q22:AX22)) -> 140 | K22: 45082 | L22: 4200641951 | M22: Juin | N22: sent | R22: 4
A23: Sony | B23: SFR | C23: 45033 | D23: Bannières Boulanger promo barres de son | E23: Maureen Masson | F23: Delivered | G23: HAV | H23: https://saranistudio-my.sharepoint.com/:f:/g/personal/team_sarani_studio/EkZE4Y3oDmxOgPwByulkRGQBO22GCn4XXiv8vxBWXU3BOQ?e=QYcm2Z | I23: =IF(SUM(Q23:AX23)=0,"-",SUM(Q23:AX23)) -> 2 | J23: =IF(SUMPRODUCT('Sony France - CM'!$Q$3:$AX$3,Q23:AX23)=0,"-",SUMPRODUCT('Sony France - CM'!$Q$3:$AX$3,Q23:AX23)) -> 155 | K23: 45036 | L23: 4200641959 | M23: Mai | N23: sent | Q23: 1 | R23: 1
A24: Sony | B24: SFR | C24: 45078 | D24: Adaptation Bannières XG300 | E24: Alice Mucke | F24: Delivered | G24: MDR | H24: https://saranistudio-my.sharepoint.com/:f:/g/personal/team_sarani_studio/Ev6IqmHMJZBCphm3dxGsXhYBeFhBvti6G9s1vJiBrYBRdA?e=gI4oeQ | I24: =IF(SUM(Q24:AX24)=0,"-",SUM(Q24:AX24)) -> 4 | J24: =IF(SUMPRODUCT($Q$3:$AX$3,Q24:AX24)=0,"-",SUMPRODUCT($Q$3:$AX$3,Q24:AX24)) -> 140 | K24: 45082 | L24: 4200647984 | M24: Juillet | N24: Sent | R24: 4
A25: Sony | B25: SFR | C25: 45084 | D25: Cross Visuel - Document de formation | E25: Alice Mucke | F25: Delivered | G25: MDR | H25: https://saranistudio-my.sharepoint.com/:f:/g/personal/team_sarani_studio/EmZPb6upSoFLpsVrD7mVPrQBWIvIxUkXO5KuEznQtZpHRA?e=gonNYb | I25: =IF(SUM(Q25:AX25)=0,"-",SUM(Q25:AX25)) -> 1 | J25: =IF(SUMPRODUCT($Q$3:$AX$3,Q25:AX25)=0,"-",SUMPRODUCT($Q$3:$AX$3,Q25:AX25)) -> 120 | L25: 4200647984 | M25: Juillet | N25: Sent | Q25: 1
A26: Sony | B26: SFR | C26: 45091 | D26: Affichages dynamiques - BOULANGER | E26: Alice Mucke | F26: Delivered | G26: MDR | H26: https://saranistudio-my.sharepoint.com/:f:/g/personal/team_sarani_studio/Enx5U2mYTNFMnJc-xIoaRV0B1eOVGObhT3Vm8PYvRQBmQQ?e=buAC3K | I26: =IF(SUM(Q26:AX26)=0,"-",SUM(Q26:AX26)) -> 1 | J26: =IF(SUMPRODUCT($Q$3:$AX$3,Q26:AX26)=0,"-",SUMPRODUCT($Q$3:$AX$3,Q26:AX26)) -> 360 | L26: 4200647984 | M26: Juillet | N26: Sent | AQ26: 1
A27: Sony | B27: SFR | C27: 45104 | D27: Soldes d'été - adaptation | E27: Alice Mucke | F27: Delivered | G27: MDR | H27: https://saranistudio-my.sharepoint.com/:f:/g/personal/team_sarani_studio/EshfpkcRdslJlWo_wRSFdokBKfbGaymAkkISj5Hs0t-4Gg?e=rxI0Dg | I27: =IF(SUM(Q27:AX27)=0,"-",SUM(Q27:AX27)) -> 1 | J27: =IF(SUMPRODUCT($Q$3:$AX$3,Q27:AX27)=0,"-",SUMPRODUCT($Q$3:$AX$3,Q27:AX27)) -> 35 | L27: 4200647984 | M27: Aout | N27: Sent | O27: F2023-0422 | P27: Paid 19/01/2024 | R27: 1
A28: Sony | B28: SFR | C28: 45127 | D28: Bannières de lancement - HT-A7X | E28: Alice Mucke | F28: Delivered | G28: HAV | H28: https://saranistudio.sharepoint.com/:f:/s/SaraniAssets/Eo4fs8B0yVxOnYJDdESxq3IBMQTRyrJaLmIY-WuqR8BCHw?e=CXm0xp | I28: =IF(SUM(Q28:AX28)=0,"-",SUM(Q28:AX28)) -> 6 | J28: =IF(SUMPRODUCT($Q$3:$AX$3,Q28:AX28)=0,"-",SUMPRODUCT($Q$3:$AX$3,Q28:AX28)) -> 295 | L28: 4200647984 | M28: Aout | N28: Sent | O28: F2023-0422 | P28: Paid 19/01/2024 | Q28: 1 | R28: 5
A29: Sony | B29: SFR | C29: 45127 | D29: Bannières teasing E5 Boulanger | E29: Maureen Masson | F29: Delivered | G29: MDR | H29: https://saranistudio.sharepoint.com/:f:/s/SaraniAssets/Et5dFqZmczRMgczFiFOa0GsBBMgBPGHSfouO-Ayz_KXs-g?e=etIRaC | I29: =IF(SUM(Q29:AX29)=0,"-",SUM(Q29:AX29)) -> 2 | J29: =IF(SUMPRODUCT($Q$3:$AX$3,Q29:AX29)=0,"-",SUMPRODUCT($Q$3:$AX$3,Q29:AX29)) -> 70 | L29: 4200647984 | M29: Aout | N29: Sent | O29: F2023-0422 | P29: Paid 19/01/2024 | R29: 2
A30: Sony | B30: SFR | C30: 24/07/2023 | D30: Adaptation bannières Boulanger | E30: Maureen Masson | F30: Delivered | G30: MDR | H30: https://saranistudio.sharepoint.com/:f:/s/SaraniAssets/Ep_e6bGp1cJGnZiPUIoGnmMBOeKbF9oZdsw2Vnw67-ugPA?e=9SpT7N | I30: =IF(SUM(Q30:AX30)=0,"-",SUM(Q30:AX30)) -> 4 | J30: =IF(SUMPRODUCT($Q$3:$AX$3,Q30:AX30)=0,"-",SUMPRODUCT($Q$3:$AX$3,Q30:AX30)) -> 140 | L30: 4200647984 | M30: Aout | N30: Sent | O30: F2023-0422 | P30: Paid 19/01/2024 | R30: 4
A31: Sony | B31: SFR | C31: 27/07/2023 | D31: FNAC DARTY WF1000XM5 | E31: Mylène Pellet | F31: Delivered | G31: MDR | H31: https://saranistudio.sharepoint.com/:f:/s/SaraniAssets/EiknNepsLsBCrpdYsClDYf4BJ3FbQd_CWM1gJFTvYGUW-Q?e=Rq1u9R | I31: =IF(SUM(Q31:AX31)=0,"-",SUM(Q31:AX31)) -> 4 | J31: =IF(SUMPRODUCT($Q$3:$AX$3,Q31:AX31)=0,"-",SUMPRODUCT($Q$3:$AX$3,Q31:AX31)) -> 225 | L31: 4200647984 | M31: Aout | N31: Sent | O31: F2023-0422 | P31: Paid 19/01/2024 | Q31: 1 | R31: 3
A32: Sony | B32: SFR | C32: 27/07/2023 | D32: Bannières Boulanger Try&Buy WF-1000XM5 | E32: Maureen Masson | F32: Delivered | G32: MDR | H32: https://saranistudio.sharepoint.com/:f:/s/SaraniAssets/EooaxtefwdJHkHIXb1uHNp0Bo4oLLxMQXbDoZSqdCMOmdA?e=0dKqff | I32: =IF(SUM(Q32:AX32)=0,"-",SUM(Q32:AX32)) -> 2 | J32: =IF(SUMPRODUCT($Q$3:$AX$3,Q32:AX32)=0,"-",SUMPRODUCT($Q$3:$AX$3,Q32:AX32)) -> 155 | L32: 4200647984 | M32: Aout | N32: Sent | O32: F2023-0422 | P32: Paid 19/01/2024 | Q32: 1 | R32: 1
A33: Sony | B33: SFR | C33: 45159 | D33: Boulanger | Social Ads - WF1000XM5 | E33: Alice Mucke | F33: Delivered | G33: MDR | H33: https://saranistudio.sharepoint.com/:f:/s/SaraniAssets/EtFcNiBU0NdFlh47hWv2DIcB350g2zzLb2TcsdaZ7gu2IA?e=VVwlcH | I33: =IF(SUM(Q33:AX33)=0,"-",SUM(Q33:AX33)) -> 2 | J33: =IF(SUMPRODUCT($Q$3:$AX$3,Q33:AX33)=0,"-",SUMPRODUCT($Q$3:$AX$3,Q33:AX33)) -> 440 | L33: 4200647984 | M33: Septembre | N33: Sent | O33: F2023-0422 | P33: Paid 19/01/2024 | AN33: 1 | AQ33: 1
A34: Sony | B34: SFR | C34: 31/10/2023 | D34: Création Assets - Régie Mégastar | E34: Lucia Alvaro | F34: Delivered | G34: MDR | H34: https://saranistudio.sharepoint.com/:f:/s/SaraniAssets/Eh6KVl3bFE5LhnPwJatp_ZAB-BRSqFvxMpNBm7iwT-IQ2Q?e=HY0ocq | I34: =IF(SUM(Q34:AX34)=0,"-",SUM(Q34:AX34)) -> 2 | J34: =IF(SUMPRODUCT('Sony France - CM'!$Q$3:$AX$3,Q34:AX34)=0,"-",SUMPRODUCT('Sony France - CM'!$Q$3:$AX$3,Q34:AX34)) -> 155 | L34: 4200647984 | M34: Janvier | N34: Sent | O34: F2023-0439 | P34: Paid 23/01/2024 | Q34: 1 | R34: 1
A35: Sony | B35: SFR | C35: 45078 | D35: OP Photo Fnac | E35: Mylène Pellet | F35: Delivered | G35: DI | H35: https://saranistudio-my.sharepoint.com/:f:/g/personal/team_sarani_studio/EmcPifH5zRNCuYQ6gTYnx6sBDvIuTZFuDZPI2FJvUxiAxw?e=XWt4Db | I35: =IF(SUM(Q35:AX35)=0,"-",SUM(Q35:AX35)) -> 6 | J35: =IF(SUMPRODUCT($Q$3:$AX$3,Q35:AX35)=0,"-",SUMPRODUCT($Q$3:$AX$3,Q35:AX35)) -> 465 | K35: 45082 | L35: 4200647987 | M35: Juillet | N35: Sent | Q35: 3 | R35: 3
A36: Sony | B36: SFR | C36: 45083 | D36: OP Photo Fnac adaptations | E36: Mylène Pellet | F36: Delivered | G36: DI | H36: https://saranistudio-my.sharepoint.com/:f:/g/personal/team_sarani_studio/EtIVwt5h1mBGvOR3ExJTZ1gBzwxRkAB45F-wXqyU66HBZg?e=Ck53W4 | I36: =IF(SUM(Q36:AX36)=0,"-",SUM(Q36:AX36)) -> 2 | J36: =IF(SUMPRODUCT($Q$3:$AX$3,Q36:AX36)=0,"-",SUMPRODUCT($Q$3:$AX$3,Q36:AX36)) -> 70 | L36: 4200647987 | M36: Juillet | N36: Sent | R36: 2
A37: Sony | B37: SFR | C37: 45089 | D37: Déclinaisons Packs VLOG / FF | E37: Alice Mucke | F37: Delivered | G37: DI | H37: https://saranistudio-my.sharepoint.com/:f:/g/personal/team_sarani_studio/EnsODutXGZlJka_h6isAGR0BOCwDvdDheBpIbUVmfdjGWQ?e=loMFxG | I37: =IF(SUM(Q37:AX37)=0,"-",SUM(Q37:AX37)) -> 21 | J37: =IF(SUMPRODUCT($Q$3:$AX$3,Q37:AX37)=0,"-",SUMPRODUCT($Q$3:$AX$3,Q37:AX37)) -> 820 | L37: 4200647987 | M37: Juillet | N37: Sent | Q37: 1 | R37: 20
A38: Sony | B38: SFR | C38: 45099 | D38: ZV-E1 - vidéo format court | E38: Mylène Pellet | F38: Delivered | G38: DI | H38: https://saranistudio-my.sharepoint.com/:f:/g/personal/team_sarani_studio/Eq9dY38BCXlJpcBriotIXLwBSlmTZTPUeCHR-CXQ-1YX2g?e=07oE5T | I38: =IF(SUM(Q38:AX38)=0,"-",SUM(Q38:AX38)) -> 1 | J38: =IF(SUMPRODUCT($Q$3:$AX$3,Q38:AX38)=0,"-",SUMPRODUCT($Q$3:$AX$3,Q38:AX38)) -> 150 | L38: 4200647987 | M38: Juillet | N38: Sent | AO38: 1
A39: Sony | B39: SFR | C39: 45103 | D39: Opération Optiques GM garantie | E39: Alice Mucke | F39: Delivered | G39: DI | H39: https://saranistudio-my.sharepoint.com/:f:/g/personal/team_sarani_studio/EjjU1nsll0ZLpfwcqkqDz1ABqwYNoyuQuP2Jpd3qOaYqaw?e=tAAr5m | I39: =IF(SUM(Q39:AX39)=0,"-",SUM(Q39:AX39)) -> 2 | J39: =IF(SUMPRODUCT($Q$3:$AX$3,Q39:AX39)=0,"-",SUMPRODUCT($Q$3:$AX$3,Q39:AX39)) -> 155 | L39: 4200647987 | M39: Aout | N39: Sent | O39: F2023-0423 | P39: Paid 19/01/2024 | Q39: 1 | R39: 1
A40: Sony | B40: SFR | C40: 45110 | D40: Op Optiques | E40: Alice Mucke | F40: Delivered | G40: DI | H40: https://saranistudio.sharepoint.com/:f:/s/SaraniAssets/EsYuFhHQcFRDtLfSjO_6uGMB0GNO5CLhpB3N6Q9GmyqNJQ?e=Y20eDi | I40: =IF(SUM(Q40:AX40)=0,"-",SUM(Q40:AX40)) -> 2 | J40: =IF(SUMPRODUCT($Q$3:$AX$3,Q40:AX40)=0,"-",SUMPRODUCT($Q$3:$AX$3,Q40:AX40)) -> 155 | L40: 4200647987 | M40: Aout | N40: Sent | O40: F2023-0423 | P40: Paid 19/01/2024 | Q40: 1 | R40: 1
A41: Sony | B41: SFR | C41: 45111 | D41: Je fais mon kit - 2023 | E41: Alice Mucke | F41: Delivered | G41: DI | H41: https://saranistudio.sharepoint.com/:f:/s/SaraniAssets/EkWffmfdAPhJqYBPKmTZI68BPTppr0WVR3suOlBsij0oiQ?e=fU70oR | I41: =IF(SUM(Q41:AX41)=0,"-",SUM(Q41:AX41)) -> 2 | J41: =IF(SUMPRODUCT($Q$3:$AX$3,Q41:AX41)=0,"-",SUMPRODUCT($Q$3:$AX$3,Q41:AX41)) -> 155 | L41: 4200647987 | M41: Aout | N41: Sent | O41: F2023-0423 | P41: Paid 19/01/2024 | Q41: 1 | R41: 1
A42: Sony | B42: SFR | C42: 45091 | D42: Affichages dynamiques - RELAY | E42: Alice Mucke | F42: Delivered | G42: TV | H42: https://saranistudio-my.sharepoint.com/:f:/g/personal/team_sarani_studio/Egj4cX4pxGtJhLcuZRe4SgIB1aofCP5Wp59nYn874HRKqw?e=QamI4u | I42: =IF(SUM(Q42:AX42)=0,"-",SUM(Q42:AX42)) -> 1 | J42: =IF(SUMPRODUCT($Q$3:$AX$3,Q42:AX42)=0,"-",SUMPRODUCT($Q$3:$AX$3,Q42:AX42)) -> 360 | L42: 4200648002 | M42: Juillet | N42: Sent | AQ42: 1
A43: Sony | B43: SFR | C43: 45110 | D43: Intégration inscreen sur visuels TV | E43: Alice Mucke | F43: Delivered | G43: TV | H43: https://saranistudio.sharepoint.com/:f:/s/SaraniAssets/EoZ04PuGIvlHkkrh7M2jUFkBNolII5PschT6ClRo9ay4iw?e=Aty2Lv | I43: =IF(SUM(Q43:AX43)=0,"-",SUM(Q43:AX43)) -> 5 | J43: =IF(SUMPRODUCT($Q$3:$AX$3,Q43:AX43)=0,"-",SUMPRODUCT($Q$3:$AX$3,Q43:AX43)) -> 260 | L43: 4200648002 | M43: Juillet | N43: Sent | Q43: 1 | R43: 4
A44: Sony | B44: SFR | C44: 45117 | D44: Bannières Braderie Boulanger | E44: Maureen Masson | F44: Delivered | G44: TV | H44: https://saranistudio.sharepoint.com/:f:/s/SaraniAssets/EnGdKGI3RDlNkYa-Rt8thvMB-hjoMEf_kapNSCKqGMYx9A?e=yuE1BI | I44: =IF(SUM(Q44:AX44)=0,"-",SUM(Q44:AX44)) -> 9 | J44: =IF(SUMPRODUCT($Q$3:$AX$3,Q44:AX44)=0,"-",SUMPRODUCT($Q$3:$AX$3,Q44:AX44)) -> 315 | L44: 4200648002 | M44: Juillet | N44: Sent | R44: 9
A45: Sony | B45: SFR | C45: 45151 | D45: Vidéo Magasin Boulanger - Coupe du Monde de Rugby | E45: Alice Mucke | F45: Delivered | G45: TV | H45: https://saranistudio.sharepoint.com/:f:/s/SaraniAssets/EsSvNf2CmCpLoLYMmLs749cBUiV0hVkSNGQXJeSn24BJww?e=mJoRlc | I45: =IF(SUM(Q45:AX45)=0,"-",SUM(Q45:AX45)) -> 1 | J45: =IF(SUMPRODUCT($Q$3:$AX$3,Q45:AX45)=0,"-",SUMPRODUCT($Q$3:$AX$3,Q45:AX45)) -> 360 | L45: 4200648002 | M45: Juillet | N45: Sent | O45: F2023-0421 | P45: Paid 19/01/2024 | AQ45: 1
A46: Sony | B46: SFR | C46: 45170 | D46: A95L Megastar | E46: Mylène Pellet | F46: Delivered | G46: TV | H46: https://saranistudio.sharepoint.com/:f:/s/SaraniAssets/EnKMlvMUmgtHl33KogLSSL4BT4by5o36kDO9QCfgduKfRg?e=h0mc84 | I46: =IF(SUM(Q46:AX46)=0,"-",SUM(Q46:AX46)) -> 1 | J46: =IF(SUMPRODUCT($Q$3:$AX$3,Q46:AX46)=0,"-",SUMPRODUCT($Q$3:$AX$3,Q46:AX46)) -> 35 | L46: 4200652021 | M46: Septembre | N46: Sent | O46: F2023-0421 | P46: Paid 19/01/2024 | R46: 1
A47: Sony | B47: SFR | C47: 45176 | D47: BOULANGER Homepage A95L | E47: Alice Mucke | F47: Delivered | G47: TV | H47: https://saranistudio.sharepoint.com/:f:/s/SaraniAssets/El4Zg-mjvdVNsHXBYyw_hr8BeakFEMytWf-TaaZWoMSIZQ?e=ro3lEN | I47: =IF(SUM(Q47:AX47)=0,"-",SUM(Q47:AX47)) -> 2 | J47: =IF(SUMPRODUCT($Q$3:$AX$3,Q47:AX47)=0,"-",SUMPRODUCT($Q$3:$AX$3,Q47:AX47)) -> 70 | L47: 4200653885 | M47: Octobre | N47: Sent | O47: F2023-0421 | P47: Paid 19/01/2024 | R47: 2
A48: Sony | B48: SFR | C48: 45188 | D48: 3 créas Meuble TV 4K | E48: Xanthi Ountzoudi | F48: Delivered | G48: TV | H48: https://saranistudio.sharepoint.com/:f:/s/SaraniAssets/EtfUCFAtvM1ClAWzs5V8ly4Bl5_BtcfUzG-ocfaZiYi-UA?e=mfemRc | I48: =IF(SUM(Q48:AX48)=0,"-",SUM(Q48:AX48)) -> 3 | J48: =IF(SUMPRODUCT($Q$3:$AX$3,Q48:AX48)=0,"-",SUMPRODUCT($Q$3:$AX$3,Q48:AX48)) -> 540 | L48: 4200653885 | M48: Octobre | N48: Sent | O48: F2023-0421 | P48: Paid 19/01/2024 | AD48: 3
A49: Sony | B49: SFR | C49: 45210 | D49: BOULANGER | -10% sur les A80L | E49: Alice Mucke | F49: Delivered | G49: TV | H49: https://saranistudio.sharepoint.com/:f:/s/SaraniAssets/Eo2gCErVUSNJhhWrswEkgr0BuKZlajnhYGCJdyMEFeChjw?e=t0AxyP | I49: =IF(SUM(Q49:AX49)=0,"-",SUM(Q49:AX49)) -> 2 | J49: =IF(SUMPRODUCT($Q$3:$AX$3,Q49:AX49)=0,"-",SUMPRODUCT($Q$3:$AX$3,Q49:AX49)) -> 70 | L49: 4200653885 | M49: Novembre | N49: Sent | O49: F2023-0424 | P49: Paid 19/01/2024 | R49: 2
A50: Sony | B50: SFR | C50: 45218 | D50: Screenfill A95L D2C adaptation | E50: Mylène Pellet | F50: Delivered | G50: TV | H50: https://saranistudio.sharepoint.com/:f:/s/SaraniAssets/EuQyocrz7aFDuO819yz0ww0BMrZ7LmNdTJ5E1BsfIs5bxw?e=A74Tv9 | I50: =IF(SUM(Q50:AX50)=0,"-",SUM(Q50:AX50)) -> 1 | J50: =IF(SUMPRODUCT($Q$3:$AX$3,Q50:AX50)=0,"-",SUMPRODUCT($Q$3:$AX$3,Q50:AX50)) -> 35 | L50: 4200653885 | M50: Novembre | N50: Sent | O50: F2023-0424 | P50: Paid 19/01/2024 | R50: 1
A51: Sony | B51: SFR | C51: 31/10/2023 | D51: RETARGETING | Formats display et natives | E51: Alice Mucke | F51: Delivered | G51: TV | H51: https://saranistudio.sharepoint.com/:f:/s/SaraniAssets/EjJ8FapyEDlGhNbQtDSCKMEBmzrKpIOokm6DzVfxKrqvfQ?e=xeCvE8 | I51: =IF(SUM(Q51:AX51)=0,"-",SUM(Q51:AX51)) -> 4 | J51: =IF(SUMPRODUCT($Q$3:$AX$3,Q51:AX51)=0,"-",SUMPRODUCT($Q$3:$AX$3,Q51:AX51)) -> 300 | L51: 4200653885 | M51: Décembre | N51: Sent | O51: F2023-0424 | P51: Paid 19/01/2024 | Q51: 1 | T51: 3
A52: Sony | B52: SFR | C52: 45232 | D52: A95L | Vidéo de 25 secondes | E52: Alice Mucke | F52: Delivered | G52: TV | H52: https://saranistudio.sharepoint.com/:f:/s/SaraniAssets/EpVLTD8AcVFOoq7WqfTgzHYBaoFcP9nMoLJncoN9hs7E7w?e=kvyV0y | I52: =IF(SUM(Q52:AX52)=0,"-",SUM(Q52:AX52)) -> 1 | J52: =IF(SUMPRODUCT($Q$3:$AX$3,Q52:AX52)=0,"-",SUMPRODUCT($Q$3:$AX$3,Q52:AX52)) -> 80 | L52: 4200653885 | M52: Décembre | N52: Sent | O52: F2023-0424 | P52: Paid 19/01/2024 | AN52: 1
A53: Sony | B53: SFR | C53: 45240 | D53: Display et Habillage TV A95L DARTY | E53: Mylène Pellet | F53: Delivered | G53: TV | H53: https://saranistudio.sharepoint.com/:f:/s/SaraniAssets/EjFSqeQ09NFHvpMTxDxk31QBAlTBXEylsg91OVIxKT6fPQ?e=flMF03 | I53: =IF(SUM(Q53:AX53)=0,"-",SUM(Q53:AX53)) -> 2 | J53: =IF(SUMPRODUCT($Q$3:$AX$3,Q53:AX53)=0,"-",SUMPRODUCT($Q$3:$AX$3,Q53:AX53)) -> 240 | L53: 4200653885 | M53: Décembre | N53: Sent | O53: F2023-0424 | P53: Paid 19/01/2024 | Q53: 2
A54: Sony | B54: SFR | C54: 45243 | D54: OFFRE ILV 65X90BF BOULANGER | E54: Alice Mucke | F54: Delivered | G54: TV | H54: https://saranistudio.sharepoint.com/:f:/s/SaraniAssets/EhaXdK045ktJg8QiQguTvs8B2qCauga7MsVE7QwYTqF63w?e=6ZHC8E | I54: =IF(SUM(Q54:AX54)=0,"-",SUM(Q54:AX54)) -> 1 | J54: =IF(SUMPRODUCT($Q$3:$AX$3,Q54:AX54)=0,"-",SUMPRODUCT($Q$3:$AX$3,Q54:AX54)) -> 135 | L54: 4200653885 | M54: Décembre | N54: Sent | O54: F2023-0424 | P54: Paid 19/01/2024 | X54: 1
A55: Sony | B55: SFR | C55: 45238 | D55: Format Impulse Barre de son Fnac Darty | E55: Mylène Pellet | F55: Delivered | G55: MDR | H55: https://saranistudio.sharepoint.com/:f:/s/SaraniAssets/EsS0n7-mcOhAizFqMCHg0M0BcG125BDooC6feMnZVwvCow?e=HC8MzD | I55: =IF(SUM(Q55:AX55)=0,"-",SUM(Q55:AX55)) -> 2 | J55: =IF(SUMPRODUCT($Q$3:$AX$3,Q55:AX55)=0,"-",SUMPRODUCT($Q$3:$AX$3,Q55:AX55)) -> 155 | L55: 4200647984 | M55: Janvier | N55: Sent | O55: F2023-0439 | P55: Paid 23/01/2024 | Q55: 1 | R55: 1
A56: Sony | B56: SFR | C56: 24/11/2023 | D56: Banniere Offre Speciale / Platine + Cross Noël | E56: Alice Mucke | F56: Delivered | G56: MDR | H56: https://saranistudio.sharepoint.com/:f:/s/SaraniAssets/Ejr-QoovUvhFlKdqynue9OgBmRMS9myizreXW47oGc6XSA?e=0nFbmm | I56: =IF(SUM(Q56:AX56)=0,"-",SUM(Q56:AX56)) -> 18 | J56: =IF(SUMPRODUCT($Q$3:$AX$3,Q56:AX56)=0,"-",SUMPRODUCT($Q$3:$AX$3,Q56:AX56)) -> 885 | L56: 4200657838 | M56: Février | N56: Sent | O56: F2024-0023 | P56: Unpaid | Q56: 3 | R56: =18-Q56 -> 15
A57: Sony | B57: SFR | C57: 45243 | D57: BOULANGER | Modification des dimensions | E57: Alice Mucke | F57: Delivered | G57: DI | H57: https://saranistudio.sharepoint.com/:f:/s/SaraniAssets/Esb88uDM9kZPvZ5uB5ZOp7IBdO3An7CZXDJUWtFeBMIAsw?e=NB7Jei | I57: =IF(SUM(Q57:AX57)=0,"-",SUM(Q57:AX57)) -> 7 | J57: =IF(SUMPRODUCT($Q$3:$AX$3,Q57:AX57)=0,"-",SUMPRODUCT($Q$3:$AX$3,Q57:AX57)) -> 245 | L57: 4200654186 | M57: Décembre | N57: Sent | O57: F2023-0425 | P57: Paid 19/01/2024 | R57: 7
A58: Sony | B58: SFR | C58: 45274 | D58: Bannière offre noël PRT // A7M3 | E58: Lucia Alvaro | F58: Delivered | G58: DI | H58: https://saranistudio.sharepoint.com/:f:/s/SaraniAssets/ElaTCnH-UbBDhAwIQzcejYIBSEVMBrpOe96t7VFsvzzqFw?e=KtU3Cp | I58: =IF(SUM(Q58:AX58)=0,"-",SUM(Q58:AX58)) -> 1 | J58: =IF(SUMPRODUCT('Sony France - CM'!$Q$3:$AX$3,Q58:AX58)=0,"-",SUMPRODUCT('Sony France - CM'!$Q$3:$AX$3,Q58:AX58)) -> 120 | L58: 4200657843 | M58: Janvier | N58: Sent | O58: F2024-0020 | P58: Unpaid | Q58: 1
A59: Sony | B59: SFR | C59: 45209 | D59: BOULANGER | Bannière HT-A9 | E59: Alice Mucke | F59: Delivered | G59: HAV | H59: https://saranistudio.sharepoint.com/:f:/s/SaraniAssets/Eu2RanequfNGsQqUWNobPq0BHu4nG3ip_jSh-z5ivF-SNg?e=Z9FmxR | I59: =IF(SUM(Q59:AX59)=0,"-",SUM(Q59:AX59)) -> 5 | J59: =IF(SUMPRODUCT($Q$3:$AX$3,Q59:AX59)=0,"-",SUMPRODUCT($Q$3:$AX$3,Q59:AX59)) -> 275 | L59: 4200654197 | M59: Novembre | N59: Sent | O59: F2023-0426 | P59: Paid 19/01/2024 | Q59: 1 | R59: 1 | Y59: 3
A60: Sony | B60: SFR | C60: 24/04/23 | D60: Le printemps Sony / Amazon | E60: Joelle Mechache | F60: Delivered | G60: MDR | H60: https://saranistudio-my.sharepoint.com/:f:/g/personal/team_sarani_studio/EhsZRSxgxfVLrM85FfWaf4wBIG1duzSBgim6pUcZ5L-q-g?e=ImXkgA | I60: =IF(SUM(Q60:AX60)=0,"-",SUM(Q60:AX60)) -> 3 | J60: =IF(SUMPRODUCT('Sony France - CM'!$Q$3:$AX$3,Q60:AX60)=0,"-",SUMPRODUCT('Sony France - CM'!$Q$3:$AX$3,Q60:AX60)) -> 190 | K60: 45044 | L60: 4200641950 | M60: Mai | N60: Sent | O60: F2024-0041 | P60: UNPAID | Q60: 1 | R60: 2
A61: Sony | B61: SFR | C61: 26/04/23 | D61: French Days - Adaptations Boulanger | E61: Maureen Masson | F61: Delivered | G61: MDR | H61: https://saranistudio-my.sharepoint.com/:f:/g/personal/team_sarani_studio/El9e7jWbxXdMjpwPrqrY1MwBS4are5bsKjLjkvs3GxUcVA?e=WhH1kd | I61: =IF(SUM(Q61:AX61)=0,"-",SUM(Q61:AX61)) -> 4 | J61: =IF(SUMPRODUCT('Sony France - CM'!$Q$3:$AX$3,Q61:AX61)=0,"-",SUMPRODUCT('Sony France - CM'!$Q$3:$AX$3,Q61:AX61)) -> 140 | K61: 45043 | L61: 4200641950 | M61: Mai | N61: Sent | O61: F2024-0041 | P61: UNPAID | R61: 4
A62: Sony | B62: SFR | C62: 45167 | D62: Back-to-School Sony Crea - AMAZON | E62: Joelle Mechache | F62: Delivered | G62: TV | H62: https://saranistudio.sharepoint.com/:f:/s/SaraniAssets/EkM4_4S2YUlChNsH90t7glEB0h_thC1ZAJOIh6EKmPcE9w?e=hxqLqh | I62: =IF(SUM(Q62:AX62)=0,"-",SUM(Q62:AX62)) -> 2 | J62: =IF(SUMPRODUCT($Q$3:$AX$3,Q62:AX62)=0,"-",SUMPRODUCT($Q$3:$AX$3,Q62:AX62)) -> 155 | L62: 4200652021 | M62: Septembre | N62: Sent | O62: F2024-0041 | P62: UNPAID | Q62: 1 | R62: 1
A63: Sony | B63: SFR | C63: 44882 | D63: TV - Displays Les Numériques | E63: Fatima-Zohra Ichi | F63: Delivered | G63: DI | H63: https://saranistudio-my.sharepoint.com/:f:/g/personal/team_sarani_studio/EhGvAIAk9nhJjmewxCW5higB28ZJKSWD-dA33c2u3yxD1w?e=RZ63bm | I63: =IF(SUM(Q63:AX63)=0,"-",SUM(Q63:AX63)) -> 4 | J63: =IF(SUMPRODUCT('Sony France - CM'!$Q$3:$AX$3,Q63:AX63)=0,"-",SUMPRODUCT('Sony France - CM'!$Q$3:$AX$3,Q63:AX63)) -> 140 | K63: 44903 | L63: 4200657838 | M63: Février | N63: Sent | O63: F2024-0040 | P63: UNPAID | R63: 4
A64: Sony | B64: SFR | C64: 27/07/2023 | D64: RUGBY WORLDCUP FNAC DARTY | E64: Mylène Pellet | F64: Delivered | G64: DI | H64: https://saranistudio.sharepoint.com/:f:/s/SaraniAssets/EiknNepsLsBCrpdYsClDYf4BJ3FbQd_CWM1gJFTvYGUW-Q?e=gKgtg0 | I64: =IF(SUM(Q64:AX64)=0,"-",SUM(Q64:AX64)) -> 7 | J64: =IF(SUMPRODUCT($Q$3:$AX$3,Q64:AX64)=0,"-",SUMPRODUCT($Q$3:$AX$3,Q64:AX64)) -> 245 | L64: 4200657838 | M64: Février | N64: Sent | O64: F2024-0040 | P64: UNPAID | R64: 7
A65: Sony | B65: SFR | C65: 31/10/2023 | D65: BOULANGER | Une PS5 à gagner pour l'achat d'un XPERIA | E65: Alice Mucke | F65: Delivered | G65: DI | H65: https://saranistudio.sharepoint.com/:f:/s/SaraniAssets/Epz1Uwo7qKRHsoXZRMrZaGUBic3akKIBcVEYe2sM45EsUQ?e=NhNinE | I65: =IF(SUM(Q65:AX65)=0,"-",SUM(Q65:AX65)) -> 2 | J65: =IF(SUMPRODUCT($Q$3:$AX$3,Q65:AX65)=0,"-",SUMPRODUCT($Q$3:$AX$3,Q65:AX65)) -> 155 | L65: 4200657838 | M65: Février | N65: Sent | O65: F2024-0040 | P65: UNPAID | Q65: 1 | R65: 1
A66: Sony | B66: SFR | C66: 45176 | D66: BOULANGER | Bannière Exclus 2 en 1 | E66: Alice Mucke | F66: Delivered | G66: DI | H66: https://saranistudio.sharepoint.com/:f:/s/SaraniAssets/EqEFLDs290NFhFKnIKvHsREBm5-NMDYOyYi9fj6Lz-NCPw?e=lTl3ml | I66: =IF(SUM(Q66:AX66)=0,"-",SUM(Q66:AX66)) -> 2 | J66: =IF(SUMPRODUCT($Q$3:$AX$3,Q66:AX66)=0,"-",SUMPRODUCT($Q$3:$AX$3,Q66:AX66)) -> 155 | L66: 4200657843 | M66: Février | N66: Sent | O66: F2024-0042 | P66: Unpaid | Q66: 1 | R66: 1
A67: Sony | B67: SFR | C67: 45214 | D67: Boulanger Alisage | E67: Alice Mucke | F67: Delivered | G67: DI | H67: https://saranistudio.sharepoint.com/:f:/s/SaraniAssets/Er1x1PPB_U5HtSXsmDKHazoBk6wVtgrwAriyWUNJ7GUixg?e=zvz3rS | I67: =IF(SUM(Q67:AX67)=0,"-",SUM(Q67:AX67)) -> 2 | J67: =IF(SUMPRODUCT($Q$3:$AX$3,Q67:AX67)=0,"-",SUMPRODUCT($Q$3:$AX$3,Q67:AX67)) -> 430 | L67: 4200657843 | M67: Février | N67: Sent | O67: F2024-0042 | P67: Unpaid | Z67: 1 | AA67: 1
A68: Sony | B68: SFR | C68: 31/10/2023 | D68: BLACK FRIDAY | Bannières Boulanger | E68: Alice Mucke | F68: Delivered | G68: DI | H68: https://saranistudio.sharepoint.com/:f:/s/SaraniAssets/ErSgv-hqFRpOuvmAVjD_t1gBaECQLYpE-t9VB7eIFXWUGQ?e=qBNZQf | I68: =IF(SUM(Q68:AX68)=0,"-",SUM(Q68:AX68)) -> 14 | J68: =IF(SUMPRODUCT($Q$3:$AX$3,Q68:AX68)=0,"-",SUMPRODUCT($Q$3:$AX$3,Q68:AX68)) -> 575 | L68: 4200657843 | M68: Février | N68: Sent | O68: F2024-0042 | P68: Unpaid | Q68: 1 | R68: 13
A69: Sony | B69: SFR | C69: 17/11/2023 | D69: Créa Impulse 65A95L | E69: Mylène Pellet | F69: Delivered | G69: DI | H69: https://saranistudio.sharepoint.com/:f:/s/SaraniAssets/ErbIaajS6sFLnYkxn-DbMdkBiP476TtQ2kiHvY381FmGjg?e=grtKaU | I69: =IF(SUM(Q69:AX69)=0,"-",SUM(Q69:AX69)) -> 2 | J69: =IF(SUMPRODUCT($Q$3:$AX$3,Q69:AX69)=0,"-",SUMPRODUCT($Q$3:$AX$3,Q69:AX69)) -> 155 | L69: 4200657843 | M69: Février | N69: Sent | O69: F2024-0042 | P69: Unpaid | Q69: 1 | R69: 1
A70: Sony | B70: SFR | C70: 45242 | D70: Assets Créa SOLDES - Boulanger | E70: Lucia Alvaro | F70: Delivered | G70: DI | H70: https://saranistudio.sharepoint.com/:f:/s/SaraniAssets/Ej_ZtFDNGhhEoYEWR38NaYUBYId-dXbNQROQXHhEAmib1Q?e=3B1uH4 | I70: =IF(SUM(Q70:AX70)=0,"-",SUM(Q70:AX70)) -> 18 | J70: =IF(SUMPRODUCT('Sony France - CM'!$Q$3:$AX$3,Q70:AX70)=0,"-",SUMPRODUCT('Sony France - CM'!$Q$3:$AX$3,Q70:AX70)) -> 885 | L70: 4200657843 | M70: Février | N70: Sent | O70: F2024-0042 | P70: Unpaid | Q70: 3 | R70: =18-Q70 -> 15
A71: Sony | B71: SFR | C71: 45303 | D71: OP LANCEMENT A9III extra asset | E71: Lucia Alvaro | F71: Delivered | G71: DI | H71: https://saranistudio.sharepoint.com/:f:/s/SaraniAssets/EgRVJ7M8DotDrEnyTLJ5S80BXA2hLOZ6s3Itax5zhMPyxQ?e=zgCO0J | I71: =IF(SUM(Q71:AX71)=0,"-",SUM(Q71:AX71)) -> 1 | J71: =IF(SUMPRODUCT($Q$3:$AX$3,Q71:AX71)=0,"-",SUMPRODUCT($Q$3:$AX$3,Q71:AX71)) -> 35 | L71: 4200657843 | M71: Février | N71: sent | O71: F2024-0021 | P71: Unpaid | R71: 1
A72: Sony | B72: SFR | C72: 21/11/2023 | D72: Bannières 98X90L | E72: Alice Mucke | F72: Delivered | G72: TV | H72: https://saranistudio.sharepoint.com/:f:/s/SaraniAssets/ErPLt4I4ugdKvV8jBHbwSlgBXz4Vz3JbCCpnY0t6_1bBKg?e=BTiFOm | I72: =IF(SUM(Q72:AX72)=0,"-",SUM(Q72:AX72)) -> 2 | J72: =IF(SUMPRODUCT($Q$3:$AX$3,Q72:AX72)=0,"-",SUMPRODUCT($Q$3:$AX$3,Q72:AX72)) -> 155 | L72: 4200657852 | M72: Janvier | N72: Sent | O72: F2023-0438 | P72: Paid 23/01/2024 | Q72: 1 | R72: 1
A73: Sony | B73: SFR | C73: 21/11/2023 | D73: TV A80L + X75WL banners | E73: Alice Mucke | F73: Delivered | G73: TV | H73: https://saranistudio.sharepoint.com/:f:/s/SaraniAssets/EgSBMO7G8CtPiA2qeVp_ODkBbAHHc8LP-rPTkwH6_xHmdg?e=efaM1O | I73: =IF(SUM(Q73:AX73)=0,"-",SUM(Q73:AX73)) -> 2 | J73: =IF(SUMPRODUCT($Q$3:$AX$3,Q73:AX73)=0,"-",SUMPRODUCT($Q$3:$AX$3,Q73:AX73)) -> 70 | L73: 4200657852 | M73: Janvier | N73: Sent | O73: F2023-0438 | P73: Paid 23/01/2024 | R73: 2
A74: Sony | B74: SFR | C74: 45294 | D74: New TV Visuels Hero - Micromania | E74: Alice Mucke | F74: Delivered | G74: TV | H74: https://saranistudio.sharepoint.com/:f:/s/SaraniAssets/Eh5uhux84DVPk0koK0veA4kBNcIs_Folxc65B8tNPAIiJw?e=eYXaB0 | I74: =IF(SUM(Q74:AX74)=0,"-",SUM(Q74:AX74)) -> 7 | J74: =IF(SUMPRODUCT($Q$3:$AX$3,Q74:AX74)=0,"-",SUMPRODUCT($Q$3:$AX$3,Q74:AX74)) -> 245 | L74: 4200657852 | M74: Janvier | N74: Sent | O74: F2024-0022 | P74: Unpaid | R74: 7
A75: Sony | B75: SFR | C75: 45299 | D75: BOULANGER | Adaptations des créas Photo Soldes | E75: Alice Mucke | F75: Delivered | G75: TV | I75: =IF(SUM(Q75:AX75)=0,"-",SUM(Q75:AX75)) -> 4 | J75: =IF(SUMPRODUCT($Q$3:$AX$3,Q75:AX75)=0,"-",SUMPRODUCT($Q$3:$AX$3,Q75:AX75)) -> 140 | L75: 4200657852 | M75: Janvier | N75: Sent | O75: F2024-0022 | P75: Unpaid | R75: 4
A76: Sony | B76: SFR | C76: 45301 | D76: BOULANGER | Bannière "Choisir sa TV" | E76: Alice Mucke | F76: Delivered | G76: TV | H76: https://saranistudio.sharepoint.com/:f:/s/SaraniAssets/EpsNyvJ0-BpHqZgKY9OcGWUBVl17ZHoLs9KuFQ-VyT8yFA?e=ydkCEr | I76: =IF(SUM(Q76:AX76)=0,"-",SUM(Q76:AX76)) -> 2 | J76: =IF(SUMPRODUCT($Q$3:$AX$3,Q76:AX76)=0,"-",SUMPRODUCT($Q$3:$AX$3,Q76:AX76)) -> 155 | L76: 4200657852 | M76: Janvier | N76: Sent | O76: F2024-0022 | P76: Unpaid | Q76: 1 | R76: 1
A77: Sony | B77: SFR | C77: 45119 | D77: MICROMANIA - Boites factices nouveautés 2023 | E77: Anissa Azediou | F77: Delivered | G77: Micromania | H77: https://saranistudio.sharepoint.com/:f:/s/SaraniAssets/EuPLdBmkrSBBjYGA9yTfmOsB8gm0yfdSaY35ycXI4CHu3Q?e=ofOhdX | I77: =IF(SUM(Q77:AX77)=0,"-",SUM(Q77:AX77)) -> 2 | J77: =IF(SUMPRODUCT($Q$3:$AX$3,Q77:AX77)=0,"-",SUMPRODUCT($Q$3:$AX$3,Q77:AX77)) -> 240 | Y77: 1 | AB77: 1
A78: Sony | B78: SFR | C78: 45306 | D78: Assets Brand Week - Amazon | E78: Lucia Alvaro | F78: Delivered | G78: PAG | H78: https://saranistudio.sharepoint.com/:f:/s/SaraniAssets/Eq-G0OXt7vlHmHi81zgLafwBcYQj-fDcP68S1bRRJECbdQ?e=jCQYCn | I78: =IF(SUM(Q78:AX78)=0,"-",SUM(Q78:AX78)) -> 14 | J78: =IF(SUMPRODUCT('Sony France - CM'!$Q$3:$AX$3,Q78:AX78)=0,"-",SUMPRODUCT('Sony France - CM'!$Q$3:$AX$3,Q78:AX78)) -> 915 | Q78: 5 | R78: 9
A79: Sony | B79: SFR | C79: 45306 | D79: MICROMANIA - Boite adaptation | E79: Anissa Azediou | F79: Delivered | G79: Micromania | H79: https://saranistudio.sharepoint.com/:f:/s/SaraniAssets/EkfqcsyPeeVHrBTexWbhyMQBHX1Dgzi-LouhHe8418G9NA?e=7FHPoe | I79: =IF(SUM(Q79:AX79)=0,"-",SUM(Q79:AX79)) -> 1 | J79: =IF(SUMPRODUCT($Q$3:$AX$3,Q79:AX79)=0,"-",SUMPRODUCT($Q$3:$AX$3,Q79:AX79)) -> 40 | Y79: 1
A80: Sony | B80: SFR | C80: 45309 | D80: SOLDES - Boulanger adaptations | E80: Alice Mucke | F80: Delivered | G80: MDR | I80: =IF(SUM(Q80:AX80)=0,"-",SUM(Q80:AX80)) -> 8 | J80: =IF(SUMPRODUCT($Q$3:$AX$3,Q80:AX80)=0,"-",SUMPRODUCT($Q$3:$AX$3,Q80:AX80)) -> 280 | R80: 8
A81: Sony | B81: SFR | C81: 45313 | D81: Assets Créa SOLDES - Boulanger | E81: Lucia Alvaro | F81: Delivered | G81: MDR | H81: https://saranistudio.sharepoint.com/:f:/s/SaraniAssets/Eq-G0OXt7vlHmHi81zgLafwBcYQj-fDcP68S1bRRJECbdQ?e=jCQYCn | I81: =IF(SUM(Q81:AX81)=0,"-",SUM(Q81:AX81)) -> 2 | J81: =IF(SUMPRODUCT($Q$3:$AX$3,Q81:AX81)=0,"-",SUMPRODUCT($Q$3:$AX$3,Q81:AX81)) -> 155 | Q81: 1 | R81: 1
A82: Sony | B82: SFR | C82: 45537 | D82: Compilation vidéo FNAC | E82: Lucia Alvaro | F82: Delivered | G82: MDR | H82: https://saranistudio.sharepoint.com/:f:/s/SaraniAssets/EtUnX_f3m65Pl1ZbIR2LtFcBdyH_pFE4j6bsj_lvVjHrzQ?e=6ao9MM | I82: =IF(SUM(Q82:AX82)=0,"-",SUM(Q82:AX82)) -> 1 | J82: =IF(SUMPRODUCT($Q$3:$AX$3,Q82:AX82)=0,"-",SUMPRODUCT($Q$3:$AX$3,Q82:AX82)) -> 80 | AN82: 1
A83: Sony | B83: SFR | C83: 31/12/2023 | D83: BOULANGER | Bannières WF-1000XM5 | E83: Alice Mucke | F83: Delivered | G83: MDR | H83: https://saranistudio.sharepoint.com/:f:/s/SaraniAssets/EgPyDxfLaM5NtZ_Kfe9TRQ4Bkvs6LnolxNbRXg41QgrwyA?e=bwzV8E | I83: =IF(SUM(Q83:AX83)=0,"-",SUM(Q83:AX83)) -> 2 | J83: =IF(SUMPRODUCT($Q$3:$AX$3,Q83:AX83)=0,"-",SUMPRODUCT($Q$3:$AX$3,Q83:AX83)) -> 155 | Q83: 1 | R83: 1
A84: Sony | B84: SFR | C84: 45334 | D84: BOULANGER | HTS400 offerte pour l'achat d'une 75X75WL | E84: Alice Mucke | F84: In progress | G84: TV | H84: https://saranistudio.sharepoint.com/:f:/s/SaraniAssets/EiD1r8hyOmVHqcBftZ43yokBQPOqC5P4SWGgKQ1TXKqYeQ?e=EVwLhY | I84: =IF(SUM(P84:AW84)=0,"-",SUM(P84:AW84)) -> 1 | J84: =IF(SUMPRODUCT('Sony France - CM'!$Q$3:$AX$3,P84:AW84)=0,"-",SUMPRODUCT('Sony France - CM'!$Q$3:$AX$3,P84:AW84)) -> 120 | P84: 1
I85: =IF(SUM(Q85:AX85)=0,"-",SUM(Q85:AX85)) -> - | J85: =IF(SUMPRODUCT($Q$3:$AX$3,Q85:AX85)=0,"-",SUMPRODUCT($Q$3:$AX$3,Q85:AX85)) -> -
I86: =IF(SUM(Q86:AX86)=0,"-",SUM(Q86:AX86)) -> - | J86: =IF(SUMPRODUCT($Q$3:$AX$3,Q86:AX86)=0,"-",SUMPRODUCT($Q$3:$AX$3,Q86:AX86)) -> -
I87: =IF(SUM(Q87:AX87)=0,"-",SUM(Q87:AX87)) -> - | J87: =IF(SUMPRODUCT($Q$3:$AX$3,Q87:AX87)=0,"-",SUMPRODUCT($Q$3:$AX$3,Q87:AX87)) -> -
I88: =IF(SUM(Q88:AX88)=0,"-",SUM(Q88:AX88)) -> - | J88: =IF(SUMPRODUCT($Q$3:$AX$3,Q88:AX88)=0,"-",SUMPRODUCT($Q$3:$AX$3,Q88:AX88)) -> -
I89: =IF(SUM(Q89:AX89)=0,"-",SUM(Q89:AX89)) -> - | J89: =IF(SUMPRODUCT($Q$3:$AX$3,Q89:AX89)=0,"-",SUMPRODUCT($Q$3:$AX$3,Q89:AX89)) -> -
I90: =IF(SUM(Q90:AX90)=0,"-",SUM(Q90:AX90)) -> - | J90: =IF(SUMPRODUCT($Q$3:$AX$3,Q90:AX90)=0,"-",SUMPRODUCT($Q$3:$AX$3,Q90:AX90)) -> -
I91: =IF(SUM(Q91:AX91)=0,"-",SUM(Q91:AX91)) -> - | J91: =IF(SUMPRODUCT($Q$3:$AX$3,Q91:AX91)=0,"-",SUMPRODUCT($Q$3:$AX$3,Q91:AX91)) -> -
I92: =IF(SUM(Q92:AX92)=0,"-",SUM(Q92:AX92)) -> - | J92: =IF(SUMPRODUCT($Q$3:$AX$3,Q92:AX92)=0,"-",SUMPRODUCT($Q$3:$AX$3,Q92:AX92)) -> -
I93: =IF(SUM(Q93:AX93)=0,"-",SUM(Q93:AX93)) -> - | J93: =IF(SUMPRODUCT($Q$3:$AX$3,Q93:AX93)=0,"-",SUMPRODUCT($Q$3:$AX$3,Q93:AX93)) -> -
I94: =IF(SUM(Q94:AX94)=0,"-",SUM(Q94:AX94)) -> - | J94: =IF(SUMPRODUCT($Q$3:$AX$3,Q94:AX94)=0,"-",SUMPRODUCT($Q$3:$AX$3,Q94:AX94)) -> -
I95: =IF(SUM(Q95:AX95)=0,"-",SUM(Q95:AX95)) -> - | J95: =IF(SUMPRODUCT($Q$3:$AX$3,Q95:AX95)=0,"-",SUMPRODUCT($Q$3:$AX$3,Q95:AX95)) -> -

Sheet Sony France - Hors CM
A1: Price File | P1: Online | W1: Offline | AF1: Presentations | AG1: Web | AM1: Videos | AS1: Virtualization | AU1: Copy
A2: Project | E2: Details | L2: Sony | M2: Sarani Ne pas toucher, svp | P2: Banner creation (static) | Q2: Banner adaptation (static) | R2: Banner creation (animated) | S2: Banner adaptation (animated) | T2: Logo | U2: Lifestyle Picture | V2: Wallpapers | W2: Offline creation (standard) | X2: Offline creation (adaptation) | Y2: Leaflet (1 page) | Z2: Leaflet (2 pages) | AA2: Packaging (box) | AB2: Merchandising Plan | AC2: Roll-up / Wall creation | AD2: Chart | AE2: Brochure (20 pages) | AF2: Slide | AG2: Newsletter (design only) | AH2: Newsletter (complete) | AI2: Landing page (design only) | AJ2: Landing page (complete) | AK2: Website (design only) | AL2: Website (complete) | AM2: Simple Edition | AN2: Social Media Video (up to 30s) | AO2: Social Media Video (up to 1 min) | AP2: Promotional | AQ2: 2D Video (up to 3min) | AR2: 3D Video (up to 3min) | AS2: Virtual space | AT2: Virtual showroom | AU2: Translation (per word) | AV2: Copywrite (per word)
A3: Customer | B3: Division | C3: Date | D3: Project | E3: Contact | F3: Status | G3: Category | H3: Link | I3: Assets | J3: Total Value | K3: Quote | L3: PO | M3: Invoice | N3: N° Invoice | O3: Status | P3: 120 | Q3: 35 | R3: 220 | S3: 60 | T3: 250 | U3: 500 | V3: 100 | W3: 135 | X3: 40 | Y3: 180 | Z3: 250 | AA3: 200 | AB3: 250 | AC3: 180 | AD3: 400 | AE3: 2200 | AF3: 35 | AG3: 500 | AH3: 600 | AI3: 500 | AJ3: 1200 | AK3: 5000 | AL3: 7000 | AM3: 80 | AN3: 260 | AO3: 360 | AP3: 5000 | AQ3: 6500 | AR3: 10000 | AS3: 2500 | AT3: 10000 | AU3: 0.1 | AV3: 0.25
A4: Sony | B4: SFR | C4: 44880 | D4: MDR MEG TW FNAC | E4: Laura Vivient | F4: Delivered | G4: V&S | H4: https://saranistudio-my.sharepoint.com/:f:/g/personal/team_sarani_studio/Etevju8IZKpEjFi3N14QmoUBp7wUTsms6pxhOWBv6e2jlQ?e=poko2y | I4: =IF(SUM(P4:AV4)=0,"-",SUM(P4:AV4)) -> 3 | J4: =IF(SUMPRODUCT($P$3:$AV$3,P4:AV4)=0,"-",SUMPRODUCT($P$3:$AV$3,P4:AV4)) -> 405 | K4: 29/11/2022 | L4: 4200630823 | M4: Sent | W4: 3
A5: Sony | B5: SFR | C5: 44880 | D5: MDR TW Stop Rayon Bluetooth Multipoint | E5: Laura Vivient | F5: Delivered | G5: V&S | H5: https://saranistudio-my.sharepoint.com/:f:/g/personal/team_sarani_studio/EiWYden95S1PhgR70pI8qxEBwY-0nfvYhECdhw2ZQdFqdw?e=oKMO8n | I5: =IF(SUM(P5:AV5)=0,"-",SUM(P5:AV5)) -> 1 | J5: =IF(SUMPRODUCT($P$3:$AV$3,P5:AV5)=0,"-",SUMPRODUCT($P$3:$AV$3,P5:AV5)) -> 135 | K5: 29/11/2022 | L5: 4200630799 | M5: Sent | W5: 1
A6: Sony | B6: SFR | C6: 44882 | D6: Xmas - Creative Assets | E6: Maxime Fenech | F6: Delivered | G6: Cross | H6: https://saranistudio-my.sharepoint.com/:f:/g/personal/team_sarani_studio/EiXLGF1XZ1VNkmFgudaLWcQB0AP6n1T0jNDvvhweNqqJwg?e=vKq0Pw | I6: =IF(SUM(P6:AV6)=0,"-",SUM(P6:AV6)) -> 19 | J6: 590 | K6: 22/11/2022 | L6: 4200632493 | M6: Sent | Q6: 19
A7: Sony | B7: SFR | C7: 44883 | D7: Bulles Boulanger 2 | E7: Laura Vivient | F7: Delivered | G7: V&S | H7: https://saranistudio-my.sharepoint.com/:f:/g/personal/team_sarani_studio/EvZFoSgMoTlGiWeuK20ZrcwBr1BCtYNuR2DptwGgJMpg-A?e=ucRI2s | I7: =IF(SUM(P7:AV7)=0,"-",SUM(P7:AV7)) -> 1 | J7: =IF(SUMPRODUCT($P$3:$AV$3,P7:AV7)=0,"-",SUMPRODUCT($P$3:$AV$3,P7:AV7)) -> 120 | K7: 29/11/2022 | L7: 4200630798 | M7: Sent | P7: 1
A8: Sony | B8: SFR | C8: 44883 | D8: Infographies PSK FR | E8: Laura Vivient | F8: Delivered | G8: V&S | H8: https://saranistudio-my.sharepoint.com/:f:/g/personal/team_sarani_studio/Evtfs8z--DpCs3Qy9Cvq1Y4BMFsqWlLop36Ti2xykheKBA?e=DSnQzV | I8: =IF(SUM(P8:AV8)=0,"-",SUM(P8:AV8)) -> 16 | J8: =IF(SUMPRODUCT($P$3:$AV$3,P8:AV8)=0,"-",SUMPRODUCT($P$3:$AV$3,P8:AV8)) -> 560 | K8: 29/11/2022 | L8: 4200630825 | M8: Sent | Q8: 16
A9: Sony | B9: SFR | C9: 44883 | D9: 1000XM5 Award | E9: Laura Vivient | F9: Delivered | G9: V&S | H9: https://saranistudio-my.sharepoint.com/:f:/g/personal/team_sarani_studio/Eiu73Y88xwJPqQdXyeju6gcBPx5Nk46QboMvzke5SksCEw?e=lK8Qjn | I9: =IF(SUM(P9:AV9)=0,"-",SUM(P9:AV9)) -> 2 | J9: =IF(SUMPRODUCT($P$3:$AV$3,P9:AV9)=0,"-",SUMPRODUCT($P$3:$AV$3,P9:AV9)) -> 70 | K9: 29/11/2022 | L9: 4270024443 | M9: Sent | Q9: 2
A10: Sony | B10: SFR | C10: 44888 | D10: A95K-A83K Topper | E10: Léa Novio | F10: Delivered | G10: TV | H10: https://saranistudio-my.sharepoint.com/:f:/g/personal/team_sarani_studio/Enb5T0uGjd5It7r-yOl8Hw4BRcePMvNEVtlCj65ShnZ1eA?e=oRN2hs | I10: =IF(SUM(P10:AV10)=0,"-",SUM(P10:AV10)) -> 2 | J10: =IF(SUMPRODUCT($P$3:$AV$3,P10:AV10)=0,"-",SUMPRODUCT($P$3:$AV$3,P10:AV10)) -> 175 | K10: 44785 | L10: 4200631414 | M10: Sent | W10: 1 | X10: 1
A11: Sony | B11: SFR | C11: 44888 | D11: Labo Fnac | E11: Léa Novio | F11: Delivered | G11: TV | H11: https://saranistudio-my.sharepoint.com/:f:/g/personal/team_sarani_studio/EmBOVYV-QulImoZen16_XSMBt4gcYjkuDidXF__Uf1-VHw?e=ibhnwE | I11: =IF(SUM(P11:AV11)=0,"-",SUM(P11:AV11)) -> 5 | J11: =IF(SUMPRODUCT($P$3:$AV$3,P11:AV11)=0,"-",SUMPRODUCT($P$3:$AV$3,P11:AV11)) -> 175 | K11: 29/11/2022 | L11: 4200631417 | M11: Sent | Q11: 5
A12: Sony | B12: SFR | C12: 44888 | D12: HAV PLV MEG BDS LEAFLET TV | E12: Laura Vivient | F12: Delivered | G12: HAV | H12: https://saranistudio-my.sharepoint.com/:f:/g/personal/team_sarani_studio/EsKN0KK2wo5EuWcP_12lMhIBc3AUZVWjUaf03MKgHmGTeQ?e=4x7Av8 | I12: =IF(SUM(P12:AV12)=0,"-",SUM(P12:AV12)) -> 2 | J12: =IF(SUMPRODUCT($P$3:$AV$3,P12:AV12)=0,"-",SUMPRODUCT($P$3:$AV$3,P12:AV12)) -> 175 | K12: 30/11/2022 | L12: 4200630829 | M12: Sent | W12: 1 | X12: 1
A13: Sony | B13: SFR | C13: 44896 | D13: LinkBuds S avec SZA | E13: Laura Vivient | F13: Delivered | G13: V&S | H13: https://saranistudio-my.sharepoint.com/:f:/g/personal/team_sarani_studio/Ev2DdJ24TI9DnMYkKwzIkq0BHlTI4PJMje_IlrhSeabtxw?e=g9BnfI | I13: =IF(SUM(P13:AV13)=0,"-",SUM(P13:AV13)) -> 5 | J13: =IF(SUMPRODUCT($P$3:$AV$3,P13:AV13)=0,"-",SUMPRODUCT($P$3:$AV$3,P13:AV13)) -> 175 | K13: 44785 | L13: 4200630821 | M13: Sent | Q13: 5
A14: Sony | B14: SFR | C14: 44896 | D14: Sony Values Poster (5 A4 assets) | E14: Françoise Burgarella | F14: Delivered | G14: Cross | H14: https://saranistudio-my.sharepoint.com/:f:/g/personal/team_sarani_studio/Em0VBaXS7r5GiCtkcsyiCosBToqjoeJ6S1SQLfPqkfkGsQ?e=fEshRi | I14: =IF(SUM(P14:AV14)=0,"-",SUM(P14:AV14)) -> 4 | J14: =IF(SUMPRODUCT($P$3:$AV$3,P14:AV14)=0,"-",SUMPRODUCT($P$3:$AV$3,P14:AV14)) -> 350 | K14: 14/12/2022 | L14: 4200631419 | M14: Sent | W14: 2 | X14: 2
A15: Sony | B15: SFR | C15: 44897 | D15: Infographies Xperia 5M4 | E15: Astrid Jean-Baptiste | F15: Delivered | G15: Xperia | H15: https://saranistudio-my.sharepoint.com/:f:/g/personal/team_sarani_studio/Eu6UoQJssNdAvleXAzibZ1MBJ1RpI-TWGcduRRM37c84hw?e=4VncEj | I15: =IF(SUM(P15:AV15)=0,"-",SUM(P15:AV15)) -> 8 | J15: =IF(SUMPRODUCT($P$3:$AV$3,P15:AV15)=0,"-",SUMPRODUCT($P$3:$AV$3,P15:AV15)) -> 280 | K15: 14/12/2022 | L15: 4200631343 | M15: Sent | O15: ok | Q15: 8
A16: Sony | B16: SFR | C16: 44909 | D16: Newsletter PRT Décembre | E16: Alice Mucke | F16: Delivered | G16: DI | H16: - | I16: =IF(SUM(P16:AV16)=0,"-",SUM(P16:AV16)) -> 1 | J16: =IF(SUMPRODUCT($P$3:$AV$3,P16:AV16)=0,"-",SUMPRODUCT($P$3:$AV$3,P16:AV16)) -> 600 | K16: 15/12/2022 | L16: 4200639267 | M16: Sent | AH16: 1
A17: Sony | B17: SFR | C17: 44914 | D17: OP FAITES VOTRE CINEMA | E17: Astrid Jean-Baptiste | F17: Delivered | G17: DI | H17: https://saranistudio-my.sharepoint.com/:f:/g/personal/team_sarani_studio/EuGwoElxdVxAqUlHd5jwPl0Bd9dIrtw0j4nHaTHU_C0F4Q?e=k1zDEI | I17: =IF(SUM(P17:AV17)=0,"-",SUM(P17:AV17)) -> 7 | J17: =IF(SUMPRODUCT($P$3:$AV$3,P17:AV17)=0,"-",SUMPRODUCT($P$3:$AV$3,P17:AV17)) -> 330 | K17: 44931 | L17: 4200633114 | M17: Sent | O17: ok | P17: 1 | Q17: 6
A18: Sony | B18: SFR | C18: 44914 | D18: VITRO A7RV | E18: Astrid Jean-Baptiste | F18: Delivered | G18: DI | H18: https://saranistudio-my.sharepoint.com/:f:/g/personal/team_sarani_studio/El0REgOxzW1Eiu8AI5a8WPQBuRgA-xuGK77IgcuOUuwGhw?e=jWWT4e | I18: =IF(SUM(P18:AV18)=0,"-",SUM(P18:AV18)) -> 20 | J18: =IF(SUMPRODUCT($P$3:$AV$3,P18:AV18)=0,"-",SUMPRODUCT($P$3:$AV$3,P18:AV18)) -> 895 | K18: 44943 | L18: 4200633341 | M18: Sent | O18: ok | W18: 1 | X18: 19
A19: Sony | B19: SFR | C19: 44914 | D19: PANNEAU PHOTO HAUT VITRINE | E19: Astrid Jean-Baptiste | F19: Delivered | G19: DI | H19: https://saranistudio-my.sharepoint.com/:f:/g/personal/team_sarani_studio/En0xaWGTYWZOtWFNrWlERJYBEkKsluD4U7oLp_2fMTfyPA?e=3dNfLG | I19: =IF(SUM(P19:AV19)=0,"-",SUM(P19:AV19)) -> 11 | J19: =IF(SUMPRODUCT($P$3:$AV$3,P19:AV19)=0,"-",SUMPRODUCT($P$3:$AV$3,P19:AV19)) -> 535 | K19: 44931 | L19: 4200633116 | M19: Sent | O19: ok | W19: 1 | X19: 10
A20: Sony | B20: SFR | C20: 44914 | D20: Winter Sales Banners adaptations | E20: Françoise Burgarella | F20: Delivered | G20: Cross | H20: https://saranistudio-my.sharepoint.com/:f:/g/personal/team_sarani_studio/EitZRBZy2n1Kkw5kaWztE5sBgYKU_BFeDcX25iDrx1Ct5w?e=j19Nkg | I20: =IF(SUM(P20:AV20)=0,"-",SUM(P20:AV20)) -> 18 | J20: 590 | K20: 22/12/2022 | L20: 4200641797 | M20: Sent | P20: 1 | Q20: 17
A21: Sony | B21: SFR | C21: 44916 | D21: Winter Sales Banners adaptations DI | E21: Astrid Jean-Baptiste | F21: Delivered | G21: DI | H21: https://saranistudio-my.sharepoint.com/:f:/g/personal/team_sarani_studio/EitZRBZy2n1Kkw5kaWztE5sBgYKU_BFeDcX25iDrx1Ct5w?e=j19Nkg | I21: =IF(SUM(P21:AV21)=0,"-",SUM(P21:AV21)) -> 9 | J21: =190+4*35 -> 330 | K21: 44931 | L21: 4200632799 | M21: Sent | O21: ok | Q21: 9
A22: Sony | B22: SFR | C22: 44917 | D22: Micromania Boites Factices Update | E22: Alice Mucke | F22: Delivered | G22: Other | H22: https://saranistudio-my.sharepoint.com/:f:/g/personal/team_sarani_studio/Ehi8kv4332BOmhmF0GTdxqcBXMS0bXPqJJq-QzgW5N5jlg?e=BJOqXJ | I22: =IF(SUM(P22:AV22)=0,"-",SUM(P22:AV22)) -> 5 | J22: =IF(SUMPRODUCT($P$3:$AV$3,P22:AV22)=0,"-",SUMPRODUCT($P$3:$AV$3,P22:AV22)) -> 360 | K22: 44931 | L22: 4200635815 | M22: Sent | X22: 4 | AA22: 1
A23: Sony | B23: SFR | C23: 44923 | D23: Invitation Dealers Days | E23: Héloïse Leroy | F23: Delivered | G23: Cross | H23: https://saranistudio-my.sharepoint.com/:f:/g/personal/team_sarani_studio/EqmJWhjv9h9NosYk49rtluQBxvyRtTDdxMXLJdwMK-1B6g?e=mNiTFd | I23: =IF(SUM(P23:AV23)=0,"-",SUM(P23:AV23)) -> 0.5 | J23: =IF(SUMPRODUCT($P$3:$AV$3,P23:AV23)=0,"-",SUMPRODUCT($P$3:$AV$3,P23:AV23)) -> 300 | K23: 44931 | L23: 4200634748 | M23: Sent | AH23: 0.5
A24: Sony | B24: SFR | C24: 44928 | D24: Banners Inzone soldes | E24: Léa Novio | F24: Delivered | G24: TV | H24: https://saranistudio-my.sharepoint.com/:f:/g/personal/team_sarani_studio/EuGDS2OAMPpGu_ldGvZT0DMBpcZ-xeMJpp8v2XzS9CAt0g?e=xhsdm9 | I24: =IF(SUM(P24:AV24)=0,"-",SUM(P24:AV24)) -> 6 | J24: =IF(SUMPRODUCT($P$3:$AV$3,P24:AV24)=0,"-",SUMPRODUCT($P$3:$AV$3,P24:AV24)) -> 380 | K24: 44931 | L24: 4200633093 | M24: Sent | P24: 2 | Q24: 4
A25: Sony | B25: SFR | C25: 44928 | D25: OP FX3 Assets | E25: Astrid Jean-Baptiste | F25: Delivered | G25: DI | H25: https://saranistudio-my.sharepoint.com/:f:/g/personal/team_sarani_studio/EitCbbZcUbZAkfWL7WBLee8BGH7SK4bXE2Dt7jdZHoYz1g?e=PygYN7 | I25: =IF(SUM(P25:AV25)=0,"-",SUM(P25:AV25)) -> 6 | J25: =IF(SUMPRODUCT($P$3:$AV$3,P25:AV25)=0,"-",SUMPRODUCT($P$3:$AV$3,P25:AV25)) -> 295 | K25: 44931 | L25: 4200632673 | M25: Sent | O25: ok | P25: 1 | Q25: 5
A26: Sony | B26: SFR | C26: 44928 | D26: OP Trade In Janvier | E26: Astrid Jean-Baptiste | F26: Delivered | G26: DI | H26: https://saranistudio-my.sharepoint.com/:f:/g/personal/team_sarani_studio/EoitW15aeoVAtVoerfyyJgAB8NtwzeqQjRMP7QJz7L-yow?e=jCYZtF | I26: =IF(SUM(P26:AV26)=0,"-",SUM(P26:AV26)) -> 6 | J26: =IF(SUMPRODUCT($P$3:$AV$3,P26:AV26)=0,"-",SUMPRODUCT($P$3:$AV$3,P26:AV26)) -> 295 | K26: 44931 | L26: 4200632670 | M26: Sent | O26: ok | P26: 1 | Q26: 5
A27: Sony | B27: SFR | C27: 44930 | D27: Infographies NW-A306 | E27: Laura Vivient | F27: Delivered | G27: V&S | H27: https://saranistudio-my.sharepoint.com/:f:/g/personal/team_sarani_studio/Ev8VV5oNGQpDt88C9YGvPJ0BeWvCOnfN80JI8f52rlCkDA?e=svUNka | I27: =IF(SUM(P27:AV27)=0,"-",SUM(P27:AV27)) -> 9 | J27: =IF(SUMPRODUCT($P$3:$AV$3,P27:AV27)=0,"-",SUMPRODUCT($P$3:$AV$3,P27:AV27)) -> 315 | K27: 44943 | L27: 4200634882 | M27: Sent | Q27: 9
A28: Sony | B28: SFR | C28: 44930 | D28: HAV Brief créa ILV A4 accessoires | E28: Léa Novio | F28: Delivered | G28: TV | H28: https://saranistudio-my.sharepoint.com/:f:/g/personal/team_sarani_studio/ErATZuFVVhFNvJLA8_C_5_kBPisr2V-sQmmcvuADdnOrlg?e=Jt6Yhl | I28: =IF(SUM(P28:AV28)=0,"-",SUM(P28:AV28)) -> 4 | J28: =IF(SUMPRODUCT($P$3:$AV$3,P28:AV28)=0,"-",SUMPRODUCT($P$3:$AV$3,P28:AV28)) -> 300 | K28: 44941 | L28: 4200635620 | M28: Sent | X28: 3 | Y28: 1
A29: Sony | B29: SFR | C29: 44931 | D29: CREA SOLDES - XB300 | E29: Françoise Burgarella | F29: Delivered | G29: V&S | H29: https://saranistudio-my.sharepoint.com/:f:/g/personal/team_sarani_studio/EqOyYJkBr71FjjKi8T4TbU8BmZDWzGHq4lIzmPemScoNIg?e=gSGgM9 | I29: =IF(SUM(P29:AV29)=0,"-",SUM(P29:AV29)) -> 4 | J29: =IF(SUMPRODUCT($P$3:$AV$3,P29:AV29)=0,"-",SUMPRODUCT($P$3:$AV$3,P29:AV29)) -> 140 | K29: 44942 | L29: 4200633321 | M29: Sent | Q29: 4
A30: Sony | B30: SFR | C30: 44936 | D30: Update - Plan merch DI | E30: Alice Mucke | F30: Delivered | G30: DI | H30: https://saranistudio-my.sharepoint.com/:f:/g/personal/team_sarani_studio/EgL726Ww1tBPiY3JLeGkgKABHLa4iBWeCZvZMffXcTD0Ow?e=Ev0d8h | I30: =IF(SUM(P30:AV30)=0,"-",SUM(P30:AV30)) -> 2 | J30: 250 | K30: 45006 | L30: 4200639269 | M30: Sent | AB30: 2
A31: Sony | B31: SFR | C31: 44938 | D31: Additional DI assets | E31: Alice Mucke | F31: Delivered | G31: DI | H31: https://saranistudio-my.sharepoint.com/:f:/g/personal/team_sarani_studio/EitZRBZy2n1Kkw5kaWztE5sBgYKU_BFeDcX25iDrx1Ct5w?e=j19Nkg | I31: =IF(SUM(P31:AV31)=0,"-",SUM(P31:AV31)) -> 4 | J31: =IF(SUMPRODUCT($P$3:$AV$3,P31:AV31)=0,"-",SUMPRODUCT($P$3:$AV$3,P31:AV31)) -> 145 | K31: 44941 | L31: 4200639281 | M31: Sent | Q31: 3 | X31: 1
A32: Sony | B32: SFR | C32: 44938 | D32: PSK - Refresh Inlay display PSK HYPERS | E32: Laura Vivient | F32: Delivered | G32: V&S | H32: https://saranistudio-my.sharepoint.com/:f:/g/personal/team_sarani_studio/EtI6MF01VhJDu73LzSQ3CuMBaxqkBPUNcHfWG9NmZXKZGA?e=cAjunF | I32: =IF(SUM(P32:AV32)=0,"-",SUM(P32:AV32)) -> 2 | J32: =IF(SUMPRODUCT($P$3:$AV$3,P32:AV32)=0,"-",SUMPRODUCT($P$3:$AV$3,P32:AV32)) -> 80 | K32: 44941 | L32: 4270024966 | M32: Sent | X32: 2
A33: Sony | B33: SFR | C33: 44942 | D33: Newsletter PRT Janvier | E33: Alice Mucke | F33: Delivered | G33: DI | H33: - | I33: =IF(SUM(P33:AV33)=0,"-",SUM(P33:AV33)) -> 1 | J33: =IF(SUMPRODUCT($P$3:$AV$3,P33:AV33)=0,"-",SUMPRODUCT($P$3:$AV$3,P33:AV33)) -> 600 | K33: 44950 | L33: 4200639268 | M33: Sent | AH33: 1
A34: Sony | B34: SFR | C34: 44943 | D34: Lenses 3D Virtual Showroom | E34: Alice Mucke | F34: Delivered | G34: DI | H34: - | I34: =IF(SUM(P34:AV34)=0,"-",SUM(P34:AV34)) -> 1.2 | J34: =IF(SUMPRODUCT($P$3:$AV$3,P34:AV34)=0,"-",SUMPRODUCT($P$3:$AV$3,P34:AV34)) -> 3000 | K34: 44950 | L34: 4200639270 | M34: Sent | N34: 63659 | O34: Paid | AS34: =3000/2500 -> 1.2
A35: Sony | B35: SFR | C35: 44943 | D35: Bannières New VX8030 | E35: Astrid Jean-Baptiste | F35: Delivered | G35: DI | H35: https://saranistudio-my.sharepoint.com/:f:/g/personal/team_sarani_studio/EksBlAWoBtxAkG5l32B3Di0BbzDMWHG22vO5j0H6ctS9zw?e=RqK3BS | I35: =IF(SUM(P35:AV35)=0,"-",SUM(P35:AV35)) -> 4 | J35: =IF(SUMPRODUCT($P$3:$AV$3,P35:AV35)=0,"-",SUMPRODUCT($P$3:$AV$3,P35:AV35)) -> 140 | K35: 44950 | L35: 4200633858 | M35: Sent | O35: ok | Q35: 4
A36: Sony | B36: SFR | C36: 44944 | D36: HAS - podium High Power Leclerc | E36: Laura Vivient | F36: Delivered | G36: V&S | H36: https://saranistudio-my.sharepoint.com/:f:/g/personal/team_sarani_studio/Euz7AgxtBlxIhnwZ-lXXmF4BeflqaS0GTyKxYGbCz-vMlw?e=IjE9RV | I36: =IF(SUM(P36:AV36)=0,"-",SUM(P36:AV36)) -> 5 | J36: =IF(SUMPRODUCT($P$3:$AV$3,P36:AV36)=0,"-",SUMPRODUCT($P$3:$AV$3,P36:AV36)) -> 485 | K36: 44963 | L36: 4200634883 | M36: Sent | W36: 3 | X36: 2
A37: Sony | B37: SFR | C37: 44951 | D37: Dealer Days 2023 DI | E37: Héloïse Leroy | F37: Delivered | G37: Cross | H37: https://saranistudio-my.sharepoint.com/:f:/g/personal/team_sarani_studio/EmLaqFBj_51MjXZHYWWXnkoBLAa6nzoR1xsPq4BDMu7-cw?e=t3K8Ml | I37: =IF(SUM(P37:AV37)=0,"-",SUM(P37:AV37)) -> 3 | J37: =IF(SUMPRODUCT($P$3:$AV$3,P37:AV37)=0,"-",SUMPRODUCT($P$3:$AV$3,P37:AV37)) -> 310 | K37: 44963 | L37: 4200635109 | M37: Sent | W37: 2 | X37: 1
A38: Sony | B38: SFR | C38: 44951 | D38: HAV ILV4 et Awards | E38: Léa Novio | F38: Delivered | G38: TV | H38: https://saranistudio-my.sharepoint.com/:f:/g/personal/team_sarani_studio/EiFOxcsYWW5HrKMAqEXG268BJdUb73tokZ2aUpOjrqGbMw?e=ZjeN6x | I38: =IF(SUM(P38:AV38)=0,"-",SUM(P38:AV38)) -> 2 | J38: =IF(SUMPRODUCT($P$3:$AV$3,P38:AV38)=0,"-",SUMPRODUCT($P$3:$AV$3,P38:AV38)) -> 215 | K38: 44963 | L38: 4200638979 | M38: Sent | Q38: 1 | Y38: 1
A39: Sony | B39: SFR | C39: 44956 | D39: Glorifier Boulanger ZV 1F | E39: Astrid Jean-Baptiste | F39: Delivered | G39: DI | H39: https://saranistudio-my.sharepoint.com/:f:/g/personal/team_sarani_studio/Et8JT6N3J55Khs36INxlBgQBUbyHbYyC93L5UVW3Wg41vA?e=Q1dlBF | I39: =IF(SUM(P39:AV39)=0,"-",SUM(P39:AV39)) -> 2 | J39: =IF(SUMPRODUCT($P$3:$AV$3,P39:AV39)=0,"-",SUMPRODUCT($P$3:$AV$3,P39:AV39)) -> 270 | K39: 44963 | L39: 4200636045 | M39: Sent | O39: ok | W39: 2
A40: Sony | B40: SFR | C40: 44956 | D40: LANCEMENT CH720 / CH520 | E40: Laura Vivient | F40: Delivered | G40: V&S | H40: https://saranistudio-my.sharepoint.com/:f:/g/personal/team_sarani_studio/EqrCH40AdxVPsCGpjT8TB8wB_B709B2_yzvFX8TAKmXMlg?e=JQ9afM | I40: =IF(SUM(P40:AV40)=0,"-",SUM(P40:AV40)) -> 27 | J40: =IF(SUMPRODUCT($P$3:$AV$3,P40:AV40)=0,"-",SUMPRODUCT($P$3:$AV$3,P40:AV40)) -> 945 | K40: 44963 | L40: 4200637328 | M40: Sent | Q40: 27
A41: Sony | B41: SFR | C41: 44958 | D41: OP Les belles ouvertures 2 | E41: Astrid Jean-Baptiste | F41: Delivered | G41: DI | H41: https://saranistudio-my.sharepoint.com/:f:/g/personal/team_sarani_studio/EoXM_bPXFQtOqtOuolOqWAQBFcKOS1eXgcsuycPvj9witg?e=ACLkrl | I41: =IF(SUM(P41:AV41)=0,"-",SUM(P41:AV41)) -> 6 | J41: =IF(SUMPRODUCT($P$3:$AV$3,P41:AV41)=0,"-",SUMPRODUCT($P$3:$AV$3,P41:AV41)) -> 295 | K41: https://saranistudio-my.sharepoint.com/:b:/g/personal/team_sarani_studio/EWLP_vMxED9FmUZQ_nOkkJwBjJNjECiaaIw3yVFqt7yTpQ?e=R7ciE8 | L41: - | P41: 1 | Q41: 5
A42: Sony | B42: SFR | C42: 44958 | D42: OP Extension de garantie | E42: Astrid Jean-Baptiste | F42: Delivered | G42: DI | H42: https://saranistudio-my.sharepoint.com/:f:/g/personal/team_sarani_studio/EhmXSE3SqJlLttJIjP3d1EwBO-MeT52KYDPXcUnZ4UeiYQ?e=EPq6RY | I42: =IF(SUM(P42:AV42)=0,"-",SUM(P42:AV42)) -> 6 | J42: =IF(SUMPRODUCT($P$3:$AV$3,P42:AV42)=0,"-",SUMPRODUCT($P$3:$AV$3,P42:AV42)) -> 295 | K42: https://saranistudio-my.sharepoint.com/:b:/g/personal/team_sarani_studio/EeqqQcvt8QpJhIrMKvXrqeMBVFpg9cjIOvDd7UQb-ahIQg?e=Va6RIJ | P42: 1 | Q42: 5
A43: Sony | B43: SFR | C43: 44964 | D43: Fiche produit WHCH720-520N | E43: Laura Vivient | F43: Delivered | G43: V&S | H43: https://saranistudio-my.sharepoint.com/:f:/g/personal/team_sarani_studio/EjWeixWwgG9KtdKsd3nfu10B4P2-8KWwWAHTtBQASfQ6Rg?e=c0kl8T | I43: =IF(SUM(P43:AV43)=0,"-",SUM(P43:AV43)) -> 2 | J43: =IF(SUMPRODUCT($P$3:$AV$3,P43:AV43)=0,"-",SUMPRODUCT($P$3:$AV$3,P43:AV43)) -> 500 | K43: 44978 | L43: 4200637327 | M43: Sent | Z43: 2
A44: Sony | B44: SFR | C44: 44964 | D44: Adaptation WE LIVE FOR THE MUSIC backdrop LOCAL | E44: Laura Vivient | F44: Delivered | G44: V&S | H44: https://saranistudio-my.sharepoint.com/:f:/g/personal/team_sarani_studio/EhV2y_XPV35GlXBIYHQS6jABX0y5PDDKSwC4di7PXUrm9w?e=g9nzP1 | I44: =IF(SUM(P44:AV44)=0,"-",SUM(P44:AV44)) -> 5 | J44: =IF(SUMPRODUCT($P$3:$AV$3,P44:AV44)=0,"-",SUMPRODUCT($P$3:$AV$3,P44:AV44)) -> 200 | K44: 44978 | L44: 4200637329 | M44: Sent | X44: 5
A45: Sony | B45: SFR | C45: 44965 | D45: OP Tryptique | E45: Astrid Jean-Baptiste | F45: Delivered | G45: DI | H45: https://saranistudio-my.sharepoint.com/:f:/g/personal/team_sarani_studio/Evv4GLCeCfpNtcFppwmuF4gBs0wDfkYfUCp2XZgOusP4jA?e=VUWW5q | I45: =IF(SUM(P45:AV45)=0,"-",SUM(P45:AV45)) -> 6 | J45: =IF(SUMPRODUCT($P$3:$AV$3,P45:AV45)=0,"-",SUMPRODUCT($P$3:$AV$3,P45:AV45)) -> 210 | K45: 44978 | L45: 4200639098 | M45: Sent | O45: ok | Q45: 6
A46: Sony | B46: SFR | C46: 44970 | D46: Inlay CH720 | E46: Laura Vivient | F46: Delivered | G46: V&S | H46: https://saranistudio-my.sharepoint.com/:f:/g/personal/team_sarani_studio/EvdB_pa-nYlJjcn2m_-V6CIBlwvd0lovLbZhSbor2xacAQ?e=54JYDm | I46: =IF(SUM(P46:AV46)=0,"-",SUM(P46:AV46)) -> 4 | J46: =IF(SUMPRODUCT($P$3:$AV$3,P46:AV46)=0,"-",SUMPRODUCT($P$3:$AV$3,P46:AV46)) -> 350 | K46: 44978 | L46: 4200639013 | M46: Sent | W46: 2 | X46: 2
A47: Sony | B47: SFR | C47: 44970 | D47: OP Trade In Février | E47: Astrid Jean-Baptiste | F47: Delivered | G47: DI | H47: https://saranistudio-my.sharepoint.com/:f:/g/personal/team_sarani_studio/Eslmo5VnmeBOls9PXeiKfcsB6Y_V2-ku-io7Yd_KczQicQ?e=vV1ZSQ | I47: =IF(SUM(P47:AV47)=0,"-",SUM(P47:AV47)) -> 11 | J47: =IF(SUMPRODUCT($P$3:$AV$3,P47:AV47)=0,"-",SUMPRODUCT($P$3:$AV$3,P47:AV47)) -> 495 | K47: 44978 | L47: 4200636098 | M47: Sent | O47: ok | P47: 1 | Q47: 5 | X47: 5
A48: Sony | B48: SFR | C48: 44971 | D48: OP REMISE IMMEDIATE DI | E48: Astrid Jean-Baptiste | F48: Delivered | G48: DI | H48: https://saranistudio-my.sharepoint.com/:f:/g/personal/team_sarani_studio/Emm2wYCHbftLi5SQSqzjQ6wB8eW0AeAyCmSo_d-F4O4-gw?e=aIQngs | I48: =IF(SUM(P48:AV48)=0,"-",SUM(P48:AV48)) -> 13 | J48: =IF(SUMPRODUCT($P$3:$AV$3,P48:AV48)=0,"-",SUMPRODUCT($P$3:$AV$3,P48:AV48)) -> 660 | K48: 44978 | L48: 4200639098 | M48: Sent | O48: ok | P48: 1 | Q48: 7 | W48: 1 | X48: 4
A49: Sony | B49: SFR | C49: 44973 | D49: Newsletter PRT Février | E49: Alice Mucke | F49: Delivered | G49: DI | H49: - | I49: =IF(SUM(P49:AV49)=0,"-",SUM(P49:AV49)) -> 1 | J49: =IF(SUMPRODUCT($P$3:$AV$3,P49:AV49)=0,"-",SUMPRODUCT($P$3:$AV$3,P49:AV49)) -> 600 | K49: 44973 | L49: 4200636262 | M49: sent | AH49: 1
A50: Sony | B50: SFR | C50: 44974 | D50: Amazon Les jours Sony | E50: Joelle Mechache | F50: Delivered | G50: Cross | H50: https://saranistudio-my.sharepoint.com/:f:/g/personal/team_sarani_studio/Evzfu13U4IpLp3GoN-MrbKcB6voUMWbQ-KWviKSEWfxHyA?e=u1uaJh | I50: =IF(SUM(P50:AV50)=0,"-",SUM(P50:AV50)) -> 2 | J50: =IF(SUMPRODUCT($P$3:$AV$3,P50:AV50)=0,"-",SUMPRODUCT($P$3:$AV$3,P50:AV50)) -> 240 | K50: 44981 | L50: 4200639291 | M50: sent | P50: 2
A51: Sony | B51: SFR | C51: 44977 | D51: MDR - FNAC NEW WALL A4 | E51: Laura Vivient | F51: Delivered | G51: V&S | H51: https://saranistudio-my.sharepoint.com/:f:/g/personal/team_sarani_studio/EplbkOAQ_RVKlimX_vm_Yz4BYsRWiropgEjSV64xwAiFlQ?e=QjcDN1 | I51: =IF(SUM(P51:AV51)=0,"-",SUM(P51:AV51)) -> 1 | J51: =IF(SUMPRODUCT($P$3:$AV$3,P51:AV51)=0,"-",SUMPRODUCT($P$3:$AV$3,P51:AV51)) -> 135 | K51: 44978 | L51: 4200638974 | M51: Sent | W51: 1
A52: Sony | B52: SFR | C52: 44977 | D52: Brief Sony Bannières Bravia Core Boulanger | E52: Maureen Masson | F52: Delivered | G52: TV | H52: https://saranistudio-my.sharepoint.com/:f:/g/personal/team_sarani_studio/Eqe3rBnlph1BiwQsMsq2QLkBMf2xPp5Wnzudz7Z8Kwje7Q?e=SJbPDi | I52: =IF(SUM(P52:AV52)=0,"-",SUM(P52:AV52)) -> 1 | J52: =IF(SUMPRODUCT($P$3:$AV$3,P52:AV52)=0,"-",SUMPRODUCT($P$3:$AV$3,P52:AV52)) -> 120 | K52: 44981 | L52: 4200639008 | M52: sent | P52: 1
A53: Sony | B53: SFR | C53: 44979 | D53: MDR - Offline POS CH720N CH520 | E53: Laura Vivient | F53: Delivered | G53: V&S | H53: https://saranistudio-my.sharepoint.com/:f:/g/personal/team_sarani_studio/EvQORSWeLIhCmtRAW0oiAUwBTsJV6BOljIGWmUFQwsMZaw?e=d5u6bG | I53: =IF(SUM(P53:AV53)=0,"-",SUM(P53:AV53)) -> 10 | J53: =IF(SUMPRODUCT($P$3:$AV$3,P53:AV53)=0,"-",SUMPRODUCT($P$3:$AV$3,P53:AV53)) -> 780 | K53: 44981 | L53: 4200639014 | M53: Sent | W53: 4 | X53: 6
A54: Sony | B54: SFR | C54: 44986 | D54: Synchro HAV lancements TV FY23 | E54: Laura Vivient | F54: Delivered | G54: HAV | H54: https://saranistudio-my.sharepoint.com/:f:/g/personal/team_sarani_studio/ElN1J_IN9NhPr2CeLrCnszQBKTAJ_nOdr-HrnPgQqoGmgA?e=2DZGUU | I54: =IF(SUM(P54:AV54)=0,"-",SUM(P54:AV54)) -> 4 | J54: =IF(SUMPRODUCT($P$3:$AV$3,P54:AV54)=0,"-",SUMPRODUCT($P$3:$AV$3,P54:AV54)) -> 540 | K54: 44981 | L54: 4200639227 | M54: Sent | W54: 4
A55: Sony | B55: SFR | C55: 44986 | D55: HAV Cashback | E55: Laura Vivient | F55: Delivered | G55: HAV | H55: https://saranistudio-my.sharepoint.com/:f:/g/personal/team_sarani_studio/EsMnikTmJL1KpvYorntrkkABl8AjzYKd5G85aBnUnFq9Iw?e=TuaAG2 | I55: =IF(SUM(P55:AV55)=0,"-",SUM(P55:AV55)) -> 11 | J55: =IF(SUMPRODUCT($P$3:$AV$3,P55:AV55)=0,"-",SUMPRODUCT($P$3:$AV$3,P55:AV55)) -> 470 | K55: 44981 | L55: 4200639226 | M55: sent | P55: 1 | Q55: 10
A56: Sony | B56: SFR | C56: 44994 | D56: Welcome to VLOG | E56: Astrid Jean-Baptiste | F56: Delivered | G56: DI | H56: https://saranistudio-my.sharepoint.com/:f:/g/personal/team_sarani_studio/Evv8Y4u5CcpBkA6LoIczitQBWRTN97zK7m4SmXnl8monYA?e=FXqhEq | I56: =IF(SUM(P56:AV56)=0,"-",SUM(P56:AV56)) -> 10 | J56: =IF(SUMPRODUCT($P$3:$AV$3,P56:AV56)=0,"-",SUMPRODUCT($P$3:$AV$3,P56:AV56)) -> 445 | K56: 45006 | L56: 4200640853 | M56: sent | O56: ok | P56: 1 | Q56: 7 | X56: 2
A57: Sony | B57: SFR | C57: 45001 | D57: Web banner WF-C700 WH-1000XM5 | E57: Laura Vivient | F57: Delivered | G57: V&S | H57: https://saranistudio-my.sharepoint.com/:f:/g/personal/team_sarani_studio/Eo2562j1PBhFsm0D9eCdORoBS6przlDgwVkoQg0sOXiM3A?e=yrz1uS | I57: =IF(SUM(P57:AV57)=0,"-",SUM(P57:AV57)) -> 9 | J57: =IF(SUMPRODUCT($P$3:$AV$3,P57:AV57)=0,"-",SUMPRODUCT($P$3:$AV$3,P57:AV57)) -> 570 | K57: 44981 | L57: 4200640930 | M57: sent | P57: 3 | Q57: 6
A58: Sony | B58: SFR | C58: 45005 | D58: Bannières awards | E58: Maureen Masson | F58: Delivered | G58: V&S | H58: https://saranistudio-my.sharepoint.com/:f:/g/personal/team_sarani_studio/EsAgXdGVXc1Bqb3hwi8zpSEBcRj8U2XkFGSGV62rqumcjw?e=mIcDe6 | I58: =IF(SUM(P58:AV58)=0,"-",SUM(P58:AV58)) -> 2 | J58: =IF(SUMPRODUCT($P$3:$AV$3,P58:AV58)=0,"-",SUMPRODUCT($P$3:$AV$3,P58:AV58)) -> 240 | K58: 45005 | L58: 4200639051 | M58: sent | P58: 2
A59: Sony | B59: SFR | C59: 45005 | D59: Adaptation Landing Page FY23 | E59: Maureen Masson | F59: - | G59: TV | H59: - | I59: =IF(SUM(P59:AV59)=0,"-",SUM(P59:AV59)) -> 0.83333333 | J59: =IF(SUMPRODUCT($P$3:$AV$3,P59:AV59)=0,"-",SUMPRODUCT($P$3:$AV$3,P59:AV59)) -> 1000 | K59: 45005 | L59: 4200639006 | M59: sent | AJ59: =1/1.2 -> 0.83333333
A60: Sony | B60: SFR | C60: 45005 | D60: Landing page Audio FY23 | E60: Maureen Masson | F60: - | G60: V&S | H60: - | I60: =IF(SUM(P60:AV60)=0,"-",SUM(P60:AV60)) -> 0.6 | J60: =IF(SUMPRODUCT($P$3:$AV$3,P60:AV60)=0,"-",SUMPRODUCT($P$3:$AV$3,P60:AV60)) -> 720 | K60: 45005 | L60: 4200638728 | M60: sent | N60: F2023-0419 | O60: PO number incorrect | AJ60: =0.6/1 -> 0.6
A61: Sony | B61: SFR | C61: 45006 | D61: Landing page Partenaires | E61: Alice Mucke | F61: - | G61: DI | H61: - | I61: =IF(SUM(P61:AV61)=0,"-",SUM(P61:AV61)) -> 0.83333333 | J61: =IF(SUMPRODUCT($P$3:$AV$3,P61:AV61)=0,"-",SUMPRODUCT($P$3:$AV$3,P61:AV61)) -> 1000 | K61: 45006 | L61: 4200639353 | M61: sent | AJ61: =1/1.2 -> 0.83333333
A62: Sony | B62: SFR | C62: 45006 | D62: Newsletter PRT Mars | E62: Alice Mucke | F62: - | G62: DI | H62: - | I62: =IF(SUM(P62:AV62)=0,"-",SUM(P62:AV62)) -> 1 | J62: =IF(SUMPRODUCT($P$3:$AV$3,P62:AV62)=0,"-",SUMPRODUCT($P$3:$AV$3,P62:AV62)) -> 600 | K62: 45006 | AH62: 1
A63: Sony | B63: SFR | C63: 45006 | D63: Lancement TV 2023 Assets | E63: Léa Novio | F63: Delivered | G63: TV | H63: - | I63: =SUM(I64:I78) -> 135 | J63: =SUM(J64:J78) -> 6130 | K63: 45006 | L63: 4200639031 | M63: sent
A64: Sony | B64: SFR | C64: 45006 | D64: Web Pop Crunchyroll | E64: Léa Novio | F64: Delivered | G64: TV | H64: https://saranistudio-my.sharepoint.com/:f:/g/personal/team_sarani_studio/Eqpu9-LPvfZElOAGt1viRf8Bhsdxnu1Eu10IOtnxqhR8Iw?e=2Uijzq | I64: =IF(SUM(P64:AV64)=0,"-",SUM(P64:AV64)) -> 1 | J64: =IF(SUMPRODUCT($P$3:$AV$3,P64:AV64)=0,"-",SUMPRODUCT($P$3:$AV$3,P64:AV64)) -> 120 | K64: - | P64: 1
A65: Sony | B65: SFR | C65: 45006 | D65: Lancement TV X80L | E65: Léa Novio | F65: Delivered | G65: TV | H65: https://saranistudio-my.sharepoint.com/:f:/g/personal/team_sarani_studio/EpbAZG5lEmVIiR_on7fzuLEB9DbDwGiQ8g3E-EP6ZMPlBw?e=WDYhbk | I65: =IF(SUM(P65:AV65)=0,"-",SUM(P65:AV65)) -> 20 | J65: =IF(SUMPRODUCT($P$3:$AV$3,P65:AV65)=0,"-",SUMPRODUCT($P$3:$AV$3,P65:AV65)) -> 730 | K65: - | Q65: 14 | X65: 6
A66: Sony | B66: SFR | C66: 45006 | D66: Lancement TV A80L | E66: Léa Novio | F66: Delivered | G66: TV | H66: https://saranistudio-my.sharepoint.com/:f:/g/personal/team_sarani_studio/EpbAZG5lEmVIiR_on7fzuLEB9DbDwGiQ8g3E-EP6ZMPlBw?e=WDYhbk | I66: =IF(SUM(P66:AV66)=0,"-",SUM(P66:AV66)) -> 21 | J66: =IF(SUMPRODUCT($P$3:$AV$3,P66:AV66)=0,"-",SUMPRODUCT($P$3:$AV$3,P66:AV66)) -> 770 | K66: - | Q66: 14 | X66: 7
A67: Sony | B67: SFR | C67: 45006 | D67: Spiderman Screenfill A80 | E67: Léa Novio | F67: Delivered | G67: TV | H67: https://saranistudio-my.sharepoint.com/:f:/g/personal/team_sarani_studio/Etv4q6mkEfNNic3xn8dvZO0BrqE8g3P8hL7SmR_Fp_I3wQ?e=9JittU | I67: =IF(SUM(P67:AV67)=0,"-",SUM(P67:AV67)) -> 4 | J67: =IF(SUMPRODUCT($P$3:$AV$3,P67:AV67)=0,"-",SUMPRODUCT($P$3:$AV$3,P67:AV67)) -> 225 | K67: - | P67: 1 | Q67: 3
A68: Sony | B68: SFR | C68: 45006 | D68: TV Bannières de lancement X80/A80 | E68: Léa Novio | F68: Delivered | G68: TV | H68: https://saranistudio-my.sharepoint.com/:f:/g/personal/team_sarani_studio/EjXst-lsglZAi0Q2IrrJuM4BaunLX6dQ9jdJrU_j-AJ-iA?e=BB0ACA | I68: =IF(SUM(P68:AV68)=0,"-",SUM(P68:AV68)) -> 12 | J68: =IF(SUMPRODUCT($P$3:$AV$3,P68:AV68)=0,"-",SUMPRODUCT($P$3:$AV$3,P68:AV68)) -> 590 | K68: - | P68: 2 | Q68: 10
A69: Sony | B69: SFR | C69: 45006 | D69: Brief leaflet & poster | E69: Léa Novio | F69: Delivered | G69: TV | H69: https://saranistudio-my.sharepoint.com/:f:/g/personal/team_sarani_studio/Et8Mg5FeJk1NtO-LbUI6GWIBaKP7wdAFxBlojd6prDrs-A?e=2HZ6NX | I69: =IF(SUM(P69:AV69)=0,"-",SUM(P69:AV69)) -> 4 | J69: =IF(SUMPRODUCT($P$3:$AV$3,P69:AV69)=0,"-",SUMPRODUCT($P$3:$AV$3,P69:AV69)) -> 720 | K69: - | Y69: 4
A70: Sony | B70: SFR | C70: 45006 | D70: TV FY23 Hero visuel webpop | E70: Léa Novio | F70: Delivered | G70: TV | H70: https://saranistudio-my.sharepoint.com/:f:/g/personal/team_sarani_studio/Ekw_x8Y39OdCmvbhTwiifiAB6YSU8f6NC-Wqd59I4hByhA?e=yq5q21 | I70: =IF(SUM(P70:AV70)=0,"-",SUM(P70:AV70)) -> 1 | J70: =IF(SUMPRODUCT($P$3:$AV$3,P70:AV70)=0,"-",SUMPRODUCT($P$3:$AV$3,P70:AV70)) -> 120 | K70: - | P70: 1
A71: Sony | B71: SFR | C71: 45006 | D71: INSCREEN STICKER VERTICAL | E71: Léa Novio | F71: Delivered | G71: TV | H71: https://saranistudio-my.sharepoint.com/:f:/g/personal/team_sarani_studio/Eja1rtCkq_5Jg3Wq74-bzXoBTCkVjZhgoxD1dq0yy1dWJQ?e=7VGydF | I71: =IF(SUM(P71:AV71)=0,"-",SUM(P71:AV71)) -> 2 | J71: =IF(SUMPRODUCT($P$3:$AV$3,P71:AV71)=0,"-",SUMPRODUCT($P$3:$AV$3,P71:AV71)) -> 80 | K71: - | X71: 2
A72: Sony | B72: SFR | C72: 45006 | D72: Bandeaux strip offline X85L ; X90L ; X95L ; X75WL | E72: Léa Novio | F72: - | G72: TV | H72: https://saranistudio-my.sharepoint.com/:f:/g/personal/team_sarani_studio/Eh0qjz1spy9PjbzagdXeAMoBf6kwU9cCsgMSuxS8Uk36pw?e=dCHHiS | I72: =IF(SUM(P72:AV72)=0,"-",SUM(P72:AV72)) -> 24 | J72: =IF(SUMPRODUCT($P$3:$AV$3,P72:AV72)=0,"-",SUMPRODUCT($P$3:$AV$3,P72:AV72)) -> 960 | K72: - | X72: 24
A73: Sony | B73: SFR | C73: 45006 | D73: Bandeaux strip offline A95L | E73: Léa Novio | F73: - | G73: TV | I73: =IF(SUM(P73:AV73)=0,"-",SUM(P73:AV73)) -> 7 | J73: =IF(SUMPRODUCT($P$3:$AV$3,P73:AV73)=0,"-",SUMPRODUCT($P$3:$AV$3,P73:AV73)) -> 280 | K73: - | X73: 7
A74: Sony | B74: SFR | C74: 45006 | D74: Webpop X85L | E74: Léa Novio | F74: Delivered | G74: TV | I74: =IF(SUM(P74:AV74)=0,"-",SUM(P74:AV74)) -> 6 | J74: =IF(SUMPRODUCT($P$3:$AV$3,P74:AV74)=0,"-",SUMPRODUCT($P$3:$AV$3,P74:AV74)) -> 210 | K74: - | Q74: 6
A75: Sony | B75: SFR | C75: 45006 | D75: Webpop X90L | E75: Léa Novio | F75: - | G75: TV | I75: =IF(SUM(P75:AV75)=0,"-",SUM(P75:AV75)) -> 11 | J75: =IF(SUMPRODUCT($P$3:$AV$3,P75:AV75)=0,"-",SUMPRODUCT($P$3:$AV$3,P75:AV75)) -> 385 | K75: - | Q75: 11
A76: Sony | B76: SFR | C76: 45006 | D76: Webpop X95L | E76: Léa Novio | F76: - | G76: TV | I76: =IF(SUM(P76:AV76)=0,"-",SUM(P76:AV76)) -> 8 | J76: =IF(SUMPRODUCT($P$3:$AV$3,P76:AV76)=0,"-",SUMPRODUCT($P$3:$AV$3,P76:AV76)) -> 280 | K76: - | Q76: 8
A77: Sony | B77: SFR | C77: 45006 | D77: Webpop X75WL | E77: Léa Novio | F77: - | G77: TV | I77: =IF(SUM(P77:AV77)=0,"-",SUM(P77:AV77)) -> 9 | J77: =IF(SUMPRODUCT($P$3:$AV$3,P77:AV77)=0,"-",SUMPRODUCT($P$3:$AV$3,P77:AV77)) -> 315 | K77: - | Q77: 9
A78: Sony | B78: SFR | C78: 45006 | D78: Bannières de lancement tous modèles | E78: Léa Novio | F78: Delivered | G78: TV | I78: =IF(SUM(P78:AV78)=0,"-",SUM(P78:AV78)) -> 5 | J78: =IF(SUMPRODUCT($P$3:$AV$3,P78:AV78)=0,"-",SUMPRODUCT($P$3:$AV$3,P78:AV78)) -> 345 | K78: - | O78: Voir avec Kenza | P78: 2 | Q78: 3
A79: Sony | B79: SFR | C79: 45008 | D79: Fiche Produit WF-C700 | E79: Laura Vivient | F79: Delivered | G79: V&S | H79: https://saranistudio-my.sharepoint.com/:f:/g/personal/team_sarani_studio/EsV2_KLDqwdOi0nyINCRhnABKsqCgrqSPww-zwD5kRW76g?e=55qEkF | I79: =IF(SUM(P79:AV79)=0,"-",SUM(P79:AV79)) -> 1 | J79: =IF(SUMPRODUCT($P$3:$AV$3,P79:AV79)=0,"-",SUMPRODUCT($P$3:$AV$3,P79:AV79)) -> 250 | K79: 45023 | L79: 4200640929 | M79: Sent | Z79: 1
A80: Sony | B80: SFR | C80: 45008 | D80: FY23 BRAVIA Launch extra assets | E80: Léa Novio | F80: Delivered | G80: TV | H80: https://saranistudio-my.sharepoint.com/:f:/g/personal/team_sarani_studio/EjXst-lsglZAi0Q2IrrJuM4BaunLX6dQ9jdJrU_j-AJ-iA?e=ZonV9A | I80: 15 | J80: 2190 | K80: 45008 | L80: 4200639284 | M80: Sent
A81: Sony | B81: SFR | C81: 45008 | D81: MDR - Assets OFFLINE WF-C700N | E81: Laura Vivient | F81: Delivered | G81: V&S | H81: https://saranistudio-my.sharepoint.com/:f:/g/personal/team_sarani_studio/Eh-XtLfnCf1LnsVtx5DtbCEBjY0SGdeSjDPwHzDnQHgN9w?e=2LU41r | I81: =IF(SUM(P81:AV81)=0,"-",SUM(P81:AV81)) -> 21 | J81: =IF(SUMPRODUCT($P$3:$AV$3,P81:AV81)=0,"-",SUMPRODUCT($P$3:$AV$3,P81:AV81)) -> 1695 | K81: 45023 | L81: 4200640938 | M81: Sent | W81: 9 | X81: 12
A82: Sony | B82: SFR | C82: 45012 | D82: ZV-E1 Launch assets | E82: Astrid Jean-Baptiste | F82: Delivered | G82: DI | H82: https://saranistudio-my.sharepoint.com/:f:/g/personal/team_sarani_studio/EvN6F1tLUb1HpsDsbcqLJpgBS_xatQW1Mdo30DXnEk4Umw?e=ZwLhqb | I82: =IF(SUM(P82:AV82)=0,"-",SUM(P82:AV82)) -> 15 | J82: =IF(SUMPRODUCT($P$3:$AV$3,P82:AV82)=0,"-",SUMPRODUCT($P$3:$AV$3,P82:AV82)) -> 550 | K82: 45008 | L82: 4200639687 | M82: Sent | O82: ok | Q82: 14 | S82: 1
A83: Sony | B83: SFR | C83: 45013 | D83: CROSS Produits + X80L + A80L​ | E83: Léa Novio | F83: Delivered | G83: TV | H83: https://saranistudio-my.sharepoint.com/:f:/g/personal/team_sarani_studio/EmtLIsoaTzxJnuMVqwFkEXEBRLxiJIn6Dx3sdurRJBv18Q?e=jb6qLr | I83: =IF(SUM(P83:AV83)=0,"-",SUM(P83:AV83)) -> 7 | J83: =IF(SUMPRODUCT($P$3:$AV$3,P83:AV83)=0,"-",SUMPRODUCT($P$3:$AV$3,P83:AV83)) -> 330 | K83: 45084 | L83: 4200648470 | M83: Sent | N83: F-(2023)-180 | O83: Paid 24/09/2023 | P83: 1 | Q83: 6
A84: Sony | B84: SFR | C84: 45022 | D84: HAV - offre caisson SW3 offert | E84: Laura Vivient | F84: Delivered | G84: V&S | H84: https://saranistudio-my.sharepoint.com/:f:/g/personal/team_sarani_studio/EkZE4Y3oDmxOgPwByulkRGQBO22GCn4XXiv8vxBWXU3BOQ?e=QYcm2Z | I84: =IF(SUM(P84:AV84)=0,"-",SUM(P84:AV84)) -> 3 | J84: =IF(SUMPRODUCT($P$3:$AV$3,P84:AV84)=0,"-",SUMPRODUCT($P$3:$AV$3,P84:AV84)) -> 405 | K84: 45035 | L84: 4200640937 | M84: Sent | W84: 3
A85: Sony | B85: SFR | C85: 45022 | D85: OP SUMMER | E85: Astrid Jean-Baptiste | F85: Delivered | G85: DI | H85: https://saranistudio-my.sharepoint.com/:f:/g/personal/team_sarani_studio/ErR6Cnz8koFJgGWWVv_vuxMB39tB1cZ0JkSx87G68Dab2A?e=ADHUf1 | I85: =IF(SUM(P85:AV85)=0,"-",SUM(P85:AV85)) -> 29 | J85: =IF(SUMPRODUCT($P$3:$AV$3,P85:AV85)=0,"-",SUMPRODUCT($P$3:$AV$3,P85:AV85)) -> 1330 | K85: 45035 | L85: 4200644207 | M85: Sent | O85: ok | Q85: 13 | W85: 1 | X85: 14 | Y85: 1
A86: Sony | B86: SFR | C86: 45027 | D86: Panneaux Photo Haut de meuble | E86: Astrid Jean-Baptiste | F86: Delivered | G86: DI | H86: https://saranistudio-my.sharepoint.com/:f:/g/personal/team_sarani_studio/Emr78pZYwmhKg7QstwR5YX8B_01h9nWSmEplb8WNjpatfQ?e=qLyHA4 | I86: =IF(SUM(P86:AV86)=0,"-",SUM(P86:AV86)) -> 13 | J86: =IF(SUMPRODUCT($P$3:$AV$3,P86:AV86)=0,"-",SUMPRODUCT($P$3:$AV$3,P86:AV86)) -> 805 | K86: 45035 | L86: 4200642825 | M86: Sent | O86: ok | W86: 3 | X86: 10
A87: Sony | B87: SFR | C87: 45033 | D87: BRIEF / FRENCH DAYS | E87: Françoise Burgarella | F87: Delivered | G87: Cross | H87: https://saranistudio-my.sharepoint.com/:f:/g/personal/team_sarani_studio/EhrI14UZk7dKhgchM2ASROYBdoIrI_P1svtBiXsGLwNAfg?e=fEdvZa | I87: =IF(SUM(P87:AV87)=0,"-",SUM(P87:AV87)) -> 18 | J87: =IF(SUMPRODUCT($P$3:$AV$3,P87:AV87)=0,"-",SUMPRODUCT($P$3:$AV$3,P87:AV87)) -> 715 | K87: 45035 | L87: 4200641787 | M87: Sent | P87: 1 | Q87: 17
A88: Sony | B88: SFR | C88: 45034 | D88: ZV-E1 Offline assets | E88: Astrid Jean-Baptiste | F88: Delivered | G88: DI | H88: https://saranistudio-my.sharepoint.com/:f:/g/personal/team_sarani_studio/EvN6F1tLUb1HpsDsbcqLJpgBS_xatQW1Mdo30DXnEk4Umw?e=ZwLhqb | I88: =IF(SUM(P88:AV88)=0,"-",SUM(P88:AV88)) -> 7 | J88: =IF(SUMPRODUCT($P$3:$AV$3,P88:AV88)=0,"-",SUMPRODUCT($P$3:$AV$3,P88:AV88)) -> 375 | K88: 45035 | L88: 4200644224 | M88: Sent | O88: ok | W88: 1 | X88: 6
A89: Sony | B89: SFR | C89: 26/04/23 | D89: HAV Cashback - Déclinaisons Online | E89: Laura Vivient | F89: Delivered | G89: HAV | H89: https://saranistudio-my.sharepoint.com/:f:/g/personal/team_sarani_studio/ErdSLaG4JVpLopEZ8cxzFtUBxHbje724J8NKcPC9cI4CxQ?e=TTH44r | I89: =IF(SUM(P89:AV89)=0,"-",SUM(P89:AV89)) -> 6 | J89: =IF(SUMPRODUCT($P$3:$AV$3,P89:AV89)=0,"-",SUMPRODUCT($P$3:$AV$3,P89:AV89)) -> 210 | K89: 45084 | L89: 4200645636 | M89: Sent | Q89: 6
A90: Sony | B90: SFR | C90: 26/04/23 | D90: OP FX30 | E90: Astrid Jean-Baptiste | F90: Delivered | G90: DI | H90: https://saranistudio-my.sharepoint.com/:f:/g/personal/team_sarani_studio/Eo_WrjVzYsBLghSpIKuCgJ4BkWtZHQIu_zjYECvNipC1AQ?e=7Ka5FQ | I90: =IF(SUM(P90:AV90)=0,"-",SUM(P90:AV90)) -> 5 | J90: =IF(SUMPRODUCT($P$3:$AV$3,P90:AV90)=0,"-",SUMPRODUCT($P$3:$AV$3,P90:AV90)) -> 365 | K90: 45071 | L90: 4200644333 | M90: sent | O90: ok | P90: 1 | Q90: 2 | W90: 1 | X90: 1
A91: Sony | B91: SFR | C91: 28/04/23 | D91: French Days - TV HAV réseaux sociaux | E91: Françoise Burgarella | F91: Delivered | G91: Cross | H91: https://saranistudio-my.sharepoint.com/:f:/g/personal/team_sarani_studio/Ess1vC7t3GRDlkrH39chUyABGRfHdGSAU5PEixcxFc0JLA?e=s28LEw | I91: =IF(SUM(P91:AV91)=0,"-",SUM(P91:AV91)) -> 2 | J91: =IF(SUMPRODUCT($P$3:$AV$3,P91:AV91)=0,"-",SUMPRODUCT($P$3:$AV$3,P91:AV91)) -> 70 | K91: https://saranistudio-my.sharepoint.com/:b:/g/personal/team_sarani_studio/Ecb_Wvnzn41Jms0Ozi5wOg0BgmWnsfYuKClAV_v1-WEylg?e=UjRbbG | L91: - | Q91: 2
A92: Sony | B92: SFR | C92: 45049 | D92: LANCEMENT XV800 Fiches produit | E92: Astrid Jean-Baptiste | F92: Delivered | G92: V&S | H92: https://saranistudio-my.sharepoint.com/:f:/g/personal/team_sarani_studio/EkLgT7b2GW1FiXyXqMeqvNoBaTEkUZ9CqiBTTtiXfQFnqw?e=bI4r6i | I92: =IF(SUM(P92:AV92)=0,"-",SUM(P92:AV92)) -> 1 | J92: =IF(SUMPRODUCT($P$3:$AV$3,P92:AV92)=0,"-",SUMPRODUCT($P$3:$AV$3,P92:AV92)) -> 250 | K92: 45084 | L92: 4200645668 | M92: sent | O92: ok | Z92: 1
A93: Sony | B93: SFR | C93: 45055 | D93: Sony INZONE Micromania | E93: Laura Vivient | F93: Delivered | G93: V&S | H93: https://saranistudio-my.sharepoint.com/:f:/g/personal/team_sarani_studio/Er1KKzEqwjxItH20UH-sjJMB6Q2eGPk-wVC73X09tW3j7w?e=yPEG2L | I93: =IF(SUM(P93:AV93)=0,"-",SUM(P93:AV93)) -> 10 | J93: =IF(SUMPRODUCT($P$3:$AV$3,P93:AV93)=0,"-",SUMPRODUCT($P$3:$AV$3,P93:AV93)) -> 365 | K93: 45084 | L93: 4200645628 | M93: sent | Q93: 7 | X93: 3
A94: Sony | B94: SFR | C94: 45056 | D94: WSK - XV800 Web banner | E94: Laura Vivient | F94: Delivered | G94: V&S | H94: https://saranistudio-my.sharepoint.com/:f:/g/personal/team_sarani_studio/Espt-U8X33FIn_OoCNAzUcYBPpS87vnP4camNLiVvGkeQA?e=kUXhS1 | I94: =IF(SUM(P94:AV94)=0,"-",SUM(P94:AV94)) -> 3 | J94: =IF(SUMPRODUCT($P$3:$AV$3,P94:AV94)=0,"-",SUMPRODUCT($P$3:$AV$3,P94:AV94)) -> 105 | K94: 45084 | L94: 4200645676 | M94: sent | Q94: 3
A95: Sony | B95: SFR | C95: 15/05/23 | D95: S2000 Web banners adaptations | E95: Laura Vivient | F95: Delivered | G95: HAV | H95: https://saranistudio-my.sharepoint.com/:f:/g/personal/team_sarani_studio/Es4vZNBp-AxAtvj3-nml6O4B84X7Wlgc4f3a4IkoogbN5Q?e=8YHYEj | I95: 3 | J95: 105 € | K95: https://saranistudio-my.sharepoint.com/:b:/g/personal/team_sarani_studio/EcR_bOe9wg5Oo1F73iFL_ZYBnCY5Z41ptfvKQMY4s7yT7Q?e=Yicbvw | L95: 4200645677 | M95: Sent | N95: F2023-0243 | O95: Unpaid | Q95: 3
A96: Sony | B96: SFR | C96: 15/05/23 | D96: Sony offre salariés - Visuel Promo | E96: Léa Novio | F96: Delivered | G96: CROSS | H96: https://saranistudio-my.sharepoint.com/:f:/g/personal/team_sarani_studio/EtK7hTypFuBHpDOePw_7ccgBRDwmVFet1fcnWhxQ1F1Cew?e=RoAcRf | I96: =IF(SUM(P96:AV96)=0,"-",SUM(P96:AV96)) -> 1 | J96: =IF(SUMPRODUCT($P$3:$AV$3,P96:AV96)=0,"-",SUMPRODUCT($P$3:$AV$3,P96:AV96)) -> 120 | K96: 45084 | L96: A déduire de 4200639284 | N96: A ne pas facturer | P96: 1
A97: Sony | B97: SFR | C97: 15/05/23 | D97: WSK - XV800 POS | E97: Laura Vivient | F97: Delivered | G97: V&S | H97: https://saranistudio-my.sharepoint.com/:f:/g/personal/team_sarani_studio/ElQaod7CY55KqoiGgYDoyv8B9dN5xE9O39YkvDCzlz6FLQ?e=5WSxf7 | I97: =IF(SUM(P97:AV97)=0,"-",SUM(P97:AV97)) -> 2 | J97: =IF(SUMPRODUCT($P$3:$AV$3,P97:AV97)=0,"-",SUMPRODUCT($P$3:$AV$3,P97:AV97)) -> 270 | K97: 45084 | L97: 4200645678 | M97: sent | W97: 2
A98: Sony | B98: SFR | C98: 16/05/23 | D98: Lancement XPERIA 1 V | E98: Astrid Jean-Baptiste | F98: Delivered | G98: Xperia | H98: https://saranistudio-my.sharepoint.com/:f:/g/personal/team_sarani_studio/Ejwkr_FCr89Nk4tFrjd8trMBGbqwHGBZWd-1CJbhqlgyGQ?e=K9fyxE | I98: =IF(SUM(P98:AV98)=0,"-",SUM(P98:AV98)) -> 8 | J98: =IF(SUMPRODUCT($P$3:$AV$3,P98:AV98)=0,"-",SUMPRODUCT($P$3:$AV$3,P98:AV98)) -> 710 | K98: 45070 | L98: 4200646347 | M98: Sent | O98: ok | Q98: 6 | Z98: 2
A99: Sony | B99: SFR | C99: 17/05/23 | D99: Lancement CX64800 Online | E99: Astrid Jean-Baptiste | F99: Delivered | G99: DI | H99: https://saranistudio-my.sharepoint.com/:f:/g/personal/team_sarani_studio/EtoGrfab8TBPqqqH2nHVI1gBmONIk1QrS4vWxTVcfPum0w?e=RQg19w | I99: =IF(SUM(P99:AV99)=0,"-",SUM(P99:AV99)) -> 9 | J99: =IF(SUMPRODUCT($P$3:$AV$3,P99:AV99)=0,"-",SUMPRODUCT($P$3:$AV$3,P99:AV99)) -> 510 | K99: https://saranistudio-my.sharepoint.com/:b:/g/personal/team_sarani_studio/EWpE3hXotlpGqUUf3-d076oBYc9ifdfAUM4r3WVYiVXhkw?e=WnxmrE | L99: 4200651991 | M99: Sent | N99: F-(2023)-227 | O99: Paid 28/11/2023 | P99: 2 | Q99: 6 | S99: 1
A100: Sony | B100: SFR | C100: 18/05/23 | D100: Xperia 1 & 10 V - Infographics | E100: Astrid Jean-Baptiste | F100: Delivered | G100: Xperia | H100: https://saranistudio-my.sharepoint.com/:f:/g/personal/team_sarani_studio/EslvmHj5SR1MhY8R-sw1arABPE3oMfscF8vtjzp50abaDw?e=r8aHPD | I100: =IF(SUM(P100:AV100)=0,"-",SUM(P100:AV100)) -> 17 | J100: =IF(SUMPRODUCT($P$3:$AV$3,P100:AV100)=0,"-",SUMPRODUCT($P$3:$AV$3,P100:AV100)) -> 595 | K100: 45070 | L100: 4200646326 | M100: sent | O100: ok | Q100: 17
...

Sheet Overview
A1: Performance Dashboard — Sony Projects
A3: REVENUS (€) | B3: 2022 | F3: 2023 | J3: 2024 | N3: 2025 | R3: 2026
B4: Q1 | C4: Q2 | D4: Q3 | E4: Q4 | F4: Q1 | G4: Q2 | H4: Q3 | I4: Q4 | J4: Q1 | K4: Q2 | L4: Q3 | M4: Q4 | N4: Q1 | O4: Q2 | P4: Q3 | Q4: Q4 | R4: Q1 | S4: Q2 | T4: Q3 | U4: Q4
A5: Sony France | B5: =SUMIFS('Sony France'!$N$4:$N$5001,'Sony France'!$F$4:$F$5001,">="&DATE(2022,1,1),'Sony France'!$F$4:$F$5001,"<="&DATE(2022,3,31)) -> 0 | C5: =SUMIFS('Sony France'!$N$4:$N$5001,'Sony France'!$F$4:$F$5001,">="&DATE(2022,4,1),'Sony France'!$F$4:$F$5001,"<="&DATE(2022,6,30)) -> 0 | D5: =SUMIFS('Sony France'!$N$4:$N$5001,'Sony France'!$F$4:$F$5001,">="&DATE(2022,7,1),'Sony France'!$F$4:$F$5001,"<="&DATE(2022,9,30)) -> 0 | E5: =SUMIFS('Sony France'!$N$4:$N$5001,'Sony France'!$F$4:$F$5001,">="&DATE(2022,10,1),'Sony France'!$F$4:$F$5001,"<="&DATE(2022,12,31)) -> 7475 | F5: =SUMIFS('Sony France'!$N$4:$N$5001,'Sony France'!$F$4:$F$5001,">="&DATE(2023,1,1),'Sony France'!$F$4:$F$5001,"<="&DATE(2023,3,31)) -> 27760 | G5: =SUMIFS('Sony France'!$N$4:$N$5001,'Sony France'!$F$4:$F$5001,">="&DATE(2023,4,1),'Sony France'!$F$4:$F$5001,"<="&DATE(2023,6,30)) -> 21464.17 | H5: =SUMIFS('Sony France'!$N$4:$N$5001,'Sony France'!$F$4:$F$5001,">="&DATE(2023,7,1),'Sony France'!$F$4:$F$5001,"<="&DATE(2023,9,30)) -> 23035 | I5: =SUMIFS('Sony France'!$N$4:$N$5001,'Sony France'!$F$4:$F$5001,">="&DATE(2023,10,1),'Sony France'!$F$4:$F$5001,"<="&DATE(2023,12,31)) -> 25643 | J5: =SUMIFS('Sony France'!$N$4:$N$5001,'Sony France'!$F$4:$F$5001,">="&DATE(2024,1,1),'Sony France'!$F$4:$F$5001,"<="&DATE(2024,3,31)) -> 18193 | K5: =SUMIFS('Sony France'!$N$4:$N$5001,'Sony France'!$F$4:$F$5001,">="&DATE(2024,4,1),'Sony France'!$F$4:$F$5001,"<="&DATE(2024,6,30)) -> 30285 | L5: =SUMIFS('Sony France'!$N$4:$N$5001,'Sony France'!$F$4:$F$5001,">="&DATE(2024,7,1),'Sony France'!$F$4:$F$5001,"<="&DATE(2024,9,30)) -> 23042 | M5: =SUMIFS('Sony France'!$N$4:$N$5001,'Sony France'!$F$4:$F$5001,">="&DATE(2024,10,1),'Sony France'!$F$4:$F$5001,"<="&DATE(2024,12,31)) -> 26065 | N5: =SUMIFS('Sony France'!$N$4:$N$5001,'Sony France'!$F$4:$F$5001,">="&DATE(2025,1,1),'Sony France'!$F$4:$F$5001,"<="&DATE(2025,3,31)) -> 20260 | O5: =SUMIFS('Sony France'!$N$4:$N$5001,'Sony France'!$F$4:$F$5001,">="&DATE(2025,4,1),'Sony France'!$F$4:$F$5001,"<="&DATE(2025,6,30)) -> 19590 | P5: =SUMIFS('Sony France'!$N$4:$N$5001,'Sony France'!$F$4:$F$5001,">="&DATE(2025,7,1),'Sony France'!$F$4:$F$5001,"<="&DATE(2025,9,30)) -> 21940 | Q5: =SUMIFS('Sony France'!$N$4:$N$5001,'Sony France'!$F$4:$F$5001,">="&DATE(2025,10,1),'Sony France'!$F$4:$F$5001,"<="&DATE(2025,12,31)) -> 22713 | R5: =SUMIFS('Sony France'!$N$4:$N$5001,'Sony France'!$F$4:$F$5001,">="&DATE(2026,1,1),'Sony France'!$F$4:$F$5001,"<="&DATE(2026,3,31)) -> 10105 | S5: =SUMIFS('Sony France'!$N$4:$N$5001,'Sony France'!$F$4:$F$5001,">="&DATE(2026,4,1),'Sony France'!$F$4:$F$5001,"<="&DATE(2026,6,30)) -> 0 | T5: =SUMIFS('Sony France'!$N$4:$N$5001,'Sony France'!$F$4:$F$5001,">="&DATE(2026,7,1),'Sony France'!$F$4:$F$5001,"<="&DATE(2026,9,30)) -> 0 | U5: =SUMIFS('Sony France'!$N$4:$N$5001,'Sony France'!$F$4:$F$5001,">="&DATE(2026,10,1),'Sony France'!$F$4:$F$5001,"<="&DATE(2026,12,31)) -> 0
A6: Sony Europe - Manu | B6: =SUMIFS('Sony Europe - Manu'!$J$6:$J$5000,'Sony Europe - Manu'!$C$6:$C$5000,">="&DATE(2022,1,1),'Sony Europe - Manu'!$C$6:$C$5000,"<="&DATE(2022,3,31)) -> 0 | C6: =SUMIFS('Sony Europe - Manu'!$J$6:$J$5000,'Sony Europe - Manu'!$C$6:$C$5000,">="&DATE(2022,4,1),'Sony Europe - Manu'!$C$6:$C$5000,"<="&DATE(2022,6,30)) -> 0 | D6: =SUMIFS('Sony Europe - Manu'!$J$6:$J$5000,'Sony Europe - Manu'!$C$6:$C$5000,">="&DATE(2022,7,1),'Sony Europe - Manu'!$C$6:$C$5000,"<="&DATE(2022,9,30)) -> 0 | E6: =SUMIFS('Sony Europe - Manu'!$J$6:$J$5000,'Sony Europe - Manu'!$C$6:$C$5000,">="&DATE(2022,10,1),'Sony Europe - Manu'!$C$6:$C$5000,"<="&DATE(2022,12,31)) -> 1995 | F6: =SUMIFS('Sony Europe - Manu'!$J$6:$J$5000,'Sony Europe - Manu'!$C$6:$C$5000,">="&DATE(2023,1,1),'Sony Europe - Manu'!$C$6:$C$5000,"<="&DATE(2023,3,31)) -> 41025 | G6: =SUMIFS('Sony Europe - Manu'!$J$6:$J$5000,'Sony Europe - Manu'!$C$6:$C$5000,">="&DATE(2023,4,1),'Sony Europe - Manu'!$C$6:$C$5000,"<="&DATE(2023,6,30)) -> 6315 | H6: =SUMIFS('Sony Europe - Manu'!$J$6:$J$5000,'Sony Europe - Manu'!$C$6:$C$5000,">="&DATE(2023,7,1),'Sony Europe - Manu'!$C$6:$C$5000,"<="&DATE(2023,9,30)) -> 20620 | I6: =SUMIFS('Sony Europe - Manu'!$J$6:$J$5000,'Sony Europe - Manu'!$C$6:$C$5000,">="&DATE(2023,10,1),'Sony Europe - Manu'!$C$6:$C$5000,"<="&DATE(2023,12,31)) -> 10440 | J6: =SUMIFS('Sony Europe - Manu'!$J$6:$J$5000,'Sony Europe - Manu'!$C$6:$C$5000,">="&DATE(2024,1,1),'Sony Europe - Manu'!$C$6:$C$5000,"<="&DATE(2024,3,31)) -> 18965 | K6: =SUMIFS('Sony Europe - Manu'!$J$6:$J$5000,'Sony Europe - Manu'!$C$6:$C$5000,">="&DATE(2024,4,1),'Sony Europe - Manu'!$C$6:$C$5000,"<="&DATE(2024,6,30)) -> 4925 | L6: =SUMIFS('Sony Europe - Manu'!$J$6:$J$5000,'Sony Europe - Manu'!$C$6:$C$5000,">="&DATE(2024,7,1),'Sony Europe - Manu'!$C$6:$C$5000,"<="&DATE(2024,9,30)) -> 8620 | M6: =SUMIFS('Sony Europe - Manu'!$J$6:$J$5000,'Sony Europe - Manu'!$C$6:$C$5000,">="&DATE(2024,10,1),'Sony Europe - Manu'!$C$6:$C$5000,"<="&DATE(2024,12,31)) -> 10709.25 | N6: =SUMIFS('Sony Europe - Manu'!$J$6:$J$5000,'Sony Europe - Manu'!$C$6:$C$5000,">="&DATE(2025,1,1),'Sony Europe - Manu'!$C$6:$C$5000,"<="&DATE(2025,3,31)) -> 5078 | O6: =SUMIFS('Sony Europe - Manu'!$J$6:$J$5000,'Sony Europe - Manu'!$C$6:$C$5000,">="&DATE(2025,4,1),'Sony Europe - Manu'!$C$6:$C$5000,"<="&DATE(2025,6,30)) -> 0 | P6: =SUMIFS('Sony Europe - Manu'!$J$6:$J$5000,'Sony Europe - Manu'!$C$6:$C$5000,">="&DATE(2025,7,1),'Sony Europe - Manu'!$C$6:$C$5000,"<="&DATE(2025,9,30)) -> 0 | Q6: =SUMIFS('Sony Europe - Manu'!$J$6:$J$5000,'Sony Europe - Manu'!$C$6:$C$5000,">="&DATE(2025,10,1),'Sony Europe - Manu'!$C$6:$C$5000,"<="&DATE(2025,12,31)) -> 0 | R6: =SUMIFS('Sony Europe - Manu'!$J$6:$J$5000,'Sony Europe - Manu'!$C$6:$C$5000,">="&DATE(2026,1,1),'Sony Europe - Manu'!$C$6:$C$5000,"<="&DATE(2026,3,31)) -> 0 | S6: =SUMIFS('Sony Europe - Manu'!$J$6:$J$5000,'Sony Europe - Manu'!$C$6:$C$5000,">="&DATE(2026,4,1),'Sony Europe - Manu'!$C$6:$C$5000,"<="&DATE(2026,6,30)) -> 0 | T6: =SUMIFS('Sony Europe - Manu'!$J$6:$J$5000,'Sony Europe - Manu'!$C$6:$C$5000,">="&DATE(2026,7,1),'Sony Europe - Manu'!$C$6:$C$5000,"<="&DATE(2026,9,30)) -> 0 | U6: =SUMIFS('Sony Europe - Manu'!$J$6:$J$5000,'Sony Europe - Manu'!$C$6:$C$5000,">="&DATE(2026,10,1),'Sony Europe - Manu'!$C$6:$C$5000,"<="&DATE(2026,12,31)) -> 0
A7: Sony Professional | B7: =SUMIFS('Sony Professional'!$J$4:$J$5000,'Sony Professional'!$C$4:$C$5000,">="&DATE(2022,1,1),'Sony Professional'!$C$4:$C$5000,"<="&DATE(2022,3,31)) -> 0 | C7: =SUMIFS('Sony Professional'!$J$4:$J$5000,'Sony Professional'!$C$4:$C$5000,">="&DATE(2022,4,1),'Sony Professional'!$C$4:$C$5000,"<="&DATE(2022,6,30)) -> 0 | D7: =SUMIFS('Sony Professional'!$J$4:$J$5000,'Sony Professional'!$C$4:$C$5000,">="&DATE(2022,7,1),'Sony Professional'!$C$4:$C$5000,"<="&DATE(2022,9,30)) -> 0 | E7: =SUMIFS('Sony Professional'!$J$4:$J$5000,'Sony Professional'!$C$4:$C$5000,">="&DATE(2022,10,1),'Sony Professional'!$C$4:$C$5000,"<="&DATE(2022,12,31)) -> 0 | F7: =SUMIFS('Sony Professional'!$J$4:$J$5000,'Sony Professional'!$C$4:$C$5000,">="&DATE(2023,1,1),'Sony Professional'!$C$4:$C$5000,"<="&DATE(2023,3,31)) -> 10600 | G7: =SUMIFS('Sony Professional'!$J$4:$J$5000,'Sony Professional'!$C$4:$C$5000,">="&DATE(2023,4,1),'Sony Professional'!$C$4:$C$5000,"<="&DATE(2023,6,30)) -> 25219.935 | H7: =SUMIFS('Sony Professional'!$J$4:$J$5000,'Sony Professional'!$C$4:$C$5000,">="&DATE(2023,7,1),'Sony Professional'!$C$4:$C$5000,"<="&DATE(2023,9,30)) -> 14970 | I7: =SUMIFS('Sony Professional'!$J$4:$J$5000,'Sony Professional'!$C$4:$C$5000,">="&DATE(2023,10,1),'Sony Professional'!$C$4:$C$5000,"<="&DATE(2023,12,31)) -> 27151.468 | J7: =SUMIFS('Sony Professional'!$J$4:$J$5000,'Sony Professional'!$C$4:$C$5000,">="&DATE(2024,1,1),'Sony Professional'!$C$4:$C$5000,"<="&DATE(2024,3,31)) -> 33576.4 | K7: =SUMIFS('Sony Professional'!$J$4:$J$5000,'Sony Professional'!$C$4:$C$5000,">="&DATE(2024,4,1),'Sony Professional'!$C$4:$C$5000,"<="&DATE(2024,6,30)) -> 7100 | L7: =SUMIFS('Sony Professional'!$J$4:$J$5000,'Sony Professional'!$C$4:$C$5000,">="&DATE(2024,7,1),'Sony Professional'!$C$4:$C$5000,"<="&DATE(2024,9,30)) -> 5308 | M7: =SUMIFS('Sony Professional'!$J$4:$J$5000,'Sony Professional'!$C$4:$C$5000,">="&DATE(2024,10,1),'Sony Professional'!$C$4:$C$5000,"<="&DATE(2024,12,31)) -> 11327.2 | N7: =SUMIFS('Sony Professional'!$J$4:$J$5000,'Sony Professional'!$C$4:$C$5000,">="&DATE(2025,1,1),'Sony Professional'!$C$4:$C$5000,"<="&DATE(2025,3,31)) -> 9327 | O7: =SUMIFS('Sony Professional'!$J$4:$J$5000,'Sony Professional'!$C$4:$C$5000,">="&DATE(2025,4,1),'Sony Professional'!$C$4:$C$5000,"<="&DATE(2025,6,30)) -> 9853.422 | P7: =SUMIFS('Sony Professional'!$J$4:$J$5000,'Sony Professional'!$C$4:$C$5000,">="&DATE(2025,7,1),'Sony Professional'!$C$4:$C$5000,"<="&DATE(2025,9,30)) -> 2320 | Q7: =SUMIFS('Sony Professional'!$J$4:$J$5000,'Sony Professional'!$C$4:$C$5000,">="&DATE(2025,10,1),'Sony Professional'!$C$4:$C$5000,"<="&DATE(2025,12,31)) -> 9190.25 | R7: =SUMIFS('Sony Professional'!$J$4:$J$5000,'Sony Professional'!$C$4:$C$5000,">="&DATE(2026,1,1),'Sony Professional'!$C$4:$C$5000,"<="&DATE(2026,3,31)) -> 1265 | S7: =SUMIFS('Sony Professional'!$J$4:$J$5000,'Sony Professional'!$C$4:$C$5000,">="&DATE(2026,4,1),'Sony Professional'!$C$4:$C$5000,"<="&DATE(2026,6,30)) -> 0 | T7: =SUMIFS('Sony Professional'!$J$4:$J$5000,'Sony Professional'!$C$4:$C$5000,">="&DATE(2026,7,1),'Sony Professional'!$C$4:$C$5000,"<="&DATE(2026,9,30)) -> 0 | U7: =SUMIFS('Sony Professional'!$J$4:$J$5000,'Sony Professional'!$C$4:$C$5000,">="&DATE(2026,10,1),'Sony Professional'!$C$4:$C$5000,"<="&DATE(2026,12,31)) -> 0
A8: Sony Europe - Other | B8: =SUMIFS('Sony Europe - Other'!$J$4:$J$5000,'Sony Europe - Other'!$C$4:$C$5000,">="&DATE(2022,1,1),'Sony Europe - Other'!$C$4:$C$5000,"<="&DATE(2022,3,31)) -> 0 | C8: =SUMIFS('Sony Europe - Other'!$J$4:$J$5000,'Sony Europe - Other'!$C$4:$C$5000,">="&DATE(2022,4,1),'Sony Europe - Other'!$C$4:$C$5000,"<="&DATE(2022,6,30)) -> 0 | D8: =SUMIFS('Sony Europe - Other'!$J$4:$J$5000,'Sony Europe - Other'!$C$4:$C$5000,">="&DATE(2022,7,1),'Sony Europe - Other'!$C$4:$C$5000,"<="&DATE(2022,9,30)) -> 0 | E8: =SUMIFS('Sony Europe - Other'!$J$4:$J$5000,'Sony Europe - Other'!$C$4:$C$5000,">="&DATE(2022,10,1),'Sony Europe - Other'!$C$4:$C$5000,"<="&DATE(2022,12,31)) -> 0 | F8: =SUMIFS('Sony Europe - Other'!$J$4:$J$5000,'Sony Europe - Other'!$C$4:$C$5000,">="&DATE(2023,1,1),'Sony Europe - Other'!$C$4:$C$5000,"<="&DATE(2023,3,31)) -> 0 | G8: =SUMIFS('Sony Europe - Other'!$J$4:$J$5000,'Sony Europe - Other'!$C$4:$C$5000,">="&DATE(2023,4,1),'Sony Europe - Other'!$C$4:$C$5000,"<="&DATE(2023,6,30)) -> 0 | H8: =SUMIFS('Sony Europe - Other'!$J$4:$J$5000,'Sony Europe - Other'!$C$4:$C$5000,">="&DATE(2023,7,1),'Sony Europe - Other'!$C$4:$C$5000,"<="&DATE(2023,9,30)) -> 0 | I8: =SUMIFS('Sony Europe - Other'!$J$4:$J$5000,'Sony Europe - Other'!$C$4:$C$5000,">="&DATE(2023,10,1),'Sony Europe - Other'!$C$4:$C$5000,"<="&DATE(2023,12,31)) -> 0 | J8: =SUMIFS('Sony Europe - Other'!$J$4:$J$5000,'Sony Europe - Other'!$C$4:$C$5000,">="&DATE(2024,1,1),'Sony Europe - Other'!$C$4:$C$5000,"<="&DATE(2024,3,31)) -> 0 | K8: =SUMIFS('Sony Europe - Other'!$J$4:$J$5000,'Sony Europe - Other'!$C$4:$C$5000,">="&DATE(2024,4,1),'Sony Europe - Other'!$C$4:$C$5000,"<="&DATE(2024,6,30)) -> 6300 | L8: =SUMIFS('Sony Europe - Other'!$J$4:$J$5000,'Sony Europe - Other'!$C$4:$C$5000,">="&DATE(2024,7,1),'Sony Europe - Other'!$C$4:$C$5000,"<="&DATE(2024,9,30)) -> 24955 | M8: =SUMIFS('Sony Europe - Other'!$J$4:$J$5000,'Sony Europe - Other'!$C$4:$C$5000,">="&DATE(2024,10,1),'Sony Europe - Other'!$C$4:$C$5000,"<="&DATE(2024,12,31)) -> 5814.6 | N8: =SUMIFS('Sony Europe - Other'!$J$4:$J$5000,'Sony Europe - Other'!$C$4:$C$5000,">="&DATE(2025,1,1),'Sony Europe - Other'!$C$4:$C$5000,"<="&DATE(2025,3,31)) -> 6615 | O8: =SUMIFS('Sony Europe - Other'!$J$4:$J$5000,'Sony Europe - Other'!$C$4:$C$5000,">="&DATE(2025,4,1),'Sony Europe - Other'!$C$4:$C$5000,"<="&DATE(2025,6,30)) -> 20403.8 | P8: =SUMIFS('Sony Europe - Other'!$J$4:$J$5000,'Sony Europe - Other'!$C$4:$C$5000,">="&DATE(2025,7,1),'Sony Europe - Other'!$C$4:$C$5000,"<="&DATE(2025,9,30)) -> 18978.08 | Q8: =SUMIFS('Sony Europe - Other'!$J$4:$J$5000,'Sony Europe - Other'!$C$4:$C$5000,">="&DATE(2025,10,1),'Sony Europe - Other'!$C$4:$C$5000,"<="&DATE(2025,12,31)) -> 23261.6 | R8: =SUMIFS('Sony Europe - Other'!$J$4:$J$5000,'Sony Europe - Other'!$C$4:$C$5000,">="&DATE(2026,1,1),'Sony Europe - Other'!$C$4:$C$5000,"<="&DATE(2026,3,31)) -> 8382.2 | S8: =SUMIFS('Sony Europe - Other'!$J$4:$J$5000,'Sony Europe - Other'!$C$4:$C$5000,">="&DATE(2026,4,1),'Sony Europe - Other'!$C$4:$C$5000,"<="&DATE(2026,6,30)) -> 0 | T8: =SUMIFS('Sony Europe - Other'!$J$4:$J$5000,'Sony Europe - Other'!$C$4:$C$5000,">="&DATE(2026,7,1),'Sony Europe - Other'!$C$4:$C$5000,"<="&DATE(2026,9,30)) -> 0 | U8: =SUMIFS('Sony Europe - Other'!$J$4:$J$5000,'Sony Europe - Other'!$C$4:$C$5000,">="&DATE(2026,10,1),'Sony Europe - Other'!$C$4:$C$5000,"<="&DATE(2026,12,31)) -> 0
A9: Sony Europe - New | B9: =SUMIFS('Sony Europe - New'!$J$4:$J$5000,'Sony Europe - New'!$C$4:$C$5000,">="&DATE(2022,1,1),'Sony Europe - New'!$C$4:$C$5000,"<="&DATE(2022,3,31)) -> 0 | C9: =SUMIFS('Sony Europe - New'!$J$4:$J$5000,'Sony Europe - New'!$C$4:$C$5000,">="&DATE(2022,4,1),'Sony Europe - New'!$C$4:$C$5000,"<="&DATE(2022,6,30)) -> 0 | D9: =SUMIFS('Sony Europe - New'!$J$4:$J$5000,'Sony Europe - New'!$C$4:$C$5000,">="&DATE(2022,7,1),'Sony Europe - New'!$C$4:$C$5000,"<="&DATE(2022,9,30)) -> 0 | E9: =SUMIFS('Sony Europe - New'!$J$4:$J$5000,'Sony Europe - New'!$C$4:$C$5000,">="&DATE(2022,10,1),'Sony Europe - New'!$C$4:$C$5000,"<="&DATE(2022,12,31)) -> 0 | F9: =SUMIFS('Sony Europe - New'!$J$4:$J$5000,'Sony Europe - New'!$C$4:$C$5000,">="&DATE(2023,1,1),'Sony Europe - New'!$C$4:$C$5000,"<="&DATE(2023,3,31)) -> 0 | G9: =SUMIFS('Sony Europe - New'!$J$4:$J$5000,'Sony Europe - New'!$C$4:$C$5000,">="&DATE(2023,4,1),'Sony Europe - New'!$C$4:$C$5000,"<="&DATE(2023,6,30)) -> 0 | H9: =SUMIFS('Sony Europe - New'!$J$4:$J$5000,'Sony Europe - New'!$C$4:$C$5000,">="&DATE(2023,7,1),'Sony Europe - New'!$C$4:$C$5000,"<="&DATE(2023,9,30)) -> 0 | I9: =SUMIFS('Sony Europe - New'!$J$4:$J$5000,'Sony Europe - New'!$C$4:$C$5000,">="&DATE(2023,10,1),'Sony Europe - New'!$C$4:$C$5000,"<="&DATE(2023,12,31)) -> 0 | J9: =SUMIFS('Sony Europe - New'!$J$4:$J$5000,'Sony Europe - New'!$C$4:$C$5000,">="&DATE(2024,1,1),'Sony Europe - New'!$C$4:$C$5000,"<="&DATE(2024,3,31)) -> 0 | K9: =SUMIFS('Sony Europe - New'!$J$4:$J$5000,'Sony Europe - New'!$C$4:$C$5000,">="&DATE(2024,4,1),'Sony Europe - New'!$C$4:$C$5000,"<="&DATE(2024,6,30)) -> 0 | L9: =SUMIFS('Sony Europe - New'!$J$4:$J$5000,'Sony Europe - New'!$C$4:$C$5000,">="&DATE(2024,7,1),'Sony Europe - New'!$C$4:$C$5000,"<="&DATE(2024,9,30)) -> 0 | M9: =SUMIFS('Sony Europe - New'!$J$4:$J$5000,'Sony Europe - New'!$C$4:$C$5000,">="&DATE(2024,10,1),'Sony Europe - New'!$C$4:$C$5000,"<="&DATE(2024,12,31)) -> 0 | N9: =SUMIFS('Sony Europe - New'!$J$4:$J$5000,'Sony Europe - New'!$C$4:$C$5000,">="&DATE(2025,1,1),'Sony Europe - New'!$C$4:$C$5000,"<="&DATE(2025,3,31)) -> 0 | O9: =SUMIFS('Sony Europe - New'!$J$4:$J$5000,'Sony Europe - New'!$C$4:$C$5000,">="&DATE(2025,4,1),'Sony Europe - New'!$C$4:$C$5000,"<="&DATE(2025,6,30)) -> 6325 | P9: =SUMIFS('Sony Europe - New'!$J$4:$J$5000,'Sony Europe - New'!$C$4:$C$5000,">="&DATE(2025,7,1),'Sony Europe - New'!$C$4:$C$5000,"<="&DATE(2025,9,30)) -> 0 | Q9: =SUMIFS('Sony Europe - New'!$J$4:$J$5000,'Sony Europe - New'!$C$4:$C$5000,">="&DATE(2025,10,1),'Sony Europe - New'!$C$4:$C$5000,"<="&DATE(2025,12,31)) -> 0 | R9: =SUMIFS('Sony Europe - New'!$J$4:$J$5000,'Sony Europe - New'!$C$4:$C$5000,">="&DATE(2026,1,1),'Sony Europe - New'!$C$4:$C$5000,"<="&DATE(2026,3,31)) -> 0 | S9: =SUMIFS('Sony Europe - New'!$J$4:$J$5000,'Sony Europe - New'!$C$4:$C$5000,">="&DATE(2026,4,1),'Sony Europe - New'!$C$4:$C$5000,"<="&DATE(2026,6,30)) -> 0 | T9: =SUMIFS('Sony Europe - New'!$J$4:$J$5000,'Sony Europe - New'!$C$4:$C$5000,">="&DATE(2026,7,1),'Sony Europe - New'!$C$4:$C$5000,"<="&DATE(2026,9,30)) -> 0 | U9: =SUMIFS('Sony Europe - New'!$J$4:$J$5000,'Sony Europe - New'!$C$4:$C$5000,">="&DATE(2026,10,1),'Sony Europe - New'!$C$4:$C$5000,"<="&DATE(2026,12,31)) -> 0
A11: TOTAL | B11: =SUM(B5:B9) -> 0 | C11: =SUM(C5:C9) -> 0 | D11: =SUM(D5:D9) -> 0 | E11: =SUM(E5:E9) -> 9470 | F11: =SUM(F5:F9) -> 79385 | G11: =SUM(G5:G9) -> 52999.105 | H11: =SUM(H5:H9) -> 58625 | I11: =SUM(I5:I9) -> 63234.468 | ... U11: =SUM(U5:U9) -> 0
A13: NOMBRE DE PROJETS | B13: 2022 | F13: 2023 | J13: 2024 | N13: 2025 | R13: 2026
B14: Q1 | C14: Q2 | D14: Q3 | E14: Q4 | F14: Q1 | G14: Q2 | H14: Q3 | I14: Q4 | J14: Q1 | K14: Q2 | L14: Q3 | M14: Q4 | N14: Q1 | O14: Q2 | P14: Q3 | Q14: Q4 | R14: Q1 | S14: Q2 | T14: Q3 | U14: Q4
A15: Sony France | B15: =COUNTIFS('Sony France'!$F$4:$F$5001,">="&DATE(2022,1,1),'Sony France'!$F$4:$F$5001,"<="&DATE(2022,3,31)) -> 0 | C15: =COUNTIFS('Sony France'!$F$4:$F$5001,">="&DATE(2022,4,1),'Sony France'!$F$4:$F$5001,"<="&DATE(2022,6,30)) -> 0 | D15: =COUNTIFS('Sony France'!$F$4:$F$5001,">="&DATE(2022,7,1),'Sony France'!$F$4:$F$5001,"<="&DATE(2022,9,30)) -> 0 | E15: =COUNTIFS('Sony France'!$F$4:$F$5001,">="&DATE(2022,10,1),'Sony France'!$F$4:$F$5001,"<="&DATE(2022,12,31)) -> 21 | F15: =COUNTIFS('Sony France'!$F$4:$F$5001,">="&DATE(2023,1,1),'Sony France'!$F$4:$F$5001,"<="&DATE(2023,3,31)) -> 48 | G15: =COUNTIFS('Sony France'!$F$4:$F$5001,">="&DATE(2023,4,1),'Sony France'!$F$4:$F$5001,"<="&DATE(2023,6,30)) -> 76 | H15: =COUNTIFS('Sony France'!$F$4:$F$5001,">="&DATE(2023,7,1),'Sony France'!$F$4:$F$5001,"<="&DATE(2023,9,30)) -> 58 | I15: =COUNTIFS('Sony France'!$F$4:$F$5001,">="&DATE(2023,10,1),'Sony France'!$F$4:$F$5001,"<="&DATE(2023,12,31)) -> 83 | J15: =COUNTIFS('Sony France'!$F$4:$F$5001,">="&DATE(2024,1,1),'Sony France'!$F$4:$F$5001,"<="&DATE(2024,3,31)) -> 65 | K15: =COUNTIFS('Sony France'!$F$4:$F$5001,">="&DATE(2024,4,1),'Sony France'!$F$4:$F$5001,"<="&DATE(2024,6,30)) -> 92 | L15: =COUNTIFS('Sony France'!$F$4:$F$5001,">="&DATE(2024,7,1),'Sony France'!$F$4:$F$5001,"<="&DATE(2024,9,30)) -> 78 | M15: =COUNTIFS('Sony France'!$F$4:$F$5001,">="&DATE(2024,10,1),'Sony France'!$F$4:$F$5001,"<="&DATE(2024,12,31)) -> 88 | N15: =COUNTIFS('Sony France'!$F$4:$F$5001,">="&DATE(2025,1,1),'Sony France'!$F$4:$F$5001,"<="&DATE(2025,3,31)) -> 67 | O15: =COUNTIFS('Sony France'!$F$4:$F$5001,">="&DATE(2025,4,1),'Sony France'!$F$4:$F$5001,"<="&DATE(2025,6,30)) -> 69 | P15: =COUNTIFS('Sony France'!$F$4:$F$5001,">="&DATE(2025,7,1),'Sony France'!$F$4:$F$5001,"<="&DATE(2025,9,30)) -> 70 | Q15: =COUNTIFS('Sony France'!$F$4:$F$5001,">="&DATE(2025,10,1),'Sony France'!$F$4:$F$5001,"<="&DATE(2025,12,31)) -> 62 | R15: =COUNTIFS('Sony France'!$F$4:$F$5001,">="&DATE(2026,1,1),'Sony France'!$F$4:$F$5001,"<="&DATE(2026,3,31)) -> 36 | S15: =COUNTIFS('Sony France'!$F$4:$F$5001,">="&DATE(2026,4,1),'Sony France'!$F$4:$F$5001,"<="&DATE(2026,6,30)) -> 0 | T15: =COUNTIFS('Sony France'!$F$4:$F$5001,">="&DATE(2026,7,1),'Sony France'!$F$4:$F$5001,"<="&DATE(2026,9,30)) -> 0 | U15: =COUNTIFS('Sony France'!$F$4:$F$5001,">="&DATE(2026,10,1),'Sony France'!$F$4:$F$5001,"<="&DATE(2026,12,31)) -> 0
A16: Sony Europe - Manu | B16: =COUNTIFS('Sony Europe - Manu'!$C$6:$C$5000,">="&DATE(2022,1,1),'Sony Europe - Manu'!$C$6:$C$5000,"<="&DATE(2022,3,31)) -> 0 | C16: =COUNTIFS('Sony Europe - Manu'!$C$6:$C$5000,">="&DATE(2022,4,1),'Sony Europe - Manu'!$C$6:$C$5000,"<="&DATE(2022,6,30)) -> 0 | D16: =COUNTIFS('Sony Europe - Manu'!$C$6:$C$5000,">="&DATE(2022,7,1),'Sony Europe - Manu'!$C$6:$C$5000,"<="&DATE(2022,9,30)) -> 0 | E16: =COUNTIFS('Sony Europe - Manu'!$C$6:$C$5000,">="&DATE(2022,10,1),'Sony Europe - Manu'!$C$6:$C$5000,"<="&DATE(2022,12,31)) -> 3 | F16: =COUNTIFS('Sony Europe - Manu'!$C$6:$C$5000,">="&DATE(2023,1,1),'Sony Europe - Manu'!$C$6:$C$5000,"<="&DATE(2023,3,31)) -> 18 | G16: =COUNTIFS('Sony Europe - Manu'!$C$6:$C$5000,">="&DATE(2023,4,1),'Sony Europe - Manu'!$C$6:$C$5000,"<="&DATE(2023,6,30)) -> 21 | H16: =COUNTIFS('Sony Europe - Manu'!$C$6:$C$5000,">="&DATE(2023,7,1),'Sony Europe - Manu'!$C$6:$C$5000,"<="&DATE(2023,9,30)) -> 26 | I16: =COUNTIFS('Sony Europe - Manu'!$C$6:$C$5000,">="&DATE(2023,10,1),'Sony Europe - Manu'!$C$6:$C$5000,"<="&DATE(2023,12,31)) -> 13 | J16: =COUNTIFS('Sony Europe - Manu'!$C$6:$C$5000,">="&DATE(2024,1,1),'Sony Europe - Manu'!$C$6:$C$5000,"<="&DATE(2024,3,31)) -> 19 | K16: =COUNTIFS('Sony Europe - Manu'!$C$6:$C$5000,">="&DATE(2024,4,1),'Sony Europe - Manu'!$C$6:$C$5000,"<="&DATE(2024,6,30)) -> 9 | L16: =COUNTIFS('Sony Europe - Manu'!$C$6:$C$5000,">="&DATE(2024,7,1),'Sony Europe - Manu'!$C$6:$C$5000,"<="&DATE(2024,9,30)) -> 13 | M16: =COUNTIFS('Sony Europe - Manu'!$C$6:$C$5000,">="&DATE(2024,10,1),'Sony Europe - Manu'!$C$6:$C$5000,"<="&DATE(2024,12,31)) -> 12 | N16: =COUNTIFS('Sony Europe - Manu'!$C$6:$C$5000,">="&DATE(2025,1,1),'Sony Europe - Manu'!$C$6:$C$5000,"<="&DATE(2025,3,31)) -> 6 | O16: =COUNTIFS('Sony Europe - Manu'!$C$6:$C$5000,">="&DATE(2025,4,1),'Sony Europe - Manu'!$C$6:$C$5000,"<="&DATE(2025,6,30)) -> 0 | P16: =COUNTIFS('Sony Europe - Manu'!$C$6:$C$5000,">="&DATE(2025,7,1),'Sony Europe - Manu'!$C$6:$C$5000,"<="&DATE(2025,9,30)) -> 0 | Q16: =COUNTIFS('Sony Europe - Manu'!$C$6:$C$5000,">="&DATE(2025,10,1),'Sony Europe - Manu'!$C$6:$C$5000,"<="&DATE(2025,12,31)) -> 0 | R16: =COUNTIFS('Sony Europe - Manu'!$C$6:$C$5000,">="&DATE(2026,1,1),'Sony Europe - Manu'!$C$6:$C$5000,"<="&DATE(2026,3,31)) -> 0 | S16: =COUNTIFS('Sony Europe - Manu'!$C$6:$C$5000,">="&DATE(2026,4,1),'Sony Europe - Manu'!$C$6:$C$5000,"<="&DATE(2026,6,30)) -> 0 | T16: =COUNTIFS('Sony Europe - Manu'!$C$6:$C$5000,">="&DATE(2026,7,1),'Sony Europe - Manu'!$C$6:$C$5000,"<="&DATE(2026,9,30)) -> 0 | U16: =COUNTIFS('Sony Europe - Manu'!$C$6:$C$5000,">="&DATE(2026,10,1),'Sony Europe - Manu'!$C$6:$C$5000,"<="&DATE(2026,12,31)) -> 0
A17: Sony Professional | B17: =COUNTIFS('Sony Professional'!$C$4:$C$5000,">="&DATE(2022,1,1),'Sony Professional'!$C$4:$C$5000,"<="&DATE(2022,3,31)) -> 0 | C17: =COUNTIFS('Sony Professional'!$C$4:$C$5000,">="&DATE(2022,4,1),'Sony Professional'!$C$4:$C$5000,"<="&DATE(2022,6,30)) -> 0 | D17: =COUNTIFS('Sony Professional'!$C$4:$C$5000,">="&DATE(2022,7,1),'Sony Professional'!$C$4:$C$5000,"<="&DATE(2022,9,30)) -> 0 | E17: =COUNTIFS('Sony Professional'!$C$4:$C$5000,">="&DATE(2022,10,1),'Sony Professional'!$C$4:$C$5000,"<="&DATE(2022,12,31)) -> 0 | F17: =COUNTIFS('Sony Professional'!$C$4:$C$5000,">="&DATE(2023,1,1),'Sony Professional'!$C$4:$C$5000,"<="&DATE(2023,3,31)) -> 4 | G17: =COUNTIFS('Sony Professional'!$C$4:$C$5000,">="&DATE(2023,4,1),'Sony Professional'!$C$4:$C$5000,"<="&DATE(2023,6,30)) -> 14 | H17: =COUNTIFS('Sony Professional'!$C$4:$C$5000,">="&DATE(2023,7,1),'Sony Professional'!$C$4:$C$5000,"<="&DATE(2023,9,30)) -> 19 | I17: =COUNTIFS('Sony Professional'!$C$4:$C$5000,">="&DATE(2023,10,1),'Sony Professional'!$C$4:$C$5000,"<="&DATE(2023,12,31)) -> 26 | J17: =COUNTIFS('Sony Professional'!$C$4:$C$5000,">="&DATE(2024,1,1),'Sony Professional'!$C$4:$C$5000,"<="&DATE(2024,3,31)) -> 19 | K17: =COUNTIFS('Sony Professional'!$C$4:$C$5000,">="&DATE(2024,4,1),'Sony Professional'!$C$4:$C$5000,"<="&DATE(2024,6,30)) -> 15 | L17: =COUNTIFS('Sony Professional'!$C$4:$C$5000,">="&DATE(2024,7,1),'Sony Professional'!$C$4:$C$5000,"<="&DATE(2024,9,30)) -> 15 | M17: =COUNTIFS('Sony Professional'!$C$4:$C$5000,">="&DATE(2024,10,1),'Sony Professional'!$C$4:$C$5000,"<="&DATE(2024,12,31)) -> 11 | N17: =COUNTIFS('Sony Professional'!$C$4:$C$5000,">="&DATE(2025,1,1),'Sony Professional'!$C$4:$C$5000,"<="&DATE(2025,3,31)) -> 9 | O17: =COUNTIFS('Sony Professional'!$C$4:$C$5000,">="&DATE(2025,4,1),'Sony Professional'!$C$4:$C$5000,"<="&DATE(2025,6,30)) -> 7 | P17: =COUNTIFS('Sony Professional'!$C$4:$C$5000,">="&DATE(2025,7,1),'Sony Professional'!$C$4:$C$5000,"<="&DATE(2025,9,30)) -> 6 | Q17: =COUNTIFS('Sony Professional'!$C$4:$C$5000,">="&DATE(2025,10,1),'Sony Professional'!$C$4:$C$5000,"<="&DATE(2025,12,31)) -> 8 | R17: =COUNTIFS('Sony Professional'!$C$4:$C$5000,">="&DATE(2026,1,1),'Sony Professional'!$C$4:$C$5000,"<="&DATE(2026,3,31)) -> 2 | S17: =COUNTIFS('Sony Professional'!$C$4:$C$5000,">="&DATE(2026,4,1),'Sony Professional'!$C$4:$C$5000,"<="&DATE(2026,6,30)) -> 0 | T17: =COUNTIFS('Sony Professional'!$C$4:$C$5000,">="&DATE(2026,7,1),'Sony Professional'!$C$4:$C$5000,"<="&DATE(2026,9,30)) -> 0 | U17: =COUNTIFS('Sony Professional'!$C$4:$C$5000,">="&DATE(2026,10,1),'Sony Professional'!$C$4:$C$5000,"<="&DATE(2026,12,31)) -> 0
A18: Sony Europe - Other | B18: =COUNTIFS('Sony Europe - Other'!$C$4:$C$5000,">="&DATE(2022,1,1),'Sony Europe - Other'!$C$4:$C$5000,"<="&DATE(2022,3,31)) -> 0 | C18: =COUNTIFS('Sony Europe - Other'!$C$4:$C$5000,">="&DATE(2022,4,1),'Sony Europe - Other'!$C$4:$C$5000,"<="&DATE(2022,6,30)) -> 0 | D18: =COUNTIFS('Sony Europe - Other'!$C$4:$C$5000,">="&DATE(2022,7,1),'Sony Europe - Other'!$C$4:$C$5000,"<="&DATE(2022,9,30)) -> 0 | E18: =COUNTIFS('Sony Europe - Other'!$C$4:$C$5000,">="&DATE(2022,10,1),'Sony Europe - Other'!$C$4:$C$5000,"<="&DATE(2022,12,31)) -> 0 | F18: =COUNTIFS('Sony Europe - Other'!$C$4:$C$5000,">="&DATE(2023,1,1),'Sony Europe - Other'!$C$4:$C$5000,"<="&DATE(2023,3,31)) -> 0 | G18: =COUNTIFS('Sony Europe - Other'!$C$4:$C$5000,">="&DATE(2023,4,1),'Sony Europe - Other'!$C$4:$C$5000,"<="&DATE(2023,6,30)) -> 0 | H18: =COUNTIFS('Sony Europe - Other'!$C$4:$C$5000,">="&DATE(2023,7,1),'Sony Europe - Other'!$C$4:$C$5000,"<="&DATE(2023,9,30)) -> 0 | I18: =COUNTIFS('Sony Europe - Other'!$C$4:$C$5000,">="&DATE(2023,10,1),'Sony Europe - Other'!$C$4:$C$5000,"<="&DATE(2023,12,31)) -> 0 | J18: =COUNTIFS('Sony Europe - Other'!$C$4:$C$5000,">="&DATE(2024,1,1),'Sony Europe - Other'!$C$4:$C$5000,"<="&DATE(2024,3,31)) -> 0 | K18: =COUNTIFS('Sony Europe - Other'!$C$4:$C$5000,">="&DATE(2024,4,1),'Sony Europe - Other'!$C$4:$C$5000,"<="&DATE(2024,6,30)) -> 3 | L18: =COUNTIFS('Sony Europe - Other'!$C$4:$C$5000,">="&DATE(2024,7,1),'Sony Europe - Other'!$C$4:$C$5000,"<="&DATE(2024,9,30)) -> 10 | M18: =COUNTIFS('Sony Europe - Other'!$C$4:$C$5000,">="&DATE(2024,10,1),'Sony Europe - Other'!$C$4:$C$5000,"<="&DATE(2024,12,31)) -> 3 | N18: =COUNTIFS('Sony Europe - Other'!$C$4:$C$5000,">="&DATE(2025,1,1),'Sony Europe - Other'!$C$4:$C$5000,"<="&DATE(2025,3,31)) -> 6 | O18: =COUNTIFS('Sony Europe - Other'!$C$4:$C$5000,">="&DATE(2025,4,1),'Sony Europe - Other'!$C$4:$C$5000,"<="&DATE(2025,6,30)) -> 17 | P18: =COUNTIFS('Sony Europe - Other'!$C$4:$C$5000,">="&DATE(2025,7,1),'Sony Europe - Other'!$C$4:$C$5000,"<="&DATE(2025,9,30)) -> 15 | Q18: =COUNTIFS('Sony Europe - Other'!$C$4:$C$5000,">="&DATE(2025,10,1),'Sony Europe - Other'!$C$4:$C$5000,"<="&DATE(2025,12,31)) -> 14 | R18: =COUNTIFS('Sony Europe - Other'!$C$4:$C$5000,">="&DATE(2026,1,1),'Sony Europe - Other'!$C$4:$C$5000,"<="&DATE(2026,3,31)) -> 9 | S18: =COUNTIFS('Sony Europe - Other'!$C$4:$C$5000,">="&DATE(2026,4,1),'Sony Europe - Other'!$C$4:$C$5000,"<="&DATE(2026,6,30)) -> 0 | T18: =COUNTIFS('Sony Europe - Other'!$C$4:$C$5000,">="&DATE(2026,7,1),'Sony Europe - Other'!$C$4:$C$5000,"<="&DATE(2026,9,30)) -> 0 | U18: =COUNTIFS('Sony Europe - Other'!$C$4:$C$5000,">="&DATE(2026,10,1),'Sony Europe - Other'!$C$4:$C$5000,"<="&DATE(2026,12,31)) -> 0
A19: Sony Europe - New | B19: =COUNTIFS('Sony Europe - New'!$C$4:$C$5000,">="&DATE(2022,1,1),'Sony Europe - New'!$C$4:$C$5000,"<="&DATE(2022,3,31)) -> 0 | C19: =COUNTIFS('Sony Europe - New'!$C$4:$C$5000,">="&DATE(2022,4,1),'Sony Europe - New'!$C$4:$C$5000,"<="&DATE(2022,6,30)) -> 0 | D19: =COUNTIFS('Sony Europe - New'!$C$4:$C$5000,">="&DATE(2022,7,1),'Sony Europe - New'!$C$4:$C$5000,"<="&DATE(2022,9,30)) -> 0 | E19: =COUNTIFS('Sony Europe - New'!$C$4:$C$5000,">="&DATE(2022,10,1),'Sony Europe - New'!$C$4:$C$5000,"<="&DATE(2022,12,31)) -> 0 | F19: =COUNTIFS('Sony Europe - New'!$C$4:$C$5000,">="&DATE(2023,1,1),'Sony Europe - New'!$C$4:$C$5000,"<="&DATE(2023,3,31)) -> 0 | G19: =COUNTIFS('Sony Europe - New'!$C$4:$C$5000,">="&DATE(2023,4,1),'Sony Europe - New'!$C$4:$C$5000,"<="&DATE(2023,6,30)) -> 0 | H19: =COUNTIFS('Sony Europe - New'!$C$4:$C$5000,">="&DATE(2023,7,1),'Sony Europe - New'!$C$4:$C$5000,"<="&DATE(2023,9,30)) -> 0 | I19: =COUNTIFS('Sony Europe - New'!$C$4:$C$5000,">="&DATE(2023,10,1),'Sony Europe - New'!$C$4:$C$5000,"<="&DATE(2023,12,31)) -> 0 | J19: =COUNTIFS('Sony Europe - New'!$C$4:$C$5000,">="&DATE(2024,1,1),'Sony Europe - New'!$C$4:$C$5000,"<="&DATE(2024,3,31)) -> 0 | K19: =COUNTIFS('Sony Europe - New'!$C$4:$C$5000,">="&DATE(2024,4,1),'Sony Europe - New'!$C$4:$C$5000,"<="&DATE(2024,6,30)) -> 0 | L19: =COUNTIFS('Sony Europe - New'!$C$4:$C$5000,">="&DATE(2024,7,1),'Sony Europe - New'!$C$4:$C$5000,"<="&DATE(2024,9,30)) -> 0 | M19: =COUNTIFS('Sony Europe - New'!$C$4:$C$5000,">="&DATE(2024,10,1),'Sony Europe - New'!$C$4:$C$5000,"<="&DATE(2024,12,31)) -> 0 | N19: =COUNTIFS('Sony Europe - New'!$C$4:$C$5000,">="&DATE(2025,1,1),'Sony Europe - New'!$C$4:$C$5000,"<="&DATE(2025,3,31)) -> 0 | O19: =COUNTIFS('Sony Europe - New'!$C$4:$C$5000,">="&DATE(2025,4,1),'Sony Europe - New'!$C$4:$C$5000,"<="&DATE(2025,6,30)) -> 6 | P19: =COUNTIFS('Sony Europe - New'!$C$4:$C$5000,">="&DATE(2025,7,1),'Sony Europe - New'!$C$4:$C$5000,"<="&DATE(2025,9,30)) -> 0 | Q19: =COUNTIFS('Sony Europe - New'!$C$4:$C$5000,">="&DATE(2025,10,1),'Sony Europe - New'!$C$4:$C$5000,"<="&DATE(2025,12,31)) -> 0 | R19: =COUNTIFS('Sony Europe - New'!$C$4:$C$5000,">="&DATE(2026,1,1),'Sony Europe - New'!$C$4:$C$5000,"<="&DATE(2026,3,31)) -> 0 | S19: =COUNTIFS('Sony Europe - New'!$C$4:$C$5000,">="&DATE(2026,4,1),'Sony Europe - New'!$C$4:$C$5000,"<="&DATE(2026,6,30)) -> 0 | T19: =COUNTIFS('Sony Europe - New'!$C$4:$C$5000,">="&DATE(2026,7,1),'Sony Europe - New'!$C$4:$C$5000,"<="&DATE(2026,9,30)) -> 0 | U19: =COUNTIFS('Sony Europe - New'!$C$4:$C$5000,">="&DATE(2026,10,1),'Sony Europe - New'!$C$4:$C$5000,"<="&DATE(2026,12,31)) -> 0
A21: TOTAL | B21: =SUM(B15:B19) -> 0 | C21: =SUM(C15:C19) -> 0 | D21: =SUM(D15:D19) -> 0 | E21: =SUM(E15:E19) -> 24 | F21: =SUM(F15:F19) -> 70 | G21: =SUM(G15:G19) -> 111 | H21: =SUM(H15:H19) -> 103 | I21: =SUM(I15:I19) -> 122 | ... U21: =SUM(U15:U19) -> 0
A23: SYNTHÈSE ANNUELLE | B23: 2022 | C23: 2023 | D23: 2024 | E23: 2025 | F23: 2026
A24: Revenus (€) | B24: =SUM(B11:E11) -> 9470 | C24: =SUM(F11:I11) -> 254243.57 | D24: =SUM(J11:M11) -> 235185.45 | E24: =SUM(N11:Q11) -> 195855.15 | F24: =SUM(R11:U11) -> 19752.2
A25: Projets | B25: =SUM(B21:E21) -> 24 | C25: =SUM(F21:I21) -> 406 | D25: =SUM(J21:M21) -> 452 | E25: =SUM(N21:Q21) -> 362 | F25: =SUM(R21:U21) -> 47
A26: Rev. / Projet (€) | B26: =IFERROR(B24/B25,"—") -> 394.58333 | C26: =IFERROR(C24/C25,"—") -> 626.2157 | D26: =IFERROR(D24/D25,"—") -> 520.32179 | E26: =IFERROR(E24/E25,"—") -> 541.03633 | F26: =IFERROR(F24/F25,"—") -> 420.25957
A27: or no

Sheet Sony France
A1: Price File | V1: Online | AC1: Offline | AL1: Presentations | AM1: Web | AS1: Videos | AZ1: Virtualization | BB1: Copy
A2: Project | H2: Details | Q2: Sony | S2: Sarani Ne pas toucher, svp | V2: Banner creation (static) | W2: Banner adaptation (static) | X2: Banner creation (animated) | Y2: Banner adaptation (animated) | Z2: Logo | AA2: Lifestyle Picture | AB2: Wallpapers | AC2: Offline creation (standard) | AD2: Offline creation (adaptation) | AE2: Leaflet (1 page) | AF2: Leaflet (2 pages) | AG2: Packaging (box) | AH2: Merchandising Plan | AI2: Roll-up / Wall creation | AJ2: Chart | AK2: Brochure (20 pages) | AL2: Slide | AM2: Newsletter (design only) | AN2: Newsletter (complete) | AO2: Landing page (design only) | AP2: Landing page (complete) | AQ2: Website (design only) | AR2: Website (complete) | AS2: Simple Edition | AT2: Advanced Edition | AU2: Social Media Video (up to 30s) | AV2: Social Media Video (up to 1 min) | AW2: Promotional | AX2: 2D Video (up to 3min) | AY2: 3D Video (up to 3min) | AZ2: Virtual space | BA2: Virtual showroom | BB2: Translation (per word) | BC2: Copywrite (per word)
A3: Customer | B3: Division | C3: FY | D3: Quarter | E3: Month | F3: Date | G3: Project | H3: Contact | I3: Status | J3: Category | K3: Team | L3: Link | M3: Assets | N3: Total Value | O3: Quote | P3: PO Status | Q3: PO | R3: Mois de Facturation | S3: Invoice | T3: N° Invoice | U3: Status | V3: 120 | W3: 35 | X3: 220 | Y3: 60 | Z3: 250 | AA3: 500 | AB3: 100 | AC3: 135 | AD3: 40 | AE3: 180 | AF3: 250 | AG3: 200 | AH3: 250 | AI3: 180 | AJ3: 400 | AK3: 2200 | AL3: 35 | AM3: 500 | AN3: 600 | AO3: 500 | AP3: 1200 | AQ3: 5000 | AR3: 7000 | AS3: 80 | AT3: 150 | AU3: 260 | AV3: 360 | AW3: 5000 | AX3: 6500 | AY3: 10000 | AZ3: 2500 | BA3: 10000 | BB3: 0.1 | BC3: 0.25
A4: Sony | B4: SFR | C4: FY22 | D4: =IF(F4="","",CHOOSE(MONTH(F4),"Q4","Q4","Q4","Q1","Q1","Q1","Q2","Q2","Q2","Q3","Q3","Q3")) -> Q3 | E4: =IF(F4="","",CHOOSE(MONTH(F4),"10-JAN","11-FEB","12-MAR","01-APR","02-MAY","03-JUN","04-JUL","05-AUG","06-SEP","07-OCT","08-NOV","09-DEC")) -> 08-NOV | F4: 44880 | G4: MDR MEG TW FNAC | H4: Laura Vivient | I4: Delivered | J4: MDR | K4: BA | L4: https://saranistudio-my.sharepoint.com/:f:/g/personal/team_sarani_studio/Etevju8IZKpEjFi3N14QmoUBp7wUTsms6pxhOWBv6e2jlQ?e=pPaido2y | M4: =IF(SUM(V4:BC4)=0,"-",SUM(V4:BC4)) -> 3 | N4: =IF(SUMPRODUCT($V$3:$BC$3,V4:BC4)=0,"-",SUMPRODUCT($V$3:$BC$3,V4:BC4)) -> 405 | O4: 29/11/2022 | P4: =IF(G4="","",IFERROR(IF(S4="Sent","",IF(I4="Delivered","PO en attente","Projet en cours")),"")) | Q4: 4200630823 | S4: Sent | T4: - | U4: Paid | AC4: 3
A5: Sony | B5: SFR | C5: FY22 | D5: =IF(F5="","",CHOOSE(MONTH(F5),"Q4","Q4","Q4","Q1","Q1","Q1","Q2","Q2","Q2","Q3","Q3","Q3")) -> Q3 | E5: =IF(F5="","",CHOOSE(MONTH(F5),"10-JAN","11-FEB","12-MAR","01-APR","02-MAY","03-JUN","04-JUL","05-AUG","06-SEP","07-OCT","08-NOV","09-DEC")) -> 08-NOV | F5: 44880 | G5: MDR TW Stop Rayon Bluetooth Multipoint | H5: Laura Vivient | I5: Delivered | J5: MDR | K5: BA | L5: https://saranistudio-my.sharepoint.com/:f:/g/personal/team_sarani_studio/EiWYden95S1PhgR70pI8qxEBwY-0nfvYhECdhw2ZQdFqdw?e=PaidMO8n | M5: =IF(SUM(V5:BC5)=0,"-",SUM(V5:BC5)) -> 1 | N5: =IF(SUMPRODUCT($V$3:$BC$3,V5:BC5)=0,"-",SUMPRODUCT($V$3:$BC$3,V5:BC5)) -> 135 | O5: 29/11/2022 | P5: =IF(G5="","",IFERROR(IF(S5="Sent","",IF(I5="Delivered","PO en attente","Projet en cours")),"")) | Q5: 4200630799 | S5: Sent | T5: - | U5: Paid | AC5: 1
A6: Sony | B6: SFR | C6: FY22 | D6: =IF(F6="","",CHOOSE(MONTH(F6),"Q4","Q4","Q4","Q1","Q1","Q1","Q2","Q2","Q2","Q3","Q3","Q3")) -> Q3 | E6: =IF(F6="","",CHOOSE(MONTH(F6),"10-JAN","11-FEB","12-MAR","01-APR","02-MAY","03-JUN","04-JUL","05-AUG","06-SEP","07-OCT","08-NOV","09-DEC")) -> 08-NOV | F6: 44882 | G6: Xmas - Creative Assets | H6: Maxime Fenech | I6: Delivered | J6: Cross | K6: BA | L6: https://saranistudio-my.sharepoint.com/:f:/g/personal/team_sarani_studio/EiXLGF1XZ1VNkmFgudaLWcQB0AP6n1T0jNDvvhweNqqJwg?e=vKq0Pw | M6: =IF(SUM(V6:BC6)=0,"-",SUM(V6:BC6)) -> 19 | N6: =IF(SUMPRODUCT($V$3:$BC$3,V6:BC6)=0,"-",SUMPRODUCT($V$3:$BC$3,V6:BC6)) -> 665 | O6: 22/11/2022 | P6: =IF(G6="","",IFERROR(IF(S6="Sent","",IF(I6="Delivered","PO en attente","Projet en cours")),"")) | Q6: 4200632493 | S6: Sent | T6: - | U6: Paid | W6: 19
A7: Sony | B7: SFR | C7: FY22 | D7: =IF(F7="","",CHOOSE(MONTH(F7),"Q4","Q4","Q4","Q1","Q1","Q1","Q2","Q2","Q2","Q3","Q3","Q3")) -> Q3 | E7: =IF(F7="","",CHOOSE(MONTH(F7),"10-JAN","11-FEB","12-MAR","01-APR","02-MAY","03-JUN","04-JUL","05-AUG","06-SEP","07-OCT","08-NOV","09-DEC")) -> 08-NOV | F7: 44883 | G7: Bulles Boulanger 2 | H7: Laura Vivient | I7: Delivered | J7: MDR | K7: BA | L7: https://saranistudio-my.sharepoint.com/:f:/g/personal/team_sarani_studio/EvZFoSgMoTlGiWeuK20ZrcwBr1BCtYNuR2DptwGgJMpg-A?e=ucRI2s | M7: =IF(SUM(V7:BC7)=0,"-",SUM(V7:BC7)) -> 1 | N7: =IF(SUMPRODUCT($V$3:$BC$3,V7:BC7)=0,"-",SUMPRODUCT($V$3:$BC$3,V7:BC7)) -> 120 | O7: 29/11/2022 | P7: =IF(G7="","",IFERROR(IF(S7="Sent","",IF(I7="Delivered","PO en attente","Projet en cours")),"")) | Q7: 4200630798 | S7: Sent | T7: - | U7: Paid | V7: 1
A8: Sony | B8: SFR | C8: FY22 | D8: =IF(F8="","",CHOOSE(MONTH(F8),"Q4","Q4","Q4","Q1","Q1","Q1","Q2","Q2","Q2","Q3","Q3","Q3")) -> Q3 | E8: =IF(F8="","",CHOOSE(MONTH(F8),"10-JAN","11-FEB","12-MAR","01-APR","02-MAY","03-JUN","04-JUL","05-AUG","06-SEP","07-OCT","08-NOV","09-DEC")) -> 08-NOV | F8: 44883 | G8: Infographies PSK FR | H8: Laura Vivient | I8: Delivered | J8: PAG | K8: BA | L8: https://saranistudio-my.sharepoint.com/:f:/g/personal/team_sarani_studio/Evtfs8z--DpCs3Qy9Cvq1Y4BMFsqWlLop36Ti2xykheKBA?e=DSnQzV | M8: =IF(SUM(V8:BC8)=0,"-",SUM(V8:BC8)) -> 16 | N8: =IF(SUMPRODUCT($V$3:$BC$3,V8:BC8)=0,"-",SUMPRODUCT($V$3:$BC$3,V8:BC8)) -> 560 | O8: 29/11/2022 | P8: =IF(G8="","",IFERROR(IF(S8="Sent","",IF(I8="Delivered","PO en attente","Projet en cours")),"")) | Q8: 4200630825 | S8: Sent | T8: - | U8: Paid | W8: 16
A9: Sony | B9: SFR | C9: FY22 | D9: =IF(F9="","",CHOOSE(MONTH(F9),"Q4","Q4","Q4","Q1","Q1","Q1","Q2","Q2","Q2","Q3","Q3","Q3")) -> Q3 | E9: =IF(F9="","",CHOOSE(MONTH(F9),"10-JAN","11-FEB","12-MAR","01-APR","02-MAY","03-JUN","04-JUL","05-AUG","06-SEP","07-OCT","08-NOV","09-DEC")) -> 08-NOV | F9: 44883 | G9: 1000XM5 Award | H9: Laura Vivient | I9: Delivered | J9: MDR | K9: BA | L9: https://saranistudio-my.sharepoint.com/:f:/g/personal/team_sarani_studio/Eiu73Y88xwJPqQdXyeju6gcBPx5Nk46QboMvzke5SksCEw?e=lK8Qjn | M9: =IF(SUM(V9:BC9)=0,"-",SUM(V9:BC9)) -> 2 | N9: =IF(SUMPRODUCT($V$3:$BC$3,V9:BC9)=0,"-",SUMPRODUCT($V$3:$BC$3,V9:BC9)) -> 70 | O9: 29/11/2022 | P9: =IF(G9="","",IFERROR(IF(S9="Sent","",IF(I9="Delivered","PO en attente","Projet en cours")),"")) | Q9: 4270024443 | S9: Sent | T9: - | U9: Paid | W9: 2
A10: Sony | B10: SFR | C10: FY22 | D10: =IF(F10="","",CHOOSE(MONTH(F10),"Q4","Q4","Q4","Q1","Q1","Q1","Q2","Q2","Q2","Q3","Q3","Q3")) -> Q3 | E10: =IF(F10="","",CHOOSE(MONTH(F10),"10-JAN","11-FEB","12-MAR","01-APR","02-MAY","03-JUN","04-JUL","05-AUG","06-SEP","07-OCT","08-NOV","09-DEC")) -> 08-NOV | F10: 44888 | G10: HAV PLV MEG BDS LEAFLET TV | H10: Laura Vivient | I10: Delivered | J10: HAV | K10: BA | L10: https://saranistudio-my.sharepoint.com/:f:/g/personal/team_sarani_studio/EsKN0KK2wo5EuWcP_12lMhIBc3AUZVWjUaf03MKgHmGTeQ?e=4x7Av8 | M10: =IF(SUM(V10:BC10)=0,"-",SUM(V10:BC10)) -> 2 | N10: =IF(SUMPRODUCT($V$3:$BC$3,V10:BC10)=0,"-",SUMPRODUCT($V$3:$BC$3,V10:BC10)) -> 175 | O10: 30/11/2022 | P10: =IF(G10="","",IFERROR(IF(S10="Sent","",IF(I10="Delivered","PO en attente","Projet en cours")),"")) | Q10: 4200630829 | S10: Sent | T10: - | U10: Paid | AC10: 1 | AD10: 1
A11: Sony | B11: SFR | C11: FY22 | D11: =IF(F11="","",CHOOSE(MONTH(F11),"Q4","Q4","Q4","Q1","Q1","Q1","Q2","Q2","Q2","Q3","Q3","Q3")) -> Q3 | E11: =IF(F11="","",CHOOSE(MONTH(F11),"10-JAN","11-FEB","12-MAR","01-APR","02-MAY","03-JUN","04-JUL","05-AUG","06-SEP","07-OCT","08-NOV","09-DEC")) -> 08-NOV | F11: 44888 | G11: A95K-A83K Topper | H11: Léa Novio | I11: Delivered | J11: TV | K11: BA | L11: https://saranistudio-my.sharepoint.com/:f:/g/personal/team_sarani_studio/Enb5T0uGjd5It7r-yOl8Hw4BRcePMvNEVtlCj65ShnZ1eA?e=oRN2hs | M11: =IF(SUM(V11:BC11)=0,"-",SUM(V11:BC11)) -> 2 | N11: =IF(SUMPRODUCT($V$3:$BC$3,V11:BC11)=0,"-",SUMPRODUCT($V$3:$BC$3,V11:BC11)) -> 175 | O11: 44785 | P11: =IF(G11="","",IFERROR(IF(S11="Sent","",IF(I11="Delivered","PO en attente","Projet en cours")),"")) | Q11: 4200631414 | S11: Sent | T11: - | U11: Paid | AC11: 1 | AD11: 1
A12: Sony | B12: SFR | C12: FY22 | D12: =IF(F12="","",CHOOSE(MONTH(F12),"Q4","Q4","Q4","Q1","Q1","Q1","Q2","Q2","Q2","Q3","Q3","Q3")) -> Q3 | E12: =IF(F12="","",CHOOSE(MONTH(F12),"10-JAN","11-FEB","12-MAR","01-APR","02-MAY","03-JUN","04-JUL","05-AUG","06-SEP","07-OCT","08-NOV","09-DEC")) -> 08-NOV | F12: 44888 | G12: Labo Fnac | H12: Léa Novio | I12: Delivered | J12: TV | K12: BA | L12: https://saranistudio-my.sharepoint.com/:f:/g/personal/team_sarani_studio/EmBOVYV-QulImoZen16_XSMBt4gcYjkuDidXF__Uf1-VHw?e=ibhnwE | M12: =IF(SUM(V12:BC12)=0,"-",SUM(V12:BC12)) -> 5 | N12: =IF(SUMPRODUCT($V$3:$BC$3,V12:BC12)=0,"-",SUMPRODUCT($V$3:$BC$3,V12:BC12)) -> 175 | O12: 29/11/2022 | P12: =IF(G12="","",IFERROR(IF(S12="Sent","",IF(I12="Delivered","PO en attente","Projet en cours")),"")) | Q12: 4200631417 | S12: Sent | T12: - | U12: Paid | W12: 5
A13: Sony | B13: SFR | C13: FY22 | D13: =IF(F13="","",CHOOSE(MONTH(F13),"Q4","Q4","Q4","Q1","Q1","Q1","Q2","Q2","Q2","Q3","Q3","Q3")) -> Q3 | E13: =IF(F13="","",CHOOSE(MONTH(F13),"10-JAN","11-FEB","12-MAR","01-APR","02-MAY","03-JUN","04-JUL","05-AUG","06-SEP","07-OCT","08-NOV","09-DEC")) -> 09-DEC | F13: 44896 | G13: Sony Values Poster (5 A4 assets) | H13: Françoise Burgarella | I13: Delivered | J13: Cross | K13: BA | L13: https://saranistudio-my.sharepoint.com/:f:/g/personal/team_sarani_studio/Em0VBaXS7r5GiCtkcsyiCosBToqjoeJ6S1SQLfPqkfkGsQ?e=fEshRi | M13: =IF(SUM(V13:BC13)=0,"-",SUM(V13:BC13)) -> 4 | N13: =IF(SUMPRODUCT($V$3:$BC$3,V13:BC13)=0,"-",SUMPRODUCT($V$3:$BC$3,V13:BC13)) -> 350 | O13: 14/12/2022 | P13: =IF(G13="","",IFERROR(IF(S13="Sent","",IF(I13="Delivered","PO en attente","Projet en cours")),"")) | Q13: 4200631419 | S13: Sent | T13: - | U13: Paid | AC13: 2 | AD13: 2
A14: Sony | B14: SFR | C14: FY22 | D14: =IF(F14="","",CHOOSE(MONTH(F14),"Q4","Q4","Q4","Q1","Q1","Q1","Q2","Q2","Q2","Q3","Q3","Q3")) -> Q3 | E14: =IF(F14="","",CHOOSE(MONTH(F14),"10-JAN","11-FEB","12-MAR","01-APR","02-MAY","03-JUN","04-JUL","05-AUG","06-SEP","07-OCT","08-NOV","09-DEC")) -> 09-DEC | F14: 44896 | G14: LinkBuds S avec SZA | H14: Laura Vivient | I14: Delivered | J14: MDR | K14: BA | L14: https://saranistudio-my.sharepoint.com/:f:/g/personal/team_sarani_studio/Ev2DdJ24TI9DnMYkKwzIkq0BHlTI4PJMje_IlrhSeabtxw?e=g9BnfI | M14: =IF(SUM(V14:BC14)=0,"-",SUM(V14:BC14)) -> 5 | N14: =IF(SUMPRODUCT($V$3:$BC$3,V14:BC14)=0,"-",SUMPRODUCT($V$3:$BC$3,V14:BC14)) -> 175 | O14: 44785 | P14: =IF(G14="","",IFERROR(IF(S14="Sent","",IF(I14="Delivered","PO en attente","Projet en cours")),"")) | Q14: 4200630821 | S14: Sent | T14: - | U14: Paid | W14: 5
A15: Sony | B15: SFR | C15: FY22 | D15: =IF(F15="","",CHOOSE(MONTH(F15),"Q4","Q4","Q4","Q1","Q1","Q1","Q2","Q2","Q2","Q3","Q3","Q3")) -> Q3 | E15: =IF(F15="","",CHOOSE(MONTH(F15),"10-JAN","11-FEB","12-MAR","01-APR","02-MAY","03-JUN","04-JUL","05-AUG","06-SEP","07-OCT","08-NOV","09-DEC")) -> 09-DEC | F15: 44897 | G15: Infographies Xperia 5M4 | H15: Astrid Jean-Baptiste | I15: Delivered | J15: DI | K15: BA | L15: https://saranistudio-my.sharepoint.com/:f:/g/personal/team_sarani_studio/Eu6UoQJssNdAvleXAzibZ1MBJ1RpI-TWGcduRRM37c84hw?e=4VncEj | M15: =IF(SUM(V15:BC15)=0,"-",SUM(V15:BC15)) -> 8 | N15: =IF(SUMPRODUCT($V$3:$BC$3,V15:BC15)=0,"-",SUMPRODUCT($V$3:$BC$3,V15:BC15)) -> 280 | O15: 14/12/2022 | P15: =IF(G15="","",IFERROR(IF(S15="Sent","",IF(I15="Delivered","PO en attente","Projet en cours")),"")) | Q15: 4200631343 | S15: Sent | T15: - | U15: Paid | W15: 8
A16: Sony | B16: SFR | C16: FY22 | D16: =IF(F16="","",CHOOSE(MONTH(F16),"Q4","Q4","Q4","Q1","Q1","Q1","Q2","Q2","Q2","Q3","Q3","Q3")) -> Q3 | E16: =IF(F16="","",CHOOSE(MONTH(F16),"10-JAN","11-FEB","12-MAR","01-APR","02-MAY","03-JUN","04-JUL","05-AUG","06-SEP","07-OCT","08-NOV","09-DEC")) -> 09-DEC | F16: 44909 | G16: Newsletter PRT Décembre | H16: Alice Mucke | I16: Delivered | J16: DI | K16: BA | L16: - | M16: =IF(SUM(V16:BC16)=0,"-",SUM(V16:BC16)) -> 1 | N16: =IF(SUMPRODUCT($V$3:$BC$3,V16:BC16)=0,"-",SUMPRODUCT($V$3:$BC$3,V16:BC16)) -> 600 | O16: 15/12/2022 | P16: =IF(G16="","",IFERROR(IF(S16="Sent","",IF(I16="Delivered","PO en attente","Projet en cours")),"")) | Q16: 4200639267 | S16: Sent | T16: - | U16: Paid | AN16: 1
A17: Sony | B17: SFR | C17: FY22 | D17: =IF(F17="","",CHOOSE(MONTH(F17),"Q4","Q4","Q4","Q1","Q1","Q1","Q2","Q2","Q2","Q3","Q3","Q3")) -> Q3 | E17: =IF(F17="","",CHOOSE(MONTH(F17),"10-JAN","11-FEB","12-MAR","01-APR","02-MAY","03-JUN","04-JUL","05-AUG","06-SEP","07-OCT","08-NOV","09-DEC")) -> 09-DEC | F17: 44914 | G17: OP FAITES VOTRE CINEMA | H17: Astrid Jean-Baptiste | I17: Delivered | J17: DI | K17: BA | L17: https://saranistudio-my.sharepoint.com/:f:/g/personal/team_sarani_studio/EuGwoElxdVxAqUlHd5jwPl0Bd9dIrtw0j4nHaTHU_C0F4Q?e=k1zDEI | M17: =IF(SUM(V17:BC17)=0,"-",SUM(V17:BC17)) -> 7 | N17: =IF(SUMPRODUCT($V$3:$BC$3,V17:BC17)=0,"-",SUMPRODUCT($V$3:$BC$3,V17:BC17)) -> 330 | O17: 44931 | P17: =IF(G17="","",IFERROR(IF(S17="Sent","",IF(I17="Delivered","PO en attente","Projet en cours")),"")) | Q17: 4200633114 | S17: Sent | T17: - | U17: Paid | V17: 1 | W17: 6
A18: Sony | B18: SFR | C18: FY22 | D18: =IF(F18="","",CHOOSE(MONTH(F18),"Q4","Q4","Q4","Q1","Q1","Q1","Q2","Q2","Q2","Q3","Q3","Q3")) -> Q3 | E18: =IF(F18="","",CHOOSE(MONTH(F18),"10-JAN","11-FEB","12-MAR","01-APR","02-MAY","03-JUN","04-JUL","05-AUG","06-SEP","07-OCT","08-NOV","09-DEC")) -> 09-DEC | F18: 44914 | G18: VITRO A7RV | H18: Astrid Jean-Baptiste | I18: Delivered | J18: DI | K18: BA | L18: https://saranistudio-my.sharepoint.com/:f:/g/personal/team_sarani_studio/El0REgOxzW1Eiu8AI5a8WPQBuRgA-xuGK77IgcuOUuwGhw?e=jWWT4e | M18: =IF(SUM(V18:BC18)=0,"-",SUM(V18:BC18)) -> 20 | N18: =IF(SUMPRODUCT($V$3:$BC$3,V18:BC18)=0,"-",SUMPRODUCT($V$3:$BC$3,V18:BC18)) -> 895 | O18: 44943 | P18: =IF(G18="","",IFERROR(IF(S18="Sent","",IF(I18="Delivered","PO en attente","Projet en cours")),"")) | Q18: 4200633341 | S18: Sent | T18: - | U18: Paid | AC18: 1 | AD18: 19
A19: Sony | B19: SFR | C19: FY22 | D19: =IF(F19="","",CHOOSE(MONTH(F19),"Q4","Q4","Q4","Q1","Q1","Q1","Q2","Q2","Q2","Q3","Q3","Q3")) -> Q3 | E19: =IF(F19="","",CHOOSE(MONTH(F19),"10-JAN","11-FEB","12-MAR","01-APR","02-MAY","03-JUN","04-JUL","05-AUG","06-SEP","07-OCT","08-NOV","09-DEC")) -> 09-DEC | F19: 44914 | G19: PANNEAU PHOTO HAUT VITRINE | H19: Astrid Jean-Baptiste | I19: Delivered | J19: DI | K19: BA | L19: https://saranistudio-my.sharepoint.com/:f:/g/personal/team_sarani_studio/En0xaWGTYWZOtWFNrWlERJYBEkKsluD4U7oLp_2fMTfyPA?e=3dNfLG | M19: =IF(SUM(V19:BC19)=0,"-",SUM(V19:BC19)) -> 11 | N19: =IF(SUMPRODUCT($V$3:$BC$3,V19:BC19)=0,"-",SUMPRODUCT($V$3:$BC$3,V19:BC19)) -> 535 | O19: 44931 | P19: =IF(G19="","",IFERROR(IF(S19="Sent","",IF(I19="Delivered","PO en attente","Projet en cours")),"")) | Q19: 4200633116 | S19: Sent | T19: - | U19: Paid | AC19: 1 | AD19: 10
A20: Sony | B20: SFR | C20: FY22 | D20: =IF(F20="","",CHOOSE(MONTH(F20),"Q4","Q4","Q4","Q1","Q1","Q1","Q2","Q2","Q2","Q3","Q3","Q3")) -> Q3 | E20: =IF(F20="","",CHOOSE(MONTH(F20),"10-JAN","11-FEB","12-MAR","01-APR","02-MAY","03-JUN","04-JUL","05-AUG","06-SEP","07-OCT","08-NOV","09-DEC")) -> 09-DEC | F20: 44916 | G20: Winter Sales Banners adaptations DI | H20: Astrid Jean-Baptiste | I20: Delivered | J20: DI | K20: BA | L20: https://saranistudio-my.sharepoint.com/:f:/g/personal/team_sarani_studio/EitZRBZy2n1Kkw5kaWztE5sBgYKU_BFeDcX25iDrx1Ct5w?e=j19Nkg | M20: =IF(SUM(V20:BC20)=0,"-",SUM(V20:BC20)) -> 9 | N20: =IF(SUMPRODUCT($V$3:$BC$3,V20:BC20)=0,"-",SUMPRODUCT($V$3:$BC$3,V20:BC20)) -> 315 | O20: 44931 | P20: =IF(G20="","",IFERROR(IF(S20="Sent","",IF(I20="Delivered","PO en attente","Projet en cours")),"")) | Q20: 4200632799 | S20: Sent | T20: - | U20: Paid | W20: 9
A21: Sony | B21: SFR | C21: FY22 | D21: =IF(F21="","",CHOOSE(MONTH(F21),"Q4","Q4","Q4","Q1","Q1","Q1","Q2","Q2","Q2","Q3","Q3","Q3")) -> Q3 | E21: =IF(F21="","",CHOOSE(MONTH(F21),"10-JAN","11-FEB","12-MAR","01-APR","02-MAY","03-JUN","04-JUL","05-AUG","06-SEP","07-OCT","08-NOV","09-DEC")) -> 09-DEC | F21: 44917 | G21: Micromania Boites Factices Update | H21: Alice Mucke | I21: Delivered | J21: MDR | K21: CM | L21: https://saranistudio-my.sharepoint.com/:f:/g/personal/team_sarani_studio/Ehi8kv4332BOmhmF0GTdxqcBXMS0bXPqJJq-QzgW5N5jlg?e=BJOqXJ | M21: =IF(SUM(V21:BC21)=0,"-",SUM(V21:BC21)) -> 5 | N21: =IF(SUMPRODUCT($V$3:$BC$3,V21:BC21)=0,"-",SUMPRODUCT($V$3:$BC$3,V21:BC21)) -> 360 | O21: 44931 | P21: =IF(G21="","",IFERROR(IF(S21="Sent","",IF(I21="Delivered","PO en attente","Projet en cours")),"")) | Q21: 4200635815 | S21: Sent | T21: - | U21: Paid | AD21: 4 | AG21: 1
A22: Sony | B22: SFR | C22: FY22 | D22: =IF(F22="","",CHOOSE(MONTH(F22),"Q4","Q4","Q4","Q1","Q1","Q1","Q2","Q2","Q2","Q3","Q3","Q3")) -> Q3 | E22: =IF(F22="","",CHOOSE(MONTH(F22),"10-JAN","11-FEB","12-MAR","01-APR","02-MAY","03-JUN","04-JUL","05-AUG","06-SEP","07-OCT","08-NOV","09-DEC")) -> 09-DEC | F22: 44923 | G22: Invitation Dealers Days | H22: Héloïse Leroy | I22: Delivered | J22: Cross | K22: BA | L22: https://saranistudio-my.sharepoint.com/:f:/g/personal/team_sarani_studio/EqmJWhjv9h9NosYk49rtluQBxvyRtTDdxMXLJdwMK-1B6g?e=mNiTFd | M22: =IF(SUM(V22:BC22)=0,"-",SUM(V22:BC22)) -> 0.5 | N22: =IF(SUMPRODUCT($V$3:$BC$3,V22:BC22)=0,"-",SUMPRODUCT($V$3:$BC$3,V22:BC22)) -> 300 | O22: 44931 | P22: =IF(G22="","",IFERROR(IF(S22="Sent","",IF(I22="Delivered","PO en attente","Projet en cours")),"")) | Q22: 4200634748 | S22: Sent | T22: - | U22: Paid | AN22: 0.5
A23: Sony | B23: SFR | C23: FY22 | D23: =IF(F23="","",CHOOSE(MONTH(F23),"Q4","Q4","Q4","Q1","Q1","Q1","Q2","Q2","Q2","Q3","Q3","Q3")) -> Q4 | E23: =IF(F23="","",CHOOSE(MONTH(F23),"10-JAN","11-FEB","12-MAR","01-APR","02-MAY","03-JUN","04-JUL","05-AUG","06-SEP","07-OCT","08-NOV","09-DEC")) -> 10-JAN | F23: 44928 | G23: OP FX3 Assets | H23: Astrid Jean-Baptiste | I23: Delivered | J23: DI | K23: BA | L23: https://saranistudio-my.sharepoint.com/:f:/g/personal/team_sarani_studio/EitCbbZcUbZAkfWL7WBLee8BGH7SK4bXE2Dt7jdZHoYz1g?e=PygYN7 | M23: =IF(SUM(V23:BC23)=0,"-",SUM(V23:BC23)) -> 6 | N23: =IF(SUMPRODUCT($V$3:$BC$3,V23:BC23)=0,"-",SUMPRODUCT($V$3:$BC$3,V23:BC23)) -> 295 | O23: 44931 | P23: =IF(G23="","",IFERROR(IF(S23="Sent","",IF(I23="Delivered","PO en attente","Projet en cours")),"")) | Q23: 4200632673 | S23: Sent | T23: - | U23: Paid | V23: 1 | W23: 5
A24: Sony | B24: SFR | C24: FY22 | D24: =IF(F24="","",CHOOSE(MONTH(F24),"Q4","Q4","Q4","Q1","Q1","Q1","Q2","Q2","Q2","Q3","Q3","Q3")) -> Q4 | E24: =IF(F24="","",CHOOSE(MONTH(F24),"10-JAN","11-FEB","12-MAR","01-APR","02-MAY","03-JUN","04-JUL","05-AUG","06-SEP","07-OCT","08-NOV","09-DEC")) -> 10-JAN | F24: 44928 | G24: OP Trade In Janvier | H24: Astrid Jean-Baptiste | I24: Delivered | J24: DI | K24: BA | L24: https://saranistudio-my.sharepoint.com/:f:/g/personal/team_sarani_studio/EoitW15aeoVAtVoerfyyJgAB8NtwzeqQjRMP7QJz7L-yow?e=jCYZtF | M24: =IF(SUM(V24:BC24)=0,"-",SUM(V24:BC24)) -> 6 | N24: =IF(SUMPRODUCT($V$3:$BC$3,V24:BC24)=0,"-",SUMPRODUCT($V$3:$BC$3,V24:BC24)) -> 295 | O24: 44931 | P24: =IF(G24="","",IFERROR(IF(S24="Sent","",IF(I24="Delivered","PO en attente","Projet en cours")),"")) | Q24: 4200632670 | S24: Sent | T24: - | U24: Paid | V24: 1 | W24: 5
A25: Sony | B25: SFR | C25: FY22 | D25: =IF(F25="","",CHOOSE(MONTH(F25),"Q4","Q4","Q4","Q1","Q1","Q1","Q2","Q2","Q2","Q3","Q3","Q3")) -> Q4 | E25: =IF(F25="","",CHOOSE(MONTH(F25),"10-JAN","11-FEB","12-MAR","01-APR","02-MAY","03-JUN","04-JUL","05-AUG","06-SEP","07-OCT","08-NOV","09-DEC")) -> 10-JAN | F25: 44928 | G25: Banners Inzone soldes | H25: Léa Novio | I25: Delivered | J25: MDR | K25: BA | L25: https://saranistudio-my.sharepoint.com/:f:/g/personal/team_sarani_studio/EuGDS2OAMPpGu_ldGvZT0DMBpcZ-xeMJpp8v2XzS9CAt0g?e=xhsdm9 | M25: =IF(SUM(V25:BC25)=0,"-",SUM(V25:BC25)) -> 6 | N25: =IF(SUMPRODUCT($V$3:$BC$3,V25:BC25)=0,"-",SUMPRODUCT($V$3:$BC$3,V25:BC25)) -> 380 | O25: 44931 | P25: =IF(G25="","",IFERROR(IF(S25="Sent","",IF(I25="Delivered","PO en attente","Projet en cours")),"")) | Q25: 4200633093 | S25: Sent | T25: - | U25: Paid | V25: 2 | W25: 4
A26: Sony | B26: SFR | C26: FY22 | D26: =IF(F26="","",CHOOSE(MONTH(F26),"Q4","Q4","Q4","Q1","Q1","Q1","Q2","Q2","Q2","Q3","Q3","Q3")) -> Q4 | E26: =IF(F26="","",CHOOSE(MONTH(F26),"10-JAN","11-FEB","12-MAR","01-APR","02-MAY","03-JUN","04-JUL","05-AUG","06-SEP","07-OCT","08-NOV","09-DEC")) -> 10-JAN | F26: 44930 | G26: Infographies NW-A306 | H26: Laura Vivient | I26: Delivered | J26: MDR | K26: BA | L26: https://saranistudio-my.sharepoint.com/:f:/g/personal/team_sarani_studio/Ev8VV5oNGQpDt88C9YGvPJ0BeWvCOnfN80JI8f52rlCkDA?e=svUNka | M26: =IF(SUM(V26:BC26)=0,"-",SUM(V26:BC26)) -> 9 | N26: =IF(SUMPRODUCT($V$3:$BC$3,V26:BC26)=0,"-",SUMPRODUCT($V$3:$BC$3,V26:BC26)) -> 315 | O26: 44943 | P26: =IF(G26="","",IFERROR(IF(S26="Sent","",IF(I26="Delivered","PO en attente","Projet en cours")),"")) | Q26: 4200634882 | S26: Sent | T26: - | U26: Paid | W26: 9
A27: Sony | B27: SFR | C27: FY22 | D27: =IF(F27="","",CHOOSE(MONTH(F27),"Q4","Q4","Q4","Q1","Q1","Q1","Q2","Q2","Q2","Q3","Q3","Q3")) -> Q4 | E27: =IF(F27="","",CHOOSE(MONTH(F27),"10-JAN","11-FEB","12-MAR","01-APR","02-MAY","03-JUN","04-JUL","05-AUG","06-SEP","07-OCT","08-NOV","09-DEC")) -> 10-JAN | F27: 44930 | G27: HAV Brief créa ILV A4 accessoires | H27: Léa Novio | I27: Delivered | J27: TV | K27: BA | L27: https://saranistudio-my.sharepoint.com/:f:/g/personal/team_sarani_studio/ErATZuFVVhFNvJLA8_C_5_kBPisr2V-sQmmcvuADdnOrlg?e=Jt6Yhl | M27: =IF(SUM(V27:BC27)=0,"-",SUM(V27:BC27)) -> 4 | N27: =IF(SUMPRODUCT($V$3:$BC$3,V27:BC27)=0,"-",SUMPRODUCT($V$3:$BC$3,V27:BC27)) -> 300 | O27: 44941 | P27: =IF(G27="","",IFERROR(IF(S27="Sent","",IF(I27="Delivered","PO en attente","Projet en cours")),"")) | Q27: 4200635620 | S27: Sent | T27: - | U27: Paid | AD27: 3 | AE27: 1
A28: Sony | B28: SFR | C28: FY22 | D28: =IF(F28="","",CHOOSE(MONTH(F28),"Q4","Q4","Q4","Q1","Q1","Q1","Q2","Q2","Q2","Q3","Q3","Q3")) -> Q4 | E28: =IF(F28="","",CHOOSE(MONTH(F28),"10-JAN","11-FEB","12-MAR","01-APR","02-MAY","03-JUN","04-JUL","05-AUG","06-SEP","07-OCT","08-NOV","09-DEC")) -> 10-JAN | F28: 44931 | G28: CREA SOLDES - XB300 | H28: Françoise Burgarella | I28: Delivered | J28: PAG | K28: BA | L28: https://saranistudio-my.sharepoint.com/:f:/g/personal/team_sarani_studio/EqOyYJkBr71FjjKi8T4TbU8BmZDWzGHq4lIzmPemScoNIg?e=gSGgM9 | M28: =IF(SUM(V28:BC28)=0,"-",SUM(V28:BC28)) -> 4 | N28: =IF(SUMPRODUCT($V$3:$BC$3,V28:BC28)=0,"-",SUMPRODUCT($V$3:$BC$3,V28:BC28)) -> 140 | O28: 44942 | P28: =IF(G28="","",IFERROR(IF(S28="Sent","",IF(I28="Delivered","PO en attente","Projet en cours")),"")) | Q28: 4200633321 | S28: Sent | T28: - | U28: Paid | W28: 4
A29: Sony | B29: SFR | C29: FY22 | D29: =IF(F29="","",CHOOSE(MONTH(F29),"Q4","Q4","Q4","Q1","Q1","Q1","Q2","Q2","Q2","Q3","Q3","Q3")) -> Q4 | E29: =IF(F29="","",CHOOSE(MONTH(F29),"10-JAN","11-FEB","12-MAR","01-APR","02-MAY","03-JUN","04-JUL","05-AUG","06-SEP","07-OCT","08-NOV","09-DEC")) -> 10-JAN | F29: 44936 | G29: Update - Plan merch DI | H29: Alice Mucke | I29: Delivered | J29: DI | K29: CM | L29: https://saranistudio-my.sharepoint.com/:f:/g/personal/team_sarani_studio/EgL726Ww1tBPiY3JLeGkgKABHLa4iBWeCZvZMffXcTD0Ow?e=Ev0d8h | M29: =IF(SUM(V29:BC29)=0,"-",SUM(V29:BC29)) -> 2 | N29: =IF(SUMPRODUCT($V$3:$BC$3,V29:BC29)=0,"-",SUMPRODUCT($V$3:$BC$3,V29:BC29)) -> 500 | O29: 45006 | P29: =IF(G29="","",IFERROR(IF(S29="Sent","",IF(I29="Delivered","PO en attente","Projet en cours")),"")) | Q29: 4200639269 | S29: Sent | T29: - | U29: Paid | AH29: 2
A30: Sony | B30: SFR | C30: FY22 | D30: =IF(F30="","",CHOOSE(MONTH(F30),"Q4","Q4","Q4","Q1","Q1","Q1","Q2","Q2","Q2","Q3","Q3","Q3")) -> Q4 | E30: =IF(F30="","",CHOOSE(MONTH(F30),"10-JAN","11-FEB","12-MAR","01-APR","02-MAY","03-JUN","04-JUL","05-AUG","06-SEP","07-OCT","08-NOV","09-DEC")) -> 10-JAN | F30: 44938 | G30: Additional DI assets | H30: Alice Mucke | I30: Delivered | J30: DI | K30: CM | L30: https://saranistudio-my.sharepoint.com/:f:/g/personal/team_sarani_studio/EitZRBZy2n1Kkw5kaWztE5sBgYKU_BFeDcX25iDrx1Ct5w?e=j19Nkg | M30: =IF(SUM(V30:BC30)=0,"-",SUM(V30:BC30)) -> 4 | N30: =IF(SUMPRODUCT($V$3:$BC$3,V30:BC30)=0,"-",SUMPRODUCT($V$3:$BC$3,V30:BC30)) -> 145 | O30: 44941 | P30: =IF(G30="","",IFERROR(IF(S30="Sent","",IF(I30="Delivered","PO en attente","Projet en cours")),"")) | Q30: 4200639281 | S30: Sent | T30: - | U30: Paid | W30: 3 | AD30: 1
A31: Sony | B31: SFR | C31: FY22 | D31: =IF(F31="","",CHOOSE(MONTH(F31),"Q4","Q4","Q4","Q1","Q1","Q1","Q2","Q2","Q2","Q3","Q3","Q3")) -> Q4 | E31: =IF(F31="","",CHOOSE(MONTH(F31),"10-JAN","11-FEB","12-MAR","01-APR","02-MAY","03-JUN","04-JUL","05-AUG","06-SEP","07-OCT","08-NOV","09-DEC")) -> 10-JAN | F31: 44938 | G31: PSK - Refresh Inlay display PSK HYPERS | H31: Laura Vivient | I31: Delivered | J31: PAG | K31: BA | L31: https://saranistudio-my.sharepoint.com/:f:/g/personal/team_sarani_studio/EtI6MF01VhJDu73LzSQ3CuMBaxqkBPUNcHfWG9NmZXKZGA?e=cAjunF | M31: =IF(SUM(V31:BC31)=0,"-",SUM(V31:BC31)) -> 2 | N31: =IF(SUMPRODUCT($V$3:$BC$3,V31:BC31)=0,"-",SUMPRODUCT($V$3:$BC$3,V31:BC31)) -> 80 | O31: 44941 | P31: =IF(G31="","",IFERROR(IF(S31="Sent","",IF(I31="Delivered","PO en attente","Projet en cours")),"")) | Q31: 4270024966 | S31: Sent | T31: - | U31: Paid | AD31: 2
A32: Sony | B32: SFR | C32: FY22 | D32: =IF(F32="","",CHOOSE(MONTH(F32),"Q4","Q4","Q4","Q1","Q1","Q1","Q2","Q2","Q2","Q3","Q3","Q3")) -> Q4 | E32: =IF(F32="","",CHOOSE(MONTH(F32),"10-JAN","11-FEB","12-MAR","01-APR","02-MAY","03-JUN","04-JUL","05-AUG","06-SEP","07-OCT","08-NOV","09-DEC")) -> 10-JAN | F32: 44942 | G32: Newsletter PRT Janvier | H32: Alice Mucke | I32: Delivered | J32: DI | K32: BA | L32: - | M32: =IF(SUM(V32:BC32)=0,"-",SUM(V32:BC32)) -> 1 | N32: =IF(SUMPRODUCT($V$3:$BC$3,V32:BC32)=0,"-",SUMPRODUCT($V$3:$BC$3,V32:BC32)) -> 600 | O32: 44950 | P32: =IF(G32="","",IFERROR(IF(S32="Sent","",IF(I32="Delivered","PO en attente","Projet en cours")),"")) | Q32: 4200639268 | S32: Sent | T32: - | U32: Paid | AN32: 1
A33: Sony | B33: SFR | C33: FY22 | D33: =IF(F33="","",CHOOSE(MONTH(F33),"Q4","Q4","Q4","Q1","Q1","Q1","Q2","Q2","Q2","Q3","Q3","Q3")) -> Q4 | E33: =IF(F33="","",CHOOSE(MONTH(F33),"10-JAN","11-FEB","12-MAR","01-APR","02-MAY","03-JUN","04-JUL","05-AUG","06-SEP","07-OCT","08-NOV","09-DEC")) -> 10-JAN | F33: 44943 | G33: Lenses 3D Virtual Showroom | H33: Alice Mucke | I33: Delivered | J33: DI | K33: CM | L33: - | M33: =IF(SUM(V33:BC33)=0,"-",SUM(V33:BC33)) -> 1.2 | N33: =IF(SUMPRODUCT($V$3:$BC$3,V33:BC33)=0,"-",SUMPRODUCT($V$3:$BC$3,V33:BC33)) -> 3000 | O33: 44950 | P33: =IF(G33="","",IFERROR(IF(S33="Sent","",IF(I33="Delivered","PO en attente","Projet en cours")),"")) | Q33: 4200639270 | S33: Sent | T33: - | U33: Paid | AZ33: =3000/2500 -> 1.2
A34: Sony | B34: SFR | C34: FY22 | D34: =IF(F34="","",CHOOSE(MONTH(F34),"Q4","Q4","Q4","Q1","Q1","Q1","Q2","Q2","Q2","Q3","Q3","Q3")) -> Q4 | E34: =IF(F34="","",CHOOSE(MONTH(F34),"10-JAN","11-FEB","12-MAR","01-APR","02-MAY","03-JUN","04-JUL","05-AUG","06-SEP","07-OCT","08-NOV","09-DEC")) -> 10-JAN | F34: 44943 | G34: Bannières New VX8030 | H34: Astrid Jean-Baptiste | I34: Delivered | J34: DI | K34: BA | L34: https://saranistudio-my.sharepoint.com/:f:/g/personal/team_sarani_studio/EksBlAWoBtxAkG5l32B3Di0BbzDMWHG22vO5j0H6ctS9zw?e=RqK3BS | M34: =IF(SUM(V34:BC34)=0,"-",SUM(V34:BC34)) -> 4 | N34: =IF(SUMPRODUCT($V$3:$BC$3,V34:BC34)=0,"-",SUMPRODUCT($V$3:$BC$3,V34:BC34)) -> 140 | O34: 44950 | P34: =IF(G34="","",IFERROR(IF(S34="Sent","",IF(I34="Delivered","PO en attente","Projet en cours")),"")) | Q34: 4200633858 | S34: Sent | T34: - | U34: Paid | W34: 4
A35: Sony | B35: SFR | C35: FY22 | D35: =IF(F35="","",CHOOSE(MONTH(F35),"Q4","Q4","Q4","Q1","Q1","Q1","Q2","Q2","Q2","Q3","Q3","Q3")) -> Q4 | E35: =IF(F35="","",CHOOSE(MONTH(F35),"10-JAN","11-FEB","12-MAR","01-APR","02-MAY","03-JUN","04-JUL","05-AUG","06-SEP","07-OCT","08-NOV","09-DEC")) -> 10-JAN | F35: 44944 | G35: HAS - podium High Power Leclerc | H35: Laura Vivient | I35: Delivered | J35: PAG | K35: BA | L35: https://saranistudio-my.sharepoint.com/:f:/g/personal/team_sarani_studio/Euz7AgxtBlxIhnwZ-lXXmF4BeflqaS0GTyKxYGbCz-vMlw?e=IjE9RV | M35: =IF(SUM(V35:BC35)=0,"-",SUM(V35:BC35)) -> 5 | N35: =IF(SUMPRODUCT($V$3:$BC$3,V35:BC35)=0,"-",SUMPRODUCT($V$3:$BC$3,V35:BC35)) -> 485 | O35: 44963 | P35: =IF(G35="","",IFERROR(IF(S35="Sent","",IF(I35="Delivered","PO en attente","Projet en cours")),"")) | Q35: 4200634883 | S35: Sent | T35: - | U35: Paid | AC35: 3 | AD35: 2
A36: Sony | B36: SFR | C36: FY22 | D36: =IF(F36="","",CHOOSE(MONTH(F36),"Q4","Q4","Q4","Q1","Q1","Q1","Q2","Q2","Q2","Q3","Q3","Q3")) -> Q4 | E36: =IF(F36="","",CHOOSE(MONTH(F36),"10-JAN","11-FEB","12-MAR","01-APR","02-MAY","03-JUN","04-JUL","05-AUG","06-SEP","07-OCT","08-NOV","09-DEC")) -> 10-JAN | F36: 44951 | G36: Dealer Days 2023 DI | H36: Héloïse Leroy | I36: Delivered | J36: DI | K36: BA | L36: https://saranistudio-my.sharepoint.com/:f:/g/personal/team_sarani_studio/EmLaqFBj_51MjXZHYWWXnkoBLAa6nzoR1xsPq4BDMu7-cw?e=t3K8Ml | M36: =IF(SUM(V36:BC36)=0,"-",SUM(V36:BC36)) -> 3 | N36: =IF(SUMPRODUCT($V$3:$BC$3,V36:BC36)=0,"-",SUMPRODUCT($V$3:$BC$3,V36:BC36)) -> 310 | O36: 44963 | P36: =IF(G36="","",IFERROR(IF(S36="Sent","",IF(I36="Delivered","PO en attente","Projet en cours")),"")) | Q36: 4200635109 | S36: Sent | T36: - | U36: Paid | AC36: 2 | AD36: 1
A37: Sony | B37: SFR | C37: FY22 | D37: =IF(F37="","",CHOOSE(MONTH(F37),"Q4","Q4","Q4","Q1","Q1","Q1","Q2","Q2","Q2","Q3","Q3","Q3")) -> Q4 | E37: =IF(F37="","",CHOOSE(MONTH(F37),"10-JAN","11-FEB","12-MAR","01-APR","02-MAY","03-JUN","04-JUL","05-AUG","06-SEP","07-OCT","08-NOV","09-DEC")) -> 10-JAN | F37: 44951 | G37: HAV ILV4 et Awards | H37: Léa Novio | I37: Delivered | J37: TV | K37: BA | L37: https://saranistudio-my.sharepoint.com/:f:/g/personal/team_sarani_studio/EiFOxcsYWW5HrKMAqEXG268BJdUb73tPaidZ2aUpOjrqGbMw?e=ZjeN6x | M37: =IF(SUM(V37:BC37)=0,"-",SUM(V37:BC37)) -> 2 | N37: =IF(SUMPRODUCT($V$3:$BC$3,V37:BC37)=0,"-",SUMPRODUCT($V$3:$BC$3,V37:BC37)) -> 215 | O37: 44963 | P37: =IF(G37="","",IFERROR(IF(S37="Sent","",IF(I37="Delivered","PO en attente","Projet en cours")),"")) | Q37: 4200638979 | S37: Sent | T37: - | U37: Paid | W37: 1 | AE37: 1
A38: Sony | B38: SFR | C38: FY22 | D38: =IF(F38="","",CHOOSE(MONTH(F38),"Q4","Q4","Q4","Q1","Q1","Q1","Q2","Q2","Q2","Q3","Q3","Q3")) -> Q4 | E38: =IF(F38="","",CHOOSE(MONTH(F38),"10-JAN","11-FEB","12-MAR","01-APR","02-MAY","03-JUN","04-JUL","05-AUG","06-SEP","07-OCT","08-NOV","09-DEC")) -> 10-JAN | F38: 44956 | G38: Glorifier Boulanger ZV 1F | H38: Astrid Jean-Baptiste | I38: Delivered | J38: DI | K38: BA | L38: https://saranistudio-my.sharepoint.com/:f:/g/personal/team_sarani_studio/Et8JT6N3J55Khs36INxlBgQBUbyHbYyC93L5UVW3Wg41vA?e=Q1dlBF | M38: =IF(SUM(V38:BC38)=0,"-",SUM(V38:BC38)) -> 2 | N38: =IF(SUMPRODUCT($V$3:$BC$3,V38:BC38)=0,"-",SUMPRODUCT($V$3:$BC$3,V38:BC38)) -> 270 | O38: 44963 | P38: =IF(G38="","",IFERROR(IF(S38="Sent","",IF(I38="Delivered","PO en attente","Projet en cours")),"")) | Q38: 4200636045 | S38: Sent | T38: - | U38: Paid | AC38: 2
A39: Sony | B39: SFR | C39: FY22 | D39: =IF(F39="","",CHOOSE(MONTH(F39),"Q4","Q4","Q4","Q1","Q1","Q1","Q2","Q2","Q2","Q3","Q3","Q3")) -> Q4 | E39: =IF(F39="","",CHOOSE(MONTH(F39),"10-JAN","11-FEB","12-MAR","01-APR","02-MAY","03-JUN","04-JUL","05-AUG","06-SEP","07-OCT","08-NOV","09-DEC")) -> 10-JAN | F39: 44956 | G39: LANCEMENT CH720 / CH520 | H39: Laura Vivient | I39: Delivered | J39: MDR | K39: BA | L39: https://saranistudio-my.sharepoint.com/:f:/g/personal/team_sarani_studio/EqrCH40AdxVPsCGpjT8TB8wB_B709B2_yzvFX8TAKmXMlg?e=JQ9afM | M39: =IF(SUM(V39:BC39)=0,"-",SUM(V39:BC39)) -> 27 | N39: =IF(SUMPRODUCT($V$3:$BC$3,V39:BC39)=0,"-",SUMPRODUCT($V$3:$BC$3,V39:BC39)) -> 945 | O39: 44963 | P39: =IF(G39="","",IFERROR(IF(S39="Sent","",IF(I39="Delivered","PO en attente","Projet en cours")),"")) | Q39: 4200637328 | S39: Sent | T39: - | U39: Paid | W39: 27
A40: Sony | B40: SFR | C40: FY22 | D40: =IF(F40="","",CHOOSE(MONTH(F40),"Q4","Q4","Q4","Q1","Q1","Q1","Q2","Q2","Q2","Q3","Q3","Q3")) -> Q4 | E40: =IF(F40="","",CHOOSE(MONTH(F40),"10-JAN","11-FEB","12-MAR","01-APR","02-MAY","03-JUN","04-JUL","05-AUG","06-SEP","07-OCT","08-NOV","09-DEC")) -> 11-FEB | F40: 44964 | G40: Fiche produit WHCH720-520N | H40: Laura Vivient | I40: Delivered | J40: MDR | K40: BA | L40: https://saranistudio-my.sharepoint.com/:f:/g/personal/team_sarani_studio/EjWeixWwgG9KtdKsd3nfu10B4P2-8KWwWAHTtBQASfQ6Rg?e=c0kl8T | M40: =IF(SUM(V40:BC40)=0,"-",SUM(V40:BC40)) -> 2 | N40: =IF(SUMPRODUCT($V$3:$BC$3,V40:BC40)=0,"-",SUMPRODUCT($V$3:$BC$3,V40:BC40)) -> 500 | O40: 44978 | P40: =IF(G40="","",IFERROR(IF(S40="Sent","",IF(I40="Delivered","PO en attente","Projet en cours")),"")) | Q40: 4200637327 | S40: Sent | T40: - | U40: Paid | AF40: 2
A41: Sony | B41: SFR | C41: FY22 | D41: =IF(F41="","",CHOOSE(MONTH(F41),"Q4","Q4","Q4","Q1","Q1","Q1","Q2","Q2","Q2","Q3","Q3","Q3")) -> Q4 | E41: =IF(F41="","",CHOOSE(MONTH(F41),"10-JAN","11-FEB","12-MAR","01-APR","02-MAY","03-JUN","04-JUL","05-AUG","06-SEP","07-OCT","08-NOV","09-DEC")) -> 11-FEB | F41: 44964 | G41: Adaptation WE LIVE FOR THE MUSIC backdrop LOCAL | H41: Laura Vivient | I41: Delivered | J41: MDR | K41: BA | L41: https://saranistudio-my.sharepoint.com/:f:/g/personal/team_sarani_studio/EhV2y_XPV35GlXBIYHQS6jABX0y5PDDKSwC4di7PXUrm9w?e=g9nzP1 | M41: =IF(SUM(V41:BC41)=0,"-",SUM(V41:BC41)) -> 5 | N41: =IF(SUMPRODUCT($V$3:$BC$3,V41:BC41)=0,"-",SUMPRODUCT($V$3:$BC$3,V41:BC41)) -> 200 | O41: 44978 | P41: =IF(G41="","",IFERROR(IF(S41="Sent","",IF(I41="Delivered","PO en attente","Projet en cours")),"")) | Q41: 4200637329 | S41: Sent | T41: - | U41: Paid | AD41: 5
A42: Sony | B42: SFR | C42: FY22 | D42: =IF(F42="","",CHOOSE(MONTH(F42),"Q4","Q4","Q4","Q1","Q1","Q1","Q2","Q2","Q2","Q3","Q3","Q3")) -> Q4 | E42: =IF(F42="","",CHOOSE(MONTH(F42),"10-JAN","11-FEB","12-MAR","01-APR","02-MAY","03-JUN","04-JUL","05-AUG","06-SEP","07-OCT","08-NOV","09-DEC")) -> 11-FEB | F42: 44965 | G42: OP Tryptique | H42: Astrid Jean-Baptiste | I42: Delivered | J42: DI | K42: BA | L42: https://saranistudio-my.sharepoint.com/:f:/g/personal/team_sarani_studio/Evv4GLCeCfpNtcFppwmuF4gBs0wDfkYfUCp2XZgOusP4jA?e=VUWW5q | M42: =IF(SUM(V42:BC42)=0,"-",SUM(V42:BC42)) -> 6 | N42: =IF(SUMPRODUCT($V$3:$BC$3,V42:BC42)=0,"-",SUMPRODUCT($V$3:$BC$3,V42:BC42)) -> 210 | O42: 44978 | P42: =IF(G42="","",IFERROR(IF(S42="Sent","",IF(I42="Delivered","PO en attente","Projet en cours")),"")) | Q42: 4200639098 | S42: Sent | T42: - | U42: Paid | W42: 6
A43: Sony | B43: SFR | C43: FY22 | D43: =IF(F43="","",CHOOSE(MONTH(F43),"Q4","Q4","Q4","Q1","Q1","Q1","Q2","Q2","Q2","Q3","Q3","Q3")) -> Q4 | E43: =IF(F43="","",CHOOSE(MONTH(F43),"10-JAN","11-FEB","12-MAR","01-APR","02-MAY","03-JUN","04-JUL","05-AUG","06-SEP","07-OCT","08-NOV","09-DEC")) -> 11-FEB | F43: 44970 | G43: OP Trade In Février | H43: Astrid Jean-Baptiste | I43: Delivered | J43: DI | K43: BA | L43: https://saranistudio-my.sharepoint.com/:f:/g/personal/team_sarani_studio/Eslmo5VnmeBOls9PXeiKfcsB6Y_V2-ku-io7Yd_KczQicQ?e=vV1ZSQ | M43: =IF(SUM(V43:BC43)=0,"-",SUM(V43:BC43)) -> 11 | N43: =IF(SUMPRODUCT($V$3:$BC$3,V43:BC43)=0,"-",SUMPRODUCT($V$3:$BC$3,V43:BC43)) -> 495 | O43: 44978 | P43: =IF(G43="","",IFERROR(IF(S43="Sent","",IF(I43="Delivered","PO en attente","Projet en cours")),"")) | Q43: 4200636098 | S43: Sent | T43: - | U43: Paid | V43: 1 | W43: 5 | AD43: 5
A44: Sony | B44: SFR | C44: FY22 | D44: =IF(F44="","",CHOOSE(MONTH(F44),"Q4","Q4","Q4","Q1","Q1","Q1","Q2","Q2","Q2","Q3","Q3","Q3")) -> Q4 | E44: =IF(F44="","",CHOOSE(MONTH(F44),"10-JAN","11-FEB","12-MAR","01-APR","02-MAY","03-JUN","04-JUL","05-AUG","06-SEP","07-OCT","08-NOV","09-DEC")) -> 11-FEB | F44: 44970 | G44: Inlay CH720 | H44: Laura Vivient | I44: Delivered | J44: MDR | K44: BA | L44: https://saranistudio-my.sharepoint.com/:f:/g/personal/team_sarani_studio/EvdB_pa-nYlJjcn2m_-V6CIBlwvd0lovLbZhSbor2xacAQ?e=54JYDm | M44: =IF(SUM(V44:BC44)=0,"-",SUM(V44:BC44)) -> 4 | N44: =IF(SUMPRODUCT($V$3:$BC$3,V44:BC44)=0,"-",SUMPRODUCT($V$3:$BC$3,V44:BC44)) -> 350 | O44: 44978 | P44: =IF(G44="","",IFERROR(IF(S44="Sent","",IF(I44="Delivered","PO en attente","Projet en cours")),"")) | Q44: 4200639013 | S44: Sent | T44: - | U44: Paid | AC44: 2 | AD44: 2
A45: Sony | B45: SFR | C45: FY22 | D45: =IF(F45="","",CHOOSE(MONTH(F45),"Q4","Q4","Q4","Q1","Q1","Q1","Q2","Q2","Q2","Q3","Q3","Q3")) -> Q4 | E45: =IF(F45="","",CHOOSE(MONTH(F45),"10-JAN","11-FEB","12-MAR","01-APR","02-MAY","03-JUN","04-JUL","05-AUG","06-SEP","07-OCT","08-NOV","09-DEC")) -> 11-FEB | F45: 44971 | G45: OP REMISE IMMEDIATE DI | H45: Astrid Jean-Baptiste | I45: Delivered | J45: DI | K45: BA | L45: https://saranistudio-my.sharepoint.com/:f:/g/personal/team_sarani_studio/Emm2wYCHbftLi5SQSqzjQ6wB8eW0AeAyCmSo_d-F4O4-gw?e=aIQngs | M45: =IF(SUM(V45:BC45)=0,"-",SUM(V45:BC45)) -> 13 | N45: =IF(SUMPRODUCT($V$3:$BC$3,V45:BC45)=0,"-",SUMPRODUCT($V$3:$BC$3,V45:BC45)) -> 660 | O45: 44978 | P45: =IF(G45="","",IFERROR(IF(S45="Sent","",IF(I45="Delivered","PO en attente","Projet en cours")),"")) | Q45: 4200639098 | S45: Sent | T45: - | U45: Paid | V45: 1 | W45: 7 | AC45: 1 | AD45: 4
A46: Sony | B46: SFR | C46: FY22 | D46: =IF(F46="","",CHOOSE(MONTH(F46),"Q4","Q4","Q4","Q1","Q1","Q1","Q2","Q2","Q2","Q3","Q3","Q3")) -> Q4 | E46: =IF(F46="","",CHOOSE(MONTH(F46),"10-JAN","11-FEB","12-MAR","01-APR","02-MAY","03-JUN","04-JUL","05-AUG","06-SEP","07-OCT","08-NOV","09-DEC")) -> 11-FEB | F46: 44973 | G46: Newsletter PRT Février | H46: Alice Mucke | I46: Delivered | J46: DI | K46: BA | L46: - | M46: =IF(SUM(V46:BC46)=0,"-",SUM(V46:BC46)) -> 1 | N46: =IF(SUMPRODUCT($V$3:$BC$3,V46:BC46)=0,"-",SUMPRODUCT($V$3:$BC$3,V46:BC46)) -> 600 | O46: 44973 | P46: =IF(G46="","",IFERROR(IF(S46="Sent","",IF(I46="Delivered","PO en attente","Projet en cours")),"")) | Q46: 4200636262 | S46: sent | T46: - | U46: Paid | AN46: 1
A47: Sony | B47: SFR | C47: FY22 | D47: =IF(F47="","",CHOOSE(MONTH(F47),"Q4","Q4","Q4","Q1","Q1","Q1","Q2","Q2","Q2","Q3","Q3","Q3")) -> Q4 | E47: =IF(F47="","",CHOOSE(MONTH(F47),"10-JAN","11-FEB","12-MAR","01-APR","02-MAY","03-JUN","04-JUL","05-AUG","06-SEP","07-OCT","08-NOV","09-DEC")) -> 11-FEB | F47: 44974 | G47: Amazon Les jours Sony | H47: Joelle Mechache | I47: Delivered | J47: Cross | K47: CM | L47: https://saranistudio-my.sharepoint.com/:f:/g/personal/team_sarani_studio/Evzfu13U4IpLp3GoN-MrbKcB6voUMWbQ-KWviKSEWfxHyA?e=u1uaJh | M47: =IF(SUM(V47:BC47)=0,"-",SUM(V47:BC47)) -> 2 | N47: =IF(SUMPRODUCT($V$3:$BC$3,V47:BC47)=0,"-",SUMPRODUCT($V$3:$BC$3,V47:BC47)) -> 240 | O47: 44981 | P47: =IF(G47="","",IFERROR(IF(S47="Sent","",IF(I47="Delivered","PO en attente","Projet en cours")),"")) | Q47: 4200639291 | S47: sent | T47: - | U47: Paid | V47: 2
A48: Sony | B48: SFR | C48: FY22 | D48: =IF(F48="","",CHOOSE(MONTH(F48),"Q4","Q4","Q4","Q1","Q1","Q1","Q2","Q2","Q2","Q3","Q3","Q3")) -> Q4 | E48: =IF(F48="","",CHOOSE(MONTH(F48),"10-JAN","11-FEB","12-MAR","01-APR","02-MAY","03-JUN","04-JUL","05-AUG","06-SEP","07-OCT","08-NOV","09-DEC")) -> 11-FEB | F48: 44977 | G48: MDR - FNAC NEW WALL A4 | H48: Laura Vivient | I48: Delivered | J48: MDR | K48: BA | L48: https://saranistudio-my.sharepoint.com/:f:/g/personal/team_sarani_studio/EplbkOAQ_RVKlimX_vm_Yz4BYsRWiropgEjSV64xwAiFlQ?e=QjcDN1 | M48: =IF(SUM(V48:BC48)=0,"-",SUM(V48:BC48)) -> 1 | N48: =IF(SUMPRODUCT($V$3:$BC$3,V48:BC48)=0,"-",SUMPRODUCT($V$3:$BC$3,V48:BC48)) -> 135 | O48: 44978 | P48: =IF(G48="","",IFERROR(IF(S48="Sent","",IF(I48="Delivered","PO en attente","Projet en cours")),"")) | Q48: 4200638974 | S48: Sent | T48: - | U48: Paid | AC48: 1
A49: Sony | B49: SFR | C49: FY22 | D49: =IF(F49="","",CHOOSE(MONTH(F49),"Q4","Q4","Q4","Q1","Q1","Q1","Q2","Q2","Q2","Q3","Q3","Q3")) -> Q4 | E49: =IF(F49="","",CHOOSE(MONTH(F49),"10-JAN","11-FEB","12-MAR","01-APR","02-MAY","03-JUN","04-JUL","05-AUG","06-SEP","07-OCT","08-NOV","09-DEC")) -> 11-FEB | F49: 44977 | G49: Brief Sony Bannières Bravia Core Boulanger | H49: Maureen Masson | I49: Delivered | J49: TV | K49: CM | L49: https://saranistudio-my.sharepoint.com/:f:/g/personal/team_sarani_studio/Eqe3rBnlph1BiwQsMsq2QLkBMf2xPp5Wnzudz7Z8Kwje7Q?e=SJbPDi | M49: =IF(SUM(V49:BC49)=0,"-",SUM(V49:BC49)) -> 1 | N49: =IF(SUMPRODUCT($V$3:$BC$3,V49:BC49)=0,"-",SUMPRODUCT($V$3:$BC$3,V49:BC49)) -> 120 | O49: 44981 | P49: =IF(G49="","",IFERROR(IF(S49="Sent","",IF(I49="Delivered","PO en attente","Projet en cours")),"")) | Q49: 4200639008 | S49: sent | T49: - | U49: Paid | V49: 1
A50: Sony | B50: SFR | C50: FY22 | D50: =IF(F50="","",CHOOSE(MONTH(F50),"Q4","Q4","Q4","Q1","Q1","Q1","Q2","Q2","Q2","Q3","Q3","Q3")) -> Q4 | E50: =IF(F50="","",CHOOSE(MONTH(F50),"10-JAN","11-FEB","12-MAR","01-APR","02-MAY","03-JUN","04-JUL","05-AUG","06-SEP","07-OCT","08-NOV","09-DEC")) -> 11-FEB | F50: 44979 | G50: MDR - Offline POS CH720N CH520 | H50: Laura Vivient | I50: Delivered | J50: MDR | K50: BA | L50: https://saranistudio-my.sharepoint.com/:f:/g/personal/team_sarani_studio/EvQORSWeLIhCmtRAW0oiAUwBTsJV6BOljIGWmUFQwsMZaw?e=d5u6bG | M50: =IF(SUM(V50:BC50)=0,"-",SUM(V50:BC50)) -> 10 | N50: =IF(SUMPRODUCT($V$3:$BC$3,V50:BC50)=0,"-",SUMPRODUCT($V$3:$BC$3,V50:BC50)) -> 780 | O50: 44981 | P50: =IF(G50="","",IFERROR(IF(S50="Sent","",IF(I50="Delivered","PO en attente","Projet en cours")),"")) | Q50: 4200639014 | S50: Sent | T50: - | U50: Paid | AC50: 4 | AD50: 6
A51: Sony | B51: SFR | C51: FY22 | D51: =IF(F51="","",CHOOSE(MONTH(F51),"Q4","Q4","Q4","Q1","Q1","Q1","Q2","Q2","Q2","Q3","Q3","Q3")) -> Q4 | E51: =IF(F51="","",CHOOSE(MONTH(F51),"10-JAN","11-FEB","12-MAR","01-APR","02-MAY","03-JUN","04-JUL","05-AUG","06-SEP","07-OCT","08-NOV","09-DEC")) -> 12-MAR | F51: 44986 | G51: Synchro HAV lancements TV FY23 | H51: Laura Vivient | I51: Delivered | J51: HAV | K51: BA | L51: https://saranistudio-my.sharepoint.com/:f:/g/personal/team_sarani_studio/ElN1J_IN9NhPr2CeLrCnszQBKTAJ_nOdr-HrnPgQqoGmgA?e=2DZGUU | M51: =IF(SUM(V51:BC51)=0,"-",SUM(V51:BC51)) -> 4 | N51: =IF(SUMPRODUCT($V$3:$BC$3,V51:BC51)=0,"-",SUMPRODUCT($V$3:$BC$3,V51:BC51)) -> 540 | O51: 44981 | P51: =IF(G51="","",IFERROR(IF(S51="Sent","",IF(I51="Delivered","PO en attente","Projet en cours")),"")) | Q51: 4200639227 | S51: Sent | T51: - | U51: Paid | AC51: 4
A52: Sony | B52: SFR | C52: FY22 | D52: =IF(F52="","",CHOOSE(MONTH(F52),"Q4","Q4","Q4","Q1","Q1","Q1","Q2","Q2","Q2","Q3","Q3","Q3")) -> Q4 | E52: =IF(F52="","",CHOOSE(MONTH(F52),"10-JAN","11-FEB","12-MAR","01-APR","02-MAY","03-JUN","04-JUL","05-AUG","06-SEP","07-OCT","08-NOV","09-DEC")) -> 12-MAR | F52: 44986 | G52: HAV Cashback | H52: Laura Vivient | I52: Delivered | J52: HAV | K52: BA | L52: https://saranistudio-my.sharepoint.com/:f:/g/personal/team_sarani_studio/EsMnikTmJL1KpvYorntrkkABl8AjzYKd5G85aBnUnFq9Iw?e=TuaAG2 | M52: =IF(SUM(V52:BC52)=0,"-",SUM(V52:BC52)) -> 11 | N52: =IF(SUMPRODUCT($V$3:$BC$3,V52:BC52)=0,"-",SUMPRODUCT($V$3:$BC$3,V52:BC52)) -> 470 | O52: 44981 | P52: =IF(G52="","",IFERROR(IF(S52="Sent","",IF(I52="Delivered","PO en attente","Projet en cours")),"")) | Q52: 4200639226 | S52: sent | T52: - | U52: Paid | V52: 1 | W52: 10
A53: Sony | B53: SFR | C53: FY22 | D53: =IF(F53="","",CHOOSE(MONTH(F53),"Q4","Q4","Q4","Q1","Q1","Q1","Q2","Q2","Q2","Q3","Q3","Q3")) -> Q4 | E53: =IF(F53="","",CHOOSE(MONTH(F53),"10-JAN","11-FEB","12-MAR","01-APR","02-MAY","03-JUN","04-JUL","05-AUG","06-SEP","07-OCT","08-NOV","09-DEC")) -> 12-MAR | F53: 44994 | G53: Welcome to VLOG | H53: Astrid Jean-Baptiste | I53: Delivered | J53: DI | K53: BA | L53: https://saranistudio-my.sharepoint.com/:f:/g/personal/team_sarani_studio/Evv8Y4u5CcpBkA6LoIczitQBWRTN97zK7m4SmXnl8monYA?e=FXqhEq | M53: =IF(SUM(V53:BC53)=0,"-",SUM(V53:BC53)) -> 10 | N53: =IF(SUMPRODUCT($V$3:$BC$3,V53:BC53)=0,"-",SUMPRODUCT($V$3:$BC$3,V53:BC53)) -> 445 | O53: 45006 | P53: =IF(G53="","",IFERROR(IF(S53="Sent","",IF(I53="Delivered","PO en attente","Projet en cours")),"")) | Q53: 4200640853 | S53: sent | T53: - | U53: Paid | V53: 1 | W53: 7 | AD53: 2
A54: Sony | B54: SFR | C54: FY22 | D54: =IF(F54="","",CHOOSE(MONTH(F54),"Q4","Q4","Q4","Q1","Q1","Q1","Q2","Q2","Q2","Q3","Q3","Q3")) -> Q4 | E54: =IF(F54="","",CHOOSE(MONTH(F54),"10-JAN","11-FEB","12-MAR","01-APR","02-MAY","03-JUN","04-JUL","05-AUG","06-SEP","07-OCT","08-NOV","09-DEC")) -> 12-MAR | F54: 45001 | G54: Web banner WF-C700 WH-1000XM5 | H54: Laura Vivient | I54: Delivered | J54: MDR | K54: BA | L54: https://saranistudio-my.sharepoint.com/:f:/g/personal/team_sarani_studio/Eo2562j1PBhFsm0D9eCdORoBS6przlDgwVkoQg0sOXiM3A?e=yrz1uS | M54: =IF(SUM(V54:BC54)=0,"-",SUM(V54:BC54)) -> 9 | N54: =IF(SUMPRODUCT($V$3:$BC$3,V54:BC54)=0,"-",SUMPRODUCT($V$3:$BC$3,V54:BC54)) -> 570 | O54: 44981 | P54: =IF(G54="","",IFERROR(IF(S54="Sent","",IF(I54="Delivered","PO en attente","Projet en cours")),"")) | Q54: 4200640930 | S54: sent | T54: - | U54: Paid | V54: 3 | W54: 6
A55: Sony | B55: SFR | C55: FY22 | D55: =IF(F55="","",CHOOSE(MONTH(F55),"Q4","Q4","Q4","Q1","Q1","Q1","Q2","Q2","Q2","Q3","Q3","Q3")) -> Q4 | E55: =IF(F55="","",CHOOSE(MONTH(F55),"10-JAN","11-FEB","12-MAR","01-APR","02-MAY","03-JUN","04-JUL","05-AUG","06-SEP","07-OCT","08-NOV","09-DEC")) -> 12-MAR | F55: 45005 | G55: Adaptation Landing Page FY23 | H55: Maureen Masson | I55: - | J55: TV | K55: CM | L55: - | M55: =IF(SUM(V55:BC55)=0,"-",SUM(V55:BC55)) -> 0.83333333 | N55: =IF(SUMPRODUCT($V$3:$BC$3,V55:BC55)=0,"-",SUMPRODUCT($V$3:$BC$3,V55:BC55)) -> 1000 | O55: 45005 | P55: =IF(G55="","",IFERROR(IF(S55="Sent","",IF(I55="Delivered","PO en attente","Projet en cours")),"")) | Q55: 4200639006 | S55: sent | T55: - | U55: Paid | AP55: =1/1.2 -> 0.83333333
A56: Sony | B56: SFR | C56: FY22 | D56: =IF(F56="","",CHOOSE(MONTH(F56),"Q4","Q4","Q4","Q1","Q1","Q1","Q2","Q2","Q2","Q3","Q3","Q3")) -> Q4 | E56: =IF(F56="","",CHOOSE(MONTH(F56),"10-JAN","11-FEB","12-MAR","01-APR","02-MAY","03-JUN","04-JUL","05-AUG","06-SEP","07-OCT","08-NOV","09-DEC")) -> 12-MAR | F56: 45005 | G56: Bannières awards | H56: Maureen Masson | I56: Delivered | J56: MDR | K56: CM | L56: https://saranistudio-my.sharepoint.com/:f:/g/personal/team_sarani_studio/EsAgXdGVXc1Bqb3hwi8zpSEBcRj8U2XkFGSGV62rqumcjw?e=mIcDe6 | M56: =IF(SUM(V56:BC56)=0,"-",SUM(V56:BC56)) -> 2 | N56: =IF(SUMPRODUCT($V$3:$BC$3,V56:BC56)=0,"-",SUMPRODUCT($V$3:$BC$3,V56:BC56)) -> 240 | O56: 45005 | P56: =IF(G56="","",IFERROR(IF(S56="Sent","",IF(I56="Delivered","PO en attente","Projet en cours")),"")) | Q56: 4200639051 | S56: sent | T56: - | U56: Paid | V56: 2
A57: Sony | B57: SFR | C57: FY22 | D57: =IF(F57="","",CHOOSE(MONTH(F57),"Q4","Q4","Q4","Q1","Q1","Q1","Q2","Q2","Q2","Q3","Q3","Q3")) -> Q4 | E57: =IF(F57="","",CHOOSE(MONTH(F57),"10-JAN","11-FEB","12-MAR","01-APR","02-MAY","03-JUN","04-JUL","05-AUG","06-SEP","07-OCT","08-NOV","09-DEC")) -> 12-MAR | F57: 45006 | G57: Landing page Partenaires | H57: Alice Mucke | I57: - | J57: DI | K57: CM | L57: - | M57: =IF(SUM(V57:BC57)=0,"-",SUM(V57:BC57)) -> 0.83333333 | N57: =IF(SUMPRODUCT($V$3:$BC$3,V57:BC57)=0,"-",SUMPRODUCT($V$3:$BC$3,V57:BC57)) -> 1000 | O57: 45006 | P57: =IF(G57="","",IFERROR(IF(S57="Sent","",IF(I57="Delivered","PO en attente","Projet en cours")),"")) | Q57: 4200639353 | S57: sent | T57: - | U57: Paid | AP57: =1/1.2 -> 0.83333333
A58: Sony | B58: SFR | C58: FY22 | D58: =IF(F58="","",CHOOSE(MONTH(F58),"Q4","Q4","Q4","Q1","Q1","Q1","Q2","Q2","Q2","Q3","Q3","Q3")) -> Q4 | E58: =IF(F58="","",CHOOSE(MONTH(F58),"10-JAN","11-FEB","12-MAR","01-APR","02-MAY","03-JUN","04-JUL","05-AUG","06-SEP","07-OCT","08-NOV","09-DEC")) -> 12-MAR | F58: 45006 | G58: Lancement TV 2023 Assets | H58: Léa Novio | I58: Delivered | J58: TV | K58: BA | L58: https://saranistudio-my.sharepoint.com/:f:/g/personal/team_sarani_studio/EpbAZG5lEmVIiR_on7fzuLEB9DbDwGiQ8g3E-EP6ZMPlBw?e=WDYhbk | M58: 134 | N58: 6010 | O58: 45006 | P58: =IF(G58="","",IFERROR(IF(S58="Sent","",IF(I58="Delivered","PO en attente","Projet en cours")),"")) | Q58: 4200639031 | S58: sent | T58: - | U58: Paid
A59: Sony | B59: SFR | C59: FY22 | D59: =IF(F59="","",CHOOSE(MONTH(F59),"Q4","Q4","Q4","Q1","Q1","Q1","Q2","Q2","Q2","Q3","Q3","Q3")) -> Q4 | E59: =IF(F59="","",CHOOSE(MONTH(F59),"10-JAN","11-FEB","12-MAR","01-APR","02-MAY","03-JUN","04-JUL","05-AUG","06-SEP","07-OCT","08-NOV","09-DEC")) -> 12-MAR | F59: 45006 | G59: Web Pop Crunchyroll | H59: Léa Novio | I59: Delivered | J59: TV | K59: BA | L59: https://saranistudio-my.sharepoint.com/:f:/g/personal/team_sarani_studio/Eqpu9-LPvfZElOAGt1viRf8Bhsdxnu1Eu10IOtnxqhR8Iw?e=2Uijzq | M59: =IF(SUM(V59:BC59)=0,"-",SUM(V59:BC59)) -> 1 | N59: =IF(SUMPRODUCT($V$3:$BC$3,V59:BC59)=0,"-",SUMPRODUCT($V$3:$BC$3,V59:BC59)) -> 120 | O59: - | Q59: Covered | S59: sent | T59: - | U59: Paid | V59: 1
A60: Sony | B60: SFR | C60: FY22 | D60: =IF(F60="","",CHOOSE(MONTH(F60),"Q4","Q4","Q4","Q1","Q1","Q1","Q2","Q2","Q2","Q3","Q3","Q3")) -> Q4 | E60: =IF(F60="","",CHOOSE(MONTH(F60),"10-JAN","11-FEB","12-MAR","01-APR","02-MAY","03-JUN","04-JUL","05-AUG","06-SEP","07-OCT","08-NOV","09-DEC")) -> 12-MAR | F60: 45008 | G60: Fiche Produit WF-C700 | H60: Laura Vivient | I60: Delivered | J60: MDR | K60: BA | L60: https://saranistudio-my.sharepoint.com/:f:/g/personal/team_sarani_studio/EsV2_KLDqwdOi0nyINCRhnABKsqCgrqSPww-zwD5kRW76g?e=55qEkF | M60: =IF(SUM(V60:BC60)=0,"-",SUM(V60:BC60)) -> 1 | N60: =IF(SUMPRODUCT($V$3:$BC$3,V60:BC60)=0,"-",SUMPRODUCT($V$3:$BC$3,V60:BC60)) -> 250 | O60: 45023 | P60: =IF(G60="","",IFERROR(IF(S60="Sent","",IF(I60="Delivered","PO en attente","Projet en cours")),"")) | Q60: 4200640929 | S60: Sent | T60: - | U60: Paid | AF60: 1
A61: Sony | B61: SFR | C61: FY22 | D61: =IF(F61="","",CHOOSE(MONTH(F61),"Q4","Q4","Q4","Q1","Q1","Q1","Q2","Q2","Q2","Q3","Q3","Q3")) -> Q4 | E61: =IF(F61="","",CHOOSE(MONTH(F61),"10-JAN","11-FEB","12-MAR","01-APR","02-MAY","03-JUN","04-JUL","05-AUG","06-SEP","07-OCT","08-NOV","09-DEC")) -> 12-MAR | F61: 45008 | G61: MDR - Assets OFFLINE WF-C700N | H61: Laura Vivient | I61: Delivered | J61: MDR | K61: BA | L61: https://saranistudio-my.sharepoint.com/:f:/g/personal/team_sarani_studio/Eh-XtLfnCf1LnsVtx5DtbCEBjY0SGdeSjDPwHzDnQHgN9w?e=2LU41r | M61: =IF(SUM(V61:BC61)=0,"-",SUM(V61:BC61)) -> 21 | N61: =IF(SUMPRODUCT($V$3:$BC$3,V61:BC61)=0,"-",SUMPRODUCT($V$3:$BC$3,V61:BC61)) -> 1695 | O61: 45023 | P61: =IF(G61="","",IFERROR(IF(S61="Sent","",IF(I61="Delivered","PO en attente","Projet en cours")),"")) | Q61: 4200640938 | S61: Sent | T61: - | U61: Paid | AC61: 9 | AD61: 12
A62: Sony | B62: SFR | C62: FY22 | D62: =IF(F62="","",CHOOSE(MONTH(F62),"Q4","Q4","Q4","Q1","Q1","Q1","Q2","Q2","Q2","Q3","Q3","Q3")) -> Q4 | E62: =IF(F62="","",CHOOSE(MONTH(F62),"10-JAN","11-FEB","12-MAR","01-APR","02-MAY","03-JUN","04-JUL","05-AUG","06-SEP","07-OCT","08-NOV","09-DEC")) -> 12-MAR | F62: 45008 | G62: FY23 BRAVIA Launch extra assets | H62: Léa Novio | I62: Delivered | J62: TV | K62: BA | L62: https://saranistudio-my.sharepoint.com/:f:/g/personal/team_sarani_studio/EjXst-lsglZAi0Q2IrrJuM4BaunLX6dQ9jdJrU_j-AJ-iA?e=ZonV9A | M62: =IF(SUM(V62:BC62)=0,"-",SUM(V62:BC62)) -> - | N62: =IF(SUMPRODUCT($V$3:$BC$3,V62:BC62)=0,"-",SUMPRODUCT($V$3:$BC$3,V62:BC62)) -> - | O62: 45008 | P62: =IF(G62="","",IFERROR(IF(S62="Sent","",IF(I62="Delivered","PO en attente","Projet en cours")),"")) | Q62: 4200639284 | S62: Sent | T62: - | U62: Paid
A63: Sony | B63: SFR | C63: FY22 | D63: =IF(F63="","",CHOOSE(MONTH(F63),"Q4","Q4","Q4","Q1","Q1","Q1","Q2","Q2","Q2","Q3","Q3","Q3")) -> Q4 | E63: =IF(F63="","",CHOOSE(MONTH(F63),"10-JAN","11-FEB","12-MAR","01-APR","02-MAY","03-JUN","04-JUL","05-AUG","06-SEP","07-OCT","08-NOV","09-DEC")) -> 12-MAR | F63: 45012 | G63: ZV-E1 Launch assets | H63: Astrid Jean-Baptiste | I63: Delivered | J63: DI | K63: BA | L63: https://saranistudio-my.sharepoint.com/:f:/g/personal/team_sarani_studio/EvN6F1tLUb1HpsDsbcqLJpgBS_xatQW1Mdo30DXnEk4Umw?e=ZwLhqb | M63: =IF(SUM(V63:BC63)=0,"-",SUM(V63:BC63)) -> 15 | N63: =IF(SUMPRODUCT($V$3:$BC$3,V63:BC63)=0,"-",SUMPRODUCT($V$3:$BC$3,V63:BC63)) -> 550 | O63: 45008 | P63: =IF(G63="","",IFERROR(IF(S63="Sent","",IF(I63="Delivered","PO en attente","Projet en cours")),"")) | Q63: 4200639687 | S63: Sent | T63: - | U63: Paid | W63: 14 | Y63: 1
A64: Sony | B64: SFR | C64: FY23 | D64: =IF(F64="","",CHOOSE(MONTH(F64),"Q4","Q4","Q4","Q1","Q1","Q1","Q2","Q2","Q2","Q3","Q3","Q3")) -> Q1 | E64: =IF(F64="","",CHOOSE(MONTH(F64),"10-JAN","11-FEB","12-MAR","01-APR","02-MAY","03-JUN","04-JUL","05-AUG","06-SEP","07-OCT","08-NOV","09-DEC")) -> 01-APR | F64: 45022 | G64: HAV - offre caisson SW3 offert | H64: Laura Vivient | I64: Delivered | J64: HAV | K64: BA | L64: https://saranistudio-my.sharepoint.com/:f:/g/personal/team_sarani_studio/EkZE4Y3oDmxOgPwByulkRGQBO22GCn4XXiv8vxBWXU3BOQ?e=QYcm2Z | M64: =IF(SUM(V64:BC64)=0,"-",SUM(V64:BC64)) -> 3 | N64: =IF(SUMPRODUCT($V$3:$BC$3,V64:BC64)=0,"-",SUMPRODUCT($V$3:$BC$3,V64:BC64)) -> 405 | O64: 45035 | P64: =IF(G64="","",IFERROR(IF(S64="Sent","",IF(I64="Delivered","PO en attente","Projet en cours")),"")) | Q64: 4200640937 | S64: Sent | T64: - | U64: Paid | AC64: 3
A65: Sony | B65: SFR | C65: FY23 | D65: =IF(F65="","",CHOOSE(MONTH(F65),"Q4","Q4","Q4","Q1","Q1","Q1","Q2","Q2","Q2","Q3","Q3","Q3")) -> Q3 | E65: =IF(F65="","",CHOOSE(MONTH(F65),"10-JAN","11-FEB","12-MAR","01-APR","02-MAY","03-JUN","04-JUL","05-AUG","06-SEP","07-OCT","08-NOV","09-DEC")) -> 08-NOV | F65: 44882 | G65: TV - Displays Les Numériques | H65: Fatima-Zohra Ichi | I65: Delivered | J65: DI | K65: CM | L65: https://saranistudio-my.sharepoint.com/:f:/g/personal/team_sarani_studio/EhGvAIAk9nhJjmewxCW5higB28ZJKSWD-dA33c2u3yxD1w?e=RZ63bm | M65: =IF(SUM(V65:BC65)=0,"-",SUM(V65:BC65)) -> 4 | N65: =IF(SUMPRODUCT($V$3:$BC$3,V65:BC65)=0,"-",SUMPRODUCT($V$3:$BC$3,V65:BC65)) -> 140 | O65: 44903 | P65: =IF(G65="","",IFERROR(IF(S65="Sent","",IF(I65="Delivered","PO en attente","Projet en cours")),"")) | Q65: 4200657838 | R65: Février | S65: Sent | T65: F2024-0140 | U65: Paid 23/04/2024 | W65: 4
A66: Sony | B66: SFR | C66: FY22 | D66: =IF(F66="","",CHOOSE(MONTH(F66),"Q4","Q4","Q4","Q1","Q1","Q1","Q2","Q2","Q2","Q3","Q3","Q3")) -> Q3 | E66: =IF(F66="","",CHOOSE(MONTH(F66),"10-JAN","11-FEB","12-MAR","01-APR","02-MAY","03-JUN","04-JUL","05-AUG","06-SEP","07-OCT","08-NOV","09-DEC")) -> 09-DEC | F66: 44914 | G66: Winter Sales Banners adaptations | H66: Françoise Burgarella | I66: Delivered | J66: Cross | K66: BA | L66: https://saranistudio-my.sharepoint.com/:f:/g/personal/team_sarani_studio/EitZRBZy2n1Kkw5kaWztE5sBgYKU_BFeDcX25iDrx1Ct5w?e=j19Nkg | M66: =IF(SUM(V66:BC66)=0,"-",SUM(V66:BC66)) -> 18 | N66: =IF(SUMPRODUCT($V$3:$BC$3,V66:BC66)=0,"-",SUMPRODUCT($V$3:$BC$3,V66:BC66)) -> 715 | O66: 22/12/2022 | P66: =IF(G66="","",IFERROR(IF(S66="Sent","",IF(I66="Delivered","PO en attente","Projet en cours")),"")) | Q66: 4200641797 | S66: Sent | T66: F2023-0612 | U66: Paid | V66: 1 | W66: 17
A67: Sony | B67: SFR | C67: FY22 | D67: =IF(F67="","",CHOOSE(MONTH(F67),"Q4","Q4","Q4","Q1","Q1","Q1","Q2","Q2","Q2","Q3","Q3","Q3")) -> Q4 | E67: =IF(F67="","",CHOOSE(MONTH(F67),"10-JAN","11-FEB","12-MAR","01-APR","02-MAY","03-JUN","04-JUL","05-AUG","06-SEP","07-OCT","08-NOV","09-DEC")) -> 11-FEB | F67: 44958 | G67: OP Les belles ouvertures 2 | H67: Astrid Jean-Baptiste | I67: Delivered | J67: DI | K67: BA | L67: https://saranistudio-my.sharepoint.com/:f:/g/personal/team_sarani_studio/EoXM_bPXFQtOqtOuolOqWAQBFcKOS1eXgcsuycPvj9witg?e=ACLkrl | M67: =IF(SUM(V67:BC67)=0,"-",SUM(V67:BC67)) -> 6 | N67: =IF(SUMPRODUCT($V$3:$BC$3,V67:BC67)=0,"-",SUMPRODUCT($V$3:$BC$3,V67:BC67)) -> 295 | O67: https://saranistudio-my.sharepoint.com/:b:/g/personal/team_sarani_studio/EWLP_vMxED9FmUZQ_nPaidkJwBjJNjECiaaIw3yVFqt7yTpQ?e=R7ciE8 | P67: =IF(G67="","",IFERROR(IF(S67="Sent","",IF(I67="Delivered","PO en attente","Projet en cours")),"")) | Q67: 4200661507 | S67: Sent | T67: F2024-0100 | U67: Paid 16/05/2024 | V67: 1 | W67: 5
A68: Sony | B68: SFR | C68: FY22 | D68: =IF(F68="","",CHOOSE(MONTH(F68),"Q4","Q4","Q4","Q1","Q1","Q1","Q2","Q2","Q2","Q3","Q3","Q3")) -> Q4 | E68: =IF(F68="","",CHOOSE(MONTH(F68),"10-JAN","11-FEB","12-MAR","01-APR","02-MAY","03-JUN","04-JUL","05-AUG","06-SEP","07-OCT","08-NOV","09-DEC")) -> 11-FEB | F68: 44958 | G68: OP Extension de garantie | H68: Astrid Jean-Baptiste | I68: Delivered | J68: DI | K68: BA | L68: https://saranistudio-my.sharepoint.com/:f:/g/personal/team_sarani_studio/EhmXSE3SqJlLttJIjP3d1EwBO-MeT52KYDPXcUnZ4UeiYQ?e=EPq6RY | M68: =IF(SUM(V68:BC68)=0,"-",SUM(V68:BC68)) -> 6 | N68: =IF(SUMPRODUCT($V$3:$BC$3,V68:BC68)=0,"-",SUMPRODUCT($V$3:$BC$3,V68:BC68)) -> 295 | O68: https://saranistudio-my.sharepoint.com/:b:/g/personal/team_sarani_studio/EeqqQcvt8QpJhIrMKvXrqeMBVFpg9cjIOvDd7UQb-ahIQg?e=Va6RIJ | P68: =IF(G68="","",IFERROR(IF(S68="Sent","",IF(I68="Delivered","PO en attente","Projet en cours")),"")) | Q68: 4200661507 | S68: Sent | T68: F2024-0100 | U68: Paid 16/05/2024 | V68: 1 | W68: 5
A69: Sony | B69: SFR | C69: FY22 | D69: =IF(F69="","",CHOOSE(MONTH(F69),"Q4","Q4","Q4","Q1","Q1","Q1","Q2","Q2","Q2","Q3","Q3","Q3")) -> Q4 | E69: =IF(F69="","",CHOOSE(MONTH(F69),"10-JAN","11-FEB","12-MAR","01-APR","02-MAY","03-JUN","04-JUL","05-AUG","06-SEP","07-OCT","08-NOV","09-DEC")) -> 12-MAR | F69: 45005 | G69: Landing page Audio FY23 | H69: Maureen Masson | I69: - | J69: MDR | K69: CM | L69: - | M69: =IF(SUM(V69:BC69)=0,"-",SUM(V69:BC69)) -> 0.6 | N69: =IF(SUMPRODUCT($V$3:$BC$3,V69:BC69)=0,"-",SUMPRODUCT($V$3:$BC$3,V69:BC69)) -> 720 | O69: 45005 | P69: =IF(G69="","",IFERROR(IF(S69="Sent","",IF(I69="Delivered","PO en attente","Projet en cours")),"")) | Q69: 4200638728 | S69: sent | T69: F2023-0419 | U69: Paid | AP69: =0.6/1 -> 0.6
A70: Sony | B70: SFR | C70: FY22 | D70: =IF(F70="","",CHOOSE(MONTH(F70),"Q4","Q4","Q4","Q1","Q1","Q1","Q2","Q2","Q2","Q3","Q3","Q3")) -> Q4 | E70: =IF(F70="","",CHOOSE(MONTH(F70),"10-JAN","11-FEB","12-MAR","01-APR","02-MAY","03-JUN","04-JUL","05-AUG","06-SEP","07-OCT","08-NOV","09-DEC")) -> 12-MAR | F70: 45008 | G70: Adaptation Offres MEGASTAR | H70: Mylène Pellet | I70: Delivered | J70: TV | K70: CM | L70: https://saranistudio-my.sharepoint.com/:f:/g/personal/team_sarani_studio/Em9OAsLQ3rVAsCjuhjlyf9ABulvOo8C6xbY6ZkPMG8hkFQ?e=cTZegr | M70: =IF(SUM(V70:BC70)=0,"-",SUM(V70:BC70)) -> 3 | N70: =IF(SUMPRODUCT($V$3:$BC$3,V70:BC70)=0,"-",SUMPRODUCT($V$3:$BC$3,V70:BC70)) -> 105 | O70: 45071 | P70: =IF(G70="","",IFERROR(IF(S70="Sent","",IF(I70="Delivered","PO en attente","Projet en cours")),"")) | Q70: 4200641929 | R70: Avril | S70: sent | T70: F2023-0603 | U70: Paid | W70: 3
A71: Sony | B71: SFR | C71: FY23 | D71: =IF(F71="","",CHOOSE(MONTH(F71),"Q4","Q4","Q4","Q1","Q1","Q1","Q2","Q2","Q2","Q3","Q3","Q3")) -> Q4 | E71: =IF(F71="","",CHOOSE(MONTH(F71),"10-JAN","11-FEB","12-MAR","01-APR","02-MAY","03-JUN","04-JUL","05-AUG","06-SEP","07-OCT","08-NOV","09-DEC")) -> 12-MAR | F71: 45012 | G71: Déclinaisons TV / DI | H71: Alice Mucke | I71: Delivered | J71: DI | K71: CM | L71: https://saranistudio-my.sharepoint.com/:f:/g/personal/team_sarani_studio/EmtLIsoaTzxJnuMVqwFkEXEBRLxiJIn6Dx3sdurRJBv18Q?e=g8c6h9 | M71: =IF(SUM(V71:BC71)=0,"-",SUM(V71:BC71)) -> 6 | N71: =IF(SUMPRODUCT($V$3:$BC$3,V71:BC71)=0,"-",SUMPRODUCT($V$3:$BC$3,V71:BC71)) -> 210 | O71: 45041 | P71: =IF(G71="","",IFERROR(IF(S71="Sent","",IF(I71="Delivered","PO en attente","Projet en cours")),"")) | Q71: 4200641951 | R71: Avril | S71: Sent | T71: F2023-0609 | U71: Paid | W71: 6
A72: Sony | B72: SFR | C72: FY22 | D72: =IF(F72="","",CHOOSE(MONTH(F72),"Q4","Q4","Q4","Q1","Q1","Q1","Q2","Q2","Q2","Q3","Q3","Q3")) -> Q4 | E72: =IF(F72="","",CHOOSE(MONTH(F72),"10-JAN","11-FEB","12-MAR","01-APR","02-MAY","03-JUN","04-JUL","05-AUG","06-SEP","07-OCT","08-NOV","09-DEC")) -> 12-MAR | F72: 45013 | G72: CROSS Produits + X80L + A80L​ | H72: Léa Novio | I72: Delivered | J72: TV | K72: BA | L72: https://saranistudio-my.sharepoint.com/:f:/g/personal/team_sarani_studio/EmtLIsoaTzxJnuMVqwFkEXEBRLxiJIn6Dx3sdurRJBv18Q?e=jb6qLr | M72: =IF(SUM(V72:BC72)=0,"-",SUM(V72:BC72)) -> 7 | N72: =IF(SUMPRODUCT($V$3:$BC$3,V72:BC72)=0,"-",SUMPRODUCT($V$3:$BC$3,V72:BC72)) -> 330 | O72: 45084 | P72: =IF(G72="","",IFERROR(IF(S72="Sent","",IF(I72="Delivered","PO en attente","Projet en cours")),"")) | Q72: 4200648470 | S72: Sent | T72: F2023-0572 | U72: Paid 24/09/2023 | V72: 1 | W72: 6
A73: Sony | B73: SFR | C73: FY22 | D73: =IF(F73="","",CHOOSE(MONTH(F73),"Q4","Q4","Q4","Q1","Q1","Q1","Q2","Q2","Q2","Q3","Q3","Q3")) -> Q4 | E73: =IF(F73="","",CHOOSE(MONTH(F73),"10-JAN","11-FEB","12-MAR","01-APR","02-MAY","03-JUN","04-JUL","05-AUG","06-SEP","07-OCT","08-NOV","09-DEC")) -> 12-MAR | F73: 45013 | G73: Bannières de lancement A80L + ZV-E1 | H73: Alice Mucke | I73: Delivered | J73: TV | K73: CM | L73: https://saranistudio-my.sharepoint.com/:f:/g/personal/team_sarani_studio/EmtLIsoaTzxJnuMVqwFkEXEBRLxiJIn6Dx3sdurRJBv18Q?e=SUZpe2 | M73: =IF(SUM(V73:BC73)=0,"-",SUM(V73:BC73)) -> 6 | N73: =IF(SUMPRODUCT($V$3:$BC$3,V73:BC73)=0,"-",SUMPRODUCT($V$3:$BC$3,V73:BC73)) -> 210 | O73: 45023 | P73: =IF(G73="","",IFERROR(IF(S73="Sent","",IF(I73="Delivered","PO en attente","Projet en cours")),"")) | Q73: 4200641929 | R73: Avril | S73: Sent | T73: F2023-0600 | U73: Paid | W73: 6
A74: Sony | B74: SFR | C74: FY23 | D74: =IF(F74="","",CHOOSE(MONTH(F74),"Q4","Q4","Q4","Q1","Q1","Q1","Q2","Q2","Q2","Q3","Q3","Q3")) -> Q1 | E74: =IF(F74="","",CHOOSE(MONTH(F74),"10-JAN","11-FEB","12-MAR","01-APR","02-MAY","03-JUN","04-JUL","05-AUG","06-SEP","07-OCT","08-NOV","09-DEC")) -> 01-APR | F74: 45019 | G74: New C700 Video - Short Video Editing | H74: Joelle Mechache | I74: Delivered | J74: MDR | K74: CM | L74: https://saranistudio-my.sharepoint.com/:f:/g/personal/team_sarani_studio/EkiROo65MdxOl4foCK_JnkMB7b1GqAM5JaGtE7NM2E563A?e=zgcdCi | M74: =IF(SUM(V74:BC74)=0,"-",SUM(V74:BC74)) -> 1 | N74: =IF(SUMPRODUCT($V$3:$BC$3,V74:BC74)=0,"-",SUMPRODUCT($V$3:$BC$3,V74:BC74)) -> 360 | O74: 45023 | P74: =IF(G74="","",IFERROR(IF(S74="Sent","",IF(I74="Delivered","PO en attente","Projet en cours")),"")) | Q74: 4200641950 | R74: Mai | S74: Sent | T74: F2023-0577 | U74: Paid | AV74: 1
A75: Sony | B75: SFR | C75: FY23 | D75: =IF(F75="","",CHOOSE(MONTH(F75),"Q4","Q4","Q4","Q1","Q1","Q1","Q2","Q2","Q2","Q3","Q3","Q3")) -> Q1 | E75: =IF(F75="","",CHOOSE(MONTH(F75),"10-JAN","11-FEB","12-MAR","01-APR","02-MAY","03-JUN","04-JUL","05-AUG","06-SEP","07-OCT","08-NOV","09-DEC")) -> 01-APR | F75: 45022 | G75: OP SUMMER | H75: Astrid Jean-Baptiste | I75: Delivered | J75: DI | K75: BA | L75: https://saranistudio-my.sharepoint.com/:f:/g/personal/team_sarani_studio/ErR6Cnz8koFJgGWWVv_vuxMB39tB1cZ0JkSx87G68Dab2A?e=ADHUf1 | M75: =IF(SUM(V75:BC75)=0,"-",SUM(V75:BC75)) -> 29 | N75: =IF(SUMPRODUCT($V$3:$BC$3,V75:BC75)=0,"-",SUMPRODUCT($V$3:$BC$3,V75:BC75)) -> 1330 | O75: 45035 | P75: =IF(G75="","",IFERROR(IF(S75="Sent","",IF(I75="Delivered","PO en attente","Projet en cours")),"")) | Q75: 4200644207 | S75: Sent | T75: F2023-0607 | U75: Paid | W75: 13 | AC75: 1 | AD75: 14 | AE75: 1
A76: Sony | B76: SFR | C76: FY23 | D76: =IF(F76="","",CHOOSE(MONTH(F76),"Q4","Q4","Q4","Q1","Q1","Q1","Q2","Q2","Q2","Q3","Q3","Q3")) -> Q1 | E76: =IF(F76="","",CHOOSE(MONTH(F76),"10-JAN","11-FEB","12-MAR","01-APR","02-MAY","03-JUN","04-JUL","05-AUG","06-SEP","07-OCT","08-NOV","09-DEC")) -> 01-APR | F76: 45027 | G76: Panneaux Photo Haut de meuble | H76: Astrid Jean-Baptiste | I76: Delivered | J76: DI | K76: BA | L76: https://saranistudio-my.sharepoint.com/:f:/g/personal/team_sarani_studio/Emr78pZYwmhKg7QstwR5YX8B_01h9nWSmEplb8WNjpatfQ?e=qLyHA4 | M76: =IF(SUM(V76:BC76)=0,"-",SUM(V76:BC76)) -> 13 | N76: =IF(SUMPRODUCT($V$3:$BC$3,V76:BC76)=0,"-",SUMPRODUCT($V$3:$BC$3,V76:BC76)) -> 805 | O76: 45035 | P76: =IF(G76="","",IFERROR(IF(S76="Sent","",IF(I76="Delivered","PO en attente","Projet en cours")),"")) | Q76: 4200642825 | S76: Sent | T76: F2023-0608 | U76: Paid | AC76: 3 | AD76: 10
A77: Sony | B77: SFR | C77: FY23 | D77: =IF(F77="","",CHOOSE(MONTH(F77),"Q4","Q4","Q4","Q1","Q1","Q1","Q2","Q2","Q2","Q3","Q3","Q3")) -> Q1 | E77: =IF(F77="","",CHOOSE(MONTH(F77),"10-JAN","11-FEB","12-MAR","01-APR","02-MAY","03-JUN","04-JUL","05-AUG","06-SEP","07-OCT","08-NOV","09-DEC")) -> 01-APR | F77: 45033 | G77: Bannières Boulanger promo barres de son | H77: Maureen Masson | I77: Delivered | J77: HAV | K77: CM | L77: https://saranistudio-my.sharepoint.com/:f:/g/personal/team_sarani_studio/EkZE4Y3oDmxOgPwByulkRGQBO22GCn4XXiv8vxBWXU3BOQ?e=QYcm2Z | M77: =IF(SUM(V77:BC77)=0,"-",SUM(V77:BC77)) -> 2 | N77: =IF(SUMPRODUCT($V$3:$BC$3,V77:BC77)=0,"-",SUMPRODUCT($V$3:$BC$3,V77:BC77)) -> 155 | O77: 45036 | P77: =IF(G77="","",IFERROR(IF(S77="Sent","",IF(I77="Delivered","PO en attente","Projet en cours")),"")) | Q77: 4200641959 | R77: Mai | S77: sent | T77: F2023-0599 | U77: Paid | V77: 1 | W77: 1
A78: Sony | B78: SFR | C78: FY23 | D78: =IF(F78="","",CHOOSE(MONTH(F78),"Q4","Q4","Q4","Q1","Q1","Q1","Q2","Q2","Q2","Q3","Q3","Q3")) -> Q1 | E78: =IF(F78="","",CHOOSE(MONTH(F78),"10-JAN","11-FEB","12-MAR","01-APR","02-MAY","03-JUN","04-JUL","05-AUG","06-SEP","07-OCT","08-NOV","09-DEC")) -> 01-APR | F78: 45033 | G78: BRIEF / FRENCH DAYS | H78: Françoise Burgarella | I78: Delivered | J78: Cross | K78: BA | L78: https://saranistudio-my.sharepoint.com/:f:/g/personal/team_sarani_studio/EhrI14UZk7dKhgchM2ASROYBdoIrI_P1svtBiXsGLwNAfg?e=fEdvZa | M78: =IF(SUM(V78:BC78)=0,"-",SUM(V78:BC78)) -> 18 | N78: =IF(SUMPRODUCT($V$3:$BC$3,V78:BC78)=0,"-",SUMPRODUCT($V$3:$BC$3,V78:BC78)) -> 715 | O78: 45035 | P78: =IF(G78="","",IFERROR(IF(S78="Sent","",IF(I78="Delivered","PO en attente","Projet en cours")),"")) | Q78: 4200641787 | S78: Sent | T78: F2023-0611 | U78: Paid | V78: 1 | W78: 17
A79: Sony | B79: SFR | C79: FY23 | D79: =IF(F79="","",CHOOSE(MONTH(F79),"Q4","Q4","Q4","Q1","Q1","Q1","Q2","Q2","Q2","Q3","Q3","Q3")) -> Q1 | E79: =IF(F79="","",CHOOSE(MONTH(F79),"10-JAN","11-FEB","12-MAR","01-APR","02-MAY","03-JUN","04-JUL","05-AUG","06-SEP","07-OCT","08-NOV","09-DEC")) -> 01-APR | F79: 45034 | G79: Habillages de site Lancement TV FY23 | H79: Maureen Masson | I79: Delivered | J79: TV | K79: CM | L79: https://saranistudio-my.sharepoint.com/:f:/g/personal/team_sarani_studio/ErYK9M-zOA5Hl_9y0WcmEwsBwd5R8qMMwATIAABc168MWQ?e=kSNAdo | M79: =IF(SUM(V79:BC79)=0,"-",SUM(V79:BC79)) -> 3 | N79: =IF(SUMPRODUCT($V$3:$BC$3,V79:BC79)=0,"-",SUMPRODUCT($V$3:$BC$3,V79:BC79)) -> 190 | O79: 45041 | P79: =IF(G79="","",IFERROR(IF(S79="Sent","",IF(I79="Delivered","PO en attente","Projet en cours")),"")) | Q79: 4200641929 | R79: Mai | S79: sent | T79: F2023-0603 | U79: Paid | V79: 1 | W79: 2
A80: Sony | B80: SFR | C80: FY23 | D80: =IF(F80="","",CHOOSE(MONTH(F80),"Q4","Q4","Q4","Q1","Q1","Q1","Q2","Q2","Q2","Q3","Q3","Q3")) -> Q1 | E80: =IF(F80="","",CHOOSE(MONTH(F80),"10-JAN","11-FEB","12-MAR","01-APR","02-MAY","03-JUN","04-JUL","05-AUG","06-SEP","07-OCT","08-NOV","09-DEC")) -> 01-APR | F80: 45034 | G80: ZV-E1 Offline assets | H80: Astrid Jean-Baptiste | I80: Delivered | J80: DI | K80: BA | L80: https://saranistudio-my.sharepoint.com/:f:/g/personal/team_sarani_studio/EvN6F1tLUb1HpsDsbcqLJpgBS_xatQW1Mdo30DXnEk4Umw?e=ZwLhqb | M80: =IF(SUM(V80:BC80)=0,"-",SUM(V80:BC80)) -> 7 | N80: =IF(SUMPRODUCT($V$3:$BC$3,V80:BC80)=0,"-",SUMPRODUCT($V$3:$BC$3,V80:BC80)) -> 375 | O80: 45035 | P80: =IF(G80="","",IFERROR(IF(S80="Sent","",IF(I80="Delivered","PO en attente","Projet en cours")),"")) | Q80: 4200644224 | S80: Sent | T80: F2023-0606 | U80: Paid | AC80: 1 | AD80: 6
A81: Sony | B81: SFR | C81: FY23 | D81: =IF(F81="","",CHOOSE(MONTH(F81),"Q4","Q4","Q4","Q1","Q1","Q1","Q2","Q2","Q2","Q3","Q3","Q3")) -> Q1 | E81: =IF(F81="","",CHOOSE(MONTH(F81),"10-JAN","11-FEB","12-MAR","01-APR","02-MAY","03-JUN","04-JUL","05-AUG","06-SEP","07-OCT","08-NOV","09-DEC")) -> 01-APR | F81: 45040 | G81: Le printemps Sony / Amazon | H81: Joelle Mechache | I81: Delivered | J81: MDR | K81: CM | L81: https://saranistudio-my.sharepoint.com/:f:/g/personal/team_sarani_studio/EhsZRSxgxfVLrM85FfWaf4wBIG1duzSBgim6pUcZ5L-q-g?e=ImXkgA | M81: =IF(SUM(V81:BC81)=0,"-",SUM(V81:BC81)) -> 3 | N81: =IF(SUMPRODUCT($V$3:$BC$3,V81:BC81)=0,"-",SUMPRODUCT($V$3:$BC$3,V81:BC81)) -> 190 | O81: 45044 | P81: =IF(G81="","",IFERROR(IF(S81="Sent","",IF(I81="Delivered","PO en attente","Projet en cours")),"")) | Q81: 4200657837 | R81: Mai | S81: Sent | T81: F2024-0041 | U81: Paid 27/03/2024 | V81: 1 | W81: 2
A82: Sony | B82: SFR | C82: FY23 | D82: =IF(F82="","",CHOOSE(MONTH(F82),"Q4","Q4","Q4","Q1","Q1","Q1","Q2","Q2","Q2","Q3","Q3","Q3")) -> Q1 | E82: =IF(F82="","",CHOOSE(MONTH(F82),"10-JAN","11-FEB","12-MAR","01-APR","02-MAY","03-JUN","04-JUL","05-AUG","06-SEP","07-OCT","08-NOV","09-DEC")) -> 01-APR | F82: 45042 | G82: Campagne TV launch FNAC DARTY | H82: Mylène Pellet | I82: Delivered | J82: TV | K82: CM | L82: https://saranistudio-my.sharepoint.com/:f:/g/personal/team_sarani_studio/Eq7SJAAGtLFPt3_PaidqT-cAUBgqmFSKdaWA6Q3fjNYYyZLw?e=Kf8H76 | M82: =IF(SUM(V82:BC82)=0,"-",SUM(V82:BC82)) -> 7 | N82: =IF(SUMPRODUCT($V$3:$BC$3,V82:BC82)=0,"-",SUMPRODUCT($V$3:$BC$3,V82:BC82)) -> 245 | O82: 45047 | P82: =IF(G82="","",IFERROR(IF(S82="Sent","",IF(I82="Delivered","PO en attente","Projet en cours")),"")) | Q82: 4200641929 | R82: Mai | S82: sent | T82: F2023-0587 | U82: Paid | W82: 7
A83: Sony | B83: SFR | C83: FY23 | D83: =IF(F83="","",CHOOSE(MONTH(F83),"Q4","Q4","Q4","Q1","Q1","Q1","Q2","Q2","Q2","Q3","Q3","Q3")) -> Q1 | E83: =IF(F83="","",CHOOSE(MONTH(F83),"10-JAN","11-FEB","12-MAR","01-APR","02-MAY","03-JUN","04-JUL","05-AUG","06-SEP","07-OCT","08-NOV","09-DEC")) -> 01-APR | F83: 45042 | G83: HAV Cashback - Déclinaisons Online | H83: Laura Vivient | I83: Delivered | J83: HAV | K83: BA | L83: https://saranistudio-my.sharepoint.com/:f:/g/personal/team_sarani_studio/ErdSLaG4JVpLopEZ8cxzFtUBxHbje724J8NKcPC9cI4CxQ?e=TTH44r | M83: =IF(SUM(V83:BC83)=0,"-",SUM(V83:BC83)) -> 6 | N83: =IF(SUMPRODUCT($V$3:$BC$3,V83:BC83)=0,"-",SUMPRODUCT($V$3:$BC$3,V83:BC83)) -> 210 | O83: 45084 | P83: =IF(G83="","",IFERROR(IF(S83="Sent","",IF(I83="Delivered","PO en attente","Projet en cours")),"")) | Q83: 4200645636 | S83: Sent | T83: F2023-0594 | U83: Paid | W83: 6
A84: Sony | B84: SFR | C84: FY23 | D84: =IF(F84="","",CHOOSE(MONTH(F84),"Q4","Q4","Q4","Q1","Q1","Q1","Q2","Q2","Q2","Q3","Q3","Q3")) -> Q1 | E84: =IF(F84="","",CHOOSE(MONTH(F84),"10-JAN","11-FEB","12-MAR","01-APR","02-MAY","03-JUN","04-JUL","05-AUG","06-SEP","07-OCT","08-NOV","09-DEC")) -> 01-APR | F84: 45042 | G84: Adaptation Megastar Cashback TV HAV | H84: Mylène Pellet | I84: Delivered | J84: TV | K84: CM | L84: https://saranistudio-my.sharepoint.com/:f:/g/personal/team_sarani_studio/EryFOZSDujNAvnhAwzgHd6YBejy68T4VHXJZQ1QAcVGLmw?e=rKtkku | M84: =IF(SUM(V84:BC84)=0,"-",SUM(V84:BC84)) -> 1 | N84: =IF(SUMPRODUCT($V$3:$BC$3,V84:BC84)=0,"-",SUMPRODUCT($V$3:$BC$3,V84:BC84)) -> 35 | O84: 45047 | P84: =IF(G84="","",IFERROR(IF(S84="Sent","",IF(I84="Delivered","PO en attente","Projet en cours")),"")) | Q84: 4200641929 | R84: Juin | S84: sent | T84: F2023-0600 | U84: Paid | W84: 1
A85: Sony | B85: SFR | C85: FY23 | D85: =IF(F85="","",CHOOSE(MONTH(F85),"Q4","Q4","Q4","Q1","Q1","Q1","Q2","Q2","Q2","Q3","Q3","Q3")) -> Q1 | E85: =IF(F85="","",CHOOSE(MONTH(F85),"10-JAN","11-FEB","12-MAR","01-APR","02-MAY","03-JUN","04-JUL","05-AUG","06-SEP","07-OCT","08-NOV","09-DEC")) -> 01-APR | F85: 45042 | G85: OP summer - Déclinaisons Photo Univers | H85: Alice Mucke | I85: Delivered | J85: DI | K85: CM | L85: https://saranistudio-my.sharepoint.com/:f:/g/personal/team_sarani_studio/ElqnG-FXH_tIjM-5CjehobkBI3iwiykX2wZsbbcXjP2u5Q?e=cTcTX3 | M85: =IF(SUM(V85:BC85)=0,"-",SUM(V85:BC85)) -> 3 | N85: =IF(SUMPRODUCT($V$3:$BC$3,V85:BC85)=0,"-",SUMPRODUCT($V$3:$BC$3,V85:BC85)) -> 105 | O85: 45043 | P85: =IF(G85="","",IFERROR(IF(S85="Sent","",IF(I85="Delivered","PO en attente","Projet en cours")),"")) | Q85: 4200641951 | R85: Mai | S85: sent | T85: F2023-0602 | U85: Paid | W85: 3
A86: Sony | B86: SFR | C86: FY23 | D86: =IF(F86="","",CHOOSE(MONTH(F86),"Q4","Q4","Q4","Q1","Q1","Q1","Q2","Q2","Q2","Q3","Q3","Q3")) -> Q1 | E86: =IF(F86="","",CHOOSE(MONTH(F86),"10-JAN","11-FEB","12-MAR","01-APR","02-MAY","03-JUN","04-JUL","05-AUG","06-SEP","07-OCT","08-NOV","09-DEC")) -> 01-APR | F86: 45042 | G86: OP FX30 | H86: Astrid Jean-Baptiste | I86: Delivered | J86: DI | K86: BA | L86: https://saranistudio-my.sharepoint.com/:f:/g/personal/team_sarani_studio/Eo_WrjVzYsBLghSpIKuCgJ4BkWtZHQIu_zjYECvNipC1AQ?e=7Ka5FQ | M86: =IF(SUM(V86:BC86)=0,"-",SUM(V86:BC86)) -> 5 | N86: =IF(SUMPRODUCT($V$3:$BC$3,V86:BC86)=0,"-",SUMPRODUCT($V$3:$BC$3,V86:BC86)) -> 365 | O86: 45071 | P86: =IF(G86="","",IFERROR(IF(S86="Sent","",IF(I86="Delivered","PO en attente","Projet en cours")),"")) | Q86: 4200644333 | S86: sent | T86: F2023-0604 | U86: Paid | V86: 1 | W86: 2 | AC86: 1 | AD86: 1
A87: Sony | B87: SFR | C87: FY24 | D87: =IF(F87="","",CHOOSE(MONTH(F87),"Q4","Q4","Q4","Q1","Q1","Q1","Q2","Q2","Q2","Q3","Q3","Q3")) -> Q1 | E87: =IF(F87="","",CHOOSE(MONTH(F87),"10-JAN","11-FEB","12-MAR","01-APR","02-MAY","03-JUN","04-JUL","05-AUG","06-SEP","07-OCT","08-NOV","09-DEC")) -> 01-APR | F87: 45042 | G87: French Days - Adaptations Boulanger | H87: Maureen Masson | I87: Delivered | J87: MDR | K87: CM | L87: https://saranistudio-my.sharepoint.com/:f:/g/personal/team_sarani_studio/El9e7jWbxXdMjpwPrqrY1MwBS4are5bsKjLjkvs3GxUcVA?e=WhH1kd | M87: =IF(SUM(V87:BC87)=0,"-",SUM(V87:BC87)) -> 4 | N87: =IF(SUMPRODUCT($V$3:$BC$3,V87:BC87)=0,"-",SUMPRODUCT($V$3:$BC$3,V87:BC87)) -> 140 | O87: 45043 | P87: =IF(G87="","",IFERROR(IF(#REF!="Sent","",IF(I87="Delivered","PO en attente","Projet en cours")),"")) | Q87: 4200641950 | R87: Mai | S87: Sent | T87: F2024-0139 | U87: - | W87: 4
A88: Sony | B88: SFR | C88: FY23 | D88: =IF(F88="","",CHOOSE(MONTH(F88),"Q4","Q4","Q4","Q1","Q1","Q1","Q2","Q2","Q2","Q3","Q3","Q3")) -> Q1 | E88: =IF(F88="","",CHOOSE(MONTH(F88),"10-JAN","11-FEB","12-MAR","01-APR","02-MAY","03-JUN","04-JUL","05-AUG","06-SEP","07-OCT","08-NOV","09-DEC")) -> 01-APR | F88: 45044 | G88: Webpop TV FY23 | H88: Joelle Mechache | I88: Delivered | J88: TV | K88: CM | L88: https://saranistudio-my.sharepoint.com/:f:/g/personal/team_sarani_studio/EksaPdiWfxhMnbU7goZGW3wBNMdtyNVXPZFQGY1IHS_P8w?e=K0olFY | M88: =IF(SUM(V88:BC88)=0,"-",SUM(V88:BC88)) -> 1 | N88: =IF(SUMPRODUCT($V$3:$BC$3,V88:BC88)=0,"-",SUMPRODUCT($V$3:$BC$3,V88:BC88)) -> 120 | O88: 45061 | P88: =IF(G88="","",IFERROR(IF(S88="Sent","",IF(I88="Delivered","PO en attente","Projet en cours")),"")) | Q88: 4200641929 | R88: Juin | S88: sent | T88: F2023-0610 | U88: Paid | V88: 1
A89: Sony | B89: SFR | C89: FY24 | D89: =IF(F89="","",CHOOSE(MONTH(F89),"Q4","Q4","Q4","Q1","Q1","Q1","Q2","Q2","Q2","Q3","Q3","Q3")) -> Q1 | E89: =IF(F89="","",CHOOSE(MONTH(F89),"10-JAN","11-FEB","12-MAR","01-APR","02-MAY","03-JUN","04-JUL","05-AUG","06-SEP","07-OCT","08-NOV","09-DEC")) -> 01-APR | F89: 45044 | G89: French Days - TV HAV réseaux sociaux | H89: Françoise Burgarella | I89: Delivered | J89: TV | K89: BA | L89: https://saranistudio-my.sharepoint.com/:f:/g/personal/team_sarani_studio/Ess1vC7t3GRDlkrH39chUyABGRfHdGSAU5PEixcxFc0JLA?e=s28LEw | M89: =IF(SUM(V89:BC89)=0,"-",SUM(V89:BC89)) -> 2 | N89: =IF(SUMPRODUCT($V$3:$BC$3,V89:BC89)=0,"-",SUMPRODUCT($V$3:$BC$3,V89:BC89)) -> 70 | O89: https://saranistudio-my.sharepoint.com/:b:/g/personal/team_sarani_studio/Ecb_Wvnzn41Jms0Ozi5wOg0BgmWnsfYuKClAV_v1-WEylg?e=UjRbbG | P89: =IF(G89="","",IFERROR(IF(S89="Sent","",IF(I89="Delivered","PO en attente","Projet en cours")),"")) | Q89: 4200678470 | S89: Sent | T89: F2025-0143 | U89: Paid 28/05/2025 | W89: 2
A90: Sony | B90: SFR | C90: FY23 | D90: =IF(F90="","",CHOOSE(MONTH(F90),"Q4","Q4","Q4","Q1","Q1","Q1","Q2","Q2","Q2","Q3","Q3","Q3")) -> Q1 | E90: =IF(F90="","",CHOOSE(MONTH(F90),"10-JAN","11-FEB","12-MAR","01-APR","02-MAY","03-JUN","04-JUL","05-AUG","06-SEP","07-OCT","08-NOV","09-DEC")) -> 02-MAY | F90: 45048 | G90: OP FX30 - Photo Univers | H90: Alice Mucke | I90: Delivered | J90: DI | K90: CM | L90: https://saranistudio-my.sharepoint.com/:f:/g/personal/team_sarani_studio/EmGsdIsbJgRJsHn18mqoDSQB5FuBnBna9S_58xG7MtztpQ?e=qp39eM | M90: =IF(SUM(V90:BC90)=0,"-",SUM(V90:BC90)) -> 4 | N90: =IF(SUMPRODUCT($V$3:$BC$3,V90:BC90)=0,"-",SUMPRODUCT($V$3:$BC$3,V90:BC90)) -> 140 | O90: 45047 | P90: =IF(G90="","",IFERROR(IF(S90="Sent","",IF(I90="Delivered","PO en attente","Projet en cours")),"")) | Q90: 4200641951 | R90: Juin | S90: sent | T90: F2023-0588 | U90: Paid | W90: 4
