Workbook

Sheet Overview
A1: Performance Dashboard — Sarani Studio
A3: REVENUS (€) | B3: 2022 | F3: 2023 | J3: 2024 | N3: 2025 | R3: 2026
B4: Q1 | C4: Q2 | D4: Q3 | E4: Q4 | F4: Q1 | G4: Q2 | H4: Q3 | I4: Q4 | J4: Q1 | K4: Q2 | L4: Q3 | M4: Q4 | N4: Q1 | O4: Q2 | P4: Q3 | Q4: Q4 | R4: Q1 | S4: Q2 | T4: Q3 | U4: Q4
A5: All Projects | B5: =SUMIFS('All projects'!I$2:I$1000,'All projects'!B$2:B$1000,">="&DATE(2022,1,1),'All projects'!B$2:B$1000,"<="&DATE(2022,3+1,0)) -> 0 | C5: =SUMIFS('All projects'!I$2:I$1000,'All projects'!B$2:B$1000,">="&DATE(2022,4,1),'All projects'!B$2:B$1000,"<="&DATE(2022,6+1,0)) -> 0 | D5: =SUMIFS('All projects'!I$2:I$1000,'All projects'!B$2:B$1000,">="&DATE(2022,7,1),'All projects'!B$2:B$1000,"<="&DATE(2022,9+1,0)) -> 5000 | E5: =SUMIFS('All projects'!I$2:I$1000,'All projects'!B$2:B$1000,">="&DATE(2022,10,1),'All projects'!B$2:B$1000,"<="&DATE(2022,12+1,0)) -> 0 | F5: =SUMIFS('All projects'!I$2:I$1000,'All projects'!B$2:B$1000,">="&DATE(2023,1,1),'All projects'!B$2:B$1000,"<="&DATE(2023,3+1,0)) -> 0 | G5: =SUMIFS('All projects'!I$2:I$1000,'All projects'!B$2:B$1000,">="&DATE(2023,4,1),'All projects'!B$2:B$1000,"<="&DATE(2023,6+1,0)) -> 8650 | H5: =SUMIFS('All projects'!I$2:I$1000,'All projects'!B$2:B$1000,">="&DATE(2023,7,1),'All projects'!B$2:B$1000,"<="&DATE(2023,9+1,0)) -> 1950 | I5: =SUMIFS('All projects'!I$2:I$1000,'All projects'!B$2:B$1000,">="&DATE(2023,10,1),'All projects'!B$2:B$1000,"<="&DATE(2023,12+1,0)) -> 3080 | J5: =SUMIFS('All projects'!I$2:I$1000,'All projects'!B$2:B$1000,">="&DATE(2024,1,1),'All projects'!B$2:B$1000,"<="&DATE(2024,3+1,0)) -> 2840 | K5: =SUMIFS('All projects'!I$2:I$1000,'All projects'!B$2:B$1000,">="&DATE(2024,4,1),'All projects'!B$2:B$1000,"<="&DATE(2024,6+1,0)) -> 42371 | L5: =SUMIFS('All projects'!I$2:I$1000,'All projects'!B$2:B$1000,">="&DATE(2024,7,1),'All projects'!B$2:B$1000,"<="&DATE(2024,9+1,0)) -> 122955 | M5: =SUMIFS('All projects'!I$2:I$1000,'All projects'!B$2:B$1000,">="&DATE(2024,10,1),'All projects'!B$2:B$1000,"<="&DATE(2024,12+1,0)) -> 3490 | N5: =SUMIFS('All projects'!I$2:I$1000,'All projects'!B$2:B$1000,">="&DATE(2025,1,1),'All projects'!B$2:B$1000,"<="&DATE(2025,3+1,0)) -> 11105 | O5: =SUMIFS('All projects'!I$2:I$1000,'All projects'!B$2:B$1000,">="&DATE(2025,4,1),'All projects'!B$2:B$1000,"<="&DATE(2025,6+1,0)) -> 63830 | P5: =SUMIFS('All projects'!I$2:I$1000,'All projects'!B$2:B$1000,">="&DATE(2025,7,1),'All projects'!B$2:B$1000,"<="&DATE(2025,9+1,0)) -> 29620 | Q5: =SUMIFS('All projects'!I$2:I$1000,'All projects'!B$2:B$1000,">="&DATE(2025,10,1),'All projects'!B$2:B$1000,"<="&DATE(2025,12+1,0)) -> 19506.17 | R5: =SUMIFS('All projects'!I$2:I$1000,'All projects'!B$2:B$1000,">="&DATE(2026,1,1),'All projects'!B$2:B$1000,"<="&DATE(2026,3+1,0)) -> 19630 | S5: =SUMIFS('All projects'!I$2:I$1000,'All projects'!B$2:B$1000,">="&DATE(2026,4,1),'All projects'!B$2:B$1000,"<="&DATE(2026,6+1,0)) -> 0 | T5: =SUMIFS('All projects'!I$2:I$1000,'All projects'!B$2:B$1000,">="&DATE(2026,7,1),'All projects'!B$2:B$1000,"<="&DATE(2026,9+1,0)) -> 0 | U5: =SUMIFS('All projects'!I$2:I$1000,'All projects'!B$2:B$1000,">="&DATE(2026,10,1),'All projects'!B$2:B$1000,"<="&DATE(2026,12+1,0)) -> 3428
A6: ProcessOut | B6: =SUMIFS(ProcessOut!J$4:J$1000,ProcessOut!C$4:C$1000,">="&DATE(2022,1,1),ProcessOut!C$4:C$1000,"<="&DATE(2022,3+1,0)) -> 0 | C6: =SUMIFS(ProcessOut!J$4:J$1000,ProcessOut!C$4:C$1000,">="&DATE(2022,4,1),ProcessOut!C$4:C$1000,"<="&DATE(2022,6+1,0)) -> 0 | D6: =SUMIFS(ProcessOut!J$4:J$1000,ProcessOut!C$4:C$1000,">="&DATE(2022,7,1),ProcessOut!C$4:C$1000,"<="&DATE(2022,9+1,0)) -> 0 | E6: =SUMIFS(ProcessOut!J$4:J$1000,ProcessOut!C$4:C$1000,">="&DATE(2022,10,1),ProcessOut!C$4:C$1000,"<="&DATE(2022,12+1,0)) -> 0 | F6: =SUMIFS(ProcessOut!J$4:J$1000,ProcessOut!C$4:C$1000,">="&DATE(2023,1,1),ProcessOut!C$4:C$1000,"<="&DATE(2023,3+1,0)) -> 0 | G6: =SUMIFS(ProcessOut!J$4:J$1000,ProcessOut!C$4:C$1000,">="&DATE(2023,4,1),ProcessOut!C$4:C$1000,"<="&DATE(2023,6+1,0)) -> 0 | H6: =SUMIFS(ProcessOut!J$4:J$1000,ProcessOut!C$4:C$1000,">="&DATE(2023,7,1),ProcessOut!C$4:C$1000,"<="&DATE(2023,9+1,0)) -> 0 | I6: =SUMIFS(ProcessOut!J$4:J$1000,ProcessOut!C$4:C$1000,">="&DATE(2023,10,1),ProcessOut!C$4:C$1000,"<="&DATE(2023,12+1,0)) -> 0 | J6: =SUMIFS(ProcessOut!J$4:J$1000,ProcessOut!C$4:C$1000,">="&DATE(2024,1,1),ProcessOut!C$4:C$1000,"<="&DATE(2024,3+1,0)) -> 0 | K6: =SUMIFS(ProcessOut!J$4:J$1000,ProcessOut!C$4:C$1000,">="&DATE(2024,4,1),ProcessOut!C$4:C$1000,"<="&DATE(2024,6+1,0)) -> 900 | L6: =SUMIFS(ProcessOut!J$4:J$1000,ProcessOut!C$4:C$1000,">="&DATE(2024,7,1),ProcessOut!C$4:C$1000,"<="&DATE(2024,9+1,0)) -> 3600 | M6: =SUMIFS(ProcessOut!J$4:J$1000,ProcessOut!C$4:C$1000,">="&DATE(2024,10,1),ProcessOut!C$4:C$1000,"<="&DATE(2024,12+1,0)) -> 5400 | N6: =SUMIFS(ProcessOut!J$4:J$1000,ProcessOut!C$4:C$1000,">="&DATE(2025,1,1),ProcessOut!C$4:C$1000,"<="&DATE(2025,3+1,0)) -> 10600 | O6: =SUMIFS(ProcessOut!J$4:J$1000,ProcessOut!C$4:C$1000,">="&DATE(2025,4,1),ProcessOut!C$4:C$1000,"<="&DATE(2025,6+1,0)) -> 21000 | P6: =SUMIFS(ProcessOut!J$4:J$1000,ProcessOut!C$4:C$1000,">="&DATE(2025,7,1),ProcessOut!C$4:C$1000,"<="&DATE(2025,9+1,0)) -> 42900 | Q6: =SUMIFS(ProcessOut!J$4:J$1000,ProcessOut!C$4:C$1000,">="&DATE(2025,10,1),ProcessOut!C$4:C$1000,"<="&DATE(2025,12+1,0)) -> 0 | R6: =SUMIFS(ProcessOut!J$4:J$1000,ProcessOut!C$4:C$1000,">="&DATE(2026,1,1),ProcessOut!C$4:C$1000,"<="&DATE(2026,3+1,0)) -> 22350 | S6: =SUMIFS(ProcessOut!J$4:J$1000,ProcessOut!C$4:C$1000,">="&DATE(2026,4,1),ProcessOut!C$4:C$1000,"<="&DATE(2026,6+1,0)) -> 22350 | T6: =SUMIFS(ProcessOut!J$4:J$1000,ProcessOut!C$4:C$1000,">="&DATE(2026,7,1),ProcessOut!C$4:C$1000,"<="&DATE(2026,9+1,0)) -> 22350 | U6: =SUMIFS(ProcessOut!J$4:J$1000,ProcessOut!C$4:C$1000,">="&DATE(2026,10,1),ProcessOut!C$4:C$1000,"<="&DATE(2026,12+1,0)) -> 22350
A7: Connect | B7: =SUMIFS(Connect!J$4:J$1000,Connect!C$4:C$1000,">="&DATE(2022,1,1),Connect!C$4:C$1000,"<="&DATE(2022,3+1,0))/$B$25 -> 0 | C7: =SUMIFS(Connect!J$4:J$1000,Connect!C$4:C$1000,">="&DATE(2022,4,1),Connect!C$4:C$1000,"<="&DATE(2022,6+1,0))/$B$25 -> 0 | D7: =SUMIFS(Connect!J$4:J$1000,Connect!C$4:C$1000,">="&DATE(2022,7,1),Connect!C$4:C$1000,"<="&DATE(2022,9+1,0))/$B$25 -> 0 | E7: =SUMIFS(Connect!J$4:J$1000,Connect!C$4:C$1000,">="&DATE(2022,10,1),Connect!C$4:C$1000,"<="&DATE(2022,12+1,0))/$B$25 -> 0 | F7: =SUMIFS(Connect!J$4:J$1000,Connect!C$4:C$1000,">="&DATE(2023,1,1),Connect!C$4:C$1000,"<="&DATE(2023,3+1,0))/$B$25 -> 0 | G7: =SUMIFS(Connect!J$4:J$1000,Connect!C$4:C$1000,">="&DATE(2023,4,1),Connect!C$4:C$1000,"<="&DATE(2023,6+1,0))/$B$25 -> 0 | H7: =SUMIFS(Connect!J$4:J$1000,Connect!C$4:C$1000,">="&DATE(2023,7,1),Connect!C$4:C$1000,"<="&DATE(2023,9+1,0))/$B$25 -> 0 | I7: =SUMIFS(Connect!J$4:J$1000,Connect!C$4:C$1000,">="&DATE(2023,10,1),Connect!C$4:C$1000,"<="&DATE(2023,12+1,0))/$B$25 -> 0 | J7: =SUMIFS(Connect!J$4:J$1000,Connect!C$4:C$1000,">="&DATE(2024,1,1),Connect!C$4:C$1000,"<="&DATE(2024,3+1,0))/$B$25 -> 0 | K7: =SUMIFS(Connect!J$4:J$1000,Connect!C$4:C$1000,">="&DATE(2024,4,1),Connect!C$4:C$1000,"<="&DATE(2024,6+1,0))/$B$25 -> 0 | L7: =SUMIFS(Connect!J$4:J$1000,Connect!C$4:C$1000,">="&DATE(2024,7,1),Connect!C$4:C$1000,"<="&DATE(2024,9+1,0))/$B$25 -> 3913.0435 | M7: =SUMIFS(Connect!J$4:J$1000,Connect!C$4:C$1000,">="&DATE(2024,10,1),Connect!C$4:C$1000,"<="&DATE(2024,12+1,0))/$B$25 -> 1304.3478 | N7: =SUMIFS(Connect!J$4:J$1000,Connect!C$4:C$1000,">="&DATE(2025,1,1),Connect!C$4:C$1000,"<="&DATE(2025,3+1,0))/$B$25 -> 739.13043 | O7: =SUMIFS(Connect!J$4:J$1000,Connect!C$4:C$1000,">="&DATE(2025,4,1),Connect!C$4:C$1000,"<="&DATE(2025,6+1,0))/$B$25 -> 478.26087 | P7: =SUMIFS(Connect!J$4:J$1000,Connect!C$4:C$1000,">="&DATE(2025,7,1),Connect!C$4:C$1000,"<="&DATE(2025,9+1,0))/$B$25 -> 1630.4348 | Q7: =SUMIFS(Connect!J$4:J$1000,Connect!C$4:C$1000,">="&DATE(2025,10,1),Connect!C$4:C$1000,"<="&DATE(2025,12+1,0))/$B$25 -> 0 | R7: =SUMIFS(Connect!J$4:J$1000,Connect!C$4:C$1000,">="&DATE(2026,1,1),Connect!C$4:C$1000,"<="&DATE(2026,3+1,0))/$B$25 -> 0 | S7: =SUMIFS(Connect!J$4:J$1000,Connect!C$4:C$1000,">="&DATE(2026,4,1),Connect!C$4:C$1000,"<="&DATE(2026,6+1,0))/$B$25 -> 0 | T7: =SUMIFS(Connect!J$4:J$1000,Connect!C$4:C$1000,">="&DATE(2026,7,1),Connect!C$4:C$1000,"<="&DATE(2026,9+1,0))/$B$25 -> 0 | U7: =SUMIFS(Connect!J$4:J$1000,Connect!C$4:C$1000,">="&DATE(2026,10,1),Connect!C$4:C$1000,"<="&DATE(2026,12+1,0))/$B$25 -> 0
A8: Oneov | B8: =SUMIFS(Oneov!H$4:H$1000,Oneov!A$4:A$1000,">="&DATE(2022,1,1),Oneov!A$4:A$1000,"<="&DATE(2022,3+1,0)) -> 0 | C8: =SUMIFS(Oneov!H$4:H$1000,Oneov!A$4:A$1000,">="&DATE(2022,4,1),Oneov!A$4:A$1000,"<="&DATE(2022,6+1,0)) -> 0 | D8: =SUMIFS(Oneov!H$4:H$1000,Oneov!A$4:A$1000,">="&DATE(2022,7,1),Oneov!A$4:A$1000,"<="&DATE(2022,9+1,0)) -> 0 | E8: =SUMIFS(Oneov!H$4:H$1000,Oneov!A$4:A$1000,">="&DATE(2022,10,1),Oneov!A$4:A$1000,"<="&DATE(2022,12+1,0)) -> 0 | F8: =SUMIFS(Oneov!H$4:H$1000,Oneov!A$4:A$1000,">="&DATE(2023,1,1),Oneov!A$4:A$1000,"<="&DATE(2023,3+1,0)) -> 0 | G8: =SUMIFS(Oneov!H$4:H$1000,Oneov!A$4:A$1000,">="&DATE(2023,4,1),Oneov!A$4:A$1000,"<="&DATE(2023,6+1,0)) -> 0 | H8: =SUMIFS(Oneov!H$4:H$1000,Oneov!A$4:A$1000,">="&DATE(2023,7,1),Oneov!A$4:A$1000,"<="&DATE(2023,9+1,0)) -> 0 | I8: =SUMIFS(Oneov!H$4:H$1000,Oneov!A$4:A$1000,">="&DATE(2023,10,1),Oneov!A$4:A$1000,"<="&DATE(2023,12+1,0)) -> 0 | J8: =SUMIFS(Oneov!H$4:H$1000,Oneov!A$4:A$1000,">="&DATE(2024,1,1),Oneov!A$4:A$1000,"<="&DATE(2024,3+1,0)) -> 13150 | K8: =SUMIFS(Oneov!H$4:H$1000,Oneov!A$4:A$1000,">="&DATE(2024,4,1),Oneov!A$4:A$1000,"<="&DATE(2024,6+1,0)) -> 0 | L8: =SUMIFS(Oneov!H$4:H$1000,Oneov!A$4:A$1000,">="&DATE(2024,7,1),Oneov!A$4:A$1000,"<="&DATE(2024,9+1,0)) -> 0 | M8: =SUMIFS(Oneov!H$4:H$1000,Oneov!A$4:A$1000,">="&DATE(2024,10,1),Oneov!A$4:A$1000,"<="&DATE(2024,12+1,0)) -> 0 | N8: =SUMIFS(Oneov!H$4:H$1000,Oneov!A$4:A$1000,">="&DATE(2025,1,1),Oneov!A$4:A$1000,"<="&DATE(2025,3+1,0)) -> 0 | O8: =SUMIFS(Oneov!H$4:H$1000,Oneov!A$4:A$1000,">="&DATE(2025,4,1),Oneov!A$4:A$1000,"<="&DATE(2025,6+1,0)) -> 0 | P8: =SUMIFS(Oneov!H$4:H$1000,Oneov!A$4:A$1000,">="&DATE(2025,7,1),Oneov!A$4:A$1000,"<="&DATE(2025,9+1,0)) -> 0 | Q8: =SUMIFS(Oneov!H$4:H$1000,Oneov!A$4:A$1000,">="&DATE(2025,10,1),Oneov!A$4:A$1000,"<="&DATE(2025,12+1,0)) -> 0 | R8: =SUMIFS(Oneov!H$4:H$1000,Oneov!A$4:A$1000,">="&DATE(2026,1,1),Oneov!A$4:A$1000,"<="&DATE(2026,3+1,0)) -> 0 | S8: =SUMIFS(Oneov!H$4:H$1000,Oneov!A$4:A$1000,">="&DATE(2026,4,1),Oneov!A$4:A$1000,"<="&DATE(2026,6+1,0)) -> 0 | T8: =SUMIFS(Oneov!H$4:H$1000,Oneov!A$4:A$1000,">="&DATE(2026,7,1),Oneov!A$4:A$1000,"<="&DATE(2026,9+1,0)) -> 0 | U8: =SUMIFS(Oneov!H$4:H$1000,Oneov!A$4:A$1000,">="&DATE(2026,10,1),Oneov!A$4:A$1000,"<="&DATE(2026,12+1,0)) -> 0
A9: TOTAL | B9: =SUM(B5:B8) -> 0 | C9: =SUM(C5:C8) -> 0 | D9: =SUM(D5:D8) -> 5000 | E9: =SUM(E5:E8) -> 0 | F9: =SUM(F5:F8) -> 0 | G9: =SUM(G5:G8) -> 8650 | H9: =SUM(H5:H8) -> 1950 | I9: =SUM(I5:I8) -> 3080 | ... U9: =SUM(U5:U8) -> 25778
A11: NOMBRE DE PROJETS | B11: 2022 | F11: 2023 | J11: 2024 | N11: 2025 | R11: 2026
B12: Q1 | C12: Q2 | D12: Q3 | E12: Q4 | F12: Q1 | G12: Q2 | H12: Q3 | I12: Q4 | J12: Q1 | K12: Q2 | L12: Q3 | M12: Q4 | N12: Q1 | O12: Q2 | P12: Q3 | Q12: Q4 | R12: Q1 | S12: Q2 | T12: Q3 | U12: Q4
A13: All Projects | B13: =COUNTIFS('All projects'!B$2:B$1000,">="&DATE(2022,1,1),'All projects'!B$2:B$1000,"<="&DATE(2022,3+1,0)) -> 0 | C13: =COUNTIFS('All projects'!B$2:B$1000,">="&DATE(2022,4,1),'All projects'!B$2:B$1000,"<="&DATE(2022,6+1,0)) -> 0 | D13: =COUNTIFS('All projects'!B$2:B$1000,">="&DATE(2022,7,1),'All projects'!B$2:B$1000,"<="&DATE(2022,9+1,0)) -> 1 | E13: =COUNTIFS('All projects'!B$2:B$1000,">="&DATE(2022,10,1),'All projects'!B$2:B$1000,"<="&DATE(2022,12+1,0)) -> 0 | F13: =COUNTIFS('All projects'!B$2:B$1000,">="&DATE(2023,1,1),'All projects'!B$2:B$1000,"<="&DATE(2023,3+1,0)) -> 0 | G13: =COUNTIFS('All projects'!B$2:B$1000,">="&DATE(2023,4,1),'All projects'!B$2:B$1000,"<="&DATE(2023,6+1,0)) -> 4 | H13: =COUNTIFS('All projects'!B$2:B$1000,">="&DATE(2023,7,1),'All projects'!B$2:B$1000,"<="&DATE(2023,9+1,0)) -> 2 | I13: =COUNTIFS('All projects'!B$2:B$1000,">="&DATE(2023,10,1),'All projects'!B$2:B$1000,"<="&DATE(2023,12+1,0)) -> 4 | J13: =COUNTIFS('All projects'!B$2:B$1000,">="&DATE(2024,1,1),'All projects'!B$2:B$1000,"<="&DATE(2024,3+1,0)) -> 7 | K13: =COUNTIFS('All projects'!B$2:B$1000,">="&DATE(2024,4,1),'All projects'!B$2:B$1000,"<="&DATE(2024,6+1,0)) -> 15 | L13: =COUNTIFS('All projects'!B$2:B$1000,">="&DATE(2024,7,1),'All projects'!B$2:B$1000,"<="&DATE(2024,9+1,0)) -> 28 | M13: =COUNTIFS('All projects'!B$2:B$1000,">="&DATE(2024,10,1),'All projects'!B$2:B$1000,"<="&DATE(2024,12+1,0)) -> 8 | N13: =COUNTIFS('All projects'!B$2:B$1000,">="&DATE(2025,1,1),'All projects'!B$2:B$1000,"<="&DATE(2025,3+1,0)) -> 16 | O13: =COUNTIFS('All projects'!B$2:B$1000,">="&DATE(2025,4,1),'All projects'!B$2:B$1000,"<="&DATE(2025,6+1,0)) -> 16 | P13: =COUNTIFS('All projects'!B$2:B$1000,">="&DATE(2025,7,1),'All projects'!B$2:B$1000,"<="&DATE(2025,9+1,0)) -> 13 | Q13: =COUNTIFS('All projects'!B$2:B$1000,">="&DATE(2025,10,1),'All projects'!B$2:B$1000,"<="&DATE(2025,12+1,0)) -> 12 | R13: =COUNTIFS('All projects'!B$2:B$1000,">="&DATE(2026,1,1),'All projects'!B$2:B$1000,"<="&DATE(2026,3+1,0)) -> 11 | S13: =COUNTIFS('All projects'!B$2:B$1000,">="&DATE(2026,4,1),'All projects'!B$2:B$1000,"<="&DATE(2026,6+1,0)) -> 0 | T13: =COUNTIFS('All projects'!B$2:B$1000,">="&DATE(2026,7,1),'All projects'!B$2:B$1000,"<="&DATE(2026,9+1,0)) -> 0 | U13: =COUNTIFS('All projects'!B$2:B$1000,">="&DATE(2026,10,1),'All projects'!B$2:B$1000,"<="&DATE(2026,12+1,0)) -> 2
A14: ProcessOut | B14: =COUNTIFS(ProcessOut!C$4:C$1000,">="&DATE(2022,1,1),ProcessOut!C$4:C$1000,"<="&DATE(2022,3+1,0)) -> 0 | C14: =COUNTIFS(ProcessOut!C$4:C$1000,">="&DATE(2022,4,1),ProcessOut!C$4:C$1000,"<="&DATE(2022,6+1,0)) -> 0 | D14: =COUNTIFS(ProcessOut!C$4:C$1000,">="&DATE(2022,7,1),ProcessOut!C$4:C$1000,"<="&DATE(2022,9+1,0)) -> 0 | E14: =COUNTIFS(ProcessOut!C$4:C$1000,">="&DATE(2022,10,1),ProcessOut!C$4:C$1000,"<="&DATE(2022,12+1,0)) -> 0 | F14: =COUNTIFS(ProcessOut!C$4:C$1000,">="&DATE(2023,1,1),ProcessOut!C$4:C$1000,"<="&DATE(2023,3+1,0)) -> 0 | G14: =COUNTIFS(ProcessOut!C$4:C$1000,">="&DATE(2023,4,1),ProcessOut!C$4:C$1000,"<="&DATE(2023,6+1,0)) -> 0 | H14: =COUNTIFS(ProcessOut!C$4:C$1000,">="&DATE(2023,7,1),ProcessOut!C$4:C$1000,"<="&DATE(2023,9+1,0)) -> 0 | I14: =COUNTIFS(ProcessOut!C$4:C$1000,">="&DATE(2023,10,1),ProcessOut!C$4:C$1000,"<="&DATE(2023,12+1,0)) -> 0 | J14: =COUNTIFS(ProcessOut!C$4:C$1000,">="&DATE(2024,1,1),ProcessOut!C$4:C$1000,"<="&DATE(2024,3+1,0)) -> 0 | K14: =COUNTIFS(ProcessOut!C$4:C$1000,">="&DATE(2024,4,1),ProcessOut!C$4:C$1000,"<="&DATE(2024,6+1,0)) -> 3 | L14: =COUNTIFS(ProcessOut!C$4:C$1000,">="&DATE(2024,7,1),ProcessOut!C$4:C$1000,"<="&DATE(2024,9+1,0)) -> 3 | M14: =COUNTIFS(ProcessOut!C$4:C$1000,">="&DATE(2024,10,1),ProcessOut!C$4:C$1000,"<="&DATE(2024,12+1,0)) -> 3 | N14: =COUNTIFS(ProcessOut!C$4:C$1000,">="&DATE(2025,1,1),ProcessOut!C$4:C$1000,"<="&DATE(2025,3+1,0)) -> 3 | O14: =COUNTIFS(ProcessOut!C$4:C$1000,">="&DATE(2025,4,1),ProcessOut!C$4:C$1000,"<="&DATE(2025,6+1,0)) -> 3 | P14: =COUNTIFS(ProcessOut!C$4:C$1000,">="&DATE(2025,7,1),ProcessOut!C$4:C$1000,"<="&DATE(2025,9+1,0)) -> 8 | Q14: =COUNTIFS(ProcessOut!C$4:C$1000,">="&DATE(2025,10,1),ProcessOut!C$4:C$1000,"<="&DATE(2025,12+1,0)) -> 0 | R14: =COUNTIFS(ProcessOut!C$4:C$1000,">="&DATE(2026,1,1),ProcessOut!C$4:C$1000,"<="&DATE(2026,3+1,0)) -> 6 | S14: =COUNTIFS(ProcessOut!C$4:C$1000,">="&DATE(2026,4,1),ProcessOut!C$4:C$1000,"<="&DATE(2026,6+1,0)) -> 6 | T14: =COUNTIFS(ProcessOut!C$4:C$1000,">="&DATE(2026,7,1),ProcessOut!C$4:C$1000,"<="&DATE(2026,9+1,0)) -> 6 | U14: =COUNTIFS(ProcessOut!C$4:C$1000,">="&DATE(2026,10,1),ProcessOut!C$4:C$1000,"<="&DATE(2026,12+1,0)) -> 6
A15: Connect | B15: =COUNTIFS(Connect!C$4:C$1000,">="&DATE(2022,1,1),Connect!C$4:C$1000,"<="&DATE(2022,3+1,0)) -> 0 | C15: =COUNTIFS(Connect!C$4:C$1000,">="&DATE(2022,4,1),Connect!C$4:C$1000,"<="&DATE(2022,6+1,0)) -> 0 | D15: =COUNTIFS(Connect!C$4:C$1000,">="&DATE(2022,7,1),Connect!C$4:C$1000,"<="&DATE(2022,9+1,0)) -> 0 | E15: =COUNTIFS(Connect!C$4:C$1000,">="&DATE(2022,10,1),Connect!C$4:C$1000,"<="&DATE(2022,12+1,0)) -> 0 | F15: =COUNTIFS(Connect!C$4:C$1000,">="&DATE(2023,1,1),Connect!C$4:C$1000,"<="&DATE(2023,3+1,0)) -> 0 | G15: =COUNTIFS(Connect!C$4:C$1000,">="&DATE(2023,4,1),Connect!C$4:C$1000,"<="&DATE(2023,6+1,0)) -> 0 | H15: =COUNTIFS(Connect!C$4:C$1000,">="&DATE(2023,7,1),Connect!C$4:C$1000,"<="&DATE(2023,9+1,0)) -> 0 | I15: =COUNTIFS(Connect!C$4:C$1000,">="&DATE(2023,10,1),Connect!C$4:C$1000,"<="&DATE(2023,12+1,0)) -> 0 | J15: =COUNTIFS(Connect!C$4:C$1000,">="&DATE(2024,1,1),Connect!C$4:C$1000,"<="&DATE(2024,3+1,0)) -> 0 | K15: =COUNTIFS(Connect!C$4:C$1000,">="&DATE(2024,4,1),Connect!C$4:C$1000,"<="&DATE(2024,6+1,0)) -> 0 | L15: =COUNTIFS(Connect!C$4:C$1000,">="&DATE(2024,7,1),Connect!C$4:C$1000,"<="&DATE(2024,9+1,0)) -> 3 | M15: =COUNTIFS(Connect!C$4:C$1000,">="&DATE(2024,10,1),Connect!C$4:C$1000,"<="&DATE(2024,12+1,0)) -> 1 | N15: =COUNTIFS(Connect!C$4:C$1000,">="&DATE(2025,1,1),Connect!C$4:C$1000,"<="&DATE(2025,3+1,0)) -> 2 | O15: =COUNTIFS(Connect!C$4:C$1000,">="&DATE(2025,4,1),Connect!C$4:C$1000,"<="&DATE(2025,6+1,0)) -> 1 | P15: =COUNTIFS(Connect!C$4:C$1000,">="&DATE(2025,7,1),Connect!C$4:C$1000,"<="&DATE(2025,9+1,0)) -> 1 | Q15: =COUNTIFS(Connect!C$4:C$1000,">="&DATE(2025,10,1),Connect!C$4:C$1000,"<="&DATE(2025,12+1,0)) -> 0 | R15: =COUNTIFS(Connect!C$4:C$1000,">="&DATE(2026,1,1),Connect!C$4:C$1000,"<="&DATE(2026,3+1,0)) -> 0 | S15: =COUNTIFS(Connect!C$4:C$1000,">="&DATE(2026,4,1),Connect!C$4:C$1000,"<="&DATE(2026,6+1,0)) -> 0 | T15: =COUNTIFS(Connect!C$4:C$1000,">="&DATE(2026,7,1),Connect!C$4:C$1000,"<="&DATE(2026,9+1,0)) -> 0 | U15: =COUNTIFS(Connect!C$4:C$1000,">="&DATE(2026,10,1),Connect!C$4:C$1000,"<="&DATE(2026,12+1,0)) -> 0
A16: Oneov | B16: =COUNTIFS(Oneov!A$4:A$1000,">="&DATE(2022,1,1),Oneov!A$4:A$1000,"<="&DATE(2022,3+1,0)) -> 0 | C16: =COUNTIFS(Oneov!A$4:A$1000,">="&DATE(2022,4,1),Oneov!A$4:A$1000,"<="&DATE(2022,6+1,0)) -> 0 | D16: =COUNTIFS(Oneov!A$4:A$1000,">="&DATE(2022,7,1),Oneov!A$4:A$1000,"<="&DATE(2022,9+1,0)) -> 0 | E16: =COUNTIFS(Oneov!A$4:A$1000,">="&DATE(2022,10,1),Oneov!A$4:A$1000,"<="&DATE(2022,12+1,0)) -> 0 | F16: =COUNTIFS(Oneov!A$4:A$1000,">="&DATE(2023,1,1),Oneov!A$4:A$1000,"<="&DATE(2023,3+1,0)) -> 0 | G16: =COUNTIFS(Oneov!A$4:A$1000,">="&DATE(2023,4,1),Oneov!A$4:A$1000,"<="&DATE(2023,6+1,0)) -> 0 | H16: =COUNTIFS(Oneov!A$4:A$1000,">="&DATE(2023,7,1),Oneov!A$4:A$1000,"<="&DATE(2023,9+1,0)) -> 0 | I16: =COUNTIFS(Oneov!A$4:A$1000,">="&DATE(2023,10,1),Oneov!A$4:A$1000,"<="&DATE(2023,12+1,0)) -> 0 | J16: =COUNTIFS(Oneov!A$4:A$1000,">="&DATE(2024,1,1),Oneov!A$4:A$1000,"<="&DATE(2024,3+1,0)) -> 7 | K16: =COUNTIFS(Oneov!A$4:A$1000,">="&DATE(2024,4,1),Oneov!A$4:A$1000,"<="&DATE(2024,6+1,0)) -> 0 | L16: =COUNTIFS(Oneov!A$4:A$1000,">="&DATE(2024,7,1),Oneov!A$4:A$1000,"<="&DATE(2024,9+1,0)) -> 0 | M16: =COUNTIFS(Oneov!A$4:A$1000,">="&DATE(2024,10,1),Oneov!A$4:A$1000,"<="&DATE(2024,12+1,0)) -> 0 | N16: =COUNTIFS(Oneov!A$4:A$1000,">="&DATE(2025,1,1),Oneov!A$4:A$1000,"<="&DATE(2025,3+1,0)) -> 0 | O16: =COUNTIFS(Oneov!A$4:A$1000,">="&DATE(2025,4,1),Oneov!A$4:A$1000,"<="&DATE(2025,6+1,0)) -> 0 | P16: =COUNTIFS(Oneov!A$4:A$1000,">="&DATE(2025,7,1),Oneov!A$4:A$1000,"<="&DATE(2025,9+1,0)) -> 0 | Q16: =COUNTIFS(Oneov!A$4:A$1000,">="&DATE(2025,10,1),Oneov!A$4:A$1000,"<="&DATE(2025,12+1,0)) -> 0 | R16: =COUNTIFS(Oneov!A$4:A$1000,">="&DATE(2026,1,1),Oneov!A$4:A$1000,"<="&DATE(2026,3+1,0)) -> 0 | S16: =COUNTIFS(Oneov!A$4:A$1000,">="&DATE(2026,4,1),Oneov!A$4:A$1000,"<="&DATE(2026,6+1,0)) -> 0 | T16: =COUNTIFS(Oneov!A$4:A$1000,">="&DATE(2026,7,1),Oneov!A$4:A$1000,"<="&DATE(2026,9+1,0)) -> 0 | U16: =COUNTIFS(Oneov!A$4:A$1000,">="&DATE(2026,10,1),Oneov!A$4:A$1000,"<="&DATE(2026,12+1,0)) -> 0
A17: TOTAL | B17: =SUM(B13:B16) -> 0 | C17: =SUM(C13:C16) -> 0 | D17: =SUM(D13:D16) -> 1 | E17: =SUM(E13:E16) -> 0 | F17: =SUM(F13:F16) -> 0 | G17: =SUM(G13:G16) -> 4 | H17: =SUM(H13:H16) -> 2 | I17: =SUM(I13:I16) -> 4 | ... U17: =SUM(U13:U16) -> 8
A19: SYNTHÈSE ANNUELLE | B19: 2022 | C19: 2023 | D19: 2024 | E19: 2025 | F19: 2026
A20: Revenus (€) | B20: =SUM(B9:E9) -> 5000 | C20: =SUM(F9:I9) -> 13680 | D20: =SUM(J9:M9) -> 199923.39 | E20: =SUM(N9:Q9) -> 201409 | F20: =SUM(R9:U9) -> 112458
A21: Projets | B21: =SUM(B17:E17) -> 1 | C21: =SUM(F17:I17) -> 10 | D21: =SUM(J17:M17) -> 78 | E21: =SUM(N17:Q17) -> 75 | F21: =SUM(R17:U17) -> 37
A22: Rev. / Projet (€) | B22: =IFERROR(B20/B21,"—") -> 5000 | C22: =IFERROR(C20/C21,"—") -> 1368 | D22: =IFERROR(D20/D21,"—") -> 2563.1204 | E22: =IFERROR(E20/E21,"—") -> 2685.4533 | F22: =IFERROR(F20/F21,"—") -> 3039.4054
A24: Hypothèses
A25: Taux EUR/USD | B25: 1.15

Sheet All
A1: Project | E1: Details | R1: Banner creation (static) | S1: Banner adaptation (static) | T1: Banner creation (animated) | U1: Banner adaptation (animated) | V1: Branding pack | W1: Logo | X1: Lifestyle Picture | Y1: Wallpapers | Z1: Offline creation (standard) | AA1: Offline creation (adaptation) | AB1: Leaflet (1 page) | AC1: Leaflet (2 pages) | AD1: Roll-up / Wall creation | AE1: Chart | AF1: Brochure (20 pages) | AG1: Slide | AH1: Landing page (design only) | AI1: Landing page (complete) | AJ1: Website (design only) | AK1: Website (complete) | AL1: Video Edition | AM1: Video Subtitles | AN1: Social Media Video (up to 30s) | AO1: Social Media Video (up to 1 min) | AP1: Promotional Video (up to 1 min) | AQ1: 2D Video (up to 3mn) | AR1: 3D Video (up to 3min) | AS1: Virtual space | AT1: Virtual showroom | AU1: Translation (per word) | AV1: Copywrite (per word)
A2: Customer | B2: Division | C2: Date | D2: Project | E2: Contact | F2: Status | G2: Category | H2: Link | I2: Assets | J2: Total Value | K2: Quote | L2: PO | M2: Invoice | N2: N° invoice | O2: Status2 | P2: Echéance | Q2: Colonne3 | R2: 135 | S2: 30 | T2: 220 | U2: 50 | V2: 2000 | W2: 250 | X2: 400 | Y2: 85 | Z2: 135 | AA2: 30 | AB2: 180 | AC2: 260 | AD2: 180 | AE2: 400 | AF2: 2200 | AG2: 40 | AH2: 300 | AI2: 700 | AJ2: 5000 | AK2: 7000 | AL2: 80 | AM2: 150 | AN2: 260 | AO2: 560 | AP2: 4000 | AQ2: 5000 | AR2: 10000 | AS2: 2500 | AT2: 10000 | AU2: 0.1 | AV2: 0.25
A3: Son-video.com | B3: - | C3: 44743 | D3: Virtual Showroom | E3: Hugo Lahutte | F3: Delivered | G3: France | H3: - | I3: =IF(SUM(R3:AV3)=0,"-",SUM(R3:AV3)) -> 2 | J3: =IF(SUMPRODUCT($R$2:$AV$2,R3:AV3)=0,"-",SUMPRODUCT($R$2:$AV$2,R3:AV3)) -> 5000 | K3: 45084 | L3: - | M3: Sent | N3: F2023-0523 | O3: Payé le 11/08/2023 | AS3: 2
A4: La Maison des Bienheureux | B4: - | C4: 45083 | D4: New website | E4: Romain Petit | F4: Delivered | G4: France | H4: https://b2b.sarani.studio | I4: 1 | J4: =IF(SUMPRODUCT($R$2:$AV$2,R4:AV4)=0,"-",SUMPRODUCT($R$2:$AV$2,R4:AV4)) -> 4000 | K4: 45084 | L4: - | M4: Sent | N4: F2024-0045 | O4: Payé le 29/05/2024 | AK4: =4000/7000 -> 0.57142857
A5: Pippacorner | B5: - | C5: 45083 | D5: Pippacorner Branding | E5: Stéphane Rambaud | F5: Delivered | G5: France | H5: https://saranistudio.sharepoint.com/:f:/s/SaraniAssets/EnbyF5acw11EjdYGvMP5nx0B0d70LzvZ1gHbTGcqlFjbGA?e=zcD1fD | I5: =IF(SUM(R5:AV5)=0,"-",SUM(R5:AV5)) -> 4.376 | J5: 2000 | K5: 45084 | L5: - | M5: Sent | N5: F2023-0515 | O5: Payé le 28/07/2023 | V5: 1 | AJ5: =1500/AJ2 -> 0.3 | AO5: 2 | AQ5: =5380/AQ2 -> 1.076
A6: Pippacorner | B6: - | C6: 45083 | D6: Pippacorner Website Design | E6: Stéphane Rambaud | F6: Delivered | G6: France | H6: https://saranistudio.sharepoint.com/:f:/s/SaraniAssets/ErmhsGB8kgRAuBYr4yIhwroBiQEACi2aakOTS93vHVWT1A?e=Xu2JTN | I6: 1 | J6: 1800 | L6: - | M6: Sent | N6: F2023-0514 | O6: Payée le 26/09/2023 | V6: 1 | AJ6: =1500/AJ4 -> #DIV/0! | AO6: 2 | AQ6: =5380/AQ4 -> #DIV/0!
A7: Pippacorner | B7: - | C7: 45083 | D7: Pippacorner Catalogue | E7: Stéphane Rambaud | F7: Delivered | G7: France | H7: https://saranistudio.sharepoint.com/:f:/s/SaraniAssets/EmRcIT6D4cxGl8o_DjWi9wcB_aDUY7-whHxFK_E3rlYFFw?e=aG6faZ | I7: 1 | J7: 850 | L7: - | M7: Sent | N7: F2023-0513 | O7: Payée le 26/092023
A8: Pippacorner | B8: - | C8: 45184 | D8: Pippacorner maquettes | E8: Stéphane Rambaud | F8: Delivered | G8: France | H8: https://saranistudio.sharepoint.com/:f:/s/SaraniAssets/ErmhsGB8kgRAuBYr4yIhwroBiQEACi2aakOTS93vHVWT1A?e=Xu2JTN | I8: 10 | J8: 1500 | M8: Sent | N8: F2023-0512 | O8: Payée le 07/11/2032
A9: Pippacorner | B9: - | C9: 45185 | D9: Pippacorner Flyer | E9: Stéphane Rambaud | F9: Delivered | G9: France | H9: https://saranistudio.sharepoint.com/:f:/s/SaraniAssets/EkTN4p5LGHFGhELydt5HB-oB0aFtmnCCp7LOSYR9hymHGw?e=QPJaAL | I9: 1 | J9: 450 | M9: Sent | N9: F2023-0511 | O9: Payée le 07/11/2023
A10: Pernod-Ricard | C10: 45211 | D10: Perrier-Jouet - CP - Menu d'hiver | E10: Laura Marie through Marie Caroline Selmer | F10: Delivered | G10: France | H10: https://saranistudio.sharepoint.com/sites/SaraniAssets/Shared%20Documents/Forms/AllItems.aspx?ga=1&id=%2Fsites%2FSaraniAssets%2FShared%20Documents%2F03%2E%20Customers%2F09%2E%20Pernod%20Ricard%2F01%2E%20Press%20Release&viewid=2c2e4824%2D3cb1%2D4619%2Db7c6%2D219dce795204 | I10: 1 | J10: 40 | M10: Sent | N10: F2024-0038 | O10: Payé
A11: Pippacorner | B11: - | C11: 45214 | D11: Pippacorner Final website assets | E11: Stéphane Rambaud | F11: Delivered | G11: France | H11: https://saranistudio.sharepoint.com/:f:/s/SaraniAssets/ElcfhiK7aLhJhiN2ZjA7EwYB_oX3cVCbpCW7693MDQnjtA?e=wHOvMb | I11: 5 | J11: 250 | M11: Sent | N11: F2023-0236 | O11: Payée le 7/11/2023
A12: Pernod-Ricard | C12: 45274 | D12: Château Sainte Marguerite - CP | E12: Laura Marie through Marie Caroline Selmer | F12: Delivered | G12: France | H12: https://saranistudio.sharepoint.com/sites/SaraniAssets/Shared%20Documents/Forms/AllItems.aspx?ga=1&id=%2Fsites%2FSaraniAssets%2FShared%20Documents%2F03%2E%20Customers%2F09%2E%20Pernod%20Ricard%2F01%2E%20Press%20Release&viewid=2c2e4824%2D3cb1%2D4619%2Db7c6%2D219dce795204 | I12: 1 | J12: 40 | M12: Sent | N12: F2024-0039 | O12: Payé
A13: Pomme de Pin | C13: 45290 | D13: Site web 50% | F13: Delivered | G13: France | H13: https://saranistudio.sharepoint.com/:f:/s/SaraniAssets/EpLFm-Ryfg5LirKpuYZqX6IBW6BRaDZWa7vLEWJstShnIg?e=XkPfBa | I13: =IF(SUM(R13:AV13)=0,"-",SUM(R13:AV13)) -> - | J13: 2750 | M13: Sent | N13: F2024-0029 | O13: Payé le 30/01/2024
A14: PADOC | C14: 45292 | D14: Identité graphique | F14: Delivered | G14: France | H14: https://saranistudio.sharepoint.com/:f:/s/SaraniAssets/EtLDGZ7rZQRCnBF0YE1t2a4B2RhNm2OEYoiy6eidCd4hAw?e=JRicjA | I14: 1 | J14: 600 | K14: - | L14: - | M14: Sent | N14: F2024-0216 | O14: Payé le 17/06/2024
A15: Tour & taxi | C15: 45314 | D15: Création originale – Visuel pour impression | E15: Soraya Nouiyer | F15: Delivered | G15: France | H15: - | I15: =IF(SUM(R15:AV15)=0,"-",SUM(R15:AV15)) -> - | J15: 135 | K15: 23/01/2024 | L15: - | M15: Sent | N15: F2024-0064 | O15: Payé le 05/06/2024
A16: Tour & taxi | C16: 45314 | D16: Création originale – Visuel pour publication | E16: Soraya Nouiyer | F16: Delivered | G16: France | H16: - | I16: =IF(SUM(R16:AV16)=0,"-",SUM(R16:AV16)) -> - | J16: 135 | K16: 23/01/2024 | L16: - | M16: - | N16: - | O16: - | P16: -
A17: Dragon Rouge | C17: 45331 | D17: Vidéo roullier - V2 | E17: Cécile Mercadier | F17: Delivered | G17: France | H17: 20240902_Vidéo roullier-V2 | I17: 1 | J17: =150*5 -> 750 | L17: P022318 | M17: Sent to Thomas | N17: F2024-0508 | O17: Payée le 16/01/2025
A18: Eqiom | C18: 45331 | D18: Création originale – Visuel pour impression | E18: Cédric Lechoux, Marine Savary | F18: Delivered | G18: France | H18: - | I18: =IF(SUM(R18:AV18)=0,"-",SUM(R18:AV18)) -> - | J18: 180 | L18: - | M18: Sent | N18: F2024-0091 | O18: Payée le 26/07/2024
A19: GIE | C19: 45331 | D19: Flyers x 500 units 300g print | E19: Gabrielle Lelievre | F19: Delivered | G19: Belgium | H19: - | I19: 1 | J19: 550 | L19: - | M19: Sent | N19: F2024-0419 | O19: Payé le 05/09/2024
A20: France Chimie | C20: 45343 | D20: Kakémono (Design + Impression) + Vignettes | E20: Aurélia | F20: Delivered | G20: France | H20: - | J20: 490 | K20: - | L20: - | M20: sent | N20: F2024-0214 | O20: Payé le 10/06/2024
A21: Pernod-Ricard | C21: 45400 | D21: Facture 2024-11 (CP n°1 de PJ) | E21: Laura Marie through Marie Caroline Selmer | F21: Delivered | G21: France | H21: - | I21: 1 | J21: 40 | M21: Sent | N21: F2024-0169 | O21: Payé
A22: Pernod-Ricard | C22: 45400 | D22: Facture 2024-20 (CP n°5 de SMEP) | E22: Laura Marie through Marie Caroline Selmer | F22: Delivered | G22: France | H22: - | I22: 1 | J22: 40 | M22: Sent | N22: F2024-0170 | O22: Payé | AG22: 14
A23: Eqiom | C23: 45405 | D23: Livret d'accueil A4 Alternants | E23: Cédric Lechoux, Marine Savary | F23: Delivered | G23: France | H23: https://saranistudio.sharepoint.com/:f:/s/SaraniAssets/Eqwntg4GF4xHs_lcP9At1-0BUwZloYyi4fg05MClpbZ17w?e=DtySqI | I23: =IF(SUM(R23:AV23)=0,"-",SUM(R23:AV23)) -> - | J23: =IF(SUMPRODUCT($R$2:$AV$2,R23:AV23)=0,"-",SUMPRODUCT($R$2:$AV$2,R23:AV23)) -> - | M23: Sent | N23: F2024-0187 | O23: Payée le 10/01/2025
A24: Pernod-Ricard | C24: 45405 | D24: Facture 2024-13 (CP n°4 de SMEP) Perrier-Jouët | E24: Laura Marie through Marie Caroline Selmer | F24: Delivered | G24: France | H24: - | I24: 1 | J24: 40 | M24: Sent | N24: F2024-0195 | O24: Payé le 29/05/2024
A25: Pippacorner | C25: 45405 | D25: Pippacorner website improvements | E25: Stéphane Rambaud | F25: Delivered | G25: France | H25: - | I25: 1 | J25: 500 | M25: Sent | N25: F2024-0186 | O25: Payée le 27/05/2024
A26: SpaceProjects | C26: 45405 | D26: Pack Présentations | E26: Hassib Mounzer | F26: Delivered | G26: France | H26: - | I26: 3 | J26: 1500 | K26: - | L26: - | M26: Sent via Whatsapp | N26: F2024-0679 | O26: Payée le 17/12/2024
A27: SpaceProjects | C27: 45405 | D27: Site Web | E27: Hassib Mounzer | F27: In progress | G27: France | H27: - | I27: 1 | J27: 3000
A28: Air Corsica | C28: 45413 | D28: Influencers campaign | E28: Jean-Paul | F28: Delivered | G28: France | H28: - | J28: 500 | K28: - | L28: - | M28: - | N28: - | O28: - | P28: - | Q28: - | AD28: 9
A29: Eqiom | B29: 45405 | C29: 45415 | D29: Création Panneaux - EQIOM A1 | F29: Delivered | G29: France | H29: 20240509_Création Panneaux - EQIOM | I29: 9 | J29: =220*9 -> 1980 | K29: - | L29: C000150109 | M29: Sent | N29: F2024-0428 | O29: Payée le 25/10/2024
A30: France Chimie | C30: 45415 | D30: Kakémono classique + Tendu (Design + Impression) | E30: Clayton / Juliette | F30: Delivered | G30: France | H30: - | J30: 891 | K30: - | L30: - | M30: sent | N30: F2024-0215 | O30: Payé le 10/06/2024
A31: GIE | C31: 45444 | D31: Service proposal: GIE Munich Conference assets v2 | E31: Gabrielle Lelievre | F31: Delivered | G31: Belgium | H31: - | I31: 15 | J31: 1080 | L31: - | M31: Sent | N31: F2024-0389 | O31: Payée le 04/09/2024
A32: Aventim - Howel | C32: 45453 | D32: AXONOGRAPHIE | E32: Clément Robillard - crobillard@aventim.com | F32: Delivered | G32: France | H32: - | I32: 1 | J32: 950 | K32: - | L32: - | M32: Sent | N32: F2024-0361 | O32: Payée le 16/10/2024
A33: Air Corsica | C33: 45454 | D33: Campagne Italie Belgique | E33: Jean-Franois Colonna | F33: Delivered | G33: France | H33: - | J33: 30500 | L33: CDF00019891 | M33: Sent | N33: F2024-0282 | O33: Payé le 26/07/2024
A34: Pomme de Pin | C34: 45458 | D34: PLAN + MENU + PLANNING JUILLET AOUT + SIGNATURES | E34: Julien Bauchart | F34: Delivered | G34: France | H34: - | J34: 900 | K34: Offrir cette prestation afin de compenser les problèmes de livraison du site web Pomme de Pin. Possible de réaliser une facture de 900€ avec remise de 900€ pour que le client se rende compte du geste commercial effectué? | M34: Sent | N34: F2024-0352 | O34: Facture à 0€, pas de paiement attendu
A35: Pomme de Pin | C35: 45463 | D35: Shooting Photos | E35: Julien Bauchart | F35: Delivered | G35: France | H35: - | J35: 450 | M35: Sent | N35: F2024-0414 | O35: Payée le 04/09/2024
A36: Dialogue | C36: 45477 | D36: Campagne Influence Dialogues 2410067 | E36: Charlotte | F36: Delivered | G36: France | H36: - | I36: 1 | J36: 12500 | L36: 2410067 | M36: Sent | N36: F2024-0636 | O36: Payée le 16/12/2024
A37: Dialogue | C37: 45477 | D37: Campagne Influence Dialogues 2410066 | E37: Charlotte | F37: Delivered | G37: France | H37: - | I37: 1 | J37: 7500 | L37: 2410066 | M37: Sent | N37: F2024-0635 | O37: Payée le 16/12/2024
A38: Pernod-Ricard | C38: 45483 | D38: SMEP corporate (CP6) | E38: Laura Marie through Marie Caroline Selmer | F38: Delivered | G38: France | H38: - | I38: 1 | J38: 40 | M38: Sent | N38: F2024-0327 | O38: Payé le 22/07/2024
A39: Pernod-Ricard | C39: 45483 | D39: PERRIER-JOUET CP 7 - Réouverture Cellier | E39: Laura Marie through Marie Caroline Selmer | F39: Delivered | G39: France | H39: - | I39: 1 | J39: 40 | M39: Sent | N39: F2024-0328 | O39: Payé le 22/07/2024
A40: Quentin Carnaille | C40: 45488 | D40: STATUE - C. DE GAULLE | E40: Quentin Carnaille quentincarnaille@gmail.com | F40: Delivered | G40: France | H40: https://saranistudio.sharepoint.com/sites/SaraniAssets/Shared%20Documents/Forms/AllItems.aspx?ga=1&id=%2Fsites%2FSaraniAssets%2FShared%20Documents%2F03%2E%20Customers%2F01%2E%20Single%20Projects%2FQuentin%20Carnaille&viewid=2c2e4824%2D3cb1%2D4619%2Db7c6%2D219dce795204 | I40: 1 | J40: 3500€ | K40: - | L40: - | M40: Sent | N40: F2024-0489 | O40: Payé 13/11/2024
A41: Velux | C41: 45498 | D41: DESIRE September burst - assets digitaux | E41: Pamela Ankrah | F41: Delivered | G41: France | H41: https://saranistudio.sharepoint.com/:f:/s/SaraniAssets/EoNIo5JGichNm6_RXrv8dEQBilHwAUZF81WudIE4jMTUlQ?e=h5OWme | I41: 16 | J41: =35*16 -> 560 | M41: Sent | N41: F2024-0362 | O41: Payée le 09/09/2024 | S41: 16
A42: GIE | C42: 45503 | D42: Internal project 2 pagers | E42: Gabrielle Lelievre | F42: Delivered | G42: France | H42: https://saranistudio.sharepoint.com/:f:/s/SaraniAssets/EiKHBnr1-t1CkBJ2177ZVvsBaPQVNA_ojPNwV7zWuLyKkg?e=joXBaP | I42: 1 | J42: 180 | L42: - | M42: Sent | N42: F2024-0390 | O42: Payée le 04/09/2024
A43: ESPI | C43: 45504 | D43: Refonte site web | E43: Sophie Bollack - s.bollack@groupe-espi.fr | F43: In progress | G43: France | H43: - | I43: 1 | J43: 34000 | K43: Facturation multiple | L43: - | M43: - | N43: - | O43: - | P43: - | Q43: -
A44: ESPI | C44: 45504 | D44: Refonte site web | J44: 6800 | K44: Acompte N°1 de 20% .Notre compte client a bien été créé chez le client ESPI. Prestataire Sébastien Gras 12000€HT | L44: - | M44: Acompte 20% sent | N44: F2024-0407 | O44: Payée le 30/09/2024
A45: ESPI | C45: 45504 | D45: Refonte site web | J45: 13750 | K45: Acompte N°2. Montant : € | L45: BdC6748 | M45: Sent | N45: F2025-0350 | O45: En attente de paiement | P45: 19/07/2025
A46: ESPI | C46: 45504 | D46: Refonte site web | J46: =J43-J44-J45 -> 13450 | K46: Solde | L46: BdC5409
A47: ESPI | C47: 45504 | D47: MotionDesign | E47: Sophie Bollack - s.bollack@groupe-espi.fr | F47: In progress | G47: France | H47: - | I47: 1 | J47: 5000 | K47: Pas initié pour le moment | L47: BdC5409
A48: ESPI | C48: 45504 | D48: Acompte 20% Shooting photo / Vidéo | E48: Sophie Bollack - s.bollack@groupe-espi.fr | F48: Delivered | G48: France | H48: - | I48: 1 | J48: 3336 | K48: Acompte de 20% à facturer.Prestataire: Sébastien Gras (13344€HT, acompte de 3336€HT) | L48: - | M48: Acompte 20% sent | N48: F2024-0408 | O48: Payée le 30/09/2024
A49: ESPI | C49: 45504 | D49: Facture de solde: Shooting photo / Vidéo | E49: Sophie Bollack - s.bollack@groupe-espi.fr | F49: Delivered | G49: France | H49: - | I49: 1 | J49: 13344 | K49: Facture de Solde | L49: BdC6335 | M49: Sent | N49: F2025-0112 | O49: Payée le 18/03/2025
A50: ESPI | C50: 45504 | D50: Site web temporaire | E50: Sophie Bollack - s.bollack@groupe-espi.fr | F50: Delivered | G50: France | H50: - | I50: 1 | J50: 8000 | K50: Acompte de 20% à facturer. Prestataire: Sébastien Gras (4000€HT, acompte de 2000€HT à régler) | L50: BdC5411 | M50: Envoyée 03/09/2024 | N50: F2024-0406 | O50: Payée le 30/09/2024
A51: Pomme de Pin | C51: 45504 | D51: Site web 50% restants | E51: Julien Bauchart | F51: Delivered | G51: France | H51: https://saranistudio.sharepoint.com/:f:/s/SaraniAssets/EpLFm-Ryfg5LirKpuYZqX6IBW6BRaDZWa7vLEWJstShnIg?e=XkPfBa | I51: =IF(SUM(R51:AV51)=0,"-",SUM(R51:AV51)) -> - | J51: 2750 | M51: Sent | N51: F2024-0413 | O51: Payée le 04/09/2024
A52: GIE | C52: 45508 | D52: Munich Notebook design | E52: Mayra Pena | F52: Delivered | G52: France | H52: https://saranistudio.sharepoint.com/:f:/s/SaraniAssets/EiKHBnr1-t1CkBJ2177ZVvsBaPQVNA_ojPNwV7zWuLyKkg?e=Vg5xgJ | I52: 1 | J52: 135 | L52: - | M52: Sent | N52: F2024-0391 | O52: Payée le 04/09/2024
A53: Pernod-Ricard | C53: 45513 | D53: CP n°9 - PJ au Jardin Secret du Peninsula | E53: Laura Marie through Marie Caroline Selmer | F53: Delivered | G53: France | H53: - | I53: 1 | J53: 40 | M53: Sent | N53: F2024-0363 | O53: Payé le 04/09/2024
A54: Cicatrix | C54: 45532 | D54: Campagne influence | E54: Vanessa Fernandez | F54: Delivered | G54: France | H54: - | I54: 1 | J54: 2500 | K54: - | L54: - | M54: Sent to Thomas via Whatsapp | N54: F2024-0640 | O54: Payé le 30/12/2024
A55: Dragon Rouge | C55: 45532 | D55: Vidéo roullier - Adaptation verticale | E55: Cécile Mercadier | F55: Delivered | G55: France | H55: 20240828_Vidéo roullier_Adaptation verticale | I55: 1 | J55: 150 | L55: P022318 | M55: Sent to Thomas | N55: F2024-0508 | O55: Payée le 16/01/2025
A56: Dragon Rouge | C56: 45537 | D56: Vidéo roullier - V2 - Anglais | E56: Cécile Mercadier | F56: Delivered | G56: France | H56: 20240902_Vidéo roullier-V2 | I56: 1 | J56: 150 | L56: P022318 | M56: Sent to Thomas | N56: F2024-0508 | O56: Payée le 16/02/2025 | AG56: 43
A57: GIE | C57: 45538 | D57: GIE Speakers notes | E57: Francesco Gabrielli | F57: Delivered | G57: France | H57: Speaker notes | I57: 43 | J57: =30*I57 -> 1290 | K57: - | L57: - | M57: Sent | N57: F2024-0563 | O57: Payée le 26/11/2024
A58: GIE | C58: 45539 | D58: Kind request animated banner | E58: Gabrielle Lelievre | F58: Delivered | G58: Belgium | H58: 20240904_Kind request animated banner | I58: - | J58: 250 | L58: - | M58: Sent to Thomas | N58: F2024-0471 | O58: Payé le 27/09/2024
A59: GIE | C59: 45539 | D59: GIE AC 2024 | Badges design briefing | E59: Malika Khalidi | F59: Delivered | G59: Belgium | H59: 20240904_GIE AC 2024_Badges design briefing | I59: - | J59: 250 | L59: - | M59: Sent to Thomas | N59: F2024-0472 | O59: Payé le 27/09/2024
A60: Pernod-Ricard | C60: 45541 | D60: CP n°10 - SMEP x Byblos Beach | E60: Laura Marie through Marie Caroline Selmer | F60: Delivered | G60: France | H60: - | I60: 1 | J60: 40 | M60: Sent | N60: F2024-0426 | O60: Payé
A61: GIE | C61: 45548 | D61: GIE Strategic Storyline | E61: Tobias | F61: Delivered | G61: Belgium | H61: https://saranistudio.sharepoint.com/:f:/s/SaraniAssets/EuPIBC8QCwxKojTQkcK2azEBU99lZ2dbLp_H2hlcoMODlQ?e=nbpDqx | I61: 1 | J61: =18*40 -> 720 | L61: - | M61: Sent to Thomas | N61: F2024-0473 | O61: Payé le 27/09/2024 | AG61: 18
A62: Air Corsica | C62: 45552 | D62: Emailing Ouverture Réservations 2025 | E62: Mélanie Tolédano | F62: Delivered | G62: France | I62: 1 | J62: 450 | K62: - | L62: - | M62: Sent | N62: F2024-0562 | O62: Payée le 27/12/2024
A63: Air Corsica | C63: 45552 | D63: Emailing Black Friday | E63: Mélanie Tolédano | F63: Delivered | G63: France | H63: https://saranistudio.sharepoint.com/:f:/s/SaraniAssets/EohyeXpT9tNJkqHXbxykHC8BQoRf3Zf1kZ3UMprn3fHnXw?e=fXzyGP | I63: 1 | J63: 450 | M63: Sent | N63: F2024-0684 | O63: Payée le 27/12/2024
A64: Pernod-Ricard | C64: 45552 | D64: CP n°8 PR - RSVR MUMM | E64: Laura Marie through Marie Caroline Selmer | F64: Delivered | G64: France | H64: - | I64: 1 | J64: 40 | M64: Sent | N64: F2024-0446 | O64: Payée le 30/09/2024 | S64: 8
A65: GIE | C65: 45562 | D65: GIE AC banners | E65: Mayra Pena | F65: Delivered | G65: Belgium | H65: 20240927_GIE AC banners | I65: 8 | J65: =8*30 -> 240 | M65: Sent | N65: F2024-0564 | O65: Payée le 26/11/2024
A66: GIE | C66: 45573 | D66: GIE AC 2024 - Farewell Videos | E66: Malika Khalidi | F66: Delivered | G66: Belgium | H66: https://saranistudio.sharepoint.com/:f:/s/SaraniAssets/ErbThV3AGv1CsZvziFM8Bl8BlpFAdpVNHAykNs8SfpdTwg?e=CKOR5u | I66: 2 | J66: 700 | M66: Sent | N66: F2024-0565 | O66: Payée le 26/11/2024 | S66: 20
A67: Pernod-Ricard | C67: 45580 | D67: CP n°13 SMEP actualisation Taste of Provence | E67: Laura Marie through Marie Caroline Selmer | F67: Delivered | G67: France | H67: - | I67: 1 | J67: 40 | M67: Sent | N67: F2024-0521 | O67: Payé | AG67: 17
A68: Pernod-Ricard | C68: 45580 | D68: CP n°12 PJ FR-EN Traduction | E68: Laura Marie through Marie Caroline Selmer | F68: Delivered | G68: France | H68: - | I68: 1 | J68: 60 | M68: Sent | N68: F2024-0523 | O68: Payé
A69: Pernod-Ricard | C69: 45580 | D69: CP n°11- PJ Menu d'été | E69: Laura Marie through Marie Caroline Selmer | F69: Delivered | G69: France | H69: - | I69: 1 | J69: 40 | M69: Sent | N69: F2024-0524 | O69: Payé
A70: ESPI | C70: 45606 | D70: Traduction web | E70: Sophie Bollack - s.bollack@groupe-espi.fr | F70: Delivered | G70: France | H70: - | I70: 1 | J70: 1600 | K70: 700€ à régler au prestataire Sébastien Gras. Facture à recevoir. | L70: BdC5765 | M70: Envoyée le 11/12/2024 | N70: F2024-0681 | O70: Payée le 31/01/2025
A71: Pernod-Ricard | C71: 45618 | D71: CP n°14- Dinner in the sky | E71: Laura Marie through Marie Caroline Selmer | F71: Delivered | G71: France | H71: - | I71: 1 | J71: 40 | M71: Sent | N71: F2024-0622 | O71: Payé le 28/11/2024
A72: Air Corsica | C72: 45628 | D72: Air Corsica Email soldes | E72: Mélanie Tolédano | F72: Delivered | G72: France | H72: https://saranistudio.sharepoint.com/:f:/s/SaraniAssets/EoYgzzkVsL1FkM-EyORt1s8BrQ211V90DMBMiNgXpK74Bg?e=u62Pry | I72: 1 | J72: =450+260 -> 710 | M72: Sent | N72: F2025-0032 | O72: Payée 26/02/2025
A73: Dialogue | C73: 45630 | D73: Droits d'Images Laulevy | E73: Charlotte | F73: Delivered | G73: France | H73: - | I73: 1 | J73: 300 | K73: - | L73: 2412020 | M73: Sent | N73: F2024-0675 | O73: Payée le 10/01/2025 | AN73: 1
A74: GIE | C74: 45660 | D74: GIE | SoS Workshop | Create a Banner & Speaker Cards | E74: Mahtab Jalali Moghaddam | F74: Delivered | G74: Belgium | H74: GIE - SoS Workshop - Create a Banner & Speaker Cards | I74: 4 | J74: 435 | M74: Sent | N74: F2025-0033 | O74: Payée le 24/02/2025 | R74: 3 | S74: 1
A75: GIE | C75: 45670 | D75: GIE | SoS Workshop | Speaker Cards | E75: Mahtab Jalali Moghaddam | F75: Delivered | G75: Belgium | H75: GIE - SoS Workshop - Create a Banner & Speaker Cards | I75: 12 | J75: 360 | M75: Sent | N75: F2025-0034 | O75: Payée le 24/02/2025 | AA75: 12
A76: Air Corsica | C76: 45674 | D76: Brief Ouverture de Ligne Nice -> Florence -> Nice | E76: Mélanie Tolédano | F76: Delivered | G76: France | H76: 20250117_Brief Ouverture de Ligne Nice - Florence - Nice | I76: - | J76: 2850 | M76: Sent | N76: F2025-0102 | O76: Payée le 30/06/2025 | R76: 2 | S76: 3 | T76: 1
A77: GIE | C77: 45674 | D77: GIE - Annual Conference 2025 | Kick-off | E77: Malika Khalidi | F77: Delivered | G77: Belgium | H77: 20250117_GIE Annual Conference 2025 - Kick-off | I77: 6 | J77: =IF(SUMPRODUCT($R$2:$AV$2,R77:AV77)=0,"-",SUMPRODUCT($R$2:$AV$2,R77:AV77)) -> - | K77: - | L77: - | M77: Sent to Thomas | N77: F2025-0253 | O77: Payée le 14/05/2025
A78: Hirondo | C78: 45680 | D78: Case studies videos | E78: Yannig | F78: Delivered | G78: France | H78: https://saranistudio.sharepoint.com/:f:/s/SaraniAssets/Ehc8_JcD7K9Lr__dI4C6ebwB1zaV9l9WO3KTicPNFSi4mA?e=yALMH1 | I78: 2 | J78: 2800 | M78: Sent via Whatsapp | N78: F2025-0160 | O78: Payée le 08/04/2025
A79: GIE | C79: 45688 | D79: GIE | SoS Workshop | extra Speaker Cards | E79: Mahtab Jalali Moghaddam | F79: Delivered | G79: France | H79: GIE - SoS Workshop - Create a Banner & Speaker Cards | I79: 1 | J79: 30 | K79: - | L79: - | M79: Sent to Thomas | N79: F2025-0253 | O79: Payée le 14/05/2025 | AA79: 1
A80: GIE | C80: 45688 | D80: GIE | SoS Workshop slide | E80: Mahtab Jalali Moghaddam | F80: Delivered | G80: France | H80: 20250131_GIE SoS Workshop slide | I80: 1 | J80: 220 | K80: - | L80: - | M80: Sent to Thomas | N80: F2025-0253 | O80: Payée le 14/05/2025 | T80: 1
A81: GIE | C81: 45709 | D81: GIE | SoS Workshop | Mailing Header+ GIF and social | E81: Mahtab Jalali Moghaddam | F81: Delivered | G81: Belgium | H81: 20250117_GIE Annual Conference 2025 - Kick-off | I81: 4 | J81: 215 | K81: - | L81: - | M81: Sent to Thomas | N81: F2025-0253 | O81: Payée le 14/05/2025 | R81: 1 | S81: 2 | U81: 1
A82: GIE | C82: 45719 | D82: GIEAC | Personalized Notebooks + speaker cards | E82: Mahtab Jalali Moghaddam | F82: Delivered | G82: Belgium | I82: 3 | J82: =IF(SUMPRODUCT($R$2:$AV$2,R82:AV82)=0,"-",SUMPRODUCT($R$2:$AV$2,R82:AV82)) -> 405 | K82: - | L82: - | M82: Sent to Thomas | N82: F2025-0253 | O82: Payée le 14/05/2025 | R82: 1 | Z82: 2
A83: Pernod-Ricard | C83: 45722 | D83: CP n°17 Château Sainte Marguerite Cuvées 2024 | E83: Laura Marie through Marie Caroline Selmer | F83: Delivered | G83: France | H83: - | I83: 1 | J83: 40 | M83: Sent | N83: F2025-0083 | O83: Payée le 10/03/2025
A84: Pernod-Ricard | C84: 45722 | D84: CP 20 - Printemps Belle Epoque PJ | E84: Laura Marie through Marie Caroline Selmer | F84: Delivered | G84: France | H84: - | I84: 1 | J84: 40 | M84: Sent | N84: F2025-0333 | O84: Payée le 19/06/2025 | R84: 2 | S84: 2
A85: GIE | C85: 45723 | D85: GIE | Visuals for Biomethane Study Launch | 30 April | E85: Mahtab Jalali Moghaddam | F85: Delivered | G85: Belgium | H85: GIE - Visuals for Biomethane Study Launch - 30 April | I85: 3 | J85: =IF(SUMPRODUCT($R$2:$AV$2,R85:AV85)=0,"-",SUMPRODUCT($R$2:$AV$2,R85:AV85)) -> - | K85: - | L85: - | M85: Sent to Thomas | N85: F2025-0253 | O85: Payée le 14/05/2025
A86: Pomme de Pin | C86: 45728 | D86: Abonnement annuel - Maintenance / Tracking / SEO | E86: Julien Bauchart | F86: Delivered | G86: France | J86: 2300 | K86: 1400€ Reglé par échéancier à SG | M86: Sent | N86: F2025-0222 | O86: Payée le 06/06/2025
A87: Paradox | C87: 45730 | D87: Campagne des Money Days | E87: Farah Rouassi | F87: Delivered | G87: France | H87: https://saranistudio.sharepoint.com/:f:/s/SaraniAssets/EpTwgabtzGJBvE1QvzC9JVgBLcfZppAhj82LlolZKx4ZIw?e=bEEke8 | I87: 3 | J87: 850 | K87: - | L87: - | M87: Sent via Whatsapp | N87: F2025-0161 | O87: Payée le 12/04/2025 | AM87: 2 | AN87: 1
A88: Air Corsica | C88: 45736 | D88: AIR CORSICA - Brief Opération Destination Corse Mars/Avril | E88: Mélanie Tolédano | F88: Delivered | G88: France | H88: 20250320_Brief Opération Destination Corse Mars-Avril | I88: 3 | J88: =260+150*2 -> 560 | M88: Sent | N88: F2025-0275 | O88: Payée le 30/06/2025
A89: GIE | C89: 45757 | D89: GIEAC | Speaker cards | E89: Mahtab Jalali Moghaddam | F89: Delivered | G89: Belgium | H89: 20250303_GIEAC Personalized Notebooks | I89: 54 | J89: =IF(SUMPRODUCT($R$2:$AV$2,R89:AV89)=0,"-",SUMPRODUCT($R$2:$AV$2,R89:AV89)) -> 1080 | K89: - | L89: - | M89: Sent to Thomas | N89: F2025-0253 | O89: Payée le 14/05/2025 | S89: =54/1.5 -> 36
A90: Air Corsica | C90: 45761 | D90: Florence new email | E90: Mélanie Tolédano | F90: Delivered | G90: France | H90: https://saranistudio.sharepoint.com/:f:/s/SaraniAssets/Evu3AwE3YHpBreauZ0Kej2QB9GcsjLq_eoDkRPLfA6q3wQ?e=c3mMLw | J90: 350 | M90: Sent | N90: F2025-0275 | O90: Payée le 30/06/2025
A91: GIE | C91: 45762 | D91: GIE AC | 2 new banner format | E91: Mahtab Jalali Moghaddam | F91: Delivered | G91: Belgium | H91: 20250415_GIE AC - 2 new banner format | I91: 2 | J91: =IF(SUMPRODUCT($R$2:$AV$2,R91:AV91)=0,"-",SUMPRODUCT($R$2:$AV$2,R91:AV91)) -> 80 | K91: - | L91: - | M91: Sent to Thomas | N91: F2025-0253 | O91: Payée le 14/05/2025 | S91: 1 | U91: 1
A92: Pomme de Pin | C92: 45770 | D92: Au Pin Gourmet - Branding / Web | E92: Julien Bauchart | F92: Delivered | G92: France | J92: 5000 | M92: Sent | N92: F2025-0269 | O92: Payée le 06/06/2025
A93: Air Corsica | C93: 45774 | D93: Air Corsica New campaign assets | E93: Mélanie Tolédano | F93: Delivered | G93: France | I93: 3 | J93: 1500 | M93: Sent | N93: F2025-0275 | O93: Payée le 30/06/2025
A94: Adrien VanBeveren (Sandstorm SLU) | C94: 45782 | D94: Assistant permanent may | E94: teamvbacontact@gmail.com | F94: Delivered every month (recuring) | G94: France | J94: 1400 | K94: - | L94: - | M94: Sent | N94: F2025-0270 | O94: Payé 13/06/2025 | S94: 20
A95: GIE | C95: 45785 | D95: GIEAC | Extra speaker cards | E95: Mahtab Jalali Moghaddam | F95: Delivered | G95: Belgium | H95: 20250303_GIEAC Personalized Notebooks | I95: 20 | J95: =IF(SUMPRODUCT($R$2:$AV$2,R95:AV95)=0,"-",SUMPRODUCT($R$2:$AV$2,R95:AV95)) -> - | K95: - | L95: - | M95: Sent to Thomas | N95: F2025-0375 | O95: Payée le 08/07/2025
A96: GIE | C96: 45792 | D96: GIEAC Press Kit for Annual Conference | E96: Mahtab Jalali Moghaddam | F96: Delivered | G96: Belgium | H96: https://saranistudio.sharepoint.com/:f:/s/SaraniAssets/EkYws8HeiG5BgPWiC6ym1HYBbbvXmXpDISJDqWCkAdEizg?e=QKPCmz | I96: 17 | J96: =IF(SUMPRODUCT($R$2:$AV$2,R96:AV96)=0,"-",SUMPRODUCT($R$2:$AV$2,R96:AV96)) -> - | K96: - | L96: - | M96: Sent to Thomas | N96: F2025-0375 | O96: Payée le 08/07/2025
A97: Hirondo | C97: 45796 | D97: Hirondo video 3 | E97: Arnaud Courtel | F97: Delivered | G97: France | H97: https://saranistudio.sharepoint.com/:f:/s/SaraniAssets/EiOSFJyScHNAvCo8LOwvcNABKYjg6Ggvzl9J41YOGNKhTg?e=cYpZGh | I97: 1 | J97: 2250 | M97: Sent via Whatsapp | N97: F2025-0374 | O97: Payée le 17/09/2025
A98: Dialogue | C98: 45804 | D98: Partenariat avec des influenceurs 2025 | E98: Charlotte | F98: Delivered | G98: France | H98: - | I98: 1 | J98: 24250 | K98: - | L98: 2505065 | M98: Sent | N98: F2025-0281 | O98: Payée le 01/07/2025
A99: FERTIROC | C99: 45810 | D99: Projet vidéo - FERTIROC | E99: Maxime | F99: Delivered | G99: France | H99: 20250602_Projet vidéo - FERTIROC | I99: - | J99: 2900 | M99: Sent | N99: F2025-0521 | O99: Payée le 16/09/2025
A100: Wide’O | C100: 45810 | D100: Branding pour Wide’O | E100: Maxime | F100: Delivered | H100: 20250602_Branding pour Wide’O | I100: =IF(SUM(R100:AV100)=0,"-",SUM(R100:AV100)) -> - | J100: Inclus dans la prestation mensuelle Adrien VBA | K100: - | L100: - | M100: - | N100: - | O100: - | P100: - | Q100: -
...

Sheet All projects
A1: Customer | B1: Date | C1: Project | D1: Contact | E1: Status | F1: Category | G1: Link | H1: Assets | I1: Total Value | J1: Quote | K1: PO | L1: Invoice | M1: N° invoice | N1: Status inv. | O1: Echéance | P1: Commentaire | Q1: Banner creation (static) 135 | R1: Banner adaptation (static) 30 | S1: Banner creation (animated) 220 | T1: Banner adaptation (animated) 50 | U1: Branding pack 2000 | V1: Logo 250 | W1: Lifestyle Picture 400 | X1: Wallpapers 85 | Y1: Offline creation (standard) 135 | Z1: Offline creation (adaptation) 30 | AA1: Leaflet (1 page) 180 | AB1: Leaflet (2 pages) 260 | AC1: Roll-up / Wall creation 180 | AD1: Chart 400 | AE1: Brochure (20 pages) 2200 | AF1: Slide 40 | AG1: Landing page (design only) 300 | AH1: Landing page (complete) 700 | AI1: Website (design only) 5000 | AJ1: Website (complete) 7000 | AK1: Video Edition 80 | AL1: Video Subtitles 150 | AM1: Social Media Video (up to 30s) 260 | AN1: Social Media Video (up to 1 min) 560 | AO1: Promotional Video (up to 1 min) 4000 | AP1: 2D Video (up to 3mn) 5000 | AQ1: 3D Video (up to 3min) 10000 | AR1: Virtual space 2500 | AS1: Virtual showroom 10000 | AT1: Translation (per word) 0.1 | AU1: Copywrite (per word) 0.25
A2: Son-video.com | B2: 44743 | C2: Virtual Showroom | D2: Hugo Lahutte | E2: Delivered | F2: France | G2: - | H2: 2 | I2: 5000 | J2: 45084 | K2: - | L2: Sent | M2: F2023-0523 | N2: Payé le 11/08/2023 | AR2: 2
A3: Pippacorner | B3: 45083 | C3: Pippacorner Branding | D3: Stéphane Rambaud | E3: Delivered | F3: France | G3: https://saranistudio.sharepoint.com/:f:/s/SaraniAssets/EnbyF5acw11EjdYGvMP5nx0B0d70LzvZ1gHbTGcqlFjbGA?e=zcD1fD | H3: 4.376 | I3: 2000 | J3: 45084 | K3: - | L3: Sent | M3: F2023-0515 | N3: Payé le 28/07/2023 | U3: 1 | AI3: 0.3 | AN3: 2 | AP3: 1.076
A4: Pippacorner | B4: 45083 | C4: Pippacorner Website Design | D4: Stéphane Rambaud | E4: Delivered | F4: France | G4: https://saranistudio.sharepoint.com/:f:/s/SaraniAssets/ErmhsGB8kgRAuBYr4yIhwroBiQEACi2aakOTS93vHVWT1A?e=Xu2JTN | H4: 1 | I4: 1800 | J4: - | K4: - | L4: Sent | M4: F2023-0514 | N4: Payée le 26/09/2023 | U4: 1 | AI4: #DIV/0! | AN4: 2 | AP4: #DIV/0!
A5: La Maison des Bienheureux | B5: 45083 | C5: New website | D5: Romain Petit | E5: Delivered | F5: France | G5: https://b2b.sarani.studio | H5: 1 | I5: 4000 | J5: 45084 | K5: - | L5: Sent | M5: F2024-0045 | N5: Payé le 29/05/2024 | AJ5: 0.57142857
A6: Pippacorner | B6: 45083 | C6: Pippacorner Catalogue | D6: Stéphane Rambaud | E6: Delivered | F6: France | G6: https://saranistudio.sharepoint.com/:f:/s/SaraniAssets/EmRcIT6D4cxGl8o_DjWi9wcB_aDUY7-whHxFK_E3rlYFFw?e=aG6faZ | H6: 1 | I6: 850 | J6: - | K6: - | L6: Sent | M6: F2023-0513 | N6: Payée le 26/092023
A7: Pippacorner | B7: 45184 | C7: Pippacorner maquettes | D7: Stéphane Rambaud | E7: Delivered | F7: France | G7: https://saranistudio.sharepoint.com/:f:/s/SaraniAssets/ErmhsGB8kgRAuBYr4yIhwroBiQEACi2aakOTS93vHVWT1A?e=Xu2JTN | H7: 10 | I7: 1500 | J7: - | K7: - | L7: Sent | M7: F2023-0512 | N7: Payée le 07/11/2032
A8: Pippacorner | B8: 45185 | C8: Pippacorner Flyer | D8: Stéphane Rambaud | E8: Delivered | F8: France | G8: https://saranistudio.sharepoint.com/:f:/s/SaraniAssets/EkTN4p5LGHFGhELydt5HB-oB0aFtmnCCp7LOSYR9hymHGw?e=QPJaAL | H8: 1 | I8: 450 | J8: - | K8: - | L8: Sent | M8: F2023-0511 | N8: Payée le 07/11/2023
A9: Pernod-Ricard | B9: 45211 | C9: Perrier-Jouet - CP - Menu d'hiver | D9: Laura Marie through Marie Caroline Selmer | E9: Delivered | F9: France | G9: https://saranistudio.sharepoint.com/sites/SaraniAssets/Shared%20Documents/Forms/AllItems.aspx?ga=1&id=%2Fsites%2FSaraniAssets%2FShared%20Documents%2F03%2E%20Customers%2F09%2E%20Pernod%20Ricard%2F01%2E%20Press%20Release&viewid=2c2e4824%2D3cb1%2D4619%2Db7c6%2D219dce795204 | H9: 1 | I9: 40 | J9: - | K9: - | L9: Sent | M9: F2024-0038 | N9: Payé
A10: Pippacorner | B10: 45214 | C10: Pippacorner Final website assets | D10: Stéphane Rambaud | E10: Delivered | F10: France | G10: https://saranistudio.sharepoint.com/:f:/s/SaraniAssets/ElcfhiK7aLhJhiN2ZjA7EwYB_oX3cVCbpCW7693MDQnjtA?e=wHOvMb | H10: 5 | I10: 250 | J10: - | K10: - | L10: Sent | M10: F2023-0236 | N10: Payée le 7/11/2023
A11: Pernod-Ricard | B11: 45274 | C11: Château Sainte Marguerite - CP | D11: Laura Marie through Marie Caroline Selmer | E11: Delivered | F11: France | G11: https://saranistudio.sharepoint.com/sites/SaraniAssets/Shared%20Documents/Forms/AllItems.aspx?ga=1&id=%2Fsites%2FSaraniAssets%2FShared%20Documents%2F03%2E%20Customers%2F09%2E%20Pernod%20Ricard%2F01%2E%20Press%20Release&viewid=2c2e4824%2D3cb1%2D4619%2Db7c6%2D219dce795204 | H11: 1 | I11: 40 | J11: - | K11: - | L11: Sent | M11: F2024-0039 | N11: Payé
A12: Pomme de Pin | B12: 45290 | C12: Site web 50% | E12: Delivered | F12: France | G12: https://saranistudio.sharepoint.com/:f:/s/SaraniAssets/EpLFm-Ryfg5LirKpuYZqX6IBW6BRaDZWa7vLEWJstShnIg?e=XkPfBa | H12: - | I12: 2750 | J12: - | K12: - | L12: Sent | M12: F2024-0029 | N12: Payé le 30/01/2024
A13: PADOC | B13: 45292 | C13: Identité graphique | E13: Delivered | F13: France | G13: https://saranistudio.sharepoint.com/:f:/s/SaraniAssets/EtLDGZ7rZQRCnBF0YE1t2a4B2RhNm2OEYoiy6eidCd4hAw?e=JRicjA | H13: 1 | I13: 600 | J13: - | K13: - | L13: Sent | M13: F2024-0216 | N13: Payé le 17/06/2024
A14: Tour & taxi | B14: 45314 | C14: Création originale – Visuel pour impression | D14: Soraya Nouiyer | E14: Delivered | F14: France | G14: - | H14: - | I14: 135 | J14: 23/01/2024 | K14: - | L14: Sent | M14: F2024-0064 | N14: Payé le 05/06/2024
A15: Tour & taxi | B15: 45314 | C15: Création originale – Visuel pour publication | D15: Soraya Nouiyer | E15: Delivered | F15: France | G15: - | H15: - | I15: 135 | J15: 23/01/2024 | K15: - | L15: - | M15: - | N15: - | O15: -
A16: Dragon Rouge | B16: 45331 | C16: Vidéo roullier - V2 | D16: Cécile Mercadier | E16: Delivered | F16: France | G16: 20240902_Vidéo roullier-V2 | H16: 1 | I16: 750 | J16: - | K16: P022318 | L16: Sent to Thomas | M16: F2024-0508 | N16: Payée le 16/01/2025
A17: Eqiom | B17: 45331 | C17: Création originale – Visuel pour impression | D17: Cédric Lechoux, Marine Savary | E17: Delivered | F17: France | G17: - | H17: - | I17: 180 | J17: - | K17: - | L17: Sent | M17: F2024-0091 | N17: Payée le 26/07/2024
A18: GIE | B18: 45331 | C18: Flyers x 500 units 300g print | D18: Gabrielle Lelievre | E18: Delivered | F18: Belgium | G18: - | H18: 1 | I18: 550 | J18: - | K18: - | L18: Sent | M18: F2024-0419 | N18: Payé le 05/09/2024
A19: France Chimie | B19: 45343 | C19: Kakémono (Design + Impression) + Vignettes | D19: Aurélia | E19: Delivered | F19: France | G19: - | I19: 490 | J19: - | K19: - | L19: sent | M19: F2024-0214 | N19: Payé le 10/06/2024
A20: Pernod-Ricard | B20: 45400 | C20: Facture 2024-11 (CP n°1 de PJ) | D20: Laura Marie through Marie Caroline Selmer | E20: Delivered | F20: France | G20: - | H20: 1 | I20: 40 | J20: - | K20: - | L20: Sent | M20: F2024-0169 | N20: Payé
A21: Pernod-Ricard | B21: 45400 | C21: Facture 2024-20 (CP n°5 de SMEP) | D21: Laura Marie through Marie Caroline Selmer | E21: Delivered | F21: France | G21: - | H21: 1 | I21: 40 | J21: - | K21: - | L21: Sent | M21: F2024-0170 | N21: Payé | AF21: 14
A22: Eqiom | B22: 45405 | C22: Livret d'accueil A4 Alternants | D22: Cédric Lechoux, Marine Savary | E22: Delivered | F22: France | G22: https://saranistudio.sharepoint.com/:f:/s/SaraniAssets/Eqwntg4GF4xHs_lcP9At1-0BUwZloYyi4fg05MClpbZ17w?e=DtySqI | H22: - | I22: - | J22: - | K22: - | L22: Sent | M22: F2024-0187 | N22: Payée le 10/01/2025
A23: Pernod-Ricard | B23: 45405 | C23: Facture 2024-13 (CP n°4 de SMEP) Perrier-Jouët | D23: Laura Marie through Marie Caroline Selmer | E23: Delivered | F23: France | G23: - | H23: 1 | I23: 40 | J23: - | K23: - | L23: Sent | M23: F2024-0195 | N23: Payé le 29/05/2024
A24: Pippacorner | B24: 45405 | C24: Pippacorner website improvements | D24: Stéphane Rambaud | E24: Delivered | F24: France | G24: - | H24: 1 | I24: 500 | J24: - | K24: - | L24: Sent | M24: F2024-0186 | N24: Payée le 27/05/2024
A25: SpaceProjects | B25: 45405 | C25: Pack Présentations | D25: Hassib Mounzer | E25: Delivered | F25: France | G25: - | H25: 3 | I25: 1500 | J25: - | K25: - | L25: Sent via Whatsapp | M25: F2024-0679 | N25: Payée le 17/12/2024
A26: Air Corsica | B26: 45882 | C26: Projet Influence - Vienne et Munich | D26: Mélanie Tolédano | E26: In progress | F26: France | I26: 20000 | J26: - | K26: -
A27: Air Corsica | B27: 45413 | C27: Influencers campaign | D27: Jean-Paul | E27: Delivered | F27: France | G27: - | I27: 500 | J27: - | K27: - | L27: - | M27: - | N27: - | O27: - | P27: - | AC27: 9
A28: Eqiom | B28: 45415 | C28: Création Panneaux - EQIOM A1 | E28: Delivered | F28: France | G28: 20240509_Création Panneaux - EQIOM | H28: 9 | I28: 1980 | J28: - | K28: C000150109 | L28: Sent | M28: F2024-0428 | N28: Payée le 25/10/2024
A29: France Chimie | B29: 45415 | C29: Kakémono classique + Tendu (Design + Impression) | D29: Clayton / Juliette | E29: Delivered | F29: France | G29: - | I29: 891 | J29: - | K29: - | L29: sent | M29: F2024-0215 | N29: Payé le 10/06/2024
A30: GIE | B30: 45444 | C30: Service proposal: GIE Munich Conference assets v2 | D30: Gabrielle Lelievre | E30: Delivered | F30: Belgium | G30: - | H30: 15 | I30: 1080 | J30: - | K30: - | L30: Sent | M30: F2024-0389 | N30: Payée le 04/09/2024
A31: Aventim - Howel | B31: 45453 | C31: AXONOGRAPHIE | D31: Clément Robillard - crobillard@aventim.com | E31: Delivered | F31: France | G31: - | H31: 1 | I31: 950 | J31: - | K31: - | L31: Sent | M31: F2024-0361 | N31: Payée le 16/10/2024
A32: Air Corsica | B32: 45454 | C32: Campagne Italie Belgique | D32: Jean-Franois Colonna | E32: Delivered | F32: France | G32: - | I32: 30500 | J32: - | K32: CDF00019891 | L32: Sent | M32: F2024-0282 | N32: Payé le 26/07/2024
A33: Pomme de Pin | B33: 45458 | C33: PLAN + MENU + PLANNING JUILLET AOUT + SIGNATURES | D33: Julien Bauchart | E33: Delivered | F33: France | G33: - | I33: 900 | J33: - | K33: - | L33: Sent | M33: F2024-0352 | N33: Facture à 0€, pas de paiement attendu | P33: Offrir cette prestation afin de compenser les problèmes de livraison du site web Pomme de Pin. Possible de réaliser une facture de 900€ avec remise de 900€ pour que le client se rende compte du geste commercial effectué?
A34: Pomme de Pin | B34: 45463 | C34: Shooting Photos | D34: Julien Bauchart | E34: Delivered | F34: France | G34: - | I34: 450 | J34: - | K34: - | L34: Sent | M34: F2024-0414 | N34: Payée le 04/09/2024
A35: Dialogue | B35: 45477 | C35: Campagne Influence Dialogues 2410067 | D35: Charlotte | E35: Delivered | F35: France | G35: - | H35: 1 | I35: 12500 | J35: - | K35: 2410067 | L35: Sent | M35: F2024-0636 | N35: Payée le 16/12/2024
A36: Dialogue | B36: 45477 | C36: Campagne Influence Dialogues 2410066 | D36: Charlotte | E36: Delivered | F36: France | G36: - | H36: 1 | I36: 7500 | J36: - | K36: 2410066 | L36: Sent | M36: F2024-0635 | N36: Payée le 16/12/2024
A37: Pernod-Ricard | B37: 45483 | C37: SMEP corporate (CP6) | D37: Laura Marie through Marie Caroline Selmer | E37: Delivered | F37: France | G37: - | H37: 1 | I37: 40 | J37: - | K37: - | L37: Sent | M37: F2024-0327 | N37: Payé le 22/07/2024
A38: Pernod-Ricard | B38: 45483 | C38: PERRIER-JOUET CP 7 - Réouverture Cellier | D38: Laura Marie through Marie Caroline Selmer | E38: Delivered | F38: France | G38: - | H38: 1 | I38: 40 | J38: - | K38: - | L38: Sent | M38: F2024-0328 | N38: Payé le 22/07/2024
A39: Quentin Carnaille | B39: 45488 | C39: STATUE - C. DE GAULLE | D39: Quentin Carnaille quentincarnaille@gmail.com | E39: Delivered | F39: France | G39: https://saranistudio.sharepoint.com/sites/SaraniAssets/Shared%20Documents/Forms/AllItems.aspx?ga=1&id=%2Fsites%2FSaraniAssets%2FShared%20Documents%2F03%2E%20Customers%2F01%2E%20Single%20Projects%2FQuentin%20Carnaille&viewid=2c2e4824%2D3cb1%2D4619%2Db7c6%2D219dce795204 | H39: 1 | I39: 3500€ | J39: - | K39: - | L39: Sent | M39: F2024-0489 | N39: Payé 13/11/2024
A40: Velux | B40: 45498 | C40: DESIRE September burst - assets digitaux | D40: Pamela Ankrah | E40: Delivered | F40: France | G40: https://saranistudio.sharepoint.com/:f:/s/SaraniAssets/EoNIo5JGichNm6_RXrv8dEQBilHwAUZF81WudIE4jMTUlQ?e=h5OWme | H40: 16 | I40: 560 | J40: - | K40: - | L40: Sent | M40: F2024-0362 | N40: Payée le 09/09/2024 | R40: 16
A41: GIE | B41: 45503 | C41: Internal project 2 pagers | D41: Gabrielle Lelievre | E41: Delivered | F41: France | G41: https://saranistudio.sharepoint.com/:f:/s/SaraniAssets/EiKHBnr1-t1CkBJ2177ZVvsBaPQVNA_ojPNwV7zWuLyKkg?e=joXBaP | H41: 1 | I41: 180 | J41: - | K41: - | L41: Sent | M41: F2024-0390 | N41: Payée le 04/09/2024
A42: ESPI | B42: 45504 | C42: Refonte site web | D42: Sophie Bollack - s.bollack@groupe-espi.fr | E42: Delivered | F42: France | G42: - | H42: 1 | I42: 34000 | J42: - | K42: - | L42: - | M42: - | N42: - | O42: - | P42: Facturation multiple
A43: ESPI | B43: 45504 | C43: Refonte site web | D43: Sophie Bollack - s.bollack@groupe-espi.fr | E43: Delivered | F43: France | G43: - | H43: 1 | I43: 6800 | J43: - | K43: - | L43: Acompte 20% sent | M43: F2024-0407 | N43: Payée le 30/09/2024 | P43: Acompte N°1 de 20% .Notre compte client a bien été créé chez le client ESPI. Prestataire Sébastien Gras 12000€HT
A44: ESPI | B44: 45504 | C44: Refonte site web | D44: Sophie Bollack - s.bollack@groupe-espi.fr | E44: Delivered | F44: France | G44: - | I44: =13750+13450 -> 27200 | J44: - | K44: BdC5409 | L44: Sent | M44: F2025-0551 | N44: Payée le 03/10/2025 | P44: Acompte N°2 + Solde
A45: ESPI | B45: 45504 | C45: Acompte 20% Shooting photo / Vidéo | D45: Sophie Bollack - s.bollack@groupe-espi.fr | E45: Delivered | F45: France | G45: - | H45: 1 | I45: 3336 | J45: - | K45: - | L45: Acompte 20% sent | M45: F2024-0408 | N45: Payée le 30/09/2024 | P45: Acompte de 20% à facturer.Prestataire: Sébastien Gras (13344€HT, acompte de 3336€HT)
A46: ESPI | B46: 45504 | C46: Facture de solde: Shooting photo / Vidéo | D46: Sophie Bollack - s.bollack@groupe-espi.fr | E46: Delivered | F46: France | G46: - | H46: 1 | I46: 13344 | J46: - | K46: BdC6335 | L46: Sent | M46: F2025-0112 | N46: Payée le 18/03/2025 | P46: Facture de Solde
A47: ESPI | B47: 45504 | C47: Site web temporaire | D47: Sophie Bollack - s.bollack@groupe-espi.fr | E47: Delivered | F47: France | G47: - | H47: 1 | I47: 8000 | J47: - | K47: BdC5411 | L47: Envoyée 03/09/2024 | M47: F2024-0406 | N47: Payée le 30/09/2024 | P47: Acompte de 20% à facturer. Prestataire: Sébastien Gras (4000€HT, acompte de 2000€HT à régler)
A48: Pomme de Pin | B48: 45504 | C48: Site web 50% restants | D48: Julien Bauchart | E48: Delivered | F48: France | G48: https://saranistudio.sharepoint.com/:f:/s/SaraniAssets/EpLFm-Ryfg5LirKpuYZqX6IBW6BRaDZWa7vLEWJstShnIg?e=XkPfBa | H48: - | I48: 2750 | J48: - | K48: - | L48: Sent | M48: F2024-0413 | N48: Payée le 04/09/2024
A49: GIE | B49: 45508 | C49: Munich Notebook design | D49: Mayra Pena | E49: Delivered | F49: France | G49: https://saranistudio.sharepoint.com/:f:/s/SaraniAssets/EiKHBnr1-t1CkBJ2177ZVvsBaPQVNA_ojPNwV7zWuLyKkg?e=Vg5xgJ | H49: 1 | I49: 135 | J49: - | K49: - | L49: Sent | M49: F2024-0391 | N49: Payée le 04/09/2024
A50: Pernod-Ricard | B50: 45513 | C50: CP n°9 - PJ au Jardin Secret du Peninsula | D50: Laura Marie through Marie Caroline Selmer | E50: Delivered | F50: France | G50: - | H50: 1 | I50: 40 | J50: - | K50: - | L50: Sent | M50: F2024-0363 | N50: Payé le 04/09/2024
A51: Cicatrix | B51: 45532 | C51: Campagne influence | D51: Vanessa Fernandez | E51: Delivered | F51: France | G51: - | H51: 1 | I51: 2500 | J51: - | K51: - | L51: Sent to Thomas via Whatsapp | M51: F2024-0640 | N51: Payé le 30/12/2024
A52: Dragon Rouge | B52: 45532 | C52: Vidéo roullier - Adaptation verticale | D52: Cécile Mercadier | E52: Delivered | F52: France | G52: 20240828_Vidéo roullier_Adaptation verticale | H52: 1 | I52: 150 | J52: - | K52: P022318 | L52: Sent to Thomas | M52: F2024-0508 | N52: Payée le 16/01/2025
A53: Dragon Rouge | B53: 45537 | C53: Vidéo roullier - V2 - Anglais | D53: Cécile Mercadier | E53: Delivered | F53: France | G53: 20240902_Vidéo roullier-V2 | H53: 1 | I53: 150 | J53: - | K53: P022318 | L53: Sent to Thomas | M53: F2024-0508 | N53: Payée le 16/02/2025 | AF53: 43
A54: GIE | B54: 45538 | C54: GIE Speakers notes | D54: Francesco Gabrielli | E54: Delivered | F54: France | G54: Speaker notes | H54: 43 | I54: 1290 | J54: - | K54: - | L54: Sent | M54: F2024-0563 | N54: Payée le 26/11/2024
A55: GIE | B55: 45539 | C55: Kind request animated banner | D55: Gabrielle Lelievre | E55: Delivered | F55: Belgium | G55: 20240904_Kind request animated banner | H55: - | I55: 250 | J55: - | K55: - | L55: Sent to Thomas | M55: F2024-0471 | N55: Payé le 27/09/2024
A56: GIE | B56: 45539 | C56: GIE AC 2024 | Badges design briefing | D56: Malika Khalidi | E56: Delivered | F56: Belgium | G56: 20240904_GIE AC 2024_Badges design briefing | H56: - | I56: 250 | J56: - | K56: - | L56: Sent to Thomas | M56: F2024-0472 | N56: Payé le 27/09/2024
A57: Pernod-Ricard | B57: 45541 | C57: CP n°10 - SMEP x Byblos Beach | D57: Laura Marie through Marie Caroline Selmer | E57: Delivered | F57: France | G57: - | H57: 1 | I57: 40 | J57: - | K57: - | L57: Sent | M57: F2024-0426 | N57: Payé
A58: GIE | B58: 45548 | C58: GIE Strategic Storyline | D58: Tobias | E58: Delivered | F58: Belgium | G58: https://saranistudio.sharepoint.com/:f:/s/SaraniAssets/EuPIBC8QCwxKojTQkcK2azEBU99lZ2dbLp_H2hlcoMODlQ?e=nbpDqx | H58: 1 | I58: 720 | J58: - | K58: - | L58: Sent to Thomas | M58: F2024-0473 | N58: Payé le 27/09/2024 | AF58: 18
A59: Air Corsica | B59: 45552 | C59: Emailing Ouverture Réservations 2025 | D59: Mélanie Tolédano | E59: Delivered | F59: France | H59: 1 | I59: 450 | J59: - | K59: - | L59: Sent | M59: F2024-0562 | N59: Payée le 27/12/2024
A60: Air Corsica | B60: 45552 | C60: Emailing Black Friday | D60: Mélanie Tolédano | E60: Delivered | F60: France | G60: https://saranistudio.sharepoint.com/:f:/s/SaraniAssets/EohyeXpT9tNJkqHXbxykHC8BQoRf3Zf1kZ3UMprn3fHnXw?e=fXzyGP | H60: 1 | I60: 450 | J60: - | K60: - | L60: Sent | M60: F2024-0684 | N60: Payée le 27/12/2024
A61: Pernod-Ricard | B61: 45552 | C61: CP n°8 PR - RSVR MUMM | D61: Laura Marie through Marie Caroline Selmer | E61: Delivered | F61: France | G61: - | H61: 1 | I61: 40 | J61: - | K61: - | L61: Sent | M61: F2024-0446 | N61: Payée le 30/09/2024 | R61: 8
A62: GIE | B62: 45562 | C62: GIE AC banners | D62: Mayra Pena | E62: Delivered | F62: Belgium | G62: 20240927_GIE AC banners | H62: 8 | I62: 240 | J62: - | K62: - | L62: Sent | M62: F2024-0564 | N62: Payée le 26/11/2024
A63: GIE | B63: 45573 | C63: GIE AC 2024 - Farewell Videos | D63: Malika Khalidi | E63: Delivered | F63: Belgium | G63: https://saranistudio.sharepoint.com/:f:/s/SaraniAssets/ErbThV3AGv1CsZvziFM8Bl8BlpFAdpVNHAykNs8SfpdTwg?e=CKOR5u | H63: 2 | I63: 700 | J63: - | K63: - | L63: Sent | M63: F2024-0565 | N63: Payée le 26/11/2024 | R63: 20
A64: Pernod-Ricard | B64: 45580 | C64: CP n°13 SMEP actualisation Taste of Provence | D64: Laura Marie through Marie Caroline Selmer | E64: Delivered | F64: France | G64: - | H64: 1 | I64: 40 | J64: - | K64: - | L64: Sent | M64: F2024-0521 | N64: Payé | AF64: 17
A65: Pernod-Ricard | B65: 45580 | C65: CP n°12 PJ FR-EN Traduction | D65: Laura Marie through Marie Caroline Selmer | E65: Delivered | F65: France | G65: - | H65: 1 | I65: 60 | J65: - | K65: - | L65: Sent | M65: F2024-0523 | N65: Payé
A66: Pernod-Ricard | B66: 45580 | C66: CP n°11- PJ Menu d'été | D66: Laura Marie through Marie Caroline Selmer | E66: Delivered | F66: France | G66: - | H66: 1 | I66: 40 | J66: - | K66: - | L66: Sent | M66: F2024-0524 | N66: Payé
A67: ESPI | B67: 45606 | C67: Traduction web | D67: Sophie Bollack - s.bollack@groupe-espi.fr | E67: Delivered | F67: France | G67: - | H67: 1 | I67: 1600 | J67: - | K67: BdC5765 | L67: Envoyée le 11/12/2024 | M67: F2024-0681 | N67: Payée le 31/01/2025 | P67: 700€ à régler au prestataire Sébastien Gras. Facture à recevoir.
A68: Pernod-Ricard | B68: 45618 | C68: CP n°14- Dinner in the sky | D68: Laura Marie through Marie Caroline Selmer | E68: Delivered | F68: France | G68: - | H68: 1 | I68: 40 | J68: - | K68: - | L68: Sent | M68: F2024-0622 | N68: Payé le 28/11/2024
A69: Air Corsica | B69: 45628 | C69: Air Corsica Email soldes | D69: Mélanie Tolédano | E69: Delivered | F69: France | G69: https://saranistudio.sharepoint.com/:f:/s/SaraniAssets/EoYgzzkVsL1FkM-EyORt1s8BrQ211V90DMBMiNgXpK74Bg?e=u62Pry | H69: 1 | I69: 710 | J69: - | K69: - | L69: Sent | M69: F2025-0032 | N69: Payée 26/02/2025
A70: Dialogue | B70: 45630 | C70: Droits d'Images Laulevy | D70: Charlotte | E70: Delivered | F70: France | G70: - | H70: 1 | I70: 300 | J70: - | K70: 2412020 | L70: Sent | M70: F2024-0675 | N70: Payée le 10/01/2025 | AM70: 1
A71: GIE | B71: 45660 | C71: GIE | SoS Workshop | Create a Banner & Speaker Cards | D71: Mahtab Jalali Moghaddam | E71: Delivered | F71: Belgium | G71: GIE - SoS Workshop - Create a Banner & Speaker Cards | H71: 4 | I71: 435 | J71: - | K71: - | L71: Sent | M71: F2025-0033 | N71: Payée le 24/02/2025 | Q71: 3 | R71: 1
A72: Air Corsica | B72: 45951 | C72: Promotion Nice Florence | D72: Alexis SOYER | E72: Delivered | F72: France | H72: 21 | I72: 1450 | J72: - | K72: - | L72: Sent | M72: F2025-0727 | N72: Payée le 24/12/2025 | O72: - | P72: 1 vidéo DOOH dans 6 formats. 1 vidéo DOOH dans 9 formats. Deux vidéos réseaux sociaux dans 3 formats.
A73: GIE | B73: 45670 | C73: GIE | SoS Workshop | Speaker Cards | D73: Mahtab Jalali Moghaddam | E73: Delivered | F73: Belgium | G73: GIE - SoS Workshop - Create a Banner & Speaker Cards | H73: 12 | I73: 360 | J73: - | K73: - | L73: Sent | M73: F2025-0034 | N73: Payée le 24/02/2025 | Z73: 12
A74: Air Corsica | B74: 45674 | C74: Brief Ouverture de Ligne Nice -> Florence -> Nice | D74: Mélanie Tolédano | E74: Delivered | F74: France | G74: 20250117_Brief Ouverture de Ligne Nice - Florence - Nice | H74: - | I74: 2850 | J74: - | K74: - | L74: Sent | M74: F2025-0102 | N74: Payée le 30/06/2025 | Q74: 2 | R74: 3 | S74: 1
A75: GIE | B75: 45674 | C75: GIE - Annual Conference 2025 | Kick-off | D75: Malika Khalidi | E75: Delivered | F75: Belgium | G75: 20250117_GIE Annual Conference 2025 - Kick-off | H75: 6 | I75: - | J75: - | K75: - | L75: Sent to Thomas | M75: F2025-0253 | N75: Payée le 14/05/2025
A76: Hirondo | B76: 45680 | C76: Case studies videos | D76: Yannig | E76: Delivered | F76: France | G76: https://saranistudio.sharepoint.com/:f:/s/SaraniAssets/Ehc8_JcD7K9Lr__dI4C6ebwB1zaV9l9WO3KTicPNFSi4mA?e=yALMH1 | H76: 2 | I76: 2800 | J76: - | K76: - | L76: Sent via Whatsapp | M76: F2025-0160 | N76: Payée le 08/04/2025
A77: GIE | B77: 45688 | C77: GIE | SoS Workshop | extra Speaker Cards | D77: Mahtab Jalali Moghaddam | E77: Delivered | F77: France | G77: GIE - SoS Workshop - Create a Banner & Speaker Cards | H77: 1 | I77: 30 | J77: - | K77: - | L77: Sent to Thomas | M77: F2025-0253 | N77: Payée le 14/05/2025 | Z77: 1
A78: GIE | B78: 45688 | C78: GIE | SoS Workshop slide | D78: Mahtab Jalali Moghaddam | E78: Delivered | F78: France | G78: 20250131_GIE SoS Workshop slide | H78: 1 | I78: 220 | J78: - | K78: - | L78: Sent to Thomas | M78: F2025-0253 | N78: Payée le 14/05/2025 | S78: 1
A79: GIE | B79: 45709 | C79: GIE | SoS Workshop | Mailing Header+ GIF and social | D79: Mahtab Jalali Moghaddam | E79: Delivered | F79: Belgium | G79: 20250117_GIE Annual Conference 2025 - Kick-off | H79: 4 | I79: 215 | J79: - | K79: - | L79: Sent to Thomas | M79: F2025-0253 | N79: Payée le 14/05/2025 | Q79: 1 | R79: 2 | T79: 1
A80: GIE | B80: 45719 | C80: GIEAC | Personalized Notebooks + speaker cards | D80: Mahtab Jalali Moghaddam | E80: Delivered | F80: Belgium | H80: 3 | I80: 405 | J80: - | K80: - | L80: Sent to Thomas | M80: F2025-0253 | N80: Payée le 14/05/2025 | Q80: 1 | Y80: 2
A81: Pernod-Ricard | B81: 45722 | C81: CP n°17 Château Sainte Marguerite Cuvées 2024 | D81: Laura Marie through Marie Caroline Selmer | E81: Delivered | F81: France | G81: - | H81: 1 | I81: 40 | J81: - | K81: - | L81: Sent | M81: F2025-0083 | N81: Payée le 10/03/2025
A82: Pernod-Ricard | B82: 45722 | C82: CP °20 - Printemps Belle Epoque PJ | D82: Laura Marie through Marie Caroline Selmer | E82: Delivered | F82: France | G82: - | H82: 1 | I82: 40 | J82: - | K82: - | L82: Sent | M82: F2025-0333 | N82: Payée le 19/06/2025 | Q82: 2 | R82: 2
A83: GIE | B83: 45723 | C83: GIE | Visuals for Biomethane Study Launch | 30 April | D83: Mahtab Jalali Moghaddam | E83: Delivered | F83: Belgium | G83: GIE - Visuals for Biomethane Study Launch - 30 April | H83: 3 | I83: - | J83: - | K83: - | L83: Sent to Thomas | M83: F2025-0253 | N83: Payée le 14/05/2025
A84: Pomme de Pin | B84: 45728 | C84: Abonnement annuel - Maintenance / Tracking / SEO | D84: Julien Bauchart | E84: Delivered | F84: France | I84: 2300 | J84: - | K84: - | L84: Sent | M84: F2025-0222 | N84: Payée le 06/06/2025 | P84: 1400€ Reglé par échéancier à SG
A85: Paradox | B85: 45730 | C85: Campagne des Money Days | D85: Farah Rouassi | E85: Delivered | F85: France | G85: https://saranistudio.sharepoint.com/:f:/s/SaraniAssets/EpTwgabtzGJBvE1QvzC9JVgBLcfZppAhj82LlolZKx4ZIw?e=bEEke8 | H85: 3 | I85: 850 | J85: - | K85: - | L85: Sent via Whatsapp | M85: F2025-0161 | N85: Payée le 12/04/2025 | AL85: 2 | AM85: 1
A86: Air Corsica | B86: 45736 | C86: AIR CORSICA - Brief Opération Destination Corse Mars/Avril | D86: Mélanie Tolédano | E86: Delivered | F86: France | G86: 20250320_Brief Opération Destination Corse Mars-Avril | H86: 3 | I86: 560 | J86: - | K86: - | L86: Sent | M86: F2025-0275 | N86: Payée le 30/06/2025
A87: GIE | B87: 45757 | C87: GIEAC | Speaker cards | D87: Mahtab Jalali Moghaddam | E87: Delivered | F87: Belgium | G87: 20250303_GIEAC Personalized Notebooks | H87: 54 | I87: 1080 | J87: - | K87: - | L87: Sent to Thomas | M87: F2025-0253 | N87: Payée le 14/05/2025 | R87: 36
A88: Air Corsica | B88: 45761 | C88: Florence new email | D88: Mélanie Tolédano | E88: Delivered | F88: France | G88: https://saranistudio.sharepoint.com/:f:/s/SaraniAssets/Evu3AwE3YHpBreauZ0Kej2QB9GcsjLq_eoDkRPLfA6q3wQ?e=c3mMLw | I88: 350 | J88: - | K88: - | L88: Sent | M88: F2025-0275 | N88: Payée le 30/06/2025
A89: GIE | B89: 45762 | C89: GIE AC | 2 new banner format | D89: Mahtab Jalali Moghaddam | E89: Delivered | F89: Belgium | G89: 20250415_GIE AC - 2 new banner format | H89: 2 | I89: 80 | J89: - | K89: - | L89: Sent to Thomas | M89: F2025-0253 | N89: Payée le 14/05/2025 | R89: 1 | T89: 1
A90: Pomme de Pin | B90: 45770 | C90: Au Pin Gourmet - Branding / Web | D90: Julien Bauchart | E90: Delivered | F90: France | I90: 5000 | J90: - | K90: - | L90: Sent | M90: F2025-0269 | N90: Payée le 06/06/2025
A91: Air Corsica | B91: 45774 | C91: Air Corsica New campaign assets | D91: Mélanie Tolédano | E91: Delivered | F91: France | H91: 3 | I91: 1500 | J91: - | K91: - | L91: Sent | M91: F2025-0275 | N91: Payée le 30/06/2025
A92: VBA MOTOSPORT (Adrien VanBeveren) | B92: 45782 | C92: Assistant permanent may | D92: teamvbacontact@gmail.com | E92: Delivered every month (recuring) | F92: France | I92: 1400 | J92: - | K92: - | L92: Sent | M92: F2025-0270 | N92: Payé 13/06/2025 | R92: 20
A93: GIE | B93: 45785 | C93: GIEAC | Extra speaker cards | D93: Mahtab Jalali Moghaddam | E93: Delivered | F93: Belgium | G93: 20250303_GIEAC Personalized Notebooks | H93: 20 | I93: - | J93: - | K93: - | L93: Sent to Thomas | M93: F2025-0375 | N93: Payée le 08/07/2025
A94: GIE | B94: 45792 | C94: GIEAC Press Kit for Annual Conference | D94: Mahtab Jalali Moghaddam | E94: Delivered | F94: Belgium | G94: https://saranistudio.sharepoint.com/:f:/s/SaraniAssets/EkYws8HeiG5BgPWiC6ym1HYBbbvXmXpDISJDqWCkAdEizg?e=QKPCmz | H94: 17 | I94: - | J94: - | K94: - | L94: Sent to Thomas | M94: F2025-0375 | N94: Payée le 08/07/2025
A95: Hirondo | B95: 45796 | C95: Hirondo video 3 | D95: Arnaud Courtel | E95: Delivered | F95: France | G95: https://saranistudio.sharepoint.com/:f:/s/SaraniAssets/EiOSFJyScHNAvCo8LOwvcNABKYjg6Ggvzl9J41YOGNKhTg?e=cYpZGh | H95: 1 | I95: 2250 | J95: - | K95: - | L95: Sent via Whatsapp | M95: F2025-0374 | N95: Payée le 17/09/2025
A96: Dialogue | B96: 45804 | C96: Partenariat avec des influenceurs 2025 | D96: Charlotte | E96: Delivered | F96: France | G96: - | H96: 1 | I96: 24250 | J96: - | K96: 2505065 | L96: Sent | M96: F2025-0281 | N96: Payée le 01/07/2025
A97: Eshalore (Maaieven) | B97: 45810 | C97: Training Videos Episode 1 | D97: brianna@maaiven.com | E97: Delivered | F97: USA | G97: https://saranistudio.sharepoint.com/:f:/s/SaraniAssets/EubSg9PUiIhInKr6pDjILtsBMi-lVwyFfrwYf5zsOE6jIA?e=zHgXsE | H97: 1 | I97: 500 | J97: - | K97: - | L97: Sent | M97: F2025-0360 | N97: Payée le 24/06/2025
A98: FERTIROC | B98: 45810 | C98: Projet vidéo - FERTIROC | D98: Maxime | E98: Delivered | F98: France | G98: 20250602_Projet vidéo - FERTIROC | H98: - | I98: 2900 | J98: - | K98: - | L98: Sent | M98: F2025-0521 | N98: Payée le 16/09/2025
A99: Wide’O | B99: 45810 | C99: Branding pour Wide’O | D99: Maxime | E99: Delivered | G99: 20250602_Branding pour Wide’O | H99: - | I99: Inclus dans la prestation mensuelle Adrien VBA | J99: - | K99: - | L99: - | M99: - | N99: - | O99: - | P99: -
A100: Ogeste | B100: 45813 | C100: Logo / Charte / Humanoide / Vidéos | D100: antoinebulot3@gmail.com | E100: Delivered | F100: France | I100: =400+800+(32*340) -> 12080 | J100: - | K100: - | L100: Sent | M100: F2025-0636 | N100: Payée le 31/10/2025 | P100: Prestataire : Quentin Collus - Première facture 2600€HT pour création humanoîdes / environnement des exercices / Première vidéo. Prix négocié par vidéo: 100€
...

Sheet ESPI
A1: Customer | B1: Project | C1: Status | D1: Facturé client | E1: Cost Sébastien | F1: Cost Chloé | G1: Other | H1: Profit | I1: Quote | J1: PO | K1: Invoice | L1: N° invoice | M1: Status
A2: ESPI | B2: Refonte site web | C2: In progress | D2: 34000 | E2: 12000 | F2: 6000 | G2: 8000 | H2: =D2-E2-F2-G2 -> 8000 | I2: Acompte de 20% à facturer .Notre compte client a bien été créé chez le client ESPI. Prestataire Sébastien Gras 12000€HT | J2: - | K2: Acompte 20% sent | L2: F2024-0407 | M2: Payée le 30/09/2024
A3: ESPI | B3: MotionDesign | C3: In progress | D3: 5000 | I3: Pas initié pour le moment
A4: ESPI | B4: Shooting photo / Vidéo | C4: Delivered | D4: 16680 | E4: 15000 | H4: =D4-E4-F4-G4 -> 1680 | I4: Acompte de 20% à facturer.Prestataire: Sébastien Gras (13344€HT, acompte de 3336€HT) | J4: - | K4: Acompte 20% sent | L4: F2024-0408 | M4: Payée le 30/09/2024
A5: ESPI | B5: Site web temporaire | C5: Delivered | D5: 8000 | E5: 4000 | F5: 0 | G5: 0 | H5: =D5-E5-F5-G5 -> 4000 | I5: Acompte de 20% à facturer. Prestataire: Sébastien Gras (4000€HT, acompte de 2000€HT à régler) | J5: BdC5411 | K5: Envoyée 03/09/2024 | L5: F2024-0406 | M5: Payée le 30/09/2024
A6: ESPI | B6: Traduction web | C6: Delivered | D6: 1600 | E6: 700 | F6: 0 | G6: 310 | H6: =D6-E6-F6-G6 -> 590 | I6: 700€ à régler au prestataire Sébastien Gras. Facture à recevoir. | J6: - | K6: Envoyée le 11/12/2024 | L6: F2024-0681 | M6: Payée le 31/01/2025
A7: ESPI | B7: Maintenance
A8: ESPI | B8: Tracking
A9: ESPI | B9: TOTAL | D9: =SUM(D2:D6) -> 65280 | E9: =SUM(E2:E6) -> 31700 | F9: =SUM(F2:F6) -> 6000 | G9: =SUM(G2:G6) -> 8310 | H9: =SUM(H2:H6) -> 14270

Sheet Oneov
R1: Online | Z1: Offline | AG1: Presentations | AH1: Web | AL1: Videos | AS1: Virtualization | AU1: Copy
C2: Details : Maxime mailto:Samcommerce.r360@gmail.com | R2: Banner creation (static) | S2: Banner adaptation (static) | T2: Banner creation (animated) | U2: Banner adaptation (animated) | V2: Branding pack | W2: Logo | X2: Lifestyle Picture | Y2: Wallpapers | Z2: Offline creation (standard) | AA2: Offline creation (adaptation) | AB2: Leaflet (1 page) | AC2: Leaflet (2 pages) | AD2: Roll-up / Wall creation | AE2: Chart | AF2: Brochure (20 pages) | AG2: Slide | AH2: Landing page (design only) | AI2: Landing page (complete) | AJ2: Website (design only) | AK2: Website (complete) | AL2: Video Edition | AM2: Video Subtitles | AN2: Social Media Video (up to 30s) | AO2: Social Media Video (up to 1 min) | AP2: Promotional Video (up to 1 min) | AQ2: 2D Video (up to 3mn) | AR2: 3D Video (up to 3min) | AS2: Virtual space | AT2: Virtual showroom | AU2: Translation (per word) | AV2: Copywrite (per word)
A3: Date | B3: Project | C3: Contact | D3: Status | E3: Category | F3: Link | G3: Assets | H3: Total Value | I3: Quote | J3: PO | K3: Invoice | L3: N° invoice | M3: Status | N3: Echéance | P3: Jours de retards | Q3: Commentaire | R3: 135 | S3: 35 | T3: 220 | U3: 50 | V3: 2000 | W3: 250 | X3: 400 | Y3: 85 | Z3: 135 | AA3: 40 | AB3: 180 | AC3: 260 | AD3: 180 | AE3: 400 | AF3: 2200 | AG3: 30 | AH3: 300 | AI3: 700 | AJ3: 5000 | AK3: 7000 | AL3: 80 | AM3: 150 | AN3: 260 | AO3: 560 | AP3: 4000 | AQ3: 5000 | AR3: 10000 | AS3: 2500 | AT3: 10000 | AU3: 0.1 | AV3: 0.25
A4: - | B4: Identification de la marque | C4: Sam | D4: Delivered | E4: France | F4: - | G4: 1 | H4: 500 | I4: - | J4: - | K4: Sent | L4: F2024-0171 | M4: Waiting for payment | N4: 45435 | O4: =TODAY() -> 46106 | P4: =_xlfn.DAYS(O4,N4) -> 671 | Q4: 27/02: Procédure d'injonction de payer lancée
A5: - | B5: Création d'un logo et des déclinisations | C5: Sam | D5: Delivered | E5: France | F5: - | G5: 1 | H5: 500 | I5: - | J5: - | K5: Sent | L5: F2024-0171 | M5: Waiting for payment | N5: 45435 | O5: =TODAY() -> 46106 | P5: =_xlfn.DAYS(O5,N5) -> 671 | Q5: 27/02: Procédure d'injonction de payer lancée
A6: - | B6: Création d'une charte graphique | C6: Sam | D6: Delivered | E6: France | F6: - | G6: 1 | H6: 1000 | I6: - | J6: - | K6: Sent | L6: F2024-0171 | M6: Waiting for payment | N6: 45435 | O6: =TODAY() -> 46106 | P6: =_xlfn.DAYS(O6,N6) -> 671 | Q6: 27/02: Procédure d'injonction de payer lancée
A7: - | B7: Dépôt de la marque par un avocat en PI auprès de l'INPI | C7: Sam | D7: Delivered | E7: France | F7: - | G7: 1 | H7: 2000 | I7: - | J7: - | K7: Sent | L7: F2024-0171 | M7: Waiting for payment | N7: 45435 | O7: =TODAY() -> 46106 | P7: =_xlfn.DAYS(O7,N7) -> 671 | Q7: 27/02: Procédure d'injonction de payer lancée
A8: - | B8: Facture Print BPRIVES PARIS LAFAYETTE | C8: Sam | D8: Delivered | E8: France | F8: - | G8: 1 | H8: 750 | I8: - | J8: - | K8: Sent | L8: F2024-0172 | M8: Waiting for payment | N8: 45435 | O8: =TODAY() -> 46106 | P8: =_xlfn.DAYS(O8,N8) -> 671 | Q8: 27/02: Procédure d'injonction de payer lancée
A9: - | B9: Création de 3 Visuels pour print extérieur - Les Lillas | C9: Sam | D9: Delivered | E9: France | F9: - | G9: =IF(SUM(R9:AV9)=0,"-",SUM(R9:AV9)) -> 3 | H9: =IF(SUMPRODUCT($R$3:$AV$3,R9:AV9)=0,"-",SUMPRODUCT($R$3:$AV$3,R9:AV9)) -> 120 | I9: - | J9: - | K9: Sent | L9: F2024-0498 | M9: Waiting for payment | N9: 45602 | O9: =TODAY() -> 46106 | P9: =_xlfn.DAYS(O9,N9) -> 504 | Q9: 27/02: Procédure d'injonction de payer lancée | AA9: 3
A10: - | B10: Merchandising - Les Lillas | C10: Sam | D10: Delivered | E10: France | G10: 2900 | H10: 2900 | I10: - | J10: - | K10: Sent | L10: F2024-0499 | M10: Waiting for payment | N10: 45602 | O10: =TODAY() -> 46106 | P10: =_xlfn.DAYS(O10,N10) -> 504 | Q10: 27/02: Procédure d'injonction de payer lancée
A11: - | B11: Création d'un site web vitrine avec Optimisation SEO | C11: Sam | D11: Waiting for first payment to start | F11: - | G11: 1 | H11: 6000 | Q11: Jamais facturé
A12: - | B12: Configuration initiale des réseaux Sociaux | C12: Sam | D12: Waiting for first payment to start | F12: - | G12: 1 | H12: 500 | Q12: Jamais facturé
A13: 45355 | B13: Accompagnement Social Media / Shooting Photos Vidéos / Landing Page / SEO | C13: Lailla | E13: France | F13: - | H13: 8200 | I13: - | J13: -
B14: Facture solde | H14: 7380 | L14: F2024-0644
B15: 10% acompte | H15: 820 | L15: F2024-0255
A16: 45355 | B16: Accompagnement Instagram sur 2 mois + création d'un pack de 15 visuels | C16: Lailla | D16: Delivered | E16: France | F16: - | G16: - | H16: 2500 | J16: - | L16: F2024-0497 | M16: En attente de paiement | N16: 45602 | O16: =_xlfn.DAYS(N16,M16) -> #VALUE!
A17: 45355 | B17: Shooting photos + interviews videos présentant le concept | C17: Lailla | D17: In progress | E17: France | F17: - | G17: - | H17: 1700 | J17: - | L17: F2024-0497 | M17: En attente de paiement | N17: 45602 | O17: =_xlfn.DAYS(N17,M17) -> #VALUE!
A18: 45355 | B18: Création d'une marque et de sa charte | C18: Lailla | D18: Delivered | E18: France | F18: - | G18: - | H18: 750 | J18: - | L18: F2024-0497 | M18: En attente de paiement | N18: 45602 | O18: =_xlfn.DAYS(N18,M18) -> #VALUE!
A19: 45355 | B19: Création d'une landing page | C19: Lailla | D19: In progress | E19: France | F19: - | G19: -
A20: 45355 | B20: Optimisation SEO de la landing page | C20: Lailla | D20: In progress | E20: France | F20: - | G20: -
A21: 45355 | B21: Optimisation SEA (publicité payante) | C21: Lailla | D21: In progress | E21: France | F21: - | G21: -

Sheet Connect
A1: Price File | C1: Last update project | D1: ? | J1: LAST UPDATE FINANCE | L1: 45489 | P1: Online | X1: Offline | AE1: Presentations | AF1: Web | AJ1: Videos | AQ1: Virtualization | AS1: Copy
A2: Project | E2: We invoice : Connect Communication Advertising LLC (Bassel Kassas) 3 invoices | P2: Banner creation (static) | Q2: Banner adaptation (static) | R2: Banner creation (animated) | S2: Banner adaptation (animated) | T2: Branding pack | U2: Logo | V2: Lifestyle Picture | W2: Wallpapers | X2: Offline creation (standard) | Y2: Offline creation (adaptation) | Z2: Leaflet (1 page) | AA2: Leaflet (2 pages) | AB2: Roll-up / Wall creation | AC2: Chart | AD2: Brochure (20 pages) | AE2: Slide | AF2: Landing page (design only) | AG2: Landing page (complete) | AH2: Website (design only) | AI2: Website (complete) | AJ2: Video Edition | AK2: Video Subtitles | AL2: Social Media Video (up to 30s) | AM2: Social Media Video (up to 1 min) | AN2: Promotional Video (up to 1 min) | AO2: 2D Video (up to 3mn) | AP2: 3D Video (up to 3min) | AQ2: Virtual space | AR2: Virtual showroom | AS2: Translation (per word) | AT2: Copywrite (per word)
A3: Customer | B3: Division | C3: Date | D3: Project | E3: Contact | F3: Status | G3: Category | H3: Link | I3: Assets | J3: Total Value | K3: Quote | L3: PO | M3: Invoice | N3: N° invoice | O3: Status | P3: 135 | Q3: 30 | R3: 220 | S3: 50 | T3: 2000 | U3: 250 | V3: 400 | W3: 85 | X3: 135 | Y3: 30 | Z3: 180 | AA3: 260 | AB3: 180 | AC3: 400 | AD3: 2200 | AE3: 40 | AF3: 300 | AG3: 700 | AH3: 5000 | AI3: 7000 | AJ3: 80 | AK3: 150 | AL3: 260 | AM3: 560 | AN3: 4000 | AO3: 5000 | AP3: 10000 | AQ3: 2500 | AR3: 10000 | AS3: 0.1 | AT3: 0.25
A4: Connect | C4: 45536 | D4: CPC Branding Deck | E4: Bassel Kassas | F4: Delivered | G4: CPC | I4: 1 | J4: 1500 | K4: - | L4: - | M4: Sent | N4: F2024-0433 | O4: Paid 16/10/2024
A5: Connect | C5: 45536 | D5: IBD Profile deck | E5: Bassel Kassas | F5: Delivered | G5: CPC | H5: https://saranistudio.sharepoint.com/:f:/s/SaraniAssets/EpyzWx2RoxlDk2mb6W9Ul8MBg1Ms8d2tY2OQ8wXNLUA4ZA?e=3jQi7b | I5: 1 | J5: 1500 | K5: - | L5: - | M5: Sent | N5: F2024-0434 | O5: Paid 16/10/2024
A6: Connect | C6: 45545 | D6: IBU - Pre-Qualification Brochure | E6: Bassel Kassas | F6: Delivered | G6: CPC | H6: https://saranistudio.sharepoint.com/:f:/s/SaraniAssets/ErjOFrbH7FVHjPw1NvubUJgBfYN8x0t0vXyReRCLIlouZA?e=tNdaWa | I6: 1 | J6: 1500 | K6: - | L6: - | M6: Sent | N6: F2024-0435 | O6: Paid 16/10/2024
A7: Connect | C7: 45567 | D7: UCC Profile deck | E7: Bassel Kassas | F7: Delivered | G7: CPC | H7: 20241002_UCC Profile deck | I7: 1 | J7: 1500 | K7: - | L7: - | M7: Sent | N7: F2024-0568 | O7: Paid 09/03/2025
A8: Connect | C8: 45667 | D8: Transimed Brand Identity | E8: Bassel Kassas | F8: Delivered | G8: Transimed | I8: 1 | J8: 850 | K8: - | L8: - | M8: Sent via Whatsapp | N8: F2025-0029 | O8: Paid 28/02/2025
A9: Connect | C9: 45667 | D9: Waw packaging | E9: Wissam | F9: Delivered | G9: Waw | J9: OFFERED | K9: - | L9: - | M9: - | N9: - | O9: - | Z9: 3
A10: Connect | C10: 45818 | D10: The Body Shop Packaging | E10: Bassel Kassas | F10: Delivered | G10: TBS | I10: 3 | J10: 550 | K10: - | L10: - | M10: Sent via Whatsapp | N10: F2025-0386 | O10: Paid 10/11/2025
A11: Connect | C11: 45852 | D11: The Body Shop - 3 New Range | E11: Bassel Kassas | F11: Delivered | G11: TBS | H11: https://saranistudio.sharepoint.com/:f:/s/SaraniAssets/EuHNcWVhPKFImvd2XDHEUtwBtNbHSJEFRnTZoXyuk68DKw?e=gwaCz7 | I11: 3 | J11: =1250*I11*50% -> 1875 | K11: - | L11: - | M11: Sent via Whatsapp | N11: F2025-0628 | O11: Paid 10/11/2025

Sheet ProcessOut
A1: Price File | C1: Last update project | D1: ? | J1: LAST UPDATE FINANCE | L1: 45467 | S1: Online | AA1: Offline | AH1: Presentations | AI1: Web | AM1: Videos | AT1: Virtualization | AV1: Copy
A2: Project | E2: Details #POFR019659 | S2: Banner creation (static) | T2: Banner adaptation (static) | U2: Banner creation (animated) | V2: Banner adaptation (animated) | W2: Branding pack | X2: Logo | Y2: Lifestyle Picture | Z2: Wallpapers | AA2: Offline creation (standard) | AB2: Offline creation (adaptation) | AC2: Leaflet (1 page) | AD2: Leaflet (2 pages) | AE2: Roll-up / Wall creation | AF2: Chart | AG2: Brochure (20 pages) | AH2: Slide | AI2: Landing page (design only) | AJ2: Landing page (complete) | AK2: Website (design only) | AL2: Website (complete) | AM2: Video Edition | AN2: Video Subtitles | AO2: Social Media Video (up to 30s) | AP2: Social Media Video (up to 1 min) | AQ2: Promotional Video (up to 1 min) | AR2: 2D Video (up to 3mn) | AS2: 3D Video (up to 3min) | AT2: Virtual space | AU2: Virtual showroom | AV2: Translation (per word) | AW2: Copywrite (per word)
A3: Customer | B3: Division | C3: Date | D3: Project | E3: Contact | F3: Status | G3: Category | H3: Link | I3: Assets | J3: Total Value | K3: Quote | L3: PO | M3: Invoice | N3: N° invoice | O3: Status | P3: Echéance | S3: 135 | T3: 30 | U3: 220 | V3: 50 | W3: 2000 | X3: 250 | Y3: 400 | Z3: 85 | AA3: 135 | AB3: 30 | AC3: 180 | AD3: 260 | AE3: 180 | AF3: 400 | AG3: 2200 | AH3: 40 | AI3: 300 | AJ3: 700 | AK3: 5000 | AL3: 7000 | AM3: 80 | AN3: 150 | AO3: 260 | AP3: 560 | AQ3: 4000 | AR3: 5000 | AS3: 10000 | AT3: 2500 | AU3: 10000 | AV3: 0.1 | AW3: 0.25
A4: ProcessOut | C4: 45463 | D4: ProcessOut Kakemono 1 | E4: Alizé Amrani | F4: Delivered | G4: France | H4: https://saranistudio.sharepoint.com/:f:/s/SaraniAssets/EiEq_tcCAl5KpCw6Csa44nIBnD3l21MpG9vmZPK0gR_UoA?e=nwN5Xt | I4: 1 | J4: 250 | M4: Sent | N4: F2024-0375 | O4: Payé | P4: 45561 | Q4: =TODAY() -> 46106
A5: ProcessOut | C5: 45463 | D5: ProcessOut Kakemono 2 | E5: Alizé Amrani | F5: Delivered | G5: France | H5: https://saranistudio.sharepoint.com/:f:/s/SaraniAssets/EiEq_tcCAl5KpCw6Csa44nIBnD3l21MpG9vmZPK0gR_UoA?e=nwN5Xt | I5: 1 | J5: 250 | M5: Sent | N5: F2024-0409 | O5: Payé | P5: 45568 | Q5: =TODAY() -> 46106
A6: ProcessOut | C6: 45504 | D6: July LinkedIn Management | E6: Alizé Amrani | F6: Delivered | G6: France | I6: 1 | J6: 1800 | M6: Sent | N6: F2024-0410 | O6: Payé | P6: 45568 | Q6: =TODAY() -> 46106
A7: ProcessOut | C7: 45535 | D7: August LinkedIn Management | E7: Alizé Amrani | F7: Delivered | G7: France | I7: 1 | J7: 1800 | M7: Sent | N7: F2024-0411 | O7: Payé | P7: 45568 | Q7: =TODAY() -> 46106
A8: ProcessOut | C8: 45463 | D8: ProcessOut Brochure (thank you card) | E8: Alizé Amrani | F8: Delivered | G8: France | H8: 20240820_ProcessOut Thank You Card Design - 4 pages | I8: 1 | J8: 400 | M8: Sent | N8: F2024-0412 | O8: Payé | P8: 45568 | Q8: =TODAY() -> 46106
A9: ProcessOut | C9: 45565 | D9: September LinkedIn Management | E9: Alizé Amrani | F9: Delivered | G9: France | I9: 1 | J9: FREE | K9: - | L9: - | M9: - | N9: - | O9: - | P9: - | Q9: -
A10: ProcessOut | C10: 45597 | D10: October LinkedIn Management | E10: Alizé Amrani | F10: Delivered | G10: France | H10: 20240927_ProcessOut - Linkedin Testimonial Graphic - Ankama | I10: 1 | J10: 1800 | M10: Sent | N10: F2024-0566 | O10: Payé | P10: 45639 | Q10: =TODAY() -> 46106
A11: ProcessOut | C11: 45627 | D11: November LinkedIn Management | E11: Alizé Amrani | F11: Delivered | G11: France | H11: 20240927_ProcessOut - Linkedin Testimonial Graphic - Ankama | I11: 1 | J11: 1800 | M11: Sent | N11: F2024-0665 | O11: Payé | P11: 45639
A12: ProcessOut | C12: 45627 | D12: December LinkedIn Management | E12: Alizé Amrani | F12: Delivered | G12: France | H12: 20240927_ProcessOut - Linkedin Testimonial Graphic - Ankama | I12: 1 | J12: 1800 | M12: Sent | N12: F2025-0100 | O12: Payé | P12: 45757
A13: ProcessOut | C13: 45658 | D13: January LinkedIn Management | E13: Alizé Amrani | F13: Delivered | G13: France | H13: 20240927_ProcessOut - Linkedin Testimonial Graphic - Ankama | I13: 1 | J13: 1800 | M13: Sent | N13: F2025-0100 | O13: Payé | P13: 45757
A14: ProcessOut | C14: 45689 | D14: February LinkedIn Management | E14: Alizé Amrani | F14: Delivered | G14: France | H14: 20240927_ProcessOut - Linkedin Testimonial Graphic - Ankama | I14: 1 | J14: 1800 | M14: Sent | N14: F2025-0100 | O14: Payé | P14: 45757
A15: ProcessOut | C15: 45717 | D15: March Part-Time CMO | E15: Alizé Amrani | F15: Delivered | G15: France | H15: 20240927_ProcessOut - Linkedin Testimonial Graphic - Ankama | I15: 1 | J15: 7000 | L15: #POFR019659 | M15: Sent | N15: F2025-0205 | O15: Payé | P15: 45779
A16: ProcessOut | C16: 45778 | D16: April Part-Time CMO | E16: Alizé Amrani | F16: Delivered | G16: France | H16: 20240927_ProcessOut - Linkedin Testimonial Graphic - Ankama | I16: 1 | J16: 7000 | L16: #POFR019659 | M16: Sent | N16: F2025-0265 | O16: Payé | P16: 45824
A17: ProcessOut | C17: 45806 | D17: May Part-Time CMO | E17: Alizé Amrani | F17: Delivered | G17: France | H17: 20240927_ProcessOut - Linkedin Testimonial Graphic - Ankama | I17: 1 | J17: 7000 | L17: #POFR019659 | M17: Sent | N17: F2025-0298 | O17: Payé | P17: 45842
A18: ProcessOut | C18: 45832 | D18: June Part-Time CMO | E18: Alizé Amrani | F18: Delivered | G18: France | H18: 20240927_ProcessOut - Linkedin Testimonial Graphic - Ankama | I18: 1 | J18: 7000 | L18: #POFR019659 | M18: Sent | N18: F2025-0357 | O18: Payé | P18: 45856
A19: ProcessOut | C19: 45862 | D19: July Part-Time CMO | E19: Alizé Amrani | F19: Delivered | G19: France | H19: 20240927_ProcessOut - Linkedin Testimonial Graphic - Ankama | I19: 1 | J19: 7000 | L19: #POFR019659 | M19: Sent | N19: F2025-0414 | O19: Payé | P19: 45911
A20: ProcessOut | C20: 45862 | D20: August Part-Time CMO | E20: Alizé Amrani | F20: Delivered | G20: France | H20: 20240927_ProcessOut - Linkedin Testimonial Graphic - Ankama | I20: 1 | J20: 7000 | L20: #POFR019659 | M20: Sent | N20: F2025-0530 | O20: Payé | P20: 45940
A21: ProcessOut | C21: 45893 | D21: September Part-Time CMO | E21: Alizé Amrani | F21: Delivered | G21: France | H21: 20240927_ProcessOut - Linkedin Testimonial Graphic - Ankama | I21: 1 | J21: 7000 | L21: #POFR019659 | M21: Sent | N21: F2025-0531 | O21: Payé | P21: 45940
A22: ProcessOut | C22: 45924 | D22: October Part-Time CMO | E22: Alizé Amrani | F22: Delivered | G22: France | H22: 20240927_ProcessOut - Linkedin Testimonial Graphic - Ankama | I22: 1 | J22: 7000 | L22: #POFR019659 | M22: Sent | N22: F2025-0626 | O22: Payé | P22: 45976
A23: ProcessOut | C23: 45924 | D23: November Part-Time CMO | E23: Alizé Amrani | F23: Delivered | G23: France | H23: 20240927_ProcessOut - Linkedin Testimonial Graphic - Ankama | I23: 1 | J23: 7000 | L23: POFR748 | M23: Sent | N23: F2025-0710 | O23: Payé | P23: 46031
A24: ProcessOut | C24: 45924 | D24: November extra | E24: Alizé Amrani | F24: Delivered | G24: France | H24: 20240927_ProcessOut - Linkedin Testimonial Graphic - Ankama | I24: 1 | J24: 450 | L24: POFR748 | M24: Sent | N24: F2025-0774 | O24: Payé | P24: 46101
A25: ProcessOut | C25: 45924 | D25: December Part-Time CMO | E25: Alizé Amrani | F25: Delivered | G25: France | H25: 20240927_ProcessOut - Linkedin Testimonial Graphic - Ankama | I25: 1 | J25: 7000 | L25: POFR748 | M25: Sent | N25: F2025-0800 | O25: En attente de paiement | P25: 46037
A26: ProcessOut | C26: 45924 | D26: December extra | E26: Alizé Amrani | F26: Delivered | G26: France | H26: 20240927_ProcessOut - Linkedin Testimonial Graphic - Ankama | I26: 1 | J26: 450 | L26: POFR748 | M26: Sent | N26: F2025-0834 | O26: Payé | P26: 46031
... A32: ProcessOut | C32: 46096 | D32: March extra | E32: Alizé Amrani | F32: Delivered | G32: France | H32: 20240927_ProcessOut - Linkedin Testimonial Graphic - Ankama | I32: 1 | J32: 450 | L32: #POFR2539 | M32: Sent | N32: F2026-0113 | O32: En attente de paiement | P32: 46127
A33: ProcessOut | C33: 46127 | D33: April Part-Time CMO | E33: Alizé Amrani | F33: Delivered | G33: France | H33: 20240927_ProcessOut - Linkedin Testimonial Graphic - Ankama | I33: 1 | J33: 7000 | L33: #POFR2539
A34: ProcessOut | C34: 46127 | D34: April extra | E34: Alizé Amrani | F34: Delivered | G34: France | H34: 20240927_ProcessOut - Linkedin Testimonial Graphic - Ankama | I34: 1 | J34: 450 | L34: #POFR2539
A35: ProcessOut | C35: 46157 | D35: May Part-Time CMO | E35: Alizé Amrani | F35: Delivered | G35: France | H35: 20240927_ProcessOut - Linkedin Testimonial Graphic - Ankama | I35: 1 | J35: 7000 | L35: #POFR2539
A36: ProcessOut | C36: 46157 | D36: May extra | E36: Alizé Amrani | F36: Delivered | G36: France | H36: 20240927_ProcessOut - Linkedin Testimonial Graphic - Ankama | I36: 1 | J36: 450 | L36: #POFR2539
A37: ProcessOut | C37: 46188 | D37: June Part-Time CMO | E37: Alizé Amrani | F37: Delivered | G37: France | H37: 20240927_ProcessOut - Linkedin Testimonial Graphic - Ankama | I37: 1 | J37: 7000 | L37: #POFR2539
A38: ProcessOut | C38: 46188 | D38: June extra | E38: Alizé Amrani | F38: Delivered | G38: France | H38: 20240927_ProcessOut - Linkedin Testimonial Graphic - Ankama | I38: 1 | J38: 450 | L38: #POFR2539
A39: ProcessOut | C39: 46218 | D39: July Part-Time CMO | E39: Alizé Amrani | F39: Delivered | G39: France | H39: 20240927_ProcessOut - Linkedin Testimonial Graphic - Ankama | I39: 1 | J39: 7000 | L39: #POFR2539
A40: ProcessOut | C40: 46218 | D40: July extra | E40: Alizé Amrani | F40: Delivered | G40: France | H40: 20240927_ProcessOut - Linkedin Testimonial Graphic - Ankama | I40: 1 | J40: 450 | L40: #POFR2539
A41: ProcessOut | C41: 46249 | D41: August Part-Time CMO | E41: Alizé Amrani | F41: Delivered | G41: France | H41: 20240927_ProcessOut - Linkedin Testimonial Graphic - Ankama | I41: 1 | J41: 7000 | L41: #POFR2539
A42: ProcessOut | C42: 46249 | D42: August extra | E42: Alizé Amrani | F42: Delivered | G42: France | H42: 20240927_ProcessOut - Linkedin Testimonial Graphic - Ankama | I42: 1 | J42: 450 | L42: #POFR2539
A43: ProcessOut | C43: 46280 | D43: September Part-Time CMO | E43: Alizé Amrani | F43: Delivered | G43: France | H43: 20240927_ProcessOut - Linkedin Testimonial Graphic - Ankama | I43: 1 | J43: 7000 | L43: #POFR2539
A44: ProcessOut | C44: 46280 | D44: September extra | E44: Alizé Amrani | F44: Delivered | G44: France | H44: 20240927_ProcessOut - Linkedin Testimonial Graphic - Ankama | I44: 1 | J44: 450 | L44: #POFR2539
A45: ProcessOut | C45: 46310 | D45: October Part-Time CMO | E45: Alizé Amrani | F45: Delivered | G45: France | H45: 20240927_ProcessOut - Linkedin Testimonial Graphic - Ankama | I45: 1 | J45: 7000
A46: ProcessOut | C46: 46310 | D46: October extra | E46: Alizé Amrani | F46: Delivered | G46: France | H46: 20240927_ProcessOut - Linkedin Testimonial Graphic - Ankama | I46: 1 | J46: 450
A47: ProcessOut | C47: 46341 | D47: November Part-Time CMO | E47: Alizé Amrani | F47: Delivered | G47: France | H47: 20240927_ProcessOut - Linkedin Testimonial Graphic - Ankama | I47: 1 | J47: 7000
A48: ProcessOut | C48: 46341 | D48: November extra | E48: Alizé Amrani | F48: Delivered | G48: France | H48: 20240927_ProcessOut - Linkedin Testimonial Graphic - Ankama | I48: 1 | J48: 450
A49: ProcessOut | C49: 46371 | D49: December Part-Time CMO | E49: Alizé Amrani | F49: Delivered | G49: France | H49: 20240927_ProcessOut - Linkedin Testimonial Graphic - Ankama | I49: 1 | J49: 7000
A50: ProcessOut | C50: 46371 | D50: December extra | E50: Alizé Amrani | F50: Delivered | G50: France | H50: 20240927_ProcessOut - Linkedin Testimonial Graphic - Ankama | I50: 1 | J50: 450
