Workbook

Sheet Overview
A1: Performance Dashboard — Sarani — Aristocrat
A3: REVENUS (€) | B3: 2022 | F3: 2023 | J3: 2024 | N3: 2025 | R3: 2026
B4: Q1 | C4: Q2 | D4: Q3 | E4: Q4 | F4: Q1 | G4: Q2 | H4: Q3 | I4: Q4 | J4: Q1 | K4: Q2 | L4: Q3 | M4: Q4 | N4: Q1 | O4: Q2 | P4: Q3 | Q4: Q4 | R4: Q1 | S4: Q2 | T4: Q3 | U4: Q4
A5: Aristocrat (US-EMEA) | B5: =SUMIFS('Aristocrat (US-EMEA)'!J$6:J$500,'Aristocrat (US-EMEA)'!C$6:C$500,">="&DATE(2022,1,1),'Aristocrat (US-EMEA)'!C$6:C$500,"<="&DATE(2022,3+1,1)-1) -> 0 | C5: =SUMIFS('Aristocrat (US-EMEA)'!J$6:J$500,'Aristocrat (US-EMEA)'!C$6:C$500,">="&DATE(2022,4,1),'Aristocrat (US-EMEA)'!C$6:C$500,"<="&DATE(2022,6+1,1)-1) -> 0 | D5: =SUMIFS('Aristocrat (US-EMEA)'!J$6:J$500,'Aristocrat (US-EMEA)'!C$6:C$500,">="&DATE(2022,7,1),'Aristocrat (US-EMEA)'!C$6:C$500,"<="&DATE(2022,9+1,1)-1) -> 0 | E5: =SUMIFS('Aristocrat (US-EMEA)'!J$6:J$500,'Aristocrat (US-EMEA)'!C$6:C$500,">="&DATE(2022,10,1),'Aristocrat (US-EMEA)'!C$6:C$500,"<="&DATE(2022,12+1,1)-1) -> 0 | F5: =SUMIFS('Aristocrat (US-EMEA)'!J$6:J$500,'Aristocrat (US-EMEA)'!C$6:C$500,">="&DATE(2023,1,1),'Aristocrat (US-EMEA)'!C$6:C$500,"<="&DATE(2023,3+1,1)-1) -> 0 | G5: =SUMIFS('Aristocrat (US-EMEA)'!J$6:J$500,'Aristocrat (US-EMEA)'!C$6:C$500,">="&DATE(2023,4,1),'Aristocrat (US-EMEA)'!C$6:C$500,"<="&DATE(2023,6+1,1)-1) -> 0 | H5: =SUMIFS('Aristocrat (US-EMEA)'!J$6:J$500,'Aristocrat (US-EMEA)'!C$6:C$500,">="&DATE(2023,7,1),'Aristocrat (US-EMEA)'!C$6:C$500,"<="&DATE(2023,9+1,1)-1) -> 0 | I5: =SUMIFS('Aristocrat (US-EMEA)'!J$6:J$500,'Aristocrat (US-EMEA)'!C$6:C$500,">="&DATE(2023,10,1),'Aristocrat (US-EMEA)'!C$6:C$500,"<="&DATE(2023,12+1,1)-1) -> 0 | J5: =SUMIFS('Aristocrat (US-EMEA)'!J$6:J$500,'Aristocrat (US-EMEA)'!C$6:C$500,">="&DATE(2024,1,1),'Aristocrat (US-EMEA)'!C$6:C$500,"<="&DATE(2024,3+1,1)-1) -> 244.88 | K5: =SUMIFS('Aristocrat (US-EMEA)'!J$6:J$500,'Aristocrat (US-EMEA)'!C$6:C$500,">="&DATE(2024,4,1),'Aristocrat (US-EMEA)'!C$6:C$500,"<="&DATE(2024,6+1,1)-1) -> 5558.1 | L5: =SUMIFS('Aristocrat (US-EMEA)'!J$6:J$500,'Aristocrat (US-EMEA)'!C$6:C$500,">="&DATE(2024,7,1),'Aristocrat (US-EMEA)'!C$6:C$500,"<="&DATE(2024,9+1,1)-1) -> 2740.32 | M5: =SUMIFS('Aristocrat (US-EMEA)'!J$6:J$500,'Aristocrat (US-EMEA)'!C$6:C$500,">="&DATE(2024,10,1),'Aristocrat (US-EMEA)'!C$6:C$500,"<="&DATE(2024,12+1,1)-1) -> 4504.52 | N5: =SUMIFS('Aristocrat (US-EMEA)'!J$6:J$500,'Aristocrat (US-EMEA)'!C$6:C$500,">="&DATE(2025,1,1),'Aristocrat (US-EMEA)'!C$6:C$500,"<="&DATE(2025,3+1,1)-1) -> 7910.4 | O5: =SUMIFS('Aristocrat (US-EMEA)'!J$6:J$500,'Aristocrat (US-EMEA)'!C$6:C$500,">="&DATE(2025,4,1),'Aristocrat (US-EMEA)'!C$6:C$500,"<="&DATE(2025,6+1,1)-1) -> 4827.5 | P5: =SUMIFS('Aristocrat (US-EMEA)'!J$6:J$500,'Aristocrat (US-EMEA)'!C$6:C$500,">="&DATE(2025,7,1),'Aristocrat (US-EMEA)'!C$6:C$500,"<="&DATE(2025,9+1,1)-1) -> 91323.6 | Q5: =SUMIFS('Aristocrat (US-EMEA)'!J$6:J$500,'Aristocrat (US-EMEA)'!C$6:C$500,">="&DATE(2025,10,1),'Aristocrat (US-EMEA)'!C$6:C$500,"<="&DATE(2025,12+1,1)-1) -> 31029.84 | R5: =SUMIFS('Aristocrat (US-EMEA)'!J$6:J$500,'Aristocrat (US-EMEA)'!C$6:C$500,">="&DATE(2026,1,1),'Aristocrat (US-EMEA)'!C$6:C$500,"<="&DATE(2026,3+1,1)-1) -> 13652.28 | S5: =SUMIFS('Aristocrat (US-EMEA)'!J$6:J$500,'Aristocrat (US-EMEA)'!C$6:C$500,">="&DATE(2026,4,1),'Aristocrat (US-EMEA)'!C$6:C$500,"<="&DATE(2026,6+1,1)-1) -> 0 | T5: =SUMIFS('Aristocrat (US-EMEA)'!J$6:J$500,'Aristocrat (US-EMEA)'!C$6:C$500,">="&DATE(2026,7,1),'Aristocrat (US-EMEA)'!C$6:C$500,"<="&DATE(2026,9+1,1)-1) -> 0 | U5: =SUMIFS('Aristocrat (US-EMEA)'!J$6:J$500,'Aristocrat (US-EMEA)'!C$6:C$500,">="&DATE(2026,10,1),'Aristocrat (US-EMEA)'!C$6:C$500,"<="&DATE(2026,12+1,1)-1) -> 0
A6: Aristocrat (Asia) — conv. € | B6: =SUMIFS('Aristocrat (Asia)'!J$6:J$500,'Aristocrat (Asia)'!C$6:C$500,">="&DATE(2022,1,1),'Aristocrat (Asia)'!C$6:C$500,"<="&DATE(2022,3+1,1)-1)/$B$20 -> 0 | C6: =SUMIFS('Aristocrat (Asia)'!J$6:J$500,'Aristocrat (Asia)'!C$6:C$500,">="&DATE(2022,4,1),'Aristocrat (Asia)'!C$6:C$500,"<="&DATE(2022,6+1,1)-1)/$B$20 -> 0 | D6: =SUMIFS('Aristocrat (Asia)'!J$6:J$500,'Aristocrat (Asia)'!C$6:C$500,">="&DATE(2022,7,1),'Aristocrat (Asia)'!C$6:C$500,"<="&DATE(2022,9+1,1)-1)/$B$20 -> 0 | E6: =SUMIFS('Aristocrat (Asia)'!J$6:J$500,'Aristocrat (Asia)'!C$6:C$500,">="&DATE(2022,10,1),'Aristocrat (Asia)'!C$6:C$500,"<="&DATE(2022,12+1,1)-1)/$B$20 -> 0 | F6: =SUMIFS('Aristocrat (Asia)'!J$6:J$500,'Aristocrat (Asia)'!C$6:C$500,">="&DATE(2023,1,1),'Aristocrat (Asia)'!C$6:C$500,"<="&DATE(2023,3+1,1)-1)/$B$20 -> 0 | G6: =SUMIFS('Aristocrat (Asia)'!J$6:J$500,'Aristocrat (Asia)'!C$6:C$500,">="&DATE(2023,4,1),'Aristocrat (Asia)'!C$6:C$500,"<="&DATE(2023,6+1,1)-1)/$B$20 -> 0 | H6: =SUMIFS('Aristocrat (Asia)'!J$6:J$500,'Aristocrat (Asia)'!C$6:C$500,">="&DATE(2023,7,1),'Aristocrat (Asia)'!C$6:C$500,"<="&DATE(2023,9+1,1)-1)/$B$20 -> 0 | I6: =SUMIFS('Aristocrat (Asia)'!J$6:J$500,'Aristocrat (Asia)'!C$6:C$500,">="&DATE(2023,10,1),'Aristocrat (Asia)'!C$6:C$500,"<="&DATE(2023,12+1,1)-1)/$B$20 -> 0 | J6: =SUMIFS('Aristocrat (Asia)'!J$6:J$500,'Aristocrat (Asia)'!C$6:C$500,">="&DATE(2024,1,1),'Aristocrat (Asia)'!C$6:C$500,"<="&DATE(2024,3+1,1)-1)/$B$20 -> 0 | K6: =SUMIFS('Aristocrat (Asia)'!J$6:J$500,'Aristocrat (Asia)'!C$6:C$500,">="&DATE(2024,4,1),'Aristocrat (Asia)'!C$6:C$500,"<="&DATE(2024,6+1,1)-1)/$B$20 -> 0 | L6: =SUMIFS('Aristocrat (Asia)'!J$6:J$500,'Aristocrat (Asia)'!C$6:C$500,">="&DATE(2024,7,1),'Aristocrat (Asia)'!C$6:C$500,"<="&DATE(2024,9+1,1)-1)/$B$20 -> 0 | M6: =SUMIFS('Aristocrat (Asia)'!J$6:J$500,'Aristocrat (Asia)'!C$6:C$500,">="&DATE(2024,10,1),'Aristocrat (Asia)'!C$6:C$500,"<="&DATE(2024,12+1,1)-1)/$B$20 -> 0 | N6: =SUMIFS('Aristocrat (Asia)'!J$6:J$500,'Aristocrat (Asia)'!C$6:C$500,">="&DATE(2025,1,1),'Aristocrat (Asia)'!C$6:C$500,"<="&DATE(2025,3+1,1)-1)/$B$20 -> 0 | O6: =SUMIFS('Aristocrat (Asia)'!J$6:J$500,'Aristocrat (Asia)'!C$6:C$500,">="&DATE(2025,4,1),'Aristocrat (Asia)'!C$6:C$500,"<="&DATE(2025,6+1,1)-1)/$B$20 -> 0 | P6: =SUMIFS('Aristocrat (Asia)'!J$6:J$500,'Aristocrat (Asia)'!C$6:C$500,">="&DATE(2025,7,1),'Aristocrat (Asia)'!C$6:C$500,"<="&DATE(2025,9+1,1)-1)/$B$20 -> 0 | Q6: =SUMIFS('Aristocrat (Asia)'!J$6:J$500,'Aristocrat (Asia)'!C$6:C$500,">="&DATE(2025,10,1),'Aristocrat (Asia)'!C$6:C$500,"<="&DATE(2025,12+1,1)-1)/$B$20 -> 1408.6957 | R6: =SUMIFS('Aristocrat (Asia)'!J$6:J$500,'Aristocrat (Asia)'!C$6:C$500,">="&DATE(2026,1,1),'Aristocrat (Asia)'!C$6:C$500,"<="&DATE(2026,3+1,1)-1)/$B$20 -> 8986.9565 | S6: =SUMIFS('Aristocrat (Asia)'!J$6:J$500,'Aristocrat (Asia)'!C$6:C$500,">="&DATE(2026,4,1),'Aristocrat (Asia)'!C$6:C$500,"<="&DATE(2026,6+1,1)-1)/$B$20 -> 0 | T6: =SUMIFS('Aristocrat (Asia)'!J$6:J$500,'Aristocrat (Asia)'!C$6:C$500,">="&DATE(2026,7,1),'Aristocrat (Asia)'!C$6:C$500,"<="&DATE(2026,9+1,1)-1)/$B$20 -> 0 | U6: =SUMIFS('Aristocrat (Asia)'!J$6:J$500,'Aristocrat (Asia)'!C$6:C$500,">="&DATE(2026,10,1),'Aristocrat (Asia)'!C$6:C$500,"<="&DATE(2026,12+1,1)-1)/$B$20 -> 0
A7: TOTAL | B7: =SUM(B5:B6) -> 0 | C7: =SUM(C5:C6) -> 0 | D7: =SUM(D5:D6) -> 0 | E7: =SUM(E5:E6) -> 0 | F7: =SUM(F5:F6) -> 0 | G7: =SUM(G5:G6) -> 0 | H7: =SUM(H5:H6) -> 0 | I7: =SUM(I5:I6) -> 0 | ... U7: =SUM(U5:U6) -> 0
A9: NOMBRE DE PROJETS | B9: 2022 | F9: 2023 | J9: 2024 | N9: 2025 | R9: 2026
B10: Q1 | C10: Q2 | D10: Q3 | E10: Q4 | F10: Q1 | G10: Q2 | H10: Q3 | I10: Q4 | J10: Q1 | K10: Q2 | L10: Q3 | M10: Q4 | N10: Q1 | O10: Q2 | P10: Q3 | Q10: Q4 | R10: Q1 | S10: Q2 | T10: Q3 | U10: Q4
A11: Aristocrat (US-EMEA) | B11: =COUNTIFS('Aristocrat (US-EMEA)'!C$6:C$500,">="&DATE(2022,1,1),'Aristocrat (US-EMEA)'!C$6:C$500,"<="&DATE(2022,3+1,1)-1) -> 0 | C11: =COUNTIFS('Aristocrat (US-EMEA)'!C$6:C$500,">="&DATE(2022,4,1),'Aristocrat (US-EMEA)'!C$6:C$500,"<="&DATE(2022,6+1,1)-1) -> 0 | D11: =COUNTIFS('Aristocrat (US-EMEA)'!C$6:C$500,">="&DATE(2022,7,1),'Aristocrat (US-EMEA)'!C$6:C$500,"<="&DATE(2022,9+1,1)-1) -> 0 | E11: =COUNTIFS('Aristocrat (US-EMEA)'!C$6:C$500,">="&DATE(2022,10,1),'Aristocrat (US-EMEA)'!C$6:C$500,"<="&DATE(2022,12+1,1)-1) -> 0 | F11: =COUNTIFS('Aristocrat (US-EMEA)'!C$6:C$500,">="&DATE(2023,1,1),'Aristocrat (US-EMEA)'!C$6:C$500,"<="&DATE(2023,3+1,1)-1) -> 0 | G11: =COUNTIFS('Aristocrat (US-EMEA)'!C$6:C$500,">="&DATE(2023,4,1),'Aristocrat (US-EMEA)'!C$6:C$500,"<="&DATE(2023,6+1,1)-1) -> 0 | H11: =COUNTIFS('Aristocrat (US-EMEA)'!C$6:C$500,">="&DATE(2023,7,1),'Aristocrat (US-EMEA)'!C$6:C$500,"<="&DATE(2023,9+1,1)-1) -> 0 | I11: =COUNTIFS('Aristocrat (US-EMEA)'!C$6:C$500,">="&DATE(2023,10,1),'Aristocrat (US-EMEA)'!C$6:C$500,"<="&DATE(2023,12+1,1)-1) -> 0 | J11: =COUNTIFS('Aristocrat (US-EMEA)'!C$6:C$500,">="&DATE(2024,1,1),'Aristocrat (US-EMEA)'!C$6:C$500,"<="&DATE(2024,3+1,1)-1) -> 5 | K11: =COUNTIFS('Aristocrat (US-EMEA)'!C$6:C$500,">="&DATE(2024,4,1),'Aristocrat (US-EMEA)'!C$6:C$500,"<="&DATE(2024,6+1,1)-1) -> 13 | L11: =COUNTIFS('Aristocrat (US-EMEA)'!C$6:C$500,">="&DATE(2024,7,1),'Aristocrat (US-EMEA)'!C$6:C$500,"<="&DATE(2024,9+1,1)-1) -> 15 | M11: =COUNTIFS('Aristocrat (US-EMEA)'!C$6:C$500,">="&DATE(2024,10,1),'Aristocrat (US-EMEA)'!C$6:C$500,"<="&DATE(2024,12+1,1)-1) -> 12 | N11: =COUNTIFS('Aristocrat (US-EMEA)'!C$6:C$500,">="&DATE(2025,1,1),'Aristocrat (US-EMEA)'!C$6:C$500,"<="&DATE(2025,3+1,1)-1) -> 6 | O11: =COUNTIFS('Aristocrat (US-EMEA)'!C$6:C$500,">="&DATE(2025,4,1),'Aristocrat (US-EMEA)'!C$6:C$500,"<="&DATE(2025,6+1,1)-1) -> 7 | P11: =COUNTIFS('Aristocrat (US-EMEA)'!C$6:C$500,">="&DATE(2025,7,1),'Aristocrat (US-EMEA)'!C$6:C$500,"<="&DATE(2025,9+1,1)-1) -> 20 | Q11: =COUNTIFS('Aristocrat (US-EMEA)'!C$6:C$500,">="&DATE(2025,10,1),'Aristocrat (US-EMEA)'!C$6:C$500,"<="&DATE(2025,12+1,1)-1) -> 30 | R11: =COUNTIFS('Aristocrat (US-EMEA)'!C$6:C$500,">="&DATE(2026,1,1),'Aristocrat (US-EMEA)'!C$6:C$500,"<="&DATE(2026,3+1,1)-1) -> 16 | S11: =COUNTIFS('Aristocrat (US-EMEA)'!C$6:C$500,">="&DATE(2026,4,1),'Aristocrat (US-EMEA)'!C$6:C$500,"<="&DATE(2026,6+1,1)-1) -> 0 | T11: =COUNTIFS('Aristocrat (US-EMEA)'!C$6:C$500,">="&DATE(2026,7,1),'Aristocrat (US-EMEA)'!C$6:C$500,"<="&DATE(2026,9+1,1)-1) -> 0 | U11: =COUNTIFS('Aristocrat (US-EMEA)'!C$6:C$500,">="&DATE(2026,10,1),'Aristocrat (US-EMEA)'!C$6:C$500,"<="&DATE(2026,12+1,1)-1) -> 0
A12: Aristocrat (Asia) | B12: =COUNTIFS('Aristocrat (Asia)'!C$6:C$500,">="&DATE(2022,1,1),'Aristocrat (Asia)'!C$6:C$500,"<="&DATE(2022,3+1,1)-1) -> 0 | C12: =COUNTIFS('Aristocrat (Asia)'!C$6:C$500,">="&DATE(2022,4,1),'Aristocrat (Asia)'!C$6:C$500,"<="&DATE(2022,6+1,1)-1) -> 0 | D12: =COUNTIFS('Aristocrat (Asia)'!C$6:C$500,">="&DATE(2022,7,1),'Aristocrat (Asia)'!C$6:C$500,"<="&DATE(2022,9+1,1)-1) -> 0 | E12: =COUNTIFS('Aristocrat (Asia)'!C$6:C$500,">="&DATE(2022,10,1),'Aristocrat (Asia)'!C$6:C$500,"<="&DATE(2022,12+1,1)-1) -> 0 | F12: =COUNTIFS('Aristocrat (Asia)'!C$6:C$500,">="&DATE(2023,1,1),'Aristocrat (Asia)'!C$6:C$500,"<="&DATE(2023,3+1,1)-1) -> 0 | G12: =COUNTIFS('Aristocrat (Asia)'!C$6:C$500,">="&DATE(2023,4,1),'Aristocrat (Asia)'!C$6:C$500,"<="&DATE(2023,6+1,1)-1) -> 0 | H12: =COUNTIFS('Aristocrat (Asia)'!C$6:C$500,">="&DATE(2023,7,1),'Aristocrat (Asia)'!C$6:C$500,"<="&DATE(2023,9+1,1)-1) -> 0 | I12: =COUNTIFS('Aristocrat (Asia)'!C$6:C$500,">="&DATE(2023,10,1),'Aristocrat (Asia)'!C$6:C$500,"<="&DATE(2023,12+1,1)-1) -> 0 | J12: =COUNTIFS('Aristocrat (Asia)'!C$6:C$500,">="&DATE(2024,1,1),'Aristocrat (Asia)'!C$6:C$500,"<="&DATE(2024,3+1,1)-1) -> 0 | K12: =COUNTIFS('Aristocrat (Asia)'!C$6:C$500,">="&DATE(2024,4,1),'Aristocrat (Asia)'!C$6:C$500,"<="&DATE(2024,6+1,1)-1) -> 0 | L12: =COUNTIFS('Aristocrat (Asia)'!C$6:C$500,">="&DATE(2024,7,1),'Aristocrat (Asia)'!C$6:C$500,"<="&DATE(2024,9+1,1)-1) -> 0 | M12: =COUNTIFS('Aristocrat (Asia)'!C$6:C$500,">="&DATE(2024,10,1),'Aristocrat (Asia)'!C$6:C$500,"<="&DATE(2024,12+1,1)-1) -> 0 | N12: =COUNTIFS('Aristocrat (Asia)'!C$6:C$500,">="&DATE(2025,1,1),'Aristocrat (Asia)'!C$6:C$500,"<="&DATE(2025,3+1,1)-1) -> 0 | O12: =COUNTIFS('Aristocrat (Asia)'!C$6:C$500,">="&DATE(2025,4,1),'Aristocrat (Asia)'!C$6:C$500,"<="&DATE(2025,6+1,1)-1) -> 0 | P12: =COUNTIFS('Aristocrat (Asia)'!C$6:C$500,">="&DATE(2025,7,1),'Aristocrat (Asia)'!C$6:C$500,"<="&DATE(2025,9+1,1)-1) -> 0 | Q12: =COUNTIFS('Aristocrat (Asia)'!C$6:C$500,">="&DATE(2025,10,1),'Aristocrat (Asia)'!C$6:C$500,"<="&DATE(2025,12+1,1)-1) -> 3 | R12: =COUNTIFS('Aristocrat (Asia)'!C$6:C$500,">="&DATE(2026,1,1),'Aristocrat (Asia)'!C$6:C$500,"<="&DATE(2026,3+1,1)-1) -> 4 | S12: =COUNTIFS('Aristocrat (Asia)'!C$6:C$500,">="&DATE(2026,4,1),'Aristocrat (Asia)'!C$6:C$500,"<="&DATE(2026,6+1,1)-1) -> 0 | T12: =COUNTIFS('Aristocrat (Asia)'!C$6:C$500,">="&DATE(2026,7,1),'Aristocrat (Asia)'!C$6:C$500,"<="&DATE(2026,9+1,1)-1) -> 0 | U12: =COUNTIFS('Aristocrat (Asia)'!C$6:C$500,">="&DATE(2026,10,1),'Aristocrat (Asia)'!C$6:C$500,"<="&DATE(2026,12+1,1)-1) -> 0
A13: TOTAL | B13: =SUM(B11:B12) -> 0 | C13: =SUM(C11:C12) -> 0 | D13: =SUM(D11:D12) -> 0 | E13: =SUM(E11:E12) -> 0 | F13: =SUM(F11:F12) -> 0 | G13: =SUM(G11:G12) -> 0 | H13: =SUM(H11:H12) -> 0 | I13: =SUM(I11:I12) -> 0 | ... U13: =SUM(U11:U12) -> 0
A15: SYNTHÈSE ANNUELLE | B15: 2022 | C15: 2023 | D15: 2024 | E15: 2025 | F15: 2026
A16: Revenus (€) | B16: =SUM(B7:E7) -> 0 | C16: =SUM(F7:I7) -> 0 | D16: =SUM(J7:M7) -> 13047.82 | E16: =SUM(N7:Q7) -> 136500.04 | F16: =SUM(R7:U7) -> 22639.237
A17: Projets | B17: =SUM(B13:E13) -> 0 | C17: =SUM(F13:I13) -> 0 | D17: =SUM(J13:M13) -> 45 | E17: =SUM(N13:Q13) -> 66 | F17: =SUM(R13:U13) -> 20
A18: Rev. / Projet (€) | B18: =IFERROR(B16/B17,"—") -> — | C18: =IFERROR(C16/C17,"—") -> — | D18: =IFERROR(D16/D17,"—") -> 289.95156 | E18: =IFERROR(E16/E17,"—") -> 2068.1824 | F18: =IFERROR(F16/F17,"—") -> 1131.9618
A20: Taux de change (1€ = x $) | B20: 1.15

Sheet Aristocrat (US-EMEA)
J1: =SUBTOTAL(2,J6:J20065) -> 124 | P1: =SUBTOTAL(2,P6:P20065) -> 7 | Q1: =SUBTOTAL(2,Q6:Q20065) -> 35 | R1: =SUBTOTAL(2,R6:R20065) -> 0 | S1: =SUBTOTAL(2,S6:S20065) -> 0 | T1: =SUBTOTAL(2,T6:T20065) -> 0 | U1: =SUBTOTAL(2,U6:U20065) -> 0 | V1: =SUBTOTAL(2,V6:V20065) -> 0 | W1: =SUBTOTAL(2,W6:W20065) -> 0 | ... AT1: =SUBTOTAL(2,AT6:AT20065) -> 17
I2: =SUBTOTAL(9,I6:I20066) -> 116261 | J2: =SUBTOTAL(9,J6:J20066) -> 214352.76 | P2: =SUBTOTAL(9,P6:P20066)*P5 -> 1755 | Q2: =SUBTOTAL(9,Q6:Q20066)*Q5 -> 3090 | R2: =SUBTOTAL(9,R6:R20066)*R5 -> 0 | S2: =SUBTOTAL(9,S6:S20066)*S5 -> 0 | T2: =SUBTOTAL(9,T6:T20066)*T5 -> 0 | U2: =SUBTOTAL(9,U6:U20066)*U5 -> 0 | V2: =SUBTOTAL(9,V6:V20066)*V5 -> 0 | W2: =SUBTOTAL(9,W6:W20066)*W5 -> 0 | ... AT2: =SUBTOTAL(9,AT6:AT20066)*AT5 -> 1283
A3: Price File | P3: Online | X3: Offline | AE3: Presentations | AF3: Web | AJ3: Videos | AQ3: Virtualization | AS3: Copy
A4: Project | E4: Details | P4: Banner creation (static) | Q4: Banner adaptation (static) | R4: Banner creation (animated) | S4: Banner adaptation (animated) | T4: Buttons | U4: Logo | V4: Lifestyle Picture | W4: Wallpapers | X4: Offline creation (standard) | Y4: Offline creation (adaptation) | Z4: Leaflet (1 page) | AA4: Leaflet (2 pages) | AB4: Roll-up / Wall creation | AC4: Chart | AD4: Brochure (20 pages) | AE4: Slide | AF4: Landing page (design only) | AG4: Landing page (complete) | AH4: Website (design only) | AI4: Website (complete) | AJ4: Video Edition | AK4: Video Subtitles / Adaptations | AL4: Social Media Video (up to 30s) | AM4: Social Media Video (up to 1 min) | AN4: Promotional Video (up to 1 min) | AO4: 2D Video (up to 3mn) | AP4: 3D Video (up to 3min) | AQ4: Virtual space | AR4: Virtual showroom | AS4: Translation (per word) | AT4: Transcription (per word)
A5: Customer | B5: Division | C5: Date | D5: Project | E5: Contact | F5: Status | G5: Category | H5: Link | I5: Assets | J5: Total Value | K5: Quote | L5: PO | M5: Invoice | N5: n° Invoice | O5: Statut | P5: 135 | Q5: 30 | R5: 220 | S5: 50 | T5: 15 | U5: 250 | V5: 400 | W5: 85 | X5: 135 | Y5: 30 | Z5: 180 | AA5: 260 | AB5: 180 | AC5: 400 | AD5: 2200 | AE5: 35 | AF5: 300 | AG5: 700 | AH5: 5000 | AI5: 7000 | AJ5: 80 | AK5: 150 | AL5: 260 | AM5: 360 | AN5: 4000 | AO5: 5000 | AP5: 10000 | AQ5: 2500 | AR5: 10000 | AS5: 0.12 | AT5: 0.25
A6: Aristocrat | B6: EMEA | C6: 45302 | D6: Pilot Test Translations | E6: Daniel Browne | F6: Delivered | G6: EMEA | H6: https://saranistudio.sharepoint.com/:f:/s/SaraniAssets/EicHqBO9GotOltf9BORHCJIBc712FqijUq_259gQluFAoA?e=Jiivi4 | I6: 3 | J6: - | K6: NO INVOICE | AS6: 235 | AT6: 80
A7: Aristocrat | B7: EMEA | C7: 45303 | D7: Communiqué de presse ICE 2024 | E7: Daniel Browne | F7: Delivered | G7: EMEA | H7: https://saranistudio.sharepoint.com/:f:/s/SaraniAssets/EjVCi8Y81g5PsgKtjsrg0DIBy6kA-oKjBf_SGQZ9FG3gIQ?e=9wYSQo | I7: 1 | J7: =IF(SUMPRODUCT($P$5:$AU$5,P7:AU7)=0,"-",SUMPRODUCT($P$5:$AU$5,P7:AU7)) -> 120 | K7: - | L7: - | M7: Sent to Thomas | N7: F2024-0176 | O7: Paid 28/05/2024 | AS7: 1000
A8: Aristocrat | B8: EMEA | C8: 45317 | D8: Présentation Carnival Jackpot | E8: Daniel Browne | F8: Delivered | G8: EMEA | H8: https://saranistudio.sharepoint.com/:f:/s/SaraniAssets/ElFltiSBIpREjdA77uLJRYYBlz8fUYn92zg2K6e1A4XqqQ?e=lt6xeh | I8: 1 | J8: =IF(SUMPRODUCT($P$5:$AU$5,P8:AU8)=0,"-",SUMPRODUCT($P$5:$AU$5,P8:AU8)) -> 92 | K8: - | L8: - | M8: Sent to Thomas | N8: F2024-0176 | O8: Paid 28/05/2024 | AT8: 368
A9: Aristocrat | B9: USA | C9: 45327 | D9: 12.23 E-Blast V1_FR | E9: Megan Nimsgern | F9: Delivered | G9: USA | H9: https://saranistudio.sharepoint.com/:f:/s/SaraniAssets/ElyIX3Mo7jBAu6K49clJcLkB3uYPq9Ekqat5KsoijNSwEQ?e=Dgbppz | I9: 1 | J9: =IF(SUMPRODUCT($P$5:$AU$5,P9:AU9)=0,"-",SUMPRODUCT($P$5:$AU$5,P9:AU9)) -> 27.6 | K9: - | L9: - | M9: Sent to Thomas | N9: F2024-0176 | O9: Paid 28/05/2024 | AS9: 230
A10: Aristocrat | B10: USA | C10: 45364 | D10: Know Your Max - Welcome to Max HQ | E10: Megan Nimsgern | F10: Delivered | G10: USA | H10: https://saranistudio.sharepoint.com/:w:/s/SaraniAssets/Eck7LNoSSKRJhKCa-vUyWZMBWUpF6UToorC9K1p-89QEkw?e=641Qfg | I10: =IF(SUM(P10:AU10)=0,"-",SUM(P10:AU10)) -> 44 | J10: =IF(SUMPRODUCT($P$5:$AU$5,P10:AU10)=0,"-",SUMPRODUCT($P$5:$AU$5,P10:AU10)) -> 5.28 | K10: - | L10: - | M10: Sent to Thomas | N10: F2024-0176 | O10: Paid 28/05/2024 | AS10: 44
A11: Aristocrat | B11: EMEA | C11: 45387 | D11: Hungarian translations | E11: Lauen Feiner | F11: Delivered | G11: EMEA | H11: https://saranistudio.sharepoint.com/:f:/s/SaraniAssets/EsjQHFLgoTRJhu_jtLNpEHcBr5y8GcgOaH8eq1tt8JljCw?e=iqr6dx | I11: 12 | J11: 2750 | K11: - | L11: - | M11: Sent to Thomas | N11: F2024-0175 | O11: Paid 28/05/2024 | AS11: =7767+1951+1951+4739+4697+7754+2428+3121 -> 34408
A12: Aristocrat | B12: USA | C12: 45400 | D12: Dragon Link Page Advertising | E12: Megan Nimsgern | F12: Delivered | G12: USA | H12: https://saranistudio.sharepoint.com/:f:/s/SaraniAssets/EgV4wqclurVAjk8QfT1zRi4BWj5py5IHEgtvzYHjmD5wug?e=qHNSPI | I12: =IF(SUM(P12:AU12)=0,"-",SUM(P12:AU12)) -> 155 | J12: =IF(SUMPRODUCT($P$5:$AU$5,P12:AU12)=0,"-",SUMPRODUCT($P$5:$AU$5,P12:AU12)) -> 38.75 | K12: - | L12: - | M12: Sent to Thomas | N12: F2024-0176 | O12: Paid 28/05/2024 | AT12: 155
A13: Aristocrat | B13: USA | C13: 45400 | D13: Joy Presentation | E13: Megan Nimsgern | F13: Delivered | G13: USA | H13: 20240418_Dragon Link Page Advertising | I13: =IF(SUM(P13:AU13)=0,"-",SUM(P13:AU13)) -> 700 | J13: =IF(SUMPRODUCT($P$5:$AU$5,P13:AU13)=0,"-",SUMPRODUCT($P$5:$AU$5,P13:AU13)) -> 84 | K13: - | L13: - | M13: Sent to Thomas | N13: F2024-0176 | O13: Paid 28/05/2024 | AS13: 700
A14: Aristocrat | B14: USA | C14: 45400 | D14: Updating Dragon Link Photos | E14: Megan Nimsgern | F14: Delivered | G14: USA | H14: https://saranistudio.sharepoint.com/:f:/s/SaraniAssets/Eqha9ofIjoZPr1TIu2A69sMB4vKH3PjJO7zUgKsc2yJ0Ow?e=RWbeeV | I14: =IF(SUM(P14:AU14)=0,"-",SUM(P14:AU14)) -> 3 | J14: =IF(SUMPRODUCT($P$5:$AU$5,P14:AU14)=0,"-",SUMPRODUCT($P$5:$AU$5,P14:AU14)) -> 90 | K14: - | L14: - | M14: Sent to Thomas | N14: F2024-0176 | O14: Paid 28/05/2024 | Q14: 3
A15: Aristocrat | B15: EMEA | C15: 45405 | D15: Dragon Link Ads | E15: Daniel Browne | F15: Delivered | G15: EMEA | H15: https://saranistudio.sharepoint.com/:f:/s/SaraniAssets/ErUH4AT3xKZIiF2P4aB6THEB3fERlJB2gaIl9dYmZrPU0A?e=YqoR1K | I15: =IF(SUM(P15:AU15)=0,"-",SUM(P15:AU15)) -> 1 | J15: =IF(SUMPRODUCT($P$5:$AU$5,P15:AU15)=0,"-",SUMPRODUCT($P$5:$AU$5,P15:AU15)) -> 30 | K15: - | L15: - | M15: Sent to Thomas | N15: F2024-0257 | O15: Paid 05/07/2024 | Q15: 1
A16: Aristocrat | B16: EMEA | C16: 45411 | D16: Cashman Double Bingo Sun & Moon | E16: Gustavo Vessani | F16: Delivered | G16: EMEA | H16: https://saranistudio.sharepoint.com/:f:/s/SaraniAssets/El6ehHV_24RBn9ZgNxvKNSoBtEqrSmA3EEm-Zb8LYcWBPA?e=DeQugO | I16: =IF(SUM(P16:AU16)=0,"-",SUM(P16:AU16)) -> 1017 | J16: 122 | K16: - | L16: - | M16: Sent to Thomas | N16: F2024-0196 | O16: Paid 28/05/2024 | AS16: 1017
A17: Aristocrat | B17: USA | C17: 45433 | D17: French Game Rules - Translations | E17: Megan Nimsgern | F17: Delivered | G17: USA | H17: https://saranistudio.sharepoint.com/:f:/s/SaraniAssets/EnroNK7W9i5Mivv8g4hJkS4BD2zqxvkMcEhH6ksZ0EQJRQ?e=1SKKur | I17: =IF(SUM(P17:AU17)=0,"-",SUM(P17:AU17)) -> 17330 | J17: =IF(SUMPRODUCT($P$5:$AU$5,P17:AU17)=0,"-",SUMPRODUCT($P$5:$AU$5,P17:AU17)) -> 2079.6 | K17: - | L17: - | M17: Sent to Thomas | N17: F2024-0257 | O17: Paid 05/07/2024 | AS17: =2575+2811+664+665+745+747+2113+2115+1232+1229+1217+1217 -> 17330
A18: Aristocrat | B18: USA | C18: 45443 | D18: Peru Gaming Show | E18: Megan Nimsgern | F18: Delivered | G18: USA | H18: https://saranistudio.sharepoint.com/:f:/s/SaraniAssets/EowvOfwr33BMj-fQq9knBvcBnaujdRAc2b1WcprDqcBzhg?e=fwvcPN | I18: =IF(SUM(P18:AU18)=0,"-",SUM(P18:AU18)) -> 430 | J18: =IF(SUMPRODUCT($P$5:$AU$5,P18:AU18)=0,"-",SUMPRODUCT($P$5:$AU$5,P18:AU18)) -> 107.5 | K18: - | L18: - | M18: Sent to Thomas | N18: F2024-0257 | O18: Paid 05/07/2024 | AT18: 430
A19: Aristocrat | B19: USA | C19: 45456 | D19: Trilenium SP | E19: Megan Nimsgern | F19: Delivered | G19: USA | H19: https://saranistudio.sharepoint.com/:f:/s/SaraniAssets/EnIC2ND_-IhLtuOmQ0ywYuEB6r7gGkvOeKFO_yCblpWXuA?e=dFypTO | I19: =IF(SUM(P19:AU19)=0,"-",SUM(P19:AU19)) -> 265 | J19: =IF(SUMPRODUCT($P$5:$AU$5,P19:AU19)=0,"-",SUMPRODUCT($P$5:$AU$5,P19:AU19)) -> 66.25 | K19: - | L19: - | M19: Sent to Thomas | N19: F2024-0326 | O19: Paid 14/08/2024 | AT19: 265
A20: Aristocrat | B20: USA | C20: 45463 | D20: SP registration form | E20: Megan Nimsgern | F20: Delivered | G20: USA | H20: https://saranistudio.sharepoint.com/:f:/s/SaraniAssets/Evl07W9WGGhEtehSc2_yr28BZJ3M38Rqn6iRc7qPrpL8uQ?e=pivuZd | I20: =IF(SUM(P20:AU20)=0,"-",SUM(P20:AU20)) -> 250 | J20: =IF(SUMPRODUCT($P$5:$AU$5,P20:AU20)=0,"-",SUMPRODUCT($P$5:$AU$5,P20:AU20)) -> 30 | K20: - | L20: - | M20: Sent to Thomas | N20: F2024-0326 | O20: Paid 14/08/2024 | AS20: 250
A21: Aristocrat | B21: USA | C21: 45463 | D21: French ad | E21: Megan Nimsgern | F21: Delivered | G21: USA | H21: - Email | I21: =IF(SUM(P21:AU21)=0,"-",SUM(P21:AU21)) -> 40 | J21: =IF(SUMPRODUCT($P$5:$AU$5,P21:AU21)=0,"-",SUMPRODUCT($P$5:$AU$5,P21:AU21)) -> 10 | K21: - | L21: - | M21: Sent to Thomas | N21: F2024-0326 | O21: Paid 14/08/2024 | AT21: 40
A22: Aristocrat | B22: USA | C22: 45470 | D22: Monaco Casino Deck Translation | E22: Megan Nimsgern | F22: Delivered | G22: USA | H22: https://saranistudio.sharepoint.com/:f:/s/SaraniAssets/Eu1DdecbiRlFjp4_UiiV1aEBGaf_h3dwocON-LWLu6u8Dg?e=7fkaek | I22: =IF(SUM(P22:AU22)=0,"-",SUM(P22:AU22)) -> 400 | J22: =IF(SUMPRODUCT($P$5:$AU$5,P22:AU22)=0,"-",SUMPRODUCT($P$5:$AU$5,P22:AU22)) -> 48 | K22: - | L22: - | M22: Sent to Thomas | N22: F2024-0326 | O22: Paid 14/08/2024 | AS22: 400
A23: Aristocrat | B23: USA | C23: 45470 | D23: Bonus Highlights Translations | E23: Megan Nimsgern | F23: Delivered | G23: USA | H23: https://saranistudio.sharepoint.com/:f:/s/SaraniAssets/EjoYoNRokUJCob2AkQes1eoBOP4MJuo3Zc-1qw_-HiSnuQ?e=tABvP0 | I23: =IF(SUM(P23:AU23)=0,"-",SUM(P23:AU23)) -> 850 | J23: =IF(SUMPRODUCT($P$5:$AU$5,P23:AU23)=0,"-",SUMPRODUCT($P$5:$AU$5,P23:AU23)) -> 102 | K23: - | L23: - | M23: Sent to Thomas | N23: F2024-0326 | O23: Paid 14/08/2024 | AS23: 850
A24: Aristocrat | B24: USA | C24: 45485 | D24: EMEA Product Script Translations | E24: Megan Nimsgern | F24: Delivered | G24: USA | H24: https://saranistudio.sharepoint.com/:f:/s/SaraniAssets/Es9QBoBjb9VJvGDL3Zf9-voBWmaA_rAbTzthkJYXQAA1Mw?e=PkwSHS | I24: =IF(SUM(P24:AU24)=0,"-",SUM(P24:AU24)) -> 4140 | J24: =IF(SUMPRODUCT($P$5:$AU$5,P24:AU24)=0,"-",SUMPRODUCT($P$5:$AU$5,P24:AU24)) -> 496.8 | K24: - | L24: - | M24: Sent to Thomas | N24: F2024-0326 | O24: Paid 14/08/2024 | AS24: =690*6 -> 4140
A25: Aristocrat | B25: USA | C25: 45485 | D25: Games rules translations | E25: Megan Nimsgern | F25: Delivered | G25: USA | H25: https://saranistudio.sharepoint.com/:f:/s/SaraniAssets/EgSpS7bq8c9ClzPajLlGKnIBdqYULi6RzKofIZubAtNmwg?e=MsRkUu | I25: =IF(SUM(P25:AU25)=0,"-",SUM(P25:AU25)) -> 7100 | J25: =IF(SUMPRODUCT($P$5:$AU$5,P25:AU25)=0,"-",SUMPRODUCT($P$5:$AU$5,P25:AU25)) -> 852 | K25: - | L25: - | M25: Sent to Thomas | N25: F2024-0326 | O25: Paid 14/08/2024 | AS25: =3500+1800+1800 -> 7100
A26: Aristocrat | B26: USA | C26: 45485 | D26: Form Export | E26: Megan Nimsgern | F26: Delivered | G26: USA | H26: https://saranistudio.sharepoint.com/:f:/s/SaraniAssets/EpuE4RXdO8hAr4qLP_U7DQ0BZkLhBXgxJfYor_Z0-CduXg?e=E8bQ44 | I26: =IF(SUM(P26:AU26)=0,"-",SUM(P26:AU26)) -> 2674 | J26: =IF(SUMPRODUCT($P$5:$AU$5,P26:AU26)=0,"-",SUMPRODUCT($P$5:$AU$5,P26:AU26)) -> 320.88 | K26: - | L26: - | M26: Sent to Thomas | N26: F2024-0326 | O26: Paid 14/08/2024 | AS26: 2674
A27: Aristocrat | B27: USA | C27: 45499 | D27: G2E Invite Translation | E27: Megan Nimsgern | F27: Delivered | G27: USA | H27: - Email | I27: =IF(SUM(P27:AU27)=0,"-",SUM(P27:AU27)) -> 150 | J27: =IF(SUMPRODUCT($P$5:$AU$5,P27:AU27)=0,"-",SUMPRODUCT($P$5:$AU$5,P27:AU27)) -> 37.5 | K27: - | L27: - | M27: Sent to Thomas | N27: F2024-0392 | O27: Paid 20/09/2024 | AT27: 150
A28: Aristocrat | B28: USA | C28: 45503 | D28: Workday supplier log in instructions | E28: Megan Nimsgern | F28: Delivered | G28: USA | H28: https://saranistudio.sharepoint.com/:f:/s/SaraniAssets/EkjafVG4VKJBqf747r1_V8ABNM1X7KLOsyC1Fa0avov8yg?e=zf7vpc | I28: =IF(SUM(P28:AU28)=0,"-",SUM(P28:AU28)) -> 600 | J28: =IF(SUMPRODUCT($P$5:$AU$5,P28:AU28)=0,"-",SUMPRODUCT($P$5:$AU$5,P28:AU28)) -> 72 | K28: - | L28: - | M28: Sent to Thomas | N28: F2024-0392 | O28: Paid 20/09/2024 | AS28: 600
A29: Aristocrat | B29: USA | C29: 45508 | D29: Rules of the Road - Spanish | E29: Megan Nimsgern | F29: Delivered | G29: USA | H29: https://saranistudio.sharepoint.com/:f:/s/SaraniAssets/El90XJB1hU1Oved8pG663yEB6o7cYZpgCWrfukMVc7SU_Q?e=TainRa | I29: =IF(SUM(P29:AU29)=0,"-",SUM(P29:AU29)) -> 520 | J29: =IF(SUMPRODUCT($P$5:$AU$5,P29:AU29)=0,"-",SUMPRODUCT($P$5:$AU$5,P29:AU29)) -> 62.4 | K29: - | L29: - | M29: Sent to Thomas | N29: F2024-0392 | O29: Paid 20/09/2024 | AS29: 520
A30: Aristocrat | B30: USA | C30: 45516 | D30: French Advertisement Copy | E30: Megan Nimsgern | F30: Delivered | G30: USA | H30: - Email | I30: =IF(SUM(P30:AU30)=0,"-",SUM(P30:AU30)) -> 50 | J30: =IF(SUMPRODUCT($P$5:$AU$5,P30:AU30)=0,"-",SUMPRODUCT($P$5:$AU$5,P30:AU30)) -> 12.5 | K30: - | L30: - | M30: Sent to Thomas | N30: F2024-0392 | O30: Paid 20/09/2024 | AT30: 50
A31: Aristocrat | B31: USA | C31: 45516 | D31: The baron brochure | E31: Megan Nimsgern | F31: Delivered | G31: USA | H31: - Email | I31: =IF(SUM(P31:AU31)=0,"-",SUM(P31:AU31)) -> 430 | J31: =IF(SUMPRODUCT($P$5:$AU$5,P31:AU31)=0,"-",SUMPRODUCT($P$5:$AU$5,P31:AU31)) -> 51.6 | K31: - | L31: - | M31: Sent to Thomas | N31: F2024-0392 | O31: Paid 20/09/2024 | AS31: =215*2 -> 430
A32: Aristocrat | B32: USA | C32: 45524 | D32: French quotes | E32: Megan Nimsgern | F32: Delivered | G32: USA | H32: https://saranistudio.sharepoint.com/:f:/s/SaraniAssets/EqNVhASVLx1GqoO9fik-2WgB79N-oEll3qcYgUVBeFVSbA?e=Pmw5lb | I32: =IF(SUM(P32:AU32)=0,"-",SUM(P32:AU32)) -> 1270 | J32: =IF(SUMPRODUCT($P$5:$AU$5,P32:AU32)=0,"-",SUMPRODUCT($P$5:$AU$5,P32:AU32)) -> 152.4 | K32: - | L32: - | M32: Sent to Thomas | N32: F2024-0392 | O32: Paid 20/09/2024 | AS32: =445+225+600 -> 1270
A33: Aristocrat | B33: USA | C33: 45524 | D33: Tagline - French Translations | E33: Megan Nimsgern | F33: Delivered | G33: USA | H33: - Email | I33: =IF(SUM(P33:AU33)=0,"-",SUM(P33:AU33)) -> 20 | J33: 10 | K33: - | L33: - | M33: Sent to Thomas | N33: F2024-0392 | O33: Paid 20/09/2024 | AT33: 20
A34: Aristocrat | B34: USA | C34: 45532 | D34: Slick Spanish Translations | E34: Megan Nimsgern | F34: Delivered | G34: USA | H34: https://saranistudio.sharepoint.com/:f:/s/SaraniAssets/EkbtRDSapgtOsCGRr45n3s8BxNwNsJWvG978ep85BJ1GRg?e=4csna7 | I34: =IF(SUM(P34:AU34)=0,"-",SUM(P34:AU34)) -> 665 | J34: =IF(SUMPRODUCT($P$5:$AU$5,P34:AU34)=0,"-",SUMPRODUCT($P$5:$AU$5,P34:AU34)) -> 166.25 | K34: - | L34: - | M34: Sent to Thomas | N34: F2024-0483 | O34: Paid 18/10/2024 | AT34: 665
A35: Aristocrat | B35: USA | C35: 45532 | D35: Bao Zhu Translations | E35: Megan Nimsgern | F35: Delivered | G35: USA | H35: https://saranistudio.sharepoint.com/:f:/s/SaraniAssets/EuvalTHbCp5Epfzl2fnz76YBVf5-e6tI7B7uVbDlHJ47GA?e=WsqRLQ | I35: =IF(SUM(P35:AU35)=0,"-",SUM(P35:AU35)) -> 415 | J35: =IF(SUMPRODUCT($P$5:$AU$5,P35:AU35)=0,"-",SUMPRODUCT($P$5:$AU$5,P35:AU35)) -> 103.75 | K35: - | L35: - | M35: Sent to Thomas | N35: F2024-0483 | O35: Paid 18/10/2024 | AT35: 415
A36: Aristocrat | B36: USA | C36: 45554 | D36: Whisker Wheels Game Rules - Translation | E36: Megan Nimsgern | F36: Delivered | G36: USA | H36: 20240830_Slick Spanish Translations | I36: =IF(SUM(P36:AU36)=0,"-",SUM(P36:AU36)) -> 1801 | J36: =IF(SUMPRODUCT($P$5:$AU$5,P36:AU36)=0,"-",SUMPRODUCT($P$5:$AU$5,P36:AU36)) -> 216.12 | K36: - | L36: - | M36: Sent to Thomas | N36: F2024-0483 | O36: Paid 18/10/2024 | AS36: 1801
A37: Aristocrat | B37: USA | C37: 45562 | D37: Italian translations | E37: Megan Nimsgern | F37: Delivered | G37: USA | H37: - Email | I37: =IF(SUM(P37:AU37)=0,"-",SUM(P37:AU37)) -> 51 | J37: =IF(SUMPRODUCT($P$5:$AU$5,P37:AU37)=0,"-",SUMPRODUCT($P$5:$AU$5,P37:AU37)) -> 6.12 | K37: - | L37: - | M37: Sent to Thomas | N37: F2024-0483 | O37: Paid 18/10/2024 | AS37: 51
A38: Aristocrat | B38: USA | C38: 45562 | D38: Backdrop Graphic - Aristocrat | E38: Megan Nimsgern | F38: Delivered | G38: USA | H38: https://saranistudio.sharepoint.com/:f:/s/SaraniAssets/EmfCNS1dNjVJoVUbuLby2mQBkHLjQHrosRlQN-UqzpuzuA?e=3s2xjn | I38: =IF(SUM(P38:AU38)=0,"-",SUM(P38:AU38)) -> 1 | J38: =IF(SUMPRODUCT($P$5:$AU$5,P38:AU38)=0,"-",SUMPRODUCT($P$5:$AU$5,P38:AU38)) -> 180 | K38: - | L38: - | M38: Sent to Thomas | N38: F2024-0483 | O38: Paid 18/10/2024 | AB38: 1
A39: Aristocrat | B39: USA | C39: 45567 | D39: Cabinet Art work changes | E39: Megan Nimsgern | F39: Delivered | G39: USA | H39: https://saranistudio.sharepoint.com/:f:/s/SaraniAssets/ErWt2eivjgBOiHbZ58kvpZQBuHWAiWWJ_JCRLNww6pXmIQ?e=JBPZDA | I39: =IF(SUM(P39:AU39)=0,"-",SUM(P39:AU39)) -> 4 | J39: =IF(SUMPRODUCT($P$5:$AU$5,P39:AU39)=0,"-",SUMPRODUCT($P$5:$AU$5,P39:AU39)) -> 120 | K39: - | L39: - | M39: Sent to Thomas | N39: F2024-0567 | O39: Paid 06/12/2024 | Q39: 4
A40: Aristocrat | B40: USA | C40: 45574 | D40: Bonus Highlight Video Translations | E40: Tia Shumway | F40: Delivered | G40: USA | H40: https://saranistudio.sharepoint.com/:f:/s/SaraniAssets/EjoYoNRokUJCob2AkQes1eoBOP4MJuo3Zc-1qw_-HiSnuQ?e=WJuuAm | I40: =IF(SUM(P40:AU40)=0,"-",SUM(P40:AU40)) -> 63 | J40: =IF(SUMPRODUCT($P$5:$AU$5,P40:AU40)=0,"-",SUMPRODUCT($P$5:$AU$5,P40:AU40)) -> 7.56 | K40: - | L40: - | M40: Sent to Thomas | N40: F2024-0567 | O40: Paid 06/12/2024 | AS40: 63
A41: Aristocrat | B41: USA | C41: 45574 | D41: Video Translations | E41: Tia Shumway | F41: Delivered | G41: USA | H41: https://saranistudio.sharepoint.com/:f:/s/SaraniAssets/EldxUpTDoKdAhjulDr8hMQkBIyNdOAxN343nz9P6omm9TA?e=TezVIo | I41: =IF(SUM(P41:AU41)=0,"-",SUM(P41:AU41)) -> 790 | J41: =IF(SUMPRODUCT($P$5:$AU$5,P41:AU41)=0,"-",SUMPRODUCT($P$5:$AU$5,P41:AU41)) -> 197.5 | K41: - | L41: - | M41: Sent to Thomas | N41: F2024-0567 | O41: Paid 06/12/2024 | AT41: 790
A42: Aristocrat | B42: USA | C42: 45581 | D42: Deck to be translated into Spanish | E42: Tia Shumway | F42: Delivered | G42: USA | H42: https://saranistudio.sharepoint.com/:f:/s/SaraniAssets/ElRQWd7V7SJFvjKgW65A1o0BNyhrnz4xNqKtP6iDISX6tg?e=vTIvK5 | I42: =IF(SUM(P42:AU42)=0,"-",SUM(P42:AU42)) -> 1474 | J42: =IF(SUMPRODUCT($P$5:$AU$5,P42:AU42)=0,"-",SUMPRODUCT($P$5:$AU$5,P42:AU42)) -> 368.5 | K42: - | L42: - | M42: Sent to Thomas | N42: F2024-0567 | O42: Paid 06/12/2024 | AT42: 1474
A43: Aristocrat | B43: USA | C43: 45586 | D43: Chair Artwork Updates | E43: Megan Nimsgern | F43: Delivered | G43: USA | H43: https://saranistudio.sharepoint.com/:f:/s/SaraniAssets/Eto9_yUhJn5Epn2nhGKQ0UcBuygPh3c6P5qIJqjEP-3aIQ?e=xuFDDw | I43: =IF(SUM(P43:AU43)=0,"-",SUM(P43:AU43)) -> 4 | J43: =IF(SUMPRODUCT($P$5:$AU$5,P43:AU43)=0,"-",SUMPRODUCT($P$5:$AU$5,P43:AU43)) -> 120 | K43: - | L43: - | M43: Sent to Thomas | N43: F2024-0567 | O43: Paid 06/12/2024 | Q43: 4
A44: Aristocrat | B44: USA | C44: 45589 | D44: Pheonix Link Slogan Translations | E44: Tia Shumway | F44: Delivered | G44: USA | H44: Email | I44: =IF(SUM(P44:AU44)=0,"-",SUM(P44:AU44)) -> 30 | J44: =IF(SUMPRODUCT($P$5:$AU$5,P44:AU44)=0,"-",SUMPRODUCT($P$5:$AU$5,P44:AU44)) -> 7.5 | K44: - | L44: - | M44: Sent to Thomas | N44: F2024-0567 | O44: Paid 06/12/2024 | AT44: 30
A45: Aristocrat | B45: USA | C45: 45589 | D45: French Translations for English Help Screens | E45: Tia Shumway | F45: Delivered | G45: USA | H45: https://saranistudio.sharepoint.com/:f:/s/SaraniAssets/EnFKb_AgdaJBgllFLEfT75QBvem9NL_FXia37lU405VjOQ?e=ahAzN4 | I45: =IF(SUM(P45:AU45)=0,"-",SUM(P45:AU45)) -> 14133 | J45: =IF(SUMPRODUCT($P$5:$AU$5,P45:AU45)=0,"-",SUMPRODUCT($P$5:$AU$5,P45:AU45)) -> 1695.96 | K45: - | L45: - | M45: Sent to Thomas | N45: F2024-0567 | O45: Paid 06/12/2024 | AS45: 14133
A46: Aristocrat | B46: USA | C46: 45589 | D46: DE Whisker wheels rules translation design | E46: Tia Shumway | F46: Delivered | G46: USA | H46: https://saranistudio.sharepoint.com/:f:/s/SaraniAssets/Eh3cThpTEH5Cm_La1uA14vAByJljhYqqOEv8cFAU7h2-9w?e=wMlrD0 | I46: =IF(SUM(P46:AU46)=0,"-",SUM(P46:AU46)) -> 20 | J46: =IF(SUMPRODUCT($P$5:$AU$5,P46:AU46)=0,"-",SUMPRODUCT($P$5:$AU$5,P46:AU46)) -> 600 | K46: - | L46: - | M46: Sent to Thomas | N46: F2024-0713 | O46: Paid 10/01/2025 | Q46: 20
A47: Aristocrat | B47: USA | C47: 45592 | D47: French Translation Gaming Show | E47: Tia Shumway | F47: Delivered | G47: USA | H47: 20241127_French Translation Gaming Show | I47: =IF(SUM(P47:AU47)=0,"-",SUM(P47:AU47)) -> - | J47: 50 | K47: - | L47: - | M47: Sent to Thomas | N47: F2024-0713 | O47: Paid 10/01/2025
A48: Aristocrat | B48: USA | C48: 45630 | D48: Product Roadmap | E48: Megan Nimsgern | F48: Delivered | G48: USA | H48: 20241204_Product Roadmap | I48: =IF(SUM(P48:AU48)=0,"-",SUM(P48:AU48)) -> 30 | J48: =IF(SUMPRODUCT($P$5:$AU$5,P48:AU48)=0,"-",SUMPRODUCT($P$5:$AU$5,P48:AU48)) -> 1050 | K48: - | L48: - | M48: Sent to Thomas | N48: F2024-0713 | O48: Paid 10/01/2025 | AE48: 30
A49: Aristocrat | B49: USA | C49: 45638 | D49: Extracting and Re-inserting Symbols for Coin Trio Titles | E49: Megan Nimsgern | F49: Delivered | G49: USA | H49: 20241209_Extracting and Re-inserting Symbols for Coin Trio Titles | I49: =IF(SUM(P49:AU49)=0,"-",SUM(P49:AU49)) -> - | J49: 250 | K49: - | L49: - | M49: Sent to Thomas | N49: F2024-0713 | O49: Paid 10/01/2025
A50: Aristocrat | B50: USA | C50: 45638 | D50: Advertisement French ICE | E50: Megan Nimsgern | F50: Delivered | G50: USA | H50: 20241212_Advertisement French Translations | I50: =IF(SUM(P50:AU50)=0,"-",SUM(P50:AU50)) -> 150 | J50: =IF(SUMPRODUCT($P$5:$AU$5,P50:AU50)=0,"-",SUMPRODUCT($P$5:$AU$5,P50:AU50)) -> 37.5 | K50: - | L50: - | M50: Sent to Thomas | N50: F2024-0713 | O50: Paid 10/01/2025 | AT50: 150
A51: Aristocrat | B51: USA | C51: 45659 | D51: German Translations for Game Screens | E51: Katalina Gomez | F51: Delivered | G51: USA | H51: https://saranistudio.sharepoint.com/:f:/s/SaraniAssets/EuPkcm0f49tPpptvP3vGxl4BEVo29yQ4sa3QqPtPMdE_uA?e=45hnsK | I51: =IF(SUM(P51:AU51)=0,"-",SUM(P51:AU51)) -> 268 | J51: =IF(SUMPRODUCT($P$5:$AU$5,P51:AU51)=0,"-",SUMPRODUCT($P$5:$AU$5,P51:AU51))/2.5 -> 3216 | K51: - | L51: - | M51: Sent to Thomas | N51: F2025-0043 | O51: Paid 25/02/2025 | Y51: 268
A52: Aristocrat | B52: USA | C52: 45667 | D52: French Translations for Game Screens | E52: Katalina Gomez | F52: Delivered | G52: USA | H52: 20250110_French Translations for Game Screens | I52: =IF(SUM(P52:AU52)=0,"-",SUM(P52:AU52)) -> 188 | J52: =IF(SUMPRODUCT($P$5:$AU$5,P52:AU52)=0,"-",SUMPRODUCT($P$5:$AU$5,P52:AU52))/2.5 -> 2256 | K52: - | L52: - | M52: Sent to Thomas | N52: F2025-0043 | O52: Paid 25/02/2025 | Y52: 188
A53: Aristocrat | B53: USA | C53: 45702 | D53: Bao Zhu Zhao Fu Jade & Purple Celebration - Stickers | E53: Megan Nimsgern | F53: Delivered | G53: USA | H53: 20250213_Bao Zhu Zhao Fu Jade & Purple Celebration - Stickers | I53: =IF(SUM(P53:AU53)=0,"-",SUM(P53:AU53)) -> 2 | J53: =IF(SUMPRODUCT($P$5:$AU$5,P53:AU53)=0,"-",SUMPRODUCT($P$5:$AU$5,P53:AU53)) -> 60 | K53: - | L53: - | M53: Sent to Thomas | N53: F2025-0074 | O53: Paid 04/04/2025 | Q53: 2
A54: Aristocrat | B54: USA | C54: 45698 | D54: French Translations for Game Screens | E54: Katalina Gomez | F54: Delivered | G54: USA | H54: Batch 04 | I54: =IF(SUM(P54:AU54)=0,"-",SUM(P54:AU54)) -> 43 | J54: =IF(SUMPRODUCT($P$5:$AU$5,P54:AU54)=0,"-",SUMPRODUCT($P$5:$AU$5,P54:AU54))/2.5 -> 516 | K54: - | L54: - | M54: Sent to Thomas | N54: F2025-0074 | O54: Paid 04/04/2025 | Y54: 43
A55: Aristocrat | B55: USA | C55: 45724 | D55: Hungarian translation BZZF Wheel Blast | E55: Lauren Feiner | F55: Delivered | G55: USA | H55: https://saranistudio.sharepoint.com/:f:/s/SaraniAssets/EgJWxkOFh2NNiP5dlA5Bt9wBGtSoTi58YGzdvxoKzX-L6w?e=xNp14u | I55: =IF(SUM(P55:AU55)=0,"-",SUM(P55:AU55)) -> 2720 | J55: =IF(SUMPRODUCT($P$5:$AU$5,P55:AU55)=0,"-",SUMPRODUCT($P$5:$AU$5,P55:AU55)) -> 326.4 | K55: - | L55: - | M55: Sent to Thomas | N55: F2025-0173 | O55: Paid 12/05/2025 | AS55: =1355+1365 -> 2720
A56: Aristocrat | B56: USA | C56: 45727 | D56: French Translations for Game Screens 2 | E56: Megan Nimsgern | F56: Delivered | G56: USA | H56: https://saranistudio.sharepoint.com/:f:/s/SaraniAssets/EpMXWZTpTQhElDw67YUEdEMBMqOi_F8J38A1Xig6oxLPzA?e=ZZpTxd | I56: =IF(SUM(P56:AU56)=0,"-",SUM(P56:AU56)) -> 128 | J56: =IF(SUMPRODUCT($P$5:$AU$5,P56:AU56)=0,"-",SUMPRODUCT($P$5:$AU$5,P56:AU56))/2.5 -> 1536 | K56: - | L56: - | M56: Sent to Thomas | N56: F2025-0173 | O56: Paid 12/05/2025 | Y56: 128
A57: Aristocrat | B57: USA | C57: 45802 | D57: Request for UFC MarsX 4-Pod Image Update | E57: Megan Nimsgern | F57: Delivered | G57: USA | H57: 20250529_Request for UFC MarsX 4-Pod Image Update | I57: =IF(SUM(P57:AU57)=0,"-",SUM(P57:AU57)) -> 1 | J57: =IF(SUMPRODUCT($P$5:$AU$5,P57:AU57)=0,"-",SUMPRODUCT($P$5:$AU$5,P57:AU57)) -> 135 | K57: - | L57: - | M57: Sent to Thomas | N57: F2025-0362 | O57: Paid 22/07/2025 | P57: 1
A58: Aristocrat | B58: USA | C58: 45811 | D58: Spanish (Spain) Translations – Game Screen Folders | E58: Megan Nimsgern | F58: Delivered | G58: USA | H58: 20250603_Spanish (Spain) Translations – Game Screen Folders | I58: =IF(SUM(P58:AU58)=0,"-",SUM(P58:AU58)) -> 79 | J58: =IF(SUMPRODUCT($P$5:$AU$5,P58:AU58)=0,"-",SUMPRODUCT($P$5:$AU$5,P58:AU58)) -> 2370 | K58: - | L58: - | M58: Sent to Thomas | N58: F2025-0362 | O58: Paid 22/07/2025 | Y58: 79
A59: Aristocrat | B59: USA | C59: 45997 | D59: Product Training Video - Transcript | E59: Megan Nimsgern | F59: Delivered | G59: USA | H59: https://saranistudio.sharepoint.com/:f:/s/SaraniAssets/Elx7pAS7UXpLgatjI8yLRaIBn074kbYeY8-nd0COrB13kQ?e=jIOgIE | I59: =IF(SUM(P59:AU59)=0,"-",SUM(P59:AU59)) -> 1343 | J59: =IF(SUMPRODUCT($P$5:$AU$5,P59:AU59)=0,"-",SUMPRODUCT($P$5:$AU$5,P59:AU59)) -> 610.8 | K59: - | L59: - | M59: Sent to Thomas | N59: F2025-0450 | O59: Paid 05/09/2025 | AK59: 3 | AS59: 1340
A60: Aristocrat | B60: USA | C60: 45824 | D60: Cash Express Legends - Help Screen Translations | E60: Megan Nimsgern | F60: Delivered | G60: USA | H60: 20250616_Cash Express Legends - Help Screen Translations | I60: =IF(SUM(P60:AU60)=0,"-",SUM(P60:AU60)) -> 72 | J60: =IF(SUMPRODUCT($P$5:$AU$5,P60:AU60)=0,"-",SUMPRODUCT($P$5:$AU$5,P60:AU60)) -> 2160 | K60: - | L60: - | M60: Sent to Thomas | N60: F2025-0362 | O60: Paid 22/07/2025 | Y60: 72
A61: Aristocrat | B61: USA | C61: 45831 | D61: Slick Updates - Round 1 | E61: Megan Nimsgern | F61: Delivered | G61: USA | H61: https://saranistudio.sharepoint.com/:f:/s/SaraniAssets/EvRueomwqc9ErxTorHSLPgYBQzuLu9uKL3GKUh4wO8b6XQ?e=krKWU3 | I61: =IF(SUM(P61:AU61)=0,"-",SUM(P61:AU61)) -> 4 | J61: =IF(SUMPRODUCT($P$5:$AU$5,P61:AU61)=0,"-",SUMPRODUCT($P$5:$AU$5,P61:AU61)) -> 120 | K61: - | L61: - | M61: Sent to Thomas | N61: F2025-0362 | O61: Paid 22/07/2025 | Q61: 4
A62: Aristocrat | B62: USA | C62: 45831 | D62: Phoenix Link Spanish Translations | E62: Katalina Gomez | F62: Delivered | G62: USA | I62: =IF(SUM(P62:AU62)=0,"-",SUM(P62:AU62)) -> 30 | J62: =IF(SUMPRODUCT($P$5:$AU$5,P62:AU62)=0,"-",SUMPRODUCT($P$5:$AU$5,P62:AU62)) -> 7.5 | K62: - | L62: - | M62: Sent to Thomas | N62: F2025-0362 | O62: Paid 22/07/2025 | AT62: 30
A63: Aristocrat | B63: USA | C63: 45825 | D63: German Translation - NFL Tagline | E63: Megan Nimsgern | F63: Delivered | G63: USA | I63: =IF(SUM(P63:AU63)=0,"-",SUM(P63:AU63)) -> 20 | J63: =IF(SUMPRODUCT($P$5:$AU$5,P63:AU63)=0,"-",SUMPRODUCT($P$5:$AU$5,P63:AU63)) -> 5 | K63: - | L63: - | M63: Sent to Thomas | N63: F2025-0362 | O63: Paid 22/07/2025 | AT63: 20
A64: Aristocrat | B64: USA | C64: 45835 | D64: Buffalo Ultimate Stampede Slick Update | E64: Megan Nimsgern | F64: Delivered | G64: USA | H64: https://saranistudio.sharepoint.com/:f:/s/SaraniAssets/Ei0yMOsVb7JMpda1Te-WSHkBbthyp3kYHqVTrlo1vi08vQ?e=bgPcxe | I64: =IF(SUM(P64:AU64)=0,"-",SUM(P64:AU64)) -> 1 | J64: =IF(SUMPRODUCT($P$5:$AU$5,P64:AU64)=0,"-",SUMPRODUCT($P$5:$AU$5,P64:AU64)) -> 30 | K64: - | L64: - | M64: Sent to Thomas | N64: F2025-0450 | O64: Paid 05/09/2025 | Q64: 1
A65: Aristocrat | B65: USA | C65: 45847 | D65: Translation and Subtitling Support – EMEA Localized Video (Phase 2) | E65: Megan Nimsgern | F65: Delivered | G65: USA | H65: 20250709_Translation and Subtitling Support – EMEA Localized Video (Phase 2) | I65: =IF(SUM(P65:AU65)=0,"-",SUM(P65:AU65)) -> 1083 | J65: =IF(SUMPRODUCT($P$5:$AU$5,P65:AU65)=0,"-",SUMPRODUCT($P$5:$AU$5,P65:AU65)) -> 579.6 | M65: Made by Thomas | N65: F2025-0465 | O65: Paid 28/10/2025 | AK65: 3 | AS65: 1080
A66: Aristocrat | B66: USA | C66: 45854 | D66: Hot Product Alert Creative Request | E66: Katalina Gomez | F66: Delivered | G66: USA | H66: https://saranistudio.sharepoint.com/:f:/s/SaraniAssets/Ej4-vHD_4y5FhbW9RO5iBAIBmCGDUOGMFfcTrXFzhKbZwg?e=BNoADU | I66: =IF(SUM(P66:AU66)=0,"-",SUM(P66:AU66)) -> 2 | J66: =IF(SUMPRODUCT($P$5:$AU$5,P66:AU66)=0,"-",SUMPRODUCT($P$5:$AU$5,P66:AU66)) -> 210 | K66: - | L66: - | M66: Sent to Thomas | N66: F2025-0450 | O66: Paid 05/09/2025 | Y66: 1 | Z66: 1
A67: Aristocrat | B67: USA | C67: 45856 | D67: Urgent Asset Request – GAT Mexico Sponsorship | E67: Megan Nimsgern | F67: Delivered | G67: USA | H67: https://saranistudio.sharepoint.com/:f:/s/SaraniAssets/El9jd0HEkbhHr-V9e234FBwBMUHTMw5ZGaDCBg5qxw0Hhg?e=P0FNGt | I67: =IF(SUM(P67:AU67)=0,"-",SUM(P67:AU67)) -> 4 | J67: =IF(SUMPRODUCT($P$5:$AU$5,P67:AU67)=0,"-",SUMPRODUCT($P$5:$AU$5,P67:AU67)) -> 330 | K67: - | L67: - | M67: Sent to Thomas | N67: F2025-0450 | O67: Paid 05/09/2025 | P67: 2 | Q67: 2
A68: Aristocrat | B68: USA | C68: 45863 | D68: Game Screen Translations FR | E68: Katalina Gomez | F68: Delivered | G68: USA | H68: 20250725_Game Screen Translations FR | I68: =IF(SUM(P68:AU68)=0,"-",SUM(P68:AU68)) -> 67 | J68: =IF(SUMPRODUCT($P$5:$AU$5,P68:AU68)=0,"-",SUMPRODUCT($P$5:$AU$5,P68:AU68))/2.5 -> 804 | M68: Made by Thomas | N68: F2025-0465 | O68: Paid 28/10/2025 | Y68: 67
A69: Aristocrat | B69: USA | C69: 45868 | D69: Hungarian translation | E69: Megan Nimsgern | F69: Delivered | G69: USA | H69: https://saranistudio.sharepoint.com/:f:/s/SaraniAssets/EiMBOclNiHBBngy_eykdudgB7SN1oXkFk-XGteIVMXvauQ?e=mW2WqG | I69: =IF(SUM(P69:AU69)=0,"-",SUM(P69:AU69)) -> 48000 | J69: =IF(SUMPRODUCT($P$5:$AU$5,P69:AU69)=0,"-",SUMPRODUCT($P$5:$AU$5,P69:AU69)) -> 5760 | M69: Made by Thomas | N69: F2025-0465 | O69: Paid 28/10/2025 | AS69: =33000+15000 -> 48000
A70: Aristocrat | B70: USA | C70: 45880 | D70: Coin Trio Royal Slick Localization | E70: Megan Nimsgern | F70: Delivered | G70: USA | H70: 20250811_Coin Trio Royal Slick Localization | I70: =IF(SUM(P70:AU70)=0,"-",SUM(P70:AU70)) -> 1 | J70: =IF(SUMPRODUCT($P$5:$AU$5,P70:AU70)=0,"-",SUMPRODUCT($P$5:$AU$5,P70:AU70)) -> 30 | M70: Made by Thomas | N70: F2025-0465 | O70: Paid 28/10/2025 | Q70: 1
A71: Aristocrat | B71: USA | C71: 45882 | D71: GAT Mexico Sponsorship 2 | E71: Katalina Gomez | F71: Delivered | G71: USA | H71: 20250813_GAT Mexico Sponsorship 2 | I71: =IF(SUM(P71:AU71)=0,"-",SUM(P71:AU71)) -> 4 | J71: =IF(SUMPRODUCT($P$5:$AU$5,P71:AU71)=0,"-",SUMPRODUCT($P$5:$AU$5,P71:AU71)) -> 120 | M71: Made by Thomas | N71: F2025-0465 | O71: Paid 28/10/2025 | Q71: 4
A72: Aristocrat | B72: USA | C72: 45886 | D72: Remaining works for FY25 projects + FY26 | E72: Megan Nimsgern | F72: Delivered | G72: USA | J72: 50000 | M72: Sent to Thomas | N72: F2025-0477 | O72: Paid 13/11/2025
A73: Aristocrat | B73: USA | C73: 45886 | D73: Remaining works for FY25 projects + FY26 Part 2 | E73: Megan Nimsgern | F73: Delivered | G73: USA | J73: 25000 | M73: Made by Thomas | N73: F2025-0570 | O73: Paid 04/12/2025
A74: Aristocrat | B74: USA | C74: 45897 | D74: Phoenix Link Hot Product Alert | E74: Katalina Gomez | F74: Delivered | G74: USA | H74: https://saranistudio.sharepoint.com/:f:/s/SaraniAssets/Eg5kUneXrfBMicY9dG9lG6IBWH__UT7qfYp_2uY3o1HIQA?e=NgHnbc | I74: =IF(SUM(P74:AU74)=0,"-",SUM(P74:AU74)) -> 1 | J74: =IF(SUMPRODUCT($P$5:$AU$5,P74:AU74)=0,"-",SUMPRODUCT($P$5:$AU$5,P74:AU74)) -> 135 | K74: No invoice until the 75000€ is reached | M74: - | N74: - | O74: - | X74: 1
A75: Aristocrat | B75: USA | C75: 45903 | D75: ARC - EOL Letter - Pardot | E75: Megan Nimsgern | F75: Delivered | G75: USA | H75: https://saranistudio.sharepoint.com/:f:/s/SaraniAssets/EmuuQmCXyeVEj3E4AT0P0BoBsifWkGjvHk9yBKjBWGAS5Q?e=qM6szb | I75: =IF(SUM(P75:AU75)=0,"-",SUM(P75:AU75)) -> 1 | J75: =IF(SUMPRODUCT($P$5:$AU$5,P75:AU75)=0,"-",SUMPRODUCT($P$5:$AU$5,P75:AU75)) -> 30 | K75: No invoice until the 75000€ is reached | M75: - | N75: - | O75: - | Q75: 1
A76: Aristocrat | B76: USA | C76: 45904 | D76: Slick Mo' Mo' Mo' Mummy | E76: Megan Nimsgern | F76: Delivered | G76: USA | H76: https://saranistudio.sharepoint.com/:f:/s/SaraniAssets/EsrEi7Xth_JIhWmRTBXzFJ0BUlORnk7ZdPgOJ2-u85P6kg?e=Vb3FYi | I76: =IF(SUM(P76:AU76)=0,"-",SUM(P76:AU76)) -> 1 | J76: =IF(SUMPRODUCT($P$5:$AU$5,P76:AU76)=0,"-",SUMPRODUCT($P$5:$AU$5,P76:AU76)) -> 30 | K76: No invoice until the 75000€ is reached | M76: - | N76: - | O76: - | Q76: 1
A77: Aristocrat | B77: USA | C77: 45908 | D77: BZZF Wheel Blast - Hungarian Help Screens | E77: Megan Nimsgern | F77: Delivered | G77: USA | I77: =IF(SUM(P77:AU77)=0,"-",SUM(P77:AU77)) -> 30 | J77: =IF(SUMPRODUCT($P$5:$AU$5,P77:AU77)=0,"-",SUMPRODUCT($P$5:$AU$5,P77:AU77)) -> 900 | K77: No invoice until the 75000€ is reached | M77: - | N77: - | O77: - | Y77: 30
A78: Aristocrat | B78: USA | C78: 45908 | D78: FR Game Rules Translations - Mo Mo Mo Mummy | E78: Megan Nimsgern | F78: Delivered | G78: USA | H78: https://saranistudio.sharepoint.com/:f:/s/SaraniAssets/EmcS3cdluGBCtd-t52UKBKUBOwmX-gQya_yb5aX1X3gwQQ?e=sfa6df | I78: =IF(SUM(P78:AU78)=0,"-",SUM(P78:AU78)) -> 23 | J78: =IF(SUMPRODUCT($P$5:$AU$5,P78:AU78)=0,"-",SUMPRODUCT($P$5:$AU$5,P78:AU78)) -> 690 | K78: No invoice until the 75000€ is reached | M78: - | N78: - | O78: - | Y78: 23
A79: Aristocrat | B79: USA | C79: 45912 | D79: Slick Rework | E79: Megan Nimsgern | F79: Delivered | G79: USA | H79: 20250912_Slick Rework | I79: =IF(SUM(P79:AU79)=0,"-",SUM(P79:AU79)) -> 6 | J79: =IF(SUMPRODUCT($P$5:$AU$5,P79:AU79)=0,"-",SUMPRODUCT($P$5:$AU$5,P79:AU79)) -> 180 | K79: No invoice until the 75000€ is reached | M79: - | N79: - | O79: - | Q79: 6
A80: Aristocrat | B80: USA | C80: 45908 | D80: BZZF Wheel Blast - Hungarian Help Screens _ 2 | E80: Megan Nimsgern | F80: Delivered | G80: USA | I80: =IF(SUM(P80:AU80)=0,"-",SUM(P80:AU80)) -> 52 | J80: =IF(SUMPRODUCT($P$5:$AU$5,P80:AU80)=0,"-",SUMPRODUCT($P$5:$AU$5,P80:AU80)) -> 1560 | K80: No invoice until the 75000€ is reached | M80: - | N80: - | O80: - | Y80: 52
A81: Aristocrat | B81: USA | C81: 45919 | D81: Spooky Link Slick Update | E81: Megan Nimsgern | F81: Delivered | G81: USA | I81: =IF(SUM(P81:AU81)=0,"-",SUM(P81:AU81)) -> 1 | J81: =IF(SUMPRODUCT($P$5:$AU$5,P81:AU81)=0,"-",SUMPRODUCT($P$5:$AU$5,P81:AU81)) -> 30 | K81: No invoice until the 75000€ is reached | M81: - | N81: - | O81: - | Q81: 1
A82: Aristocrat | B82: USA | C82: 45925 | D82: Creative Request – NFL Ticket Giveaway (Empire Casino) | E82: Megan Nimsgern | F82: Delivered | G82: USA | H82: https://saranistudio.sharepoint.com/:f:/s/SaraniAssets/Et8m5EXA2mROuR5RvyHa46oBj5Bf0hks6DIU3Jd1Bi_u9Q?e=BbTudg | I82: =IF(SUM(P82:AU82)=0,"-",SUM(P82:AU82)) -> 6 | J82: =IF(SUMPRODUCT($P$5:$AU$5,P82:AU82)=0,"-",SUMPRODUCT($P$5:$AU$5,P82:AU82)) -> 285 | K82: No invoice until the 75000€ is reached | M82: - | N82: - | O82: - | P82: 1 | Q82: 5
A83: Aristocrat | B83: USA | C83: 45925 | D83: BZZF Wheel Blast - Hungarian Help Screens _ 3 | E83: Megan Nimsgern | F83: Delivered | G83: USA | H83: 20250930_French Translation Request | I83: =IF(SUM(P83:AU83)=0,"-",SUM(P83:AU83)) -> 73 | J83: =IF(SUMPRODUCT($P$5:$AU$5,P83:AU83)=0,"-",SUMPRODUCT($P$5:$AU$5,P83:AU83)) -> 2190 | K83: No invoice until the 75000€ is reached | M83: - | N83: - | O83: - | Y83: 73
A84: Aristocrat | B84: USA | C84: 45930 | D84: French Translation Request- Royal Collection III | E84: Megan Nimsgern | F84: Delivered | G84: USA | H84: 20250930_French Translation Request- Royal Collection III | I84: =IF(SUM(P84:AU84)=0,"-",SUM(P84:AU84)) -> 82 | J84: =IF(SUMPRODUCT($P$5:$AU$5,P84:AU84)=0,"-",SUMPRODUCT($P$5:$AU$5,P84:AU84)) -> 2460 | K84: No invoice until the 75000€ is reached | M84: - | N84: - | O84: - | Y84: 82
A85: Aristocrat | B85: USA | C85: 45932 | D85: Helix Plus EOL - Translation | E85: Megan Nimsgern | F85: Delivered | G85: USA | H85: https://saranistudio.sharepoint.com/:f:/s/SaraniAssets/EtknSkSz_uFJsRfqk1HFSZEBCKzM8FJMYQYlQTPPP_uWgQ?e=he2lqu | I85: =IF(SUM(P85:AU85)=0,"-",SUM(P85:AU85)) -> 373 | J85: =IF(SUMPRODUCT($P$5:$AU$5,P85:AU85)=0,"-",SUMPRODUCT($P$5:$AU$5,P85:AU85)) -> 44.76 | K85: No invoice until the 75000€ is reached | M85: - | N85: - | O85: - | AS85: 373
A86: Aristocrat | B86: USA | C86: 45947 | D86: Spooky Link and Fa Fa Fa Slick Updates | E86: Megan Nimsgern | F86: Delivered | G86: USA | H86: 20251017_Spooky Link Slick Updates 2 | I86: =IF(SUM(P86:AU86)=0,"-",SUM(P86:AU86)) -> 2 | J86: =IF(SUMPRODUCT($P$5:$AU$5,P86:AU86)=0,"-",SUMPRODUCT($P$5:$AU$5,P86:AU86)) -> 60 | K86: No invoice until the 75000€ is reached | M86: - | N86: - | O86: - | Q86: 2
A87: Aristocrat | B87: USA | C87: 45950 | D87: Dragon Link - Hungarian Translations | E87: Megan Nimsgern | F87: Delivered | G87: USA | H87: 20251020_Dragon Link - Hungarian Translations | I87: =IF(SUM(P87:AU87)=0,"-",SUM(P87:AU87)) -> 54 | J87: =IF(SUMPRODUCT($P$5:$AU$5,P87:AU87)=0,"-",SUMPRODUCT($P$5:$AU$5,P87:AU87)) -> 1620 | K87: No invoice until the 75000€ is reached | M87: - | N87: - | O87: - | Y87: 54
A88: Aristocrat | B88: USA | C88: 45961 | D88: Last Minute Request - Showcase Invitation | E88: Katalina Gomez | F88: Delivered | G88: USA | H88: https://saranistudio.sharepoint.com/:f:/s/SaraniAssets/EogOuLw9DHBLlZC0qXKt4DIBeoUBkVDOsUDWoLqdXdcwmA?e=dxxfaO | I88: =IF(SUM(P88:AU88)=0,"-",SUM(P88:AU88)) -> 102 | J88: =IF(SUMPRODUCT($P$5:$AU$5,P88:AU88)=0,"-",SUMPRODUCT($P$5:$AU$5,P88:AU88)) -> 177 | K88: No invoice until the 75000€ is reached | M88: - | N88: - | O88: - | P88: 1 | Q88: 1 | AS88: 100
A89: Aristocrat | B89: USA | C89: 45965 | D89: Aristocrat UK Slick Updates | E89: Katalina Gomez | F89: Delivered | G89: USA | H89: https://saranistudio.sharepoint.com/:f:/s/SaraniAssets/Er_7dMU59LhMiXI2ftNrw_0BYV0Q9o_HYAt9dwCOAiyboA?e=hCSDfL | I89: =IF(SUM(P89:AU89)=0,"-",SUM(P89:AU89)) -> 4 | J89: =IF(SUMPRODUCT($P$5:$AU$5,P89:AU89)=0,"-",SUMPRODUCT($P$5:$AU$5,P89:AU89)) -> 120 | K89: No invoice until the 75000€ is reached | M89: - | N89: - | O89: - | Q89: 4
A90: Aristocrat | B90: USA | C90: 45971 | D90: Baron Cabinet + Spooky Link Recipes - French Copy | E90: Megan Nimsgern | F90: Delivered | G90: USA | I90: =IF(SUM(P90:AU90)=0,"-",SUM(P90:AU90)) -> 670 | J90: =IF(SUMPRODUCT($P$5:$AU$5,P90:AU90)=0,"-",SUMPRODUCT($P$5:$AU$5,P90:AU90)) -> 80.4 | K90: No invoice until the 75000€ is reached | M90: - | N90: - | O90: - | AS90: 670
A91: Aristocrat | B91: USA | C91: 45973 | D91: Baron Cabinet SFC2A Banner | E91: Megan Nimsgern | F91: Delivered | G91: USA | H91: 20251112_Baron Cabinet SFC2A Banner | I91: =IF(SUM(P91:AU91)=0,"-",SUM(P91:AU91)) -> 1 | J91: =IF(SUMPRODUCT($P$5:$AU$5,P91:AU91)=0,"-",SUMPRODUCT($P$5:$AU$5,P91:AU91)) -> 135 | K91: No invoice until the 75000€ is reached | M91: - | N91: - | O91: - | X91: 1
A92: Aristocrat | B92: USA | C92: 45973 | D92: UK Print Adjustments - Safer Gambling Week | E92: Megan Nimsgern | F92: Delivered | G92: USA | H92: 20251112_UK Print Adjustments - Safer Gambling Week | I92: =IF(SUM(P92:AU92)=0,"-",SUM(P92:AU92)) -> 4 | J92: =IF(SUMPRODUCT($P$5:$AU$5,P92:AU92)=0,"-",SUMPRODUCT($P$5:$AU$5,P92:AU92)) -> 120 | K92: No invoice until the 75000€ is reached | M92: - | N92: - | O92: - | Q92: 4
A93: Aristocrat | B93: USA | C93: 45974 | D93: Spooky Link Recipes - FR Translation - Design | E93: Megan Nimsgern | F93: Delivered | G93: USA | H93: 20251113_Spooky Link Recipes - FR Translation - Design | I93: =IF(SUM(P93:AU93)=0,"-",SUM(P93:AU93)) -> 3 | J93: =IF(SUMPRODUCT($P$5:$AU$5,P93:AU93)=0,"-",SUMPRODUCT($P$5:$AU$5,P93:AU93)) -> 780 | K93: No invoice until the 75000€ is reached | M93: - | N93: - | O93: - | AA93: 3
A94: Aristocrat | B94: USA | C94: 45975 | D94: Spooky Link Video Translations | E94: Megan Nimsgern | F94: Delivered | G94: USA | H94: 20251013_Spooky Link Video Translations | I94: =IF(SUM(P94:AU94)=0,"-",SUM(P94:AU94)) -> 148 | J94: =IF(SUMPRODUCT($P$5:$AU$5,P94:AU94)=0,"-",SUMPRODUCT($P$5:$AU$5,P94:AU94)) -> 17.76 | K94: No invoice until the 75000€ is reached | M94: - | N94: - | O94: - | AS94: 148
A95: Aristocrat | B95: USA | C95: 45979 | D95: French Translations - ICE 2026 | E95: Katalina Gomez | F95: Delivered | G95: USA | I95: =IF(SUM(P95:AU95)=0,"-",SUM(P95:AU95)) -> 24 | J95: =IF(SUMPRODUCT($P$5:$AU$5,P95:AU95)=0,"-",SUMPRODUCT($P$5:$AU$5,P95:AU95)) -> 2.88 | K95: No invoice until the 75000€ is reached | M95: - | N95: - | O95: - | AS95: 24
A96: Aristocrat | B96: USA | C96: 45979 | D96: ICE 2026 Escalator & Pillar Branding | E96: Megan Nimsgern | F96: Delivered | G96: USA | H96: 20251118_ICE 2026 Escalator & Pillar Branding | I96: =IF(SUM(P96:AU96)=0,"-",SUM(P96:AU96)) -> 23 | J96: =IF(SUMPRODUCT($P$5:$AU$5,P96:AU96)=0,"-",SUMPRODUCT($P$5:$AU$5,P96:AU96)) -> 1395 | K96: No invoice until the 75000€ is reached | M96: - | N96: - | O96: - | X96: 1 | Y96: 18 | AB96: 4
A97: Aristocrat | B97: USA | C97: 45980 | D97: Creative Requests – Spooky Link France Launch | E97: Megan Nimsgern | F97: Delivered | G97: USA | H97: 20251119_Creative Requests – Spooky Link France Launch | I97: =IF(SUM(P97:AU97)=0,"-",SUM(P97:AU97)) -> 8 | J97: =IF(SUMPRODUCT($P$5:$AU$5,P97:AU97)=0,"-",SUMPRODUCT($P$5:$AU$5,P97:AU97)) -> 870 | K97: No invoice until the 75000€ is reached | M97: - | N97: - | O97: - | P97: 6 | Q97: 2
A98: Aristocrat | B98: USA | C98: 45981 | D98: Spooky Link Press Release - French Translation | E98: Megan Nimsgern | F98: Delivered | G98: USA | I98: =IF(SUM(P98:AU98)=0,"-",SUM(P98:AU98)) -> 191 | J98: =IF(SUMPRODUCT($P$5:$AU$5,P98:AU98)=0,"-",SUMPRODUCT($P$5:$AU$5,P98:AU98)) -> 22.92 | K98: No invoice until the 75000€ is reached | M98: - | N98: - | O98: - | AS98: 191
A99: Aristocrat | B99: USA | C99: 45981 | D99: Buffalo Ultimate Stampede Slick | E99: Megan Nimsgern | F99: Delivered | G99: USA | H99: https://saranistudio.sharepoint.com/:f:/s/SaraniAssets/IgDuOueP-jMFSJIp1LEkIhubARbm0nhhsdZDKCq-VqeGXO0?e=xQ8kBi | I99: =IF(SUM(P99:AU99)=0,"-",SUM(P99:AU99)) -> 1 | J99: =IF(SUMPRODUCT($P$5:$AU$5,P99:AU99)=0,"-",SUMPRODUCT($P$5:$AU$5,P99:AU99)) -> 30 | K99: No invoice until the 75000€ is reached | M99: - | N99: - | O99: - | Q99: 1
A100: Aristocrat | B100: USA | C100: 45981 | D100: Creative Request - ICE 2026 Teaser Ad FR & EN | E100: Megan Nimsgern | F100: Delivered | G100: USA | H100: 20251120_Creative Request - ICE 2026 Teaser Ad FR & EN | I100: =IF(SUM(P100:AU100)=0,"-",SUM(P100:AU100)) -> 4 | J100: =IF(SUMPRODUCT($P$5:$AU$5,P100:AU100)=0,"-",SUMPRODUCT($P$5:$AU$5,P100:AU100)) -> 225 | K100: No invoice until the 75000€ is reached | M100: - | N100: - | O100: - | P100: 1 | Q100: 3
...

Sheet Aristocrat (Asia)
J1: =SUBTOTAL(2,J6:J19930) -> 7 | P1: =SUBTOTAL(2,P6:P19883) -> 4 | Q1: =SUBTOTAL(2,Q6:Q19883) -> 1 | R1: =SUBTOTAL(2,R6:R19883) -> 0 | S1: =SUBTOTAL(2,S6:S19883) -> 0 | T1: =SUBTOTAL(2,T6:T19883) -> 0 | U1: =SUBTOTAL(2,U6:U19883) -> 0 | V1: =SUBTOTAL(2,V6:V19883) -> 0 | W1: =SUBTOTAL(2,W6:W19883) -> 1 | ... AK1: =SUBTOTAL(2,AK6:AK19883) -> 0 | AM1: =SUBTOTAL(2,AM6:AM19883) -> 0 | AN1: =SUBTOTAL(2,AN6:AN19883) -> 0 | AO1: =SUBTOTAL(2,AO6:AO19883) -> 0 | AP1: =SUBTOTAL(2,AP6:AP19883) -> 0 | AQ1: =SUBTOTAL(2,AQ6:AQ19883) -> 0 | AR1: =SUBTOTAL(2,AR6:AR19883) -> 0 | AS1: =SUBTOTAL(2,AS6:AS19883) -> 0 | AT1: =SUBTOTAL(2,AT6:AT19883) -> 0
I2: =SUBTOTAL(9,I6:I19931) -> 26 | J2: =SUBTOTAL(9,J6:J19931) -> 11955 | P2: =SUBTOTAL(9,P6:P19884)*P5 -> 1050 | Q2: =SUBTOTAL(9,Q6:Q19884)*Q5 -> 35 | R2: =SUBTOTAL(9,R6:R19884)*R5 -> 0 | S2: =SUBTOTAL(9,S6:S19884)*S5 -> 0 | T2: =SUBTOTAL(9,T6:T19884)*T5 -> 0 | U2: =SUBTOTAL(9,U6:U19884)*U5 -> 0 | V2: =SUBTOTAL(9,V6:V19884)*V5 -> 0 | W2: =SUBTOTAL(9,W6:W19884)*W5 -> 600 | ... AK2: =SUBTOTAL(9,AK6:AK19884)*AK5 -> 0 | AM2: =SUBTOTAL(9,AM6:AM19884)*AM5 -> 0 | AN2: =SUBTOTAL(9,AN6:AN19884)*AN5 -> 0 | AO2: =SUBTOTAL(9,AO6:AO19884)*AO5 -> 0 | AP2: =SUBTOTAL(9,AP6:AP19884)*AP5 -> 0 | AQ2: =SUBTOTAL(9,AQ6:AQ19884)*AQ5 -> 0 | AR2: =SUBTOTAL(9,AR6:AR19884)*AR5 -> 0 | AS2: =SUBTOTAL(9,AS6:AS19884)*AS5 -> 0 | AT2: =SUBTOTAL(9,AT6:AT19884)*AT5 -> 0
A3: Price File | P3: Online | W3: Offline | AC3: Presentations | AD3: Web | AH3: Videos | AO3: Contentful | AS3: Copy
A4: Project | E4: Details | P4: Banner creation (static) | Q4: Banner adaptation (static) | R4: Banner creation (animated) | S4: Banner adaptation (animated) | T4: Buttons | U4: Logo | V4: Wallpapers | W4: Offline creation (standard) | X4: Offline creation (adaptation) | Y4: Leaflet (1 page) | Z4: Leaflet (2 pages) | AA4: Roll-up / Wall creation | AB4: Brochure (20 pages) | AC4: Slide | AD4: Landing page (design only) | AE4: Landing page (complete) | AF4: Website (design only) | AG4: Website (complete) | AH4: Video Edition | AI4: Video Subtitles | AJ4: Social Media Video (up to 30s) | AK4: Social Media Video (up to 1 min) | AL4: Sizzle videos | AM4: Promotional Video (up to 1 min) | AN4: 2D Video (up to 3mn) | AO4: Case study (per article) | AP4: Blog article (per article) | AQ4: Translation (per article) | AR4: Splash (per creation/modification) | AS4: Translation (per word) | AT4: Copywrite (per word)
A5: Customer | B5: Division | C5: Date | D5: Project | E5: Contact | F5: Status | G5: Category | H5: Link | I5: Assets | J5: Total Value | K5: Quote | L5: PO | M5: Invoice | N5: n° Invoice | O5: Statut | P5: 150 | Q5: 35 | R5: 250 | S5: 55 | T5: 20 | U5: 275 | V5: 90 | W5: 150 | X5: 45 | Y5: 200 | Z5: 280 | AA5: 200 | AB5: 2500 | AC5: 35 | AD5: 350 | AE5: 750 | AF5: 5500 | AG5: 7800 | AH5: 90 | AI5: 165 | AJ5: 390 | AK5: 490 | AL5: 900 | AM5: 4500 | AN5: 5500 | AO5: 38 | AP5: 45 | AQ5: 27 | AR5: 35 | AS5: 0.15 | AT5: =0.25*1.08 -> 0.27
A6: Aristocrat | B6: Asia | C6: 45990 | D6: ASIA - Golf cart and Tee marker design | E6: Sandy Cheng | F6: Delivered | G6: Asia | H6: https://saranistudio.sharepoint.com/:f:/s/SaraniAssets/IgBdCWHuWVRfQrbR0t0XwCNIAeRvzdTBf6qlizKedyhzBgQ?e=kH1ara | I6: =IF(SUM(P6:AU6)=0,"-",SUM(P6:AU6)) -> 10 | J6: =IF(SUMPRODUCT($P$5:$AU$5,P6:AU6)=0,"-",SUMPRODUCT($P$5:$AU$5,P6:AU6)) -> 870 | M6: Sent to Sandy | N6: F2026-0011 | O6: Waiting payment for 13/02/2026 | W6: 4 | X6: 6
A7: Aristocrat | B7: Asia | C7: 45992 | D7: ASIA - Breadcrumb Trail Campaign | E7: Kimmi Siu Dewar | F7: Delivered | G7: Asia | H7: https://saranistudio.sharepoint.com/:f:/s/SaraniAssets/IgCuiILQq2S2TrXioMp8gx4fAf8B2IdugBwuN-6fB_VQhSc?e=MXflGl | I7: =IF(SUM(P7:AU7)=0,"-",SUM(P7:AU7)) -> 4 | J7: =IF(SUMPRODUCT($P$5:$AU$5,P7:AU7)=0,"-",SUMPRODUCT($P$5:$AU$5,P7:AU7)) -> 600 | M7: Sent to Sandy | N7: F2026-0011 | O7: Waiting payment for 13/02/2026 | P7: 4
A8: Aristocrat | B8: Asia | C8: 46007 | D8: 2026 APAC golf tournament invitation | E8: Kimmi Siu Dewar | F8: Delivered | G8: Asia | H8: https://saranistudio.sharepoint.com/:f:/s/SaraniAssets/IgC-ZsA9vy8mQbe2tRFmtycDAbz6VH3vle4XWtHaXmd9n8M?e=RWBfi8 | I8: =IF(SUM(P8:AU8)=0,"-",SUM(P8:AU8)) -> 1 | J8: =IF(SUMPRODUCT($P$5:$AU$5,P8:AU8)=0,"-",SUMPRODUCT($P$5:$AU$5,P8:AU8)) -> 150 | M8: Sent to Sandy | N8: F2026-0011 | O8: Waiting payment for 13/02/2026 | P8: 1
A9: Aristocrat | B9: Asia | C9: 46033 | D9: ASIA - Artwork brief BARON LAUNCH VN | E9: Kimmi Siu Dewar | F9: Delivered | G9: Asia | H9: https://saranistudio.sharepoint.com/:f:/s/SaraniAssets/IgALARsc58n_TaIw7pez_8hgAfGR1yqPDQpjLbdcLvgMDL8?e=EqPadB | I9: =IF(SUM(P9:AU9)=0,"-",SUM(P9:AU9)) -> 1 | J9: =IF(SUMPRODUCT($P$5:$AU$5,P9:AU9)=0,"-",SUMPRODUCT($P$5:$AU$5,P9:AU9)) -> 150 | M9: Sent to Sandy | N9: F2026-0094 | O9: Waiting payment for 02/04/2026 | P9: 1
A10: Aristocrat | B10: Asia | C10: 46034 | D10: Artwork brief for Print ads and web banner artwork | E10: Sandy Cheng | F10: Delivered | G10: Asia | H10: 20260112_Artwork brief for Print ads and web banner artwork | I10: =IF(SUM(P10:AU10)=0,"-",SUM(P10:AU10)) -> 2 | J10: =IF(SUMPRODUCT($P$5:$AU$5,P10:AU10)=0,"-",SUMPRODUCT($P$5:$AU$5,P10:AU10)) -> 185 | M10: Sent to Sandy | N10: F2026-0094 | O10: Waiting payment for 02/04/2026 | P10: 1 | Q10: 1
A11: Aristocrat | B11: Asia | C11: 46056 | D11: Aristocrat 3D Models -Part 1 | E11: Stephanie Che | F11: In progress | G11: Asia | H11: 20260203_Aristocrat 3D Models | I11: 4 | J11: 5000 | M11: Sent to Ameena | N11: F2026-0130 | O11: Waiting payment for 24/04/2026
A12: Aristocrat | B12: Asia | C12: 46056 | D12: Aristocrat 3D Models -Part 2 | E12: Stephanie Che | F12: In progress | G12: Asia | H12: 20260203_Aristocrat 3D Models | I12: 4 | J12: 5000
I13: =IF(SUM(P13:AU13)=0,"-",SUM(P13:AU13)) -> - | J13: =IF(SUMPRODUCT($P$5:$AU$5,P13:AU13)=0,"-",SUMPRODUCT($P$5:$AU$5,P13:AU13)) -> -
I14: =IF(SUM(P14:AU14)=0,"-",SUM(P14:AU14)) -> - | J14: =IF(SUMPRODUCT($P$5:$AU$5,P14:AU14)=0,"-",SUMPRODUCT($P$5:$AU$5,P14:AU14)) -> -
I15: =IF(SUM(P15:AU15)=0,"-",SUM(P15:AU15)) -> - | J15: =IF(SUMPRODUCT($P$5:$AU$5,P15:AU15)=0,"-",SUMPRODUCT($P$5:$AU$5,P15:AU15)) -> -
I16: =IF(SUM(P16:AU16)=0,"-",SUM(P16:AU16)) -> - | J16: =IF(SUMPRODUCT($P$5:$AU$5,P16:AU16)=0,"-",SUMPRODUCT($P$5:$AU$5,P16:AU16)) -> -
I17: =IF(SUM(P17:AU17)=0,"-",SUM(P17:AU17)) -> - | J17: =IF(SUMPRODUCT($P$5:$AU$5,P17:AU17)=0,"-",SUMPRODUCT($P$5:$AU$5,P17:AU17)) -> -
I18: =IF(SUM(P18:AU18)=0,"-",SUM(P18:AU18)) -> - | J18: =IF(SUMPRODUCT($P$5:$AU$5,P18:AU18)=0,"-",SUMPRODUCT($P$5:$AU$5,P18:AU18)) -> -
I19: =IF(SUM(P19:AU19)=0,"-",SUM(P19:AU19)) -> - | J19: =IF(SUMPRODUCT($P$5:$AU$5,P19:AU19)=0,"-",SUMPRODUCT($P$5:$AU$5,P19:AU19)) -> -
I20: =IF(SUM(P20:AU20)=0,"-",SUM(P20:AU20)) -> - | J20: =IF(SUMPRODUCT($P$5:$AU$5,P20:AU20)=0,"-",SUMPRODUCT($P$5:$AU$5,P20:AU20)) -> -
I21: =IF(SUM(P21:AU21)=0,"-",SUM(P21:AU21)) -> - | J21: =IF(SUMPRODUCT($P$5:$AU$5,P21:AU21)=0,"-",SUMPRODUCT($P$5:$AU$5,P21:AU21)) -> -
I22: =IF(SUM(P22:AU22)=0,"-",SUM(P22:AU22)) -> - | J22: =IF(SUMPRODUCT($P$5:$AU$5,P22:AU22)=0,"-",SUMPRODUCT($P$5:$AU$5,P22:AU22)) -> -
I23: =IF(SUM(P23:AU23)=0,"-",SUM(P23:AU23)) -> - | J23: =IF(SUMPRODUCT($P$5:$AU$5,P23:AU23)=0,"-",SUMPRODUCT($P$5:$AU$5,P23:AU23)) -> -
I24: =IF(SUM(P24:AU24)=0,"-",SUM(P24:AU24)) -> - | J24: =IF(SUMPRODUCT($P$5:$AU$5,P24:AU24)=0,"-",SUMPRODUCT($P$5:$AU$5,P24:AU24)) -> -
... I35: =IF(SUM(P35:AU35)=0,"-",SUM(P35:AU35)) -> - | J35: =IF(SUMPRODUCT($P$5:$AU$5,P35:AU35)=0,"-",SUMPRODUCT($P$5:$AU$5,P35:AU35)) -> -
