Workbook

Sheet Overview
A1: Performance Dashboard — Ubi (Sarani)
A3: REVENUS (€) | B3: 2025 | F3: 2026
B4: Q1 | C4: Q2 | D4: Q3 | E4: Q4 | F4: Q1 | G4: Q2 | H4: Q3 | I4: Q4
A5: Adidas | B5: =SUMIFS(Ubi!$K:$K,Ubi!$C:$C,">="&DATE(2025,1,1),Ubi!$C:$C,"<="&DATE(2025,3+1,0),Ubi!$B:$B,"*Adidas*") -> 7760 | C5: =SUMIFS(Ubi!$K:$K,Ubi!$C:$C,">="&DATE(2025,4,1),Ubi!$C:$C,"<="&DATE(2025,6+1,0),Ubi!$B:$B,"*Adidas*") -> 22995 | D5: =SUMIFS(Ubi!$K:$K,Ubi!$C:$C,">="&DATE(2025,7,1),Ubi!$C:$C,"<="&DATE(2025,9+1,0),Ubi!$B:$B,"*Adidas*") -> 10105 | E5: =SUMIFS(Ubi!$K:$K,Ubi!$C:$C,">="&DATE(2025,10,1),Ubi!$C:$C,"<="&DATE(2025,12+1,0),Ubi!$B:$B,"*Adidas*") -> 4920 | F5: =SUMIFS(Ubi!$K:$K,Ubi!$C:$C,">="&DATE(2026,1,1),Ubi!$C:$C,"<="&DATE(2026,3+1,0),Ubi!$B:$B,"*Adidas*") -> 1806.6667 | G5: =SUMIFS(Ubi!$K:$K,Ubi!$C:$C,">="&DATE(2026,4,1),Ubi!$C:$C,"<="&DATE(2026,6+1,0),Ubi!$B:$B,"*Adidas*") -> 0 | H5: =SUMIFS(Ubi!$K:$K,Ubi!$C:$C,">="&DATE(2026,7,1),Ubi!$C:$C,"<="&DATE(2026,9+1,0),Ubi!$B:$B,"*Adidas*") -> 0 | I5: =SUMIFS(Ubi!$K:$K,Ubi!$C:$C,">="&DATE(2026,10,1),Ubi!$C:$C,"<="&DATE(2026,12+1,0),Ubi!$B:$B,"*Adidas*") -> 0
A6: Red Bull | B6: =SUMIFS(Ubi!$K:$K,Ubi!$C:$C,">="&DATE(2025,1,1),Ubi!$C:$C,"<="&DATE(2025,3+1,0),Ubi!$B:$B,"*Red Bull*") -> 610 | C6: =SUMIFS(Ubi!$K:$K,Ubi!$C:$C,">="&DATE(2025,4,1),Ubi!$C:$C,"<="&DATE(2025,6+1,0),Ubi!$B:$B,"*Red Bull*") -> 0 | D6: =SUMIFS(Ubi!$K:$K,Ubi!$C:$C,">="&DATE(2025,7,1),Ubi!$C:$C,"<="&DATE(2025,9+1,0),Ubi!$B:$B,"*Red Bull*") -> 0 | E6: =SUMIFS(Ubi!$K:$K,Ubi!$C:$C,">="&DATE(2025,10,1),Ubi!$C:$C,"<="&DATE(2025,12+1,0),Ubi!$B:$B,"*Red Bull*") -> 4680 | F6: =SUMIFS(Ubi!$K:$K,Ubi!$C:$C,">="&DATE(2026,1,1),Ubi!$C:$C,"<="&DATE(2026,3+1,0),Ubi!$B:$B,"*Red Bull*") -> 0 | G6: =SUMIFS(Ubi!$K:$K,Ubi!$C:$C,">="&DATE(2026,4,1),Ubi!$C:$C,"<="&DATE(2026,6+1,0),Ubi!$B:$B,"*Red Bull*") -> 0 | H6: =SUMIFS(Ubi!$K:$K,Ubi!$C:$C,">="&DATE(2026,7,1),Ubi!$C:$C,"<="&DATE(2026,9+1,0),Ubi!$B:$B,"*Red Bull*") -> 0 | I6: =SUMIFS(Ubi!$K:$K,Ubi!$C:$C,">="&DATE(2026,10,1),Ubi!$C:$C,"<="&DATE(2026,12+1,0),Ubi!$B:$B,"*Red Bull*") -> 0
A7: LEGO | B7: =SUMIFS(Ubi!$K:$K,Ubi!$C:$C,">="&DATE(2025,1,1),Ubi!$C:$C,"<="&DATE(2025,3+1,0),Ubi!$B:$B,"*LEGO*") -> 185 | C7: =SUMIFS(Ubi!$K:$K,Ubi!$C:$C,">="&DATE(2025,4,1),Ubi!$C:$C,"<="&DATE(2025,6+1,0),Ubi!$B:$B,"*LEGO*") -> 2520 | D7: =SUMIFS(Ubi!$K:$K,Ubi!$C:$C,">="&DATE(2025,7,1),Ubi!$C:$C,"<="&DATE(2025,9+1,0),Ubi!$B:$B,"*LEGO*") -> 4515 | E7: =SUMIFS(Ubi!$K:$K,Ubi!$C:$C,">="&DATE(2025,10,1),Ubi!$C:$C,"<="&DATE(2025,12+1,0),Ubi!$B:$B,"*LEGO*") -> 0 | F7: =SUMIFS(Ubi!$K:$K,Ubi!$C:$C,">="&DATE(2026,1,1),Ubi!$C:$C,"<="&DATE(2026,3+1,0),Ubi!$B:$B,"*LEGO*") -> 0 | G7: =SUMIFS(Ubi!$K:$K,Ubi!$C:$C,">="&DATE(2026,4,1),Ubi!$C:$C,"<="&DATE(2026,6+1,0),Ubi!$B:$B,"*LEGO*") -> 0 | H7: =SUMIFS(Ubi!$K:$K,Ubi!$C:$C,">="&DATE(2026,7,1),Ubi!$C:$C,"<="&DATE(2026,9+1,0),Ubi!$B:$B,"*LEGO*") -> 0 | I7: =SUMIFS(Ubi!$K:$K,Ubi!$C:$C,">="&DATE(2026,10,1),Ubi!$C:$C,"<="&DATE(2026,12+1,0),Ubi!$B:$B,"*LEGO*") -> 0
A8: Ubisoft | B8: =SUMIFS(Ubi!$K:$K,Ubi!$C:$C,">="&DATE(2025,1,1),Ubi!$C:$C,"<="&DATE(2025,3+1,0),Ubi!$B:$B,"*Ubisoft*")+SUMIFS(Ubi!$K:$K,Ubi!$C:$C,">="&DATE(2025,1,1),Ubi!$C:$C,"<="&DATE(2025,3+1,0),Ubi!$B:$B,"UBI") -> 450 | C8: =SUMIFS(Ubi!$K:$K,Ubi!$C:$C,">="&DATE(2025,4,1),Ubi!$C:$C,"<="&DATE(2025,6+1,0),Ubi!$B:$B,"*Ubisoft*")+SUMIFS(Ubi!$K:$K,Ubi!$C:$C,">="&DATE(2025,4,1),Ubi!$C:$C,"<="&DATE(2025,6+1,0),Ubi!$B:$B,"UBI") -> 1365 | D8: =SUMIFS(Ubi!$K:$K,Ubi!$C:$C,">="&DATE(2025,7,1),Ubi!$C:$C,"<="&DATE(2025,9+1,0),Ubi!$B:$B,"*Ubisoft*")+SUMIFS(Ubi!$K:$K,Ubi!$C:$C,">="&DATE(2025,7,1),Ubi!$C:$C,"<="&DATE(2025,9+1,0),Ubi!$B:$B,"UBI") -> 0 | E8: =SUMIFS(Ubi!$K:$K,Ubi!$C:$C,">="&DATE(2025,10,1),Ubi!$C:$C,"<="&DATE(2025,12+1,0),Ubi!$B:$B,"*Ubisoft*")+SUMIFS(Ubi!$K:$K,Ubi!$C:$C,">="&DATE(2025,10,1),Ubi!$C:$C,"<="&DATE(2025,12+1,0),Ubi!$B:$B,"UBI") -> 740 | F8: =SUMIFS(Ubi!$K:$K,Ubi!$C:$C,">="&DATE(2026,1,1),Ubi!$C:$C,"<="&DATE(2026,3+1,0),Ubi!$B:$B,"*Ubisoft*")+SUMIFS(Ubi!$K:$K,Ubi!$C:$C,">="&DATE(2026,1,1),Ubi!$C:$C,"<="&DATE(2026,3+1,0),Ubi!$B:$B,"UBI") -> 0 | G8: =SUMIFS(Ubi!$K:$K,Ubi!$C:$C,">="&DATE(2026,4,1),Ubi!$C:$C,"<="&DATE(2026,6+1,0),Ubi!$B:$B,"*Ubisoft*")+SUMIFS(Ubi!$K:$K,Ubi!$C:$C,">="&DATE(2026,4,1),Ubi!$C:$C,"<="&DATE(2026,6+1,0),Ubi!$B:$B,"UBI") -> 0 | H8: =SUMIFS(Ubi!$K:$K,Ubi!$C:$C,">="&DATE(2026,7,1),Ubi!$C:$C,"<="&DATE(2026,9+1,0),Ubi!$B:$B,"*Ubisoft*")+SUMIFS(Ubi!$K:$K,Ubi!$C:$C,">="&DATE(2026,7,1),Ubi!$C:$C,"<="&DATE(2026,9+1,0),Ubi!$B:$B,"UBI") -> 0 | I8: =SUMIFS(Ubi!$K:$K,Ubi!$C:$C,">="&DATE(2026,10,1),Ubi!$C:$C,"<="&DATE(2026,12+1,0),Ubi!$B:$B,"*Ubisoft*")+SUMIFS(Ubi!$K:$K,Ubi!$C:$C,">="&DATE(2026,10,1),Ubi!$C:$C,"<="&DATE(2026,12+1,0),Ubi!$B:$B,"UBI") -> 0
A9: Perrier | B9: =SUMIFS(Ubi!$K:$K,Ubi!$C:$C,">="&DATE(2025,1,1),Ubi!$C:$C,"<="&DATE(2025,3+1,0),Ubi!$B:$B,"*Perrier*") -> 0 | C9: =SUMIFS(Ubi!$K:$K,Ubi!$C:$C,">="&DATE(2025,4,1),Ubi!$C:$C,"<="&DATE(2025,6+1,0),Ubi!$B:$B,"*Perrier*") -> 1130 | D9: =SUMIFS(Ubi!$K:$K,Ubi!$C:$C,">="&DATE(2025,7,1),Ubi!$C:$C,"<="&DATE(2025,9+1,0),Ubi!$B:$B,"*Perrier*") -> 0 | E9: =SUMIFS(Ubi!$K:$K,Ubi!$C:$C,">="&DATE(2025,10,1),Ubi!$C:$C,"<="&DATE(2025,12+1,0),Ubi!$B:$B,"*Perrier*") -> 0 | F9: =SUMIFS(Ubi!$K:$K,Ubi!$C:$C,">="&DATE(2026,1,1),Ubi!$C:$C,"<="&DATE(2026,3+1,0),Ubi!$B:$B,"*Perrier*") -> 0 | G9: =SUMIFS(Ubi!$K:$K,Ubi!$C:$C,">="&DATE(2026,4,1),Ubi!$C:$C,"<="&DATE(2026,6+1,0),Ubi!$B:$B,"*Perrier*") -> 0 | H9: =SUMIFS(Ubi!$K:$K,Ubi!$C:$C,">="&DATE(2026,7,1),Ubi!$C:$C,"<="&DATE(2026,9+1,0),Ubi!$B:$B,"*Perrier*") -> 0 | I9: =SUMIFS(Ubi!$K:$K,Ubi!$C:$C,">="&DATE(2026,10,1),Ubi!$C:$C,"<="&DATE(2026,12+1,0),Ubi!$B:$B,"*Perrier*") -> 0
A10: IKEA | B10: =SUMIFS(Ubi!$K:$K,Ubi!$C:$C,">="&DATE(2025,1,1),Ubi!$C:$C,"<="&DATE(2025,3+1,0),Ubi!$B:$B,"*IKEA*") -> 0 | C10: =SUMIFS(Ubi!$K:$K,Ubi!$C:$C,">="&DATE(2025,4,1),Ubi!$C:$C,"<="&DATE(2025,6+1,0),Ubi!$B:$B,"*IKEA*") -> 0 | D10: =SUMIFS(Ubi!$K:$K,Ubi!$C:$C,">="&DATE(2025,7,1),Ubi!$C:$C,"<="&DATE(2025,9+1,0),Ubi!$B:$B,"*IKEA*") -> 6950 | E10: =SUMIFS(Ubi!$K:$K,Ubi!$C:$C,">="&DATE(2025,10,1),Ubi!$C:$C,"<="&DATE(2025,12+1,0),Ubi!$B:$B,"*IKEA*") -> 2700 | F10: =SUMIFS(Ubi!$K:$K,Ubi!$C:$C,">="&DATE(2026,1,1),Ubi!$C:$C,"<="&DATE(2026,3+1,0),Ubi!$B:$B,"*IKEA*") -> 0 | G10: =SUMIFS(Ubi!$K:$K,Ubi!$C:$C,">="&DATE(2026,4,1),Ubi!$C:$C,"<="&DATE(2026,6+1,0),Ubi!$B:$B,"*IKEA*") -> 0 | H10: =SUMIFS(Ubi!$K:$K,Ubi!$C:$C,">="&DATE(2026,7,1),Ubi!$C:$C,"<="&DATE(2026,9+1,0),Ubi!$B:$B,"*IKEA*") -> 0 | I10: =SUMIFS(Ubi!$K:$K,Ubi!$C:$C,">="&DATE(2026,10,1),Ubi!$C:$C,"<="&DATE(2026,12+1,0),Ubi!$B:$B,"*IKEA*") -> 0
A11: L'Oréal | B11: =SUMIFS(Ubi!$K:$K,Ubi!$C:$C,">="&DATE(2025,1,1),Ubi!$C:$C,"<="&DATE(2025,3+1,0),Ubi!$B:$B,"*L'Oréal*") -> 0 | C11: =SUMIFS(Ubi!$K:$K,Ubi!$C:$C,">="&DATE(2025,4,1),Ubi!$C:$C,"<="&DATE(2025,6+1,0),Ubi!$B:$B,"*L'Oréal*") -> 0 | D11: =SUMIFS(Ubi!$K:$K,Ubi!$C:$C,">="&DATE(2025,7,1),Ubi!$C:$C,"<="&DATE(2025,9+1,0),Ubi!$B:$B,"*L'Oréal*") -> 3390 | E11: =SUMIFS(Ubi!$K:$K,Ubi!$C:$C,">="&DATE(2025,10,1),Ubi!$C:$C,"<="&DATE(2025,12+1,0),Ubi!$B:$B,"*L'Oréal*") -> 0 | F11: =SUMIFS(Ubi!$K:$K,Ubi!$C:$C,">="&DATE(2026,1,1),Ubi!$C:$C,"<="&DATE(2026,3+1,0),Ubi!$B:$B,"*L'Oréal*") -> 0 | G11: =SUMIFS(Ubi!$K:$K,Ubi!$C:$C,">="&DATE(2026,4,1),Ubi!$C:$C,"<="&DATE(2026,6+1,0),Ubi!$B:$B,"*L'Oréal*") -> 0 | H11: =SUMIFS(Ubi!$K:$K,Ubi!$C:$C,">="&DATE(2026,7,1),Ubi!$C:$C,"<="&DATE(2026,9+1,0),Ubi!$B:$B,"*L'Oréal*") -> 0 | I11: =SUMIFS(Ubi!$K:$K,Ubi!$C:$C,">="&DATE(2026,10,1),Ubi!$C:$C,"<="&DATE(2026,12+1,0),Ubi!$B:$B,"*L'Oréal*") -> 0
A12: TikTok | B12: =SUMIFS(Ubi!$K:$K,Ubi!$C:$C,">="&DATE(2025,1,1),Ubi!$C:$C,"<="&DATE(2025,3+1,0),Ubi!$B:$B,"*TikTok*") -> 0 | C12: =SUMIFS(Ubi!$K:$K,Ubi!$C:$C,">="&DATE(2025,4,1),Ubi!$C:$C,"<="&DATE(2025,6+1,0),Ubi!$B:$B,"*TikTok*") -> 0 | D12: =SUMIFS(Ubi!$K:$K,Ubi!$C:$C,">="&DATE(2025,7,1),Ubi!$C:$C,"<="&DATE(2025,9+1,0),Ubi!$B:$B,"*TikTok*") -> 0 | E12: =SUMIFS(Ubi!$K:$K,Ubi!$C:$C,">="&DATE(2025,10,1),Ubi!$C:$C,"<="&DATE(2025,12+1,0),Ubi!$B:$B,"*TikTok*") -> 9800 | F12: =SUMIFS(Ubi!$K:$K,Ubi!$C:$C,">="&DATE(2026,1,1),Ubi!$C:$C,"<="&DATE(2026,3+1,0),Ubi!$B:$B,"*TikTok*") -> 0 | G12: =SUMIFS(Ubi!$K:$K,Ubi!$C:$C,">="&DATE(2026,4,1),Ubi!$C:$C,"<="&DATE(2026,6+1,0),Ubi!$B:$B,"*TikTok*") -> 0 | H12: =SUMIFS(Ubi!$K:$K,Ubi!$C:$C,">="&DATE(2026,7,1),Ubi!$C:$C,"<="&DATE(2026,9+1,0),Ubi!$B:$B,"*TikTok*") -> 0 | I12: =SUMIFS(Ubi!$K:$K,Ubi!$C:$C,">="&DATE(2026,10,1),Ubi!$C:$C,"<="&DATE(2026,12+1,0),Ubi!$B:$B,"*TikTok*") -> 0
A13: Barilla | B13: =SUMIFS(Ubi!$K:$K,Ubi!$C:$C,">="&DATE(2025,1,1),Ubi!$C:$C,"<="&DATE(2025,3+1,0),Ubi!$B:$B,"*Barilla*") -> 0 | C13: =SUMIFS(Ubi!$K:$K,Ubi!$C:$C,">="&DATE(2025,4,1),Ubi!$C:$C,"<="&DATE(2025,6+1,0),Ubi!$B:$B,"*Barilla*") -> 0 | D13: =SUMIFS(Ubi!$K:$K,Ubi!$C:$C,">="&DATE(2025,7,1),Ubi!$C:$C,"<="&DATE(2025,9+1,0),Ubi!$B:$B,"*Barilla*") -> 0 | E13: =SUMIFS(Ubi!$K:$K,Ubi!$C:$C,">="&DATE(2025,10,1),Ubi!$C:$C,"<="&DATE(2025,12+1,0),Ubi!$B:$B,"*Barilla*") -> 165 | F13: =SUMIFS(Ubi!$K:$K,Ubi!$C:$C,">="&DATE(2026,1,1),Ubi!$C:$C,"<="&DATE(2026,3+1,0),Ubi!$B:$B,"*Barilla*") -> 0 | G13: =SUMIFS(Ubi!$K:$K,Ubi!$C:$C,">="&DATE(2026,4,1),Ubi!$C:$C,"<="&DATE(2026,6+1,0),Ubi!$B:$B,"*Barilla*") -> 0 | H13: =SUMIFS(Ubi!$K:$K,Ubi!$C:$C,">="&DATE(2026,7,1),Ubi!$C:$C,"<="&DATE(2026,9+1,0),Ubi!$B:$B,"*Barilla*") -> 0 | I13: =SUMIFS(Ubi!$K:$K,Ubi!$C:$C,">="&DATE(2026,10,1),Ubi!$C:$C,"<="&DATE(2026,12+1,0),Ubi!$B:$B,"*Barilla*") -> 0
A14: TOTAL | B14: =SUM(B5:B13) -> 9005 | C14: =SUM(C5:C13) -> 28010 | D14: =SUM(D5:D13) -> 24960 | E14: =SUM(E5:E13) -> 23005 | F14: =SUM(F5:F13) -> 1806.6667 | G14: =SUM(G5:G13) -> 0 | H14: =SUM(H5:H13) -> 0 | I14: =SUM(I5:I13) -> 0
A16: NOMBRE DE PROJETS | B16: 2025 | F16: 2026
B17: Q1 | C17: Q2 | D17: Q3 | E17: Q4 | F17: Q1 | G17: Q2 | H17: Q3 | I17: Q4
A18: Adidas | B18: =COUNTIFS(Ubi!$C:$C,">="&DATE(2025,1,1),Ubi!$C:$C,"<="&DATE(2025,3+1,0),Ubi!$B:$B,"*Adidas*") -> 13 | C18: =COUNTIFS(Ubi!$C:$C,">="&DATE(2025,4,1),Ubi!$C:$C,"<="&DATE(2025,6+1,0),Ubi!$B:$B,"*Adidas*") -> 43 | D18: =COUNTIFS(Ubi!$C:$C,">="&DATE(2025,7,1),Ubi!$C:$C,"<="&DATE(2025,9+1,0),Ubi!$B:$B,"*Adidas*") -> 11 | E18: =COUNTIFS(Ubi!$C:$C,">="&DATE(2025,10,1),Ubi!$C:$C,"<="&DATE(2025,12+1,0),Ubi!$B:$B,"*Adidas*") -> 8 | F18: =COUNTIFS(Ubi!$C:$C,">="&DATE(2026,1,1),Ubi!$C:$C,"<="&DATE(2026,3+1,0),Ubi!$B:$B,"*Adidas*") -> 11 | G18: =COUNTIFS(Ubi!$C:$C,">="&DATE(2026,4,1),Ubi!$C:$C,"<="&DATE(2026,6+1,0),Ubi!$B:$B,"*Adidas*") -> 0 | H18: =COUNTIFS(Ubi!$C:$C,">="&DATE(2026,7,1),Ubi!$C:$C,"<="&DATE(2026,9+1,0),Ubi!$B:$B,"*Adidas*") -> 0 | I18: =COUNTIFS(Ubi!$C:$C,">="&DATE(2026,10,1),Ubi!$C:$C,"<="&DATE(2026,12+1,0),Ubi!$B:$B,"*Adidas*") -> 0
A19: Red Bull | B19: =COUNTIFS(Ubi!$C:$C,">="&DATE(2025,1,1),Ubi!$C:$C,"<="&DATE(2025,3+1,0),Ubi!$B:$B,"*Red Bull*") -> 2 | C19: =COUNTIFS(Ubi!$C:$C,">="&DATE(2025,4,1),Ubi!$C:$C,"<="&DATE(2025,6+1,0),Ubi!$B:$B,"*Red Bull*") -> 0 | D19: =COUNTIFS(Ubi!$C:$C,">="&DATE(2025,7,1),Ubi!$C:$C,"<="&DATE(2025,9+1,0),Ubi!$B:$B,"*Red Bull*") -> 0 | E19: =COUNTIFS(Ubi!$C:$C,">="&DATE(2025,10,1),Ubi!$C:$C,"<="&DATE(2025,12+1,0),Ubi!$B:$B,"*Red Bull*") -> 1 | F19: =COUNTIFS(Ubi!$C:$C,">="&DATE(2026,1,1),Ubi!$C:$C,"<="&DATE(2026,3+1,0),Ubi!$B:$B,"*Red Bull*") -> 0 | G19: =COUNTIFS(Ubi!$C:$C,">="&DATE(2026,4,1),Ubi!$C:$C,"<="&DATE(2026,6+1,0),Ubi!$B:$B,"*Red Bull*") -> 0 | H19: =COUNTIFS(Ubi!$C:$C,">="&DATE(2026,7,1),Ubi!$C:$C,"<="&DATE(2026,9+1,0),Ubi!$B:$B,"*Red Bull*") -> 0 | I19: =COUNTIFS(Ubi!$C:$C,">="&DATE(2026,10,1),Ubi!$C:$C,"<="&DATE(2026,12+1,0),Ubi!$B:$B,"*Red Bull*") -> 0
A20: LEGO | B20: =COUNTIFS(Ubi!$C:$C,">="&DATE(2025,1,1),Ubi!$C:$C,"<="&DATE(2025,3+1,0),Ubi!$B:$B,"*LEGO*") -> 1 | C20: =COUNTIFS(Ubi!$C:$C,">="&DATE(2025,4,1),Ubi!$C:$C,"<="&DATE(2025,6+1,0),Ubi!$B:$B,"*LEGO*") -> 7 | D20: =COUNTIFS(Ubi!$C:$C,">="&DATE(2025,7,1),Ubi!$C:$C,"<="&DATE(2025,9+1,0),Ubi!$B:$B,"*LEGO*") -> 4 | E20: =COUNTIFS(Ubi!$C:$C,">="&DATE(2025,10,1),Ubi!$C:$C,"<="&DATE(2025,12+1,0),Ubi!$B:$B,"*LEGO*") -> 0 | F20: =COUNTIFS(Ubi!$C:$C,">="&DATE(2026,1,1),Ubi!$C:$C,"<="&DATE(2026,3+1,0),Ubi!$B:$B,"*LEGO*") -> 0 | G20: =COUNTIFS(Ubi!$C:$C,">="&DATE(2026,4,1),Ubi!$C:$C,"<="&DATE(2026,6+1,0),Ubi!$B:$B,"*LEGO*") -> 0 | H20: =COUNTIFS(Ubi!$C:$C,">="&DATE(2026,7,1),Ubi!$C:$C,"<="&DATE(2026,9+1,0),Ubi!$B:$B,"*LEGO*") -> 0 | I20: =COUNTIFS(Ubi!$C:$C,">="&DATE(2026,10,1),Ubi!$C:$C,"<="&DATE(2026,12+1,0),Ubi!$B:$B,"*LEGO*") -> 0
A21: Ubisoft | B21: =COUNTIFS(Ubi!$C:$C,">="&DATE(2025,1,1),Ubi!$C:$C,"<="&DATE(2025,3+1,0),Ubi!$B:$B,"*Ubisoft*")+COUNTIFS(Ubi!$C:$C,">="&DATE(2025,1,1),Ubi!$C:$C,"<="&DATE(2025,3+1,0),Ubi!$B:$B,"UBI") -> 2 | C21: =COUNTIFS(Ubi!$C:$C,">="&DATE(2025,4,1),Ubi!$C:$C,"<="&DATE(2025,6+1,0),Ubi!$B:$B,"*Ubisoft*")+COUNTIFS(Ubi!$C:$C,">="&DATE(2025,4,1),Ubi!$C:$C,"<="&DATE(2025,6+1,0),Ubi!$B:$B,"UBI") -> 7 | D21: =COUNTIFS(Ubi!$C:$C,">="&DATE(2025,7,1),Ubi!$C:$C,"<="&DATE(2025,9+1,0),Ubi!$B:$B,"*Ubisoft*")+COUNTIFS(Ubi!$C:$C,">="&DATE(2025,7,1),Ubi!$C:$C,"<="&DATE(2025,9+1,0),Ubi!$B:$B,"UBI") -> 0 | E21: =COUNTIFS(Ubi!$C:$C,">="&DATE(2025,10,1),Ubi!$C:$C,"<="&DATE(2025,12+1,0),Ubi!$B:$B,"*Ubisoft*")+COUNTIFS(Ubi!$C:$C,">="&DATE(2025,10,1),Ubi!$C:$C,"<="&DATE(2025,12+1,0),Ubi!$B:$B,"UBI") -> 2 | F21: =COUNTIFS(Ubi!$C:$C,">="&DATE(2026,1,1),Ubi!$C:$C,"<="&DATE(2026,3+1,0),Ubi!$B:$B,"*Ubisoft*")+COUNTIFS(Ubi!$C:$C,">="&DATE(2026,1,1),Ubi!$C:$C,"<="&DATE(2026,3+1,0),Ubi!$B:$B,"UBI") -> 0 | G21: =COUNTIFS(Ubi!$C:$C,">="&DATE(2026,4,1),Ubi!$C:$C,"<="&DATE(2026,6+1,0),Ubi!$B:$B,"*Ubisoft*")+COUNTIFS(Ubi!$C:$C,">="&DATE(2026,4,1),Ubi!$C:$C,"<="&DATE(2026,6+1,0),Ubi!$B:$B,"UBI") -> 0 | H21: =COUNTIFS(Ubi!$C:$C,">="&DATE(2026,7,1),Ubi!$C:$C,"<="&DATE(2026,9+1,0),Ubi!$B:$B,"*Ubisoft*")+COUNTIFS(Ubi!$C:$C,">="&DATE(2026,7,1),Ubi!$C:$C,"<="&DATE(2026,9+1,0),Ubi!$B:$B,"UBI") -> 0 | I21: =COUNTIFS(Ubi!$C:$C,">="&DATE(2026,10,1),Ubi!$C:$C,"<="&DATE(2026,12+1,0),Ubi!$B:$B,"*Ubisoft*")+COUNTIFS(Ubi!$C:$C,">="&DATE(2026,10,1),Ubi!$C:$C,"<="&DATE(2026,12+1,0),Ubi!$B:$B,"UBI") -> 0
A22: Perrier | B22: =COUNTIFS(Ubi!$C:$C,">="&DATE(2025,1,1),Ubi!$C:$C,"<="&DATE(2025,3+1,0),Ubi!$B:$B,"*Perrier*") -> 0 | C22: =COUNTIFS(Ubi!$C:$C,">="&DATE(2025,4,1),Ubi!$C:$C,"<="&DATE(2025,6+1,0),Ubi!$B:$B,"*Perrier*") -> 4 | D22: =COUNTIFS(Ubi!$C:$C,">="&DATE(2025,7,1),Ubi!$C:$C,"<="&DATE(2025,9+1,0),Ubi!$B:$B,"*Perrier*") -> 0 | E22: =COUNTIFS(Ubi!$C:$C,">="&DATE(2025,10,1),Ubi!$C:$C,"<="&DATE(2025,12+1,0),Ubi!$B:$B,"*Perrier*") -> 0 | F22: =COUNTIFS(Ubi!$C:$C,">="&DATE(2026,1,1),Ubi!$C:$C,"<="&DATE(2026,3+1,0),Ubi!$B:$B,"*Perrier*") -> 0 | G22: =COUNTIFS(Ubi!$C:$C,">="&DATE(2026,4,1),Ubi!$C:$C,"<="&DATE(2026,6+1,0),Ubi!$B:$B,"*Perrier*") -> 0 | H22: =COUNTIFS(Ubi!$C:$C,">="&DATE(2026,7,1),Ubi!$C:$C,"<="&DATE(2026,9+1,0),Ubi!$B:$B,"*Perrier*") -> 0 | I22: =COUNTIFS(Ubi!$C:$C,">="&DATE(2026,10,1),Ubi!$C:$C,"<="&DATE(2026,12+1,0),Ubi!$B:$B,"*Perrier*") -> 0
A23: IKEA | B23: =COUNTIFS(Ubi!$C:$C,">="&DATE(2025,1,1),Ubi!$C:$C,"<="&DATE(2025,3+1,0),Ubi!$B:$B,"*IKEA*") -> 0 | C23: =COUNTIFS(Ubi!$C:$C,">="&DATE(2025,4,1),Ubi!$C:$C,"<="&DATE(2025,6+1,0),Ubi!$B:$B,"*IKEA*") -> 0 | D23: =COUNTIFS(Ubi!$C:$C,">="&DATE(2025,7,1),Ubi!$C:$C,"<="&DATE(2025,9+1,0),Ubi!$B:$B,"*IKEA*") -> 9 | E23: =COUNTIFS(Ubi!$C:$C,">="&DATE(2025,10,1),Ubi!$C:$C,"<="&DATE(2025,12+1,0),Ubi!$B:$B,"*IKEA*") -> 1 | F23: =COUNTIFS(Ubi!$C:$C,">="&DATE(2026,1,1),Ubi!$C:$C,"<="&DATE(2026,3+1,0),Ubi!$B:$B,"*IKEA*") -> 0 | G23: =COUNTIFS(Ubi!$C:$C,">="&DATE(2026,4,1),Ubi!$C:$C,"<="&DATE(2026,6+1,0),Ubi!$B:$B,"*IKEA*") -> 0 | H23: =COUNTIFS(Ubi!$C:$C,">="&DATE(2026,7,1),Ubi!$C:$C,"<="&DATE(2026,9+1,0),Ubi!$B:$B,"*IKEA*") -> 0 | I23: =COUNTIFS(Ubi!$C:$C,">="&DATE(2026,10,1),Ubi!$C:$C,"<="&DATE(2026,12+1,0),Ubi!$B:$B,"*IKEA*") -> 0
A24: L'Oréal | B24: =COUNTIFS(Ubi!$C:$C,">="&DATE(2025,1,1),Ubi!$C:$C,"<="&DATE(2025,3+1,0),Ubi!$B:$B,"*L'Oréal*") -> 0 | C24: =COUNTIFS(Ubi!$C:$C,">="&DATE(2025,4,1),Ubi!$C:$C,"<="&DATE(2025,6+1,0),Ubi!$B:$B,"*L'Oréal*") -> 0 | D24: =COUNTIFS(Ubi!$C:$C,">="&DATE(2025,7,1),Ubi!$C:$C,"<="&DATE(2025,9+1,0),Ubi!$B:$B,"*L'Oréal*") -> 2 | E24: =COUNTIFS(Ubi!$C:$C,">="&DATE(2025,10,1),Ubi!$C:$C,"<="&DATE(2025,12+1,0),Ubi!$B:$B,"*L'Oréal*") -> 0 | F24: =COUNTIFS(Ubi!$C:$C,">="&DATE(2026,1,1),Ubi!$C:$C,"<="&DATE(2026,3+1,0),Ubi!$B:$B,"*L'Oréal*") -> 0 | G24: =COUNTIFS(Ubi!$C:$C,">="&DATE(2026,4,1),Ubi!$C:$C,"<="&DATE(2026,6+1,0),Ubi!$B:$B,"*L'Oréal*") -> 0 | H24: =COUNTIFS(Ubi!$C:$C,">="&DATE(2026,7,1),Ubi!$C:$C,"<="&DATE(2026,9+1,0),Ubi!$B:$B,"*L'Oréal*") -> 0 | I24: =COUNTIFS(Ubi!$C:$C,">="&DATE(2026,10,1),Ubi!$C:$C,"<="&DATE(2026,12+1,0),Ubi!$B:$B,"*L'Oréal*") -> 0
A25: TikTok | B25: =COUNTIFS(Ubi!$C:$C,">="&DATE(2025,1,1),Ubi!$C:$C,"<="&DATE(2025,3+1,0),Ubi!$B:$B,"*TikTok*") -> 0 | C25: =COUNTIFS(Ubi!$C:$C,">="&DATE(2025,4,1),Ubi!$C:$C,"<="&DATE(2025,6+1,0),Ubi!$B:$B,"*TikTok*") -> 0 | D25: =COUNTIFS(Ubi!$C:$C,">="&DATE(2025,7,1),Ubi!$C:$C,"<="&DATE(2025,9+1,0),Ubi!$B:$B,"*TikTok*") -> 0 | E25: =COUNTIFS(Ubi!$C:$C,">="&DATE(2025,10,1),Ubi!$C:$C,"<="&DATE(2025,12+1,0),Ubi!$B:$B,"*TikTok*") -> 1 | F25: =COUNTIFS(Ubi!$C:$C,">="&DATE(2026,1,1),Ubi!$C:$C,"<="&DATE(2026,3+1,0),Ubi!$B:$B,"*TikTok*") -> 0 | G25: =COUNTIFS(Ubi!$C:$C,">="&DATE(2026,4,1),Ubi!$C:$C,"<="&DATE(2026,6+1,0),Ubi!$B:$B,"*TikTok*") -> 0 | H25: =COUNTIFS(Ubi!$C:$C,">="&DATE(2026,7,1),Ubi!$C:$C,"<="&DATE(2026,9+1,0),Ubi!$B:$B,"*TikTok*") -> 0 | I25: =COUNTIFS(Ubi!$C:$C,">="&DATE(2026,10,1),Ubi!$C:$C,"<="&DATE(2026,12+1,0),Ubi!$B:$B,"*TikTok*") -> 0
A26: Barilla | B26: =COUNTIFS(Ubi!$C:$C,">="&DATE(2025,1,1),Ubi!$C:$C,"<="&DATE(2025,3+1,0),Ubi!$B:$B,"*Barilla*") -> 0 | C26: =COUNTIFS(Ubi!$C:$C,">="&DATE(2025,4,1),Ubi!$C:$C,"<="&DATE(2025,6+1,0),Ubi!$B:$B,"*Barilla*") -> 0 | D26: =COUNTIFS(Ubi!$C:$C,">="&DATE(2025,7,1),Ubi!$C:$C,"<="&DATE(2025,9+1,0),Ubi!$B:$B,"*Barilla*") -> 0 | E26: =COUNTIFS(Ubi!$C:$C,">="&DATE(2025,10,1),Ubi!$C:$C,"<="&DATE(2025,12+1,0),Ubi!$B:$B,"*Barilla*") -> 1 | F26: =COUNTIFS(Ubi!$C:$C,">="&DATE(2026,1,1),Ubi!$C:$C,"<="&DATE(2026,3+1,0),Ubi!$B:$B,"*Barilla*") -> 1 | G26: =COUNTIFS(Ubi!$C:$C,">="&DATE(2026,4,1),Ubi!$C:$C,"<="&DATE(2026,6+1,0),Ubi!$B:$B,"*Barilla*") -> 0 | H26: =COUNTIFS(Ubi!$C:$C,">="&DATE(2026,7,1),Ubi!$C:$C,"<="&DATE(2026,9+1,0),Ubi!$B:$B,"*Barilla*") -> 0 | I26: =COUNTIFS(Ubi!$C:$C,">="&DATE(2026,10,1),Ubi!$C:$C,"<="&DATE(2026,12+1,0),Ubi!$B:$B,"*Barilla*") -> 0
A27: TOTAL | B27: =SUM(B18:B26) -> 18 | C27: =SUM(C18:C26) -> 61 | D27: =SUM(D18:D26) -> 26 | E27: =SUM(E18:E26) -> 14 | F27: =SUM(F18:F26) -> 12 | G27: =SUM(G18:G26) -> 0 | H27: =SUM(H18:H26) -> 0 | I27: =SUM(I18:I26) -> 0
A29: SYNTHÈSE ANNUELLE | B29: 2025 | C29: 2026
A30: Revenus (€) | B30: =SUM(B14:E14) -> 84980 | C30: =SUM(F14:I14) -> 1806.6667
A31: Projets | B31: =SUM(B27:E27) -> 119 | C31: =SUM(F27:I27) -> 12
A32: Rev. / Projet (€) | B32: =IFERROR(B30/B31,"—") -> 714.11765 | C32: =IFERROR(C30/C31,"—") -> 150.55556

Sheet Ubi
K1: =SUBTOTAL(2,K6:K19661) -> 131 | Q1: =SUBTOTAL(2,Q6:Q19661) -> 50 | R1: =SUBTOTAL(2,R6:R19661) -> 87 | S1: =SUBTOTAL(2,S6:S19661) -> 30 | T1: =SUBTOTAL(2,T6:T19661) -> 0 | U1: =SUBTOTAL(2,U6:U19661) -> 0 | V1: =SUBTOTAL(2,V6:V19661) -> 0 | W1: =SUBTOTAL(2,W6:W19661) -> 0 | X1: =SUBTOTAL(2,X6:X19661) -> 4 | ... AW1: =SUBTOTAL(2,AW6:AW19661) -> 0
J2: =SUBTOTAL(9,J6:J19662) -> 2687 | K2: =SUBTOTAL(9,K6:K19662) -> 104446.67 | Q2: =SUBTOTAL(9,Q6:Q19662)*Q5 -> 15525 | R2: =SUBTOTAL(9,R6:R19662)*R5 -> 36480 | S2: =SUBTOTAL(9,S6:S19662)*S5 -> 6930 | T2: =SUBTOTAL(9,T6:T19662)*T5 -> 0 | U2: =SUBTOTAL(9,U6:U19662)*U5 -> 0 | V2: =SUBTOTAL(9,V6:V19662)*V5 -> 0 | W2: =SUBTOTAL(9,W6:W19662)*W5 -> 0 | X2: =SUBTOTAL(9,X6:X19662)*X5 -> 2000 | ... AW2: =SUBTOTAL(9,AW6:AW19662)*AW5 -> 0
A3: Tracker Projet | Q3: Online | Y3: Offline | AE3: PreEnvoyéeations | AF3: Web | AJ3: Videos | AS3: Virtualization | AU3: Copy
A4: Projet | F4: Facturation fin de mois | Q4: Création de concepts simples et bannières online (KV, statique) | R4: Adaptations de bannières à partir d'une créa existante (statique) | S4: Déclis d'adaptations (eg: naming, etc.) (statique) | T4: Création de bannières (KV, animée) | U4: Adaptations de bannières à partir d'une créa existante (animées) | V4: Boutons, Icônes | W4: Logo | X4: Rendering 3D d'image lifesyles | Y4: Création de bannières print (KV, statique) | Z4: Adaptations de bannières à partir d'une créa existante (statique) | AA4: Leaflet (1 page) | AB4: Leaflet (2 pages) | AC4: Kakemonos / Murs de stands | AD4: Brochure (20 pages) | AE4: Powerpoint / Google Slides (par slide) | AF4: Newsletter / Landing page (design) | AG4: Newsletter / Landing page (design et implémentation technique) | AH4: Site web (design only) | AI4: Site web (complet) | AJ4: Edition Vidéo simple (sous-titres, bande son, cuts, etc) | AK4: Edition Vidéo avancée (animation over footage) | AL4: Social Media Video (motion, 30s) | AM4: Social Media Video (motion, 1min) | AN4: Sizzles (avec scripts, voix, etc.) | AO4: Vidéo Promotionnelle | AP4: Vidéo 2D | AQ4: Vidéo 3D | AR4: Tournage vidéo avec crew, équipement, lieux, etc. | AS4: Espace Virtuel Interactif | AT4: Showroom Virtuel Interactif | AU4: Traduction (par mot) | AV4: Copywriting (par mot)
A5: Client | B5: Division | C5: Date | D5: Projet | E5: Code Projet | F5: Contact | G5: Statut | H5: Catégorie | I5: Lien Projet | J5: NB Assets | K5: Valeur Totale | L5: Devis | M5: Numéro de PO | N5: Facture | O5: N°Facture | P5: Statut paiement | Q5: 135 | R5: 30 | S5: 10 | T5: 220 | U5: 60 | V5: 15 | W5: 250 | X5: 500 | Y5: 150 | Z5: 35 | AA5: 180 | AB5: 260 | AC5: 250 | AD5: 2000 | AE5: 30 | AF5: 500 | AG5: 650 | AH5: 3500 | AI5: Au projet | AJ5: 80 | AK5: 150 | AL5: 360 | AM5: 460 | AN5: 900 | AO5: 3500 | AP5: Au projet | AQ5: Au projet | AR5: Au projet | AS5: 2500 | AT5: Au projet | AU5: 0.12 | AV5: 0.25
A6: Ubi | B6: Adidas | C6: 45726 | D6: adidas – ADR25 | E6: ADR25 | F6: Clara BONVARLET | G6: Delivered | H6: Exe | I6: https://saranistudio.sharepoint.com/:f:/s/SaraniAssets/Ej6RkjRw02BJv-pEIjZ9w8ABf_Ap6iR_TAA7SAMLrFeAkQ?e=N2LmRH | J6: =IF(SUM(Q6:AW6)=0,"-",SUM(Q6:AW6)) -> 17 | K6: =IF(SUMPRODUCT($Q$5:$AW$5,Q6:AW6)=0,"-",SUMPRODUCT($Q$5:$AW$5,Q6:AW6)) -> 560 | L6: - | M6: - | N6: Envoyé via Whatsapp | O6: F2025-0217 | P6: Paid 15/05/2025 | R6: 16 | AJ6: 1
A7: Ubi | B7: Red Bull | C7: 45727 | D7: ubi - KV Red Bull Wings For Life - RED06 | E7: Red06 | F7: Jeremy LE NILLON | G7: Delivered | H7: Exe | I7: 20250311_KV Red Bull Wings For Life - RED06 | J7: =IF(SUM(Q7:AW7)=0,"-",SUM(Q7:AW7)) -> 15 | K7: =IF(SUMPRODUCT($Q$5:$AW$5,Q7:AW7)=0,"-",SUMPRODUCT($Q$5:$AW$5,Q7:AW7)) -> 450 | L7: - | M7: - | N7: Envoyé via Whatsapp | O7: F2025-0217 | P7: Paid 15/05/2025 | R7: 15
A8: Ubi | B8: LEGO | C8: 45727 | D8: LEG02 : Brief affiche LEGO Le grand tournoi des Champs | E8: LEG02 | F8: Louis Keller | G8: Delivered | H8: Exe | I8: 20250311_Brief affiche LEGO Le grand tournoi des Champs | J8: =IF(SUM(Q8:AW8)=0,"-",SUM(Q8:AW8)) -> 2 | K8: =IF(SUMPRODUCT($Q$5:$AW$5,Q8:AW8)=0,"-",SUMPRODUCT($Q$5:$AW$5,Q8:AW8)) -> 185 | L8: - | M8: - | N8: Envoyé via Whatsapp | O8: F2025-0217 | P8: Paid 15/05/2025 | Y8: 1 | Z8: 1
A9: Ubi | B9: Adidas | C9: 45729 | D9: ADTAT / Flocage textile | E9: ADTAT | F9: Anouck Mottin | G9: Delivered | H9: Exe | I9: https://saranistudio.sharepoint.com/:f:/s/SaraniAssets/Evyqkra13wJEhdYuMBCPa2QBkbIgZr9J3lqx8bYghiqmoA?e=MHdPnX | J9: =IF(SUM(Q9:AW9)=0,"-",SUM(Q9:AW9)) -> 4 | K9: =IF(SUMPRODUCT($Q$5:$AW$5,Q9:AW9)=0,"-",SUMPRODUCT($Q$5:$AW$5,Q9:AW9)) -> 140 | L9: - | M9: - | N9: Envoyé via Whatsapp | O9: F2025-0217 | P9: Paid 15/05/2025 | Z9: 4
A10: Ubi | B10: Adidas | C10: 45729 | D10: Adidas Supercomfort Weekend | E10: ADR25 | F10: Louis Keller | G10: Delivered | H10: Special | I10: https://saranistudio.sharepoint.com/:f:/s/SaraniAssets/EspVANpg4GpEs0PP-J6C5s0B_G6DnxosVSFNUMyaSioBiA?e=z5gPK5 | J10: =IF(SUM(Q10:AW10)=0,"-",SUM(Q10:AW10)) -> 126 | K10: =IF(SUMPRODUCT($Q$5:$AW$5,Q10:AW10)=0,"-",SUMPRODUCT($Q$5:$AW$5,Q10:AW10)) -> 2705 | L10: - | M10: - | N10: Envoyé via Whatsapp | O10: F2025-0218 | P10: Paid 15/05/2025 | Q10: 1 | R10: =46+20 -> 66 | S10: =7+4+3+7+14+7+5+5+7 -> 59
A11: Ubi | B11: Adidas | C11: 45729 | D11: Testings adidas retail – ADRET | E11: ADRET | F11: Clara BONVARLET | G11: Delivered | H11: Exe | I11: https://saranistudio.sharepoint.com/:f:/s/SaraniAssets/Eh0MoH_-2zZEv5a97CjnsRYBBxAk1CdKecRZGQvFQGvgdA?e=k6fI4G | J11: =IF(SUM(Q11:AW11)=0,"-",SUM(Q11:AW11)) -> 5 | K11: =IF(SUMPRODUCT($Q$5:$AW$5,Q11:AW11)=0,"-",SUMPRODUCT($Q$5:$AW$5,Q11:AW11)) -> 150 | L11: - | M11: - | N11: Envoyé via Whatsapp | O11: F2025-0217 | P11: Paid 15/05/2025 | R11: 5
A12: Ubi | B12: Red Bull | C12: 45729 | D12: KV Red Bull Wings For Life - Video | E12: Red06 | F12: Jeremy LE NILLON | G12: Delivered | H12: Exe | I12: https://saranistudio.sharepoint.com/:f:/s/SaraniAssets/EuvKLKORCGNJnpFQDCWR1jMBK3-s4VKysfwEu23qPL0jrA?e=0n9yYC | J12: =IF(SUM(Q12:AW12)=0,"-",SUM(Q12:AW12)) -> 2 | K12: =IF(SUMPRODUCT($Q$5:$AW$5,Q12:AW12)=0,"-",SUMPRODUCT($Q$5:$AW$5,Q12:AW12)) -> 160 | L12: - | M12: - | N12: Envoyé via Whatsapp | O12: F2025-0217 | P12: Paid 15/05/2025 | AJ12: 2
A13: Ubi | B13: Ubisoft | C13: 45730 | D13: Graveur de Pierre Ubisoft | E13: UBI02 | F13: Inès de Laguiche | G13: Delivered | H13: Exe | I13: https://saranistudio.sharepoint.com/:f:/s/SaraniAssets/EswSC5pPpsBNpvHBnzBp7iYBgaH2yzxCR5ZiDBri_V5cTA?e=M8VcRE | J13: =IF(SUM(Q13:AW13)=0,"-",SUM(Q13:AW13)) -> 2 | K13: =IF(SUMPRODUCT($Q$5:$AW$5,Q13:AW13)=0,"-",SUMPRODUCT($Q$5:$AW$5,Q13:AW13)) -> 165 | L13: - | M13: - | N13: Envoyé via Whatsapp | O13: F2025-0217 | P13: Paid 15/05/2025 | Q13: 1 | R13: 1
A14: Ubi | B14: Adidas | C14: 45730 | D14: Branding magasins adidas - ADMAR | E14: ADMAR | F14: Jeremy LE NILLON | G14: Delivered | H14: Exe | I14: https://saranistudio.sharepoint.com/:f:/s/SaraniAssets/Ekt9En4iqM1PjHyA0QwiYp8B5ZpUPIhXgluIK9b7cUxooA?e=CSgTjt | J14: =IF(SUM(Q14:AW14)=0,"-",SUM(Q14:AW14)) -> 12 | K14: =IF(SUMPRODUCT($Q$5:$AW$5,Q14:AW14)=0,"-",SUMPRODUCT($Q$5:$AW$5,Q14:AW14)) -> 780 | L14: - | M14: - | N14: Envoyé via Whatsapp | O14: F2025-0217 | P14: Paid 15/05/2025 | Q14: =4 -> 4 | R14: 8
A15: Ubi | B15: Adidas | C15: 45730 | D15: Stand Marathon adidas - ADM25 | E15: ADM25 | F15: Jeremy LE NILLON | G15: Delivered | H15: Special | I15: https://saranistudio.sharepoint.com/:f:/s/SaraniAssets/Epa8vTKpudRIg5uy_lvnMaIBKLkQT4JXzXd8cYngVnroxA?e=PNydg2 | J15: =IF(SUM(Q15:AW15)=0,"-",SUM(Q15:AW15)) -> 96 | K15: =IF(SUMPRODUCT($Q$5:$AW$5,Q15:AW15)=0,"-",SUMPRODUCT($Q$5:$AW$5,Q15:AW15)) -> 2490 | L15: - | M15: - | N15: Envoyé via Whatsapp | O15: F2025-0218 | P15: Paid 15/05/2025 | R15: =3+10+18+3+29+10 -> 73 | S15: =2+20 -> 22 | AJ15: 1
A16: Ubi | B16: Adidas | C16: 45731 | D16: Plp Hub | E16: ADR25 | F16: Clara BONVARLET | G16: Delivered | H16: Exe | I16: https://saranistudio.sharepoint.com/:f:/s/SaraniAssets/EtTNbkr4dSZFi3TkNEoWuigB73I9k0Ta2TiWc538sv5Gng?e=HzKCVC | J16: =IF(SUM(Q16:AW16)=0,"-",SUM(Q16:AW16)) -> 6 | K16: =IF(SUMPRODUCT($Q$5:$AW$5,Q16:AW16)=0,"-",SUMPRODUCT($Q$5:$AW$5,Q16:AW16)) -> 180 | L16: - | M16: - | N16: Envoyé via Whatsapp | O16: F2025-0217 | P16: Paid 15/05/2025 | R16: 6
A17: Ubi | B17: Adidas | C17: 45741 | D17: Calendrier hebdo Instagram - ADU25 | E17: ADU25 | F17: Clara BONVARLET | G17: Delivered | H17: Exe | I17: https://saranistudio.sharepoint.com/:f:/s/SaraniAssets/EgQrdWCWPFZEkywkgCCVUIEBIddLpyi7r_OGT6myK3K6PA?e=eexic0 | J17: =IF(SUM(Q17:AW17)=0,"-",SUM(Q17:AW17)) -> 8 | K17: =IF(SUMPRODUCT($Q$5:$AW$5,Q17:AW17)=0,"-",SUMPRODUCT($Q$5:$AW$5,Q17:AW17)) -> 345 | L17: - | M17: - | N17: Envoyé via Whatsapp | O17: F2025-0217 | P17: Paid 15/05/2025 | Q17: 1 | R17: 7
A18: Ubi | B18: Adidas | C18: 45742 | D18: Seeding kit | E18: ADR25 | F18: Clara BONVARLET | G18: Delivered | H18: Créa | I18: 20250326_SEEDING KIT | J18: =IF(SUM(Q18:AW18)=0,"-",SUM(Q18:AW18)) -> 1 | K18: Concept Offert | L18: - | M18: - | N18: - | O18: - | P18: - | X18: 1
A19: Ubi | B19: Adidas | C19: 45742 | D19: ADRET / Créas adidas Retail | E19: ADRET | F19: Clara BONVARLET | G19: Delivered | H19: Exe | I19: https://saranistudio.sharepoint.com/:f:/s/SaraniAssets/Eka3DWx13PhPoPbjhloykp8BENQBYxhjzw3qTWiwYKJv0A?e=AhpWxX | J19: =IF(SUM(Q19:AW19)=0,"-",SUM(Q19:AW19)) -> 2 | K19: =IF(SUMPRODUCT($Q$5:$AW$5,Q19:AW19)=0,"-",SUMPRODUCT($Q$5:$AW$5,Q19:AW19)) -> 60 | L19: - | M19: - | N19: Envoyé via Whatsapp | O19: F2025-0217 | P19: Paid 15/05/2025 | R19: 2
A20: Ubi | B20: Ubisoft | C20: 45742 | D20: Ubisoft - boîtes personnalisées et cire parchemins | E20: UBI02 | F20: Inès de Laguiche | G20: Delivered | H20: Exe | I20: 20250326_Ubisoft - boîtes personnalisées | J20: =IF(SUM(Q20:AW20)=0,"-",SUM(Q20:AW20)) -> 6 | K20: =IF(SUMPRODUCT($Q$5:$AW$5,Q20:AW20)=0,"-",SUMPRODUCT($Q$5:$AW$5,Q20:AW20)) -> 285 | L20: - | M20: - | N20: Envoyé via Whatsapp | O20: F2025-0217 | P20: Paid 15/05/2025 | Q20: 1 | R20: 5
A21: Ubi | B21: Adidas | C21: 45743 | D21: ADTAT / Brief oriflammes | E21: ADTAT | F21: Anouck MOTTIN | G21: Delivered | H21: Exe | I21: 20250327_ADTAT - Brief oriflammes | J21: =IF(SUM(Q21:AW21)=0,"-",SUM(Q21:AW21)) -> 2 | K21: =IF(SUMPRODUCT($Q$5:$AW$5,Q21:AW21)=0,"-",SUMPRODUCT($Q$5:$AW$5,Q21:AW21)) -> 60 | L21: - | M21: - | N21: Envoyé via Whatsapp | O21: F2025-0217 | P21: Paid 15/05/2025 | R21: 2
A22: Ubi | B22: Adidas | C22: 45743 | D22: ubi - calendriers Facebook + KV - ADU25 | E22: ADU25 | F22: DROUET Pauline | G22: Delivered | H22: Exe | I22: https://saranistudio.sharepoint.com/:f:/s/SaraniAssets/Et1YZpnGo6xGk_xA-N7mRfMB-fqEThZxNt4zaIzuAVy_sg?e=P89yDW | J22: =IF(SUM(Q22:AW22)=0,"-",SUM(Q22:AW22)) -> 1 | K22: =IF(SUMPRODUCT($Q$5:$AW$5,Q22:AW22)=0,"-",SUMPRODUCT($Q$5:$AW$5,Q22:AW22)) -> 180 | L22: - | M22: - | N22: Envoyée | O22: F2025-0254 | P22: Paid 06/06/2025 | AA22: 1
A23: Ubi | B23: Adidas | C23: 45743 | D23: ADR25 / Créas adidas Brand | E23: ADR25 | F23: Clara BONVARLET | G23: Delivered | H23: Exe | I23: https://saranistudio.sharepoint.com/:f:/s/SaraniAssets/Elk4CkEUM01Ao4tt53VE974BI8_2FTp9DC-yO8ShCT11Lw?e=cgryAD | J23: =IF(SUM(Q23:AW23)=0,"-",SUM(Q23:AW23)) -> 2 | K23: =IF(SUMPRODUCT($Q$5:$AW$5,Q23:AW23)=0,"-",SUMPRODUCT($Q$5:$AW$5,Q23:AW23)) -> 110 | L23: - | M23: - | N23: Envoyé via Whatsapp | O23: F2025-0217 | P23: Paid 15/05/2025 | R23: 1 | AJ23: 1
A24: Ubi | B24: Adidas | C24: 45748 | D24: Sticker Adizero | E24: ADR25 | F24: Clara BONVARLET | G24: Delivered | H24: Exe | I24: https://saranistudio.sharepoint.com/:f:/s/SaraniAssets/EtGyAL-3rTdDmtFlPJybmpYBaroSTyRhVAXNRGshEpzIzQ?e=Obzxog | J24: =IF(SUM(Q24:AW24)=0,"-",SUM(Q24:AW24)) -> 1 | K24: =IF(SUMPRODUCT($Q$5:$AW$5,Q24:AW24)=0,"-",SUMPRODUCT($Q$5:$AW$5,Q24:AW24)) -> 30 | L24: - | M24: - | N24: Envoyée | O24: F2025-0254 | P24: Paid 06/06/2025 | R24: 1
A25: Ubi | B25: Ubisoft | C25: 45748 | D25: Créa Ubisoft 2.0 | E25: UBI02 | F25: Inès de Laguiche | G25: Delivered | H25: Exe | I25: https://saranistudio.sharepoint.com/:f:/s/SaraniAssets/EijnPi44YxZNk-dDVMyMxrkBKXrw34OtgTISSkEdq4vt4w?e=CAexvj | J25: =IF(SUM(Q25:AW25)=0,"-",SUM(Q25:AW25)) -> 3 | K25: =IF(SUMPRODUCT($Q$5:$AW$5,Q25:AW25)=0,"-",SUMPRODUCT($Q$5:$AW$5,Q25:AW25)) -> 105 | L25: - | M25: - | N25: Envoyée | O25: F2025-0254 | P25: Paid 06/06/2025 | Z25: 3
A26: Ubi | B26: Ubisoft | C26: 45748 | D26: CREA UBISOFT 3 | E26: UBI02 | F26: Inès de Laguiche | G26: Delivered | H26: Exe | I26: https://saranistudio.sharepoint.com/:f:/s/SaraniAssets/EkrVaENSDiBCilmmpkVVlWEBQk1GeDWmDw0I5jFz0fX--A?e=3GXKUR | J26: =IF(SUM(Q26:AW26)=0,"-",SUM(Q26:AW26)) -> 5 | K26: =IF(SUMPRODUCT($Q$5:$AW$5,Q26:AW26)=0,"-",SUMPRODUCT($Q$5:$AW$5,Q26:AW26)) -> 400 | L26: - | M26: - | N26: Envoyée | O26: F2025-0254 | P26: Paid 06/06/2025 | Z26: 4 | AB26: 1
A27: Ubi | B27: Adidas | C27: 45749 | D27: ADRET / Créas adidas Retail | E27: ADRET | F27: CLARA-BONVARLET | G27: Delivered | H27: Exe | I27: 20250302_ADRET - Créas adidas Retail | J27: =IF(SUM(Q27:AW27)=0,"-",SUM(Q27:AW27)) -> 1 | K27: =IF(SUMPRODUCT($Q$5:$AW$5,Q27:AW27)=0,"-",SUMPRODUCT($Q$5:$AW$5,Q27:AW27)) -> 135 | L27: - | M27: - | N27: Envoyée | O27: F2025-0254 | P27: Paid 06/06/2025 | Q27: 1
A28: Ubi | B28: Adidas | C28: 45750 | D28: Adidas 10K - ADR25 | E28: ADR25 | F28: CLARA-BONVARLET | G28: Delivered | H28: Exe | I28: 20250403_ADIDAS 10K | J28: =IF(SUM(Q28:AW28)=0,"-",SUM(Q28:AW28)) -> 5 | K28: =IF(SUMPRODUCT($Q$5:$AW$5,Q28:AW28)=0,"-",SUMPRODUCT($Q$5:$AW$5,Q28:AW28)) -> 155 | L28: - | M28: - | N28: Envoyée | O28: F2025-0254 | P28: Paid 06/06/2025 | R28: 4 | Z28: 1
A29: Ubi | B29: Ubisoft | C29: 45751 | D29: Création de dossiers de chaise personnalisés | E29: UBI02 | F29: INÈS DE LAGUICHE | G29: Delivered | H29: Exe | I29: 20250404_création de dossiers de chaise personnalisés | J29: =IF(SUM(Q29:AW29)=0,"-",SUM(Q29:AW29)) -> 1 | K29: =IF(SUMPRODUCT($Q$5:$AW$5,Q29:AW29)=0,"-",SUMPRODUCT($Q$5:$AW$5,Q29:AW29)) -> 30 | L29: - | M29: - | N29: Envoyée | O29: F2025-0254 | P29: Paid 06/06/2025 | R29: 1
A30: Ubi | B30: Adidas | C30: 45754 | D30: ADO25 - Exe adidas originals showroom (Exe uniquement) | E30: ADO25 | F30: MARIE DELGRANGE | G30: Delivered | H30: Exe | I30: 20250404_ADO25 - Exe adidas originals showroom | J30: =IF(SUM(Q30:AW30)=0,"-",SUM(Q30:AW30)) -> 26 | K30: =IF(SUMPRODUCT($Q$5:$AW$5,Q30:AW30)=0,"-",SUMPRODUCT($Q$5:$AW$5,Q30:AW30)) -> 760 | L30: - | M30: - | N30: Envoyée | O30: F2025-0254 | P30: Paid 06/06/2025 | Q30: 4 | S30: 22
A31: Ubi | B31: Adidas | C31: 45754 | D31: ADU25 - Urgence stickers | E31: ADU25 | F31: DROUET Pauline | G31: Delivered | H31: Exe | I31: https://saranistudio.sharepoint.com/:f:/s/SaraniAssets/EmH0-A8nCTtNia70gCbO2lIB2mLpLDiGgCMmmotWvly__A?e=LblSqQ | J31: =IF(SUM(Q31:AW31)=0,"-",SUM(Q31:AW31)) -> 1 | K31: =IF(SUMPRODUCT($Q$5:$AW$5,Q31:AW31)=0,"-",SUMPRODUCT($Q$5:$AW$5,Q31:AW31)) -> 30 | L31: - | M31: - | N31: Envoyée | O31: F2025-0254 | P31: Paid 06/06/2025 | R31: 1
A32: Ubi | B32: Adidas | C32: 45754 | D32: ADTLD / demandes créas | E32: ATTLD | F32: CLARA-BONVARLET | G32: Delivered | H32: Exe | I32: https://saranistudio.sharepoint.com/:f:/s/SaraniAssets/EivsIogcYXJDlu049X2ZJ3wBoVsL-oLt-gorNZ7wk8z36Q?e=XhKG3e | J32: =IF(SUM(Q32:AW32)=0,"-",SUM(Q32:AW32)) -> 6 | K32: =IF(SUMPRODUCT($Q$5:$AW$5,Q32:AW32)=0,"-",SUMPRODUCT($Q$5:$AW$5,Q32:AW32)) -> 285 | L32: - | M32: - | N32: Envoyée | O32: F2025-0254 | P32: Paid 06/06/2025 | Q32: 1 | R32: 5
A33: Ubi | B33: Adidas | C33: 45754 | D33: Adidas 10K custom gift | E33: ADR25 | F33: CLARA-BONVARLET | G33: Delivered | H33: Créa | I33: https://saranistudio.sharepoint.com/:f:/s/SaraniAssets/EkwkV8YCxw9DoN-6W3d8Y40B0YO3ktRfoSp5gPiMZn_r3g?e=m0BnIB | J33: 3 | K33: =IF(SUMPRODUCT($Q$5:$AW$5,Q33:AW33)=0,"-",SUMPRODUCT($Q$5:$AW$5,Q33:AW33)) -> 405 | L33: - | M33: - | N33: Envoyée | O33: F2025-0254 | P33: Paid 06/06/2025 | Q33: 3
A34: Ubi | B34: Adidas | C34: 45754 | D34: Seeding kit Exé | E34: ADR25 | F34: Clara BONVARLET | G34: Delivered | H34: Exe | I34: 20250326_SEEDING KIT | J34: =IF(SUM(Q34:AW34)=0,"-",SUM(Q34:AW34)) -> 63 | K34: =IF(SUMPRODUCT($Q$5:$AW$5,Q34:AW34)=0,"-",SUMPRODUCT($Q$5:$AW$5,Q34:AW34)) -> 1635 | N34: Envoyée | O34: F2025-0316 | P34: Paid 21/07/2025 | Q34: 3 | R34: 7 | S34: 52 | X34: 1
A35: Ubi | B35: Adidas | C35: 45762 | D35: BRIEF Adidas Testing before tasting | E35: ADR25 | F35: Louis KELLER | G35: Delivered | H35: Special | I35: 20250415_BRIEF Adidas Testing before tasting | J35: =IF(SUM(Q35:AW35)=0,"-",SUM(Q35:AW35)) -> 37 | K35: =IF(SUMPRODUCT($Q$5:$AW$5,Q35:AW35)=0,"-",SUMPRODUCT($Q$5:$AW$5,Q35:AW35)) -> 770 | L35: - | M35: - | N35: Envoyée | O35: F2025-0254 | P35: Paid 06/06/2025 | R35: 20 | S35: 17
A36: Ubi | B36: Ubisoft | C36: 45762 | D36: Demande urgente nouveau drapeau | E36: UBI02 | F36: INÈS DE LAGUICHE | G36: Delivered | H36: Exe | I36: https://saranistudio.sharepoint.com/:f:/s/SaraniAssets/EqN-VbwAEzxLt8dI9bxAhL0BDMANZz9z9o9706t-nElyRw?e=WC6cnP | J36: =IF(SUM(Q36:AW36)=0,"-",SUM(Q36:AW36)) -> 1 | K36: =IF(SUMPRODUCT($Q$5:$AW$5,Q36:AW36)=0,"-",SUMPRODUCT($Q$5:$AW$5,Q36:AW36)) -> 30 | L36: - | M36: - | N36: Envoyée | O36: F2025-0254 | P36: Paid 06/06/2025 | R36: 1
A37: Ubi | B37: Adidas | C37: 45763 | D37: Adidas 10K Après course concept | E37: ADR25 | F37: CLARA-BONVARLET | G37: Delivered | H37: Exe | I37: https://saranistudio.sharepoint.com/:f:/s/SaraniAssets/EmR8ktNWJplImqGX_AZgTDUB-qwnT2ZpJ0COt3mm7O5ODw?e=OAW5eO | J37: =IF(SUM(Q37:AW37)=0,"-",SUM(Q37:AW37)) -> 1 | K37: =IF(SUMPRODUCT($Q$5:$AW$5,Q37:AW37)=0,"-",SUMPRODUCT($Q$5:$AW$5,Q37:AW37)) -> 135 | L37: - | M37: - | N37: Envoyée | O37: F2025-0254 | P37: Paid 06/06/2025 | Q37: 1
A38: Ubi | B38: Adidas | C38: 45763 | D38: Adidas 10K Retraits dossards | E38: ADR25 | F38: CLARA-BONVARLET | G38: Delivered | H38: Exe | I38: https://saranistudio.sharepoint.com/:f:/s/SaraniAssets/Euv4WdeFGLJNug8wvC-YPrMBP7k8zO0-QCOLso0JUyu_0w?e=E3WeEX | J38: =IF(SUM(Q38:AW38)=0,"-",SUM(Q38:AW38)) -> 6 | K38: =IF(SUMPRODUCT($Q$5:$AW$5,Q38:AW38)=0,"-",SUMPRODUCT($Q$5:$AW$5,Q38:AW38)) -> 285 | L38: - | M38: - | N38: Envoyée | O38: F2025-0254 | P38: Paid 06/06/2025 | Q38: 1 | R38: 5
A39: Ubi | B39: Adidas | C39: 45763 | D39: Créas Brand | E39: ADR25 | F39: CLARA-BONVARLET | G39: Delivered | H39: Exe | I39: 20250417_Créas Brand | J39: =IF(SUM(Q39:AW39)=0,"-",SUM(Q39:AW39)) -> 19 | K39: =IF(SUMPRODUCT($Q$5:$AW$5,Q39:AW39)=0,"-",SUMPRODUCT($Q$5:$AW$5,Q39:AW39)) -> 570 | L39: - | M39: - | N39: Envoyée | O39: F2025-0254 | P39: Paid 06/06/2025 | R39: 19
A40: Ubi | B40: Adidas | C40: 45764 | D40: ADU25 / Exes Wings for life | E40: ADU25 | F40: Anouck MOTTIN | G40: Delivered | H40: Exe | I40: 20250417_ADU25 - Exes Wings for life | J40: =IF(SUM(Q40:AW40)=0,"-",SUM(Q40:AW40)) -> 24 | K40: =IF(SUMPRODUCT($Q$5:$AW$5,Q40:AW40)=0,"-",SUMPRODUCT($Q$5:$AW$5,Q40:AW40)) -> 720 | L40: - | M40: - | N40: Envoyée | O40: F2025-0254 | P40: Paid 06/06/2025 | R40: 24
A41: Ubi | B41: LEGO | C41: 45764 | D41: LEG02 : Le grand tournoi des Champs - MockUp | E41: LEG02 | F41: Louis Keller | G41: Delivered | H41: Exe | I41: 20250417_LEG02 - Brief affiche LEGO Le grand tournoi des Champs - MockUp | J41: =IF(SUM(Q41:AW41)=0,"-",SUM(Q41:AW41)) -> 3 | K41: =IF(SUMPRODUCT($Q$5:$AW$5,Q41:AW41)=0,"-",SUMPRODUCT($Q$5:$AW$5,Q41:AW41)) -> 405 | N41: Envoyée | O41: F2025-0316 | P41: Paid 21/07/2025 | Q41: 3
A42: Ubi | B42: Ubisoft | C42: 45765 | D42: Crea Menu UBISOFT | E42: UBI02 | F42: INÈS DE LAGUICHE | G42: Delivered | H42: Exe | I42: 20240418_Crea Menu UBISOFT | J42: =IF(SUM(Q42:AW42)=0,"-",SUM(Q42:AW42)) -> 2 | K42: =IF(SUMPRODUCT($Q$5:$AW$5,Q42:AW42)=0,"-",SUMPRODUCT($Q$5:$AW$5,Q42:AW42)) -> 60 | L42: - | M42: - | N42: Envoyée | O42: F2025-0254 | P42: Paid 06/06/2025 | R42: 2
A43: Ubi | B43: Ubisoft | C43: 45770 | D43: Demande autocollant Ubisoft | E43: UBI02 | F43: INÈS DE LAGUICHE | G43: Delivered | H43: Exe | I43: 20250423_Demande autocollant Ubisoft | J43: 4 | K43: =IF(SUMPRODUCT($Q$5:$AW$5,Q43:AW43)=0,"-",SUMPRODUCT($Q$5:$AW$5,Q43:AW43)) -> 120 | L43: - | M43: - | N43: Envoyée | O43: F2025-0254 | P43: Paid 06/06/2025 | R43: 4
A44: Ubi | B44: Ubisoft | C44: 45771 | D44: Marque place ubisoft | E44: UBI02 | F44: INÈS DE LAGUICHE | G44: Delivered | H44: Exe | I44: https://saranistudio.sharepoint.com/:f:/s/SaraniAssets/EkRS9mGFge5Kl1x7FVSML_QBB6CYNpdGfHuA16loUK0C7Q?e=dvKG85 | J44: 4 | K44: =IF(SUMPRODUCT($Q$5:$AW$5,Q44:AW44)=0,"-",SUMPRODUCT($Q$5:$AW$5,Q44:AW44)) -> 620 | L44: - | M44: - | N44: Envoyée | O44: F2025-0254 | P44: Paid 06/06/2025 | R44: 1 | S44: 59
A45: Ubi | B45: Adidas | C45: 45775 | D45: Adidas Testing before tasting - Fasta Pasta | E45: ADR25 | F45: Louis Keller | G45: Delivered | H45: Exe | I45: https://saranistudio.sharepoint.com/:f:/s/SaraniAssets/EtkoMD_b7IhCvxTQ5JH1Fc0BDogoddmhRdZFw8Su9kzzow?e=RpKU4Z | J45: =IF(SUM(Q45:AW45)=0,"-",SUM(Q45:AW45)) -> 7 | K45: =IF(SUMPRODUCT($Q$5:$AW$5,Q45:AW45)=0,"-",SUMPRODUCT($Q$5:$AW$5,Q45:AW45)) -> 210 | N45: Envoyée | O45: F2025-0316 | P45: Paid 21/07/2025 | R45: 7
A46: Ubi | B46: Perrier | C46: 45775 | D46: Maquette Perrier x Concorde / PER03 | E46: PER03 | F46: Clémence VIGNERON | G46: Delivered | H46: Exe | I46: https://saranistudio.sharepoint.com/sites/SaraniAssets/Shared%20Documents/Forms/AllItems.aspx?id=%2Fsites%2FSaraniAssets%2FShared%20Documents%2F03%2E%20Customers%2F17%2E%20Ubi%2F06%2E%20Perrier%2F02%2EProjects&p=true&ga=1 | J46: 1 | K46: 350 | L46: - | M46: - | N46: Envoyée | O46: F2025-0254 | P46: Paid 06/06/2025
A47: Ubi | B47: Adidas | C47: 45776 | D47: 10K RD - Habillage magasins | E47: ADRDK | F47: Chloé DESIGAUX | G47: Delivered | H47: Exe | I47: 20250429_10K RD - Habillage magasins | J47: =IF(SUM(Q47:AW47)=0,"-",SUM(Q47:AW47)) -> 60 | K47: =IF(SUMPRODUCT($Q$5:$AW$5,Q47:AW47)=0,"-",SUMPRODUCT($Q$5:$AW$5,Q47:AW47)) -> 1715 | N47: Envoyée | O47: F2025-0316 | P47: Paid 21/07/2025 | Q47: 3 | R47: 37 | S47: 20
A48: Ubi | B48: Adidas | C48: 45779 | D48: Fiche produits chaussure | E48: ADR25 | F48: Clémence VIGNERON | G48: Delivered | H48: Exe | I48: https://saranistudio.sharepoint.com/:f:/s/SaraniAssets/EkRW8XEd48hLmvSLGNJtptcBcwDUthsR2343tayGPKrqtA?e=UeQqDQ | J48: =IF(SUM(Q48:AW48)=0,"-",SUM(Q48:AW48)) -> 3 | K48: =IF(SUMPRODUCT($Q$5:$AW$5,Q48:AW48)=0,"-",SUMPRODUCT($Q$5:$AW$5,Q48:AW48)) -> 405 | N48: Envoyée | O48: F2025-0316 | P48: Paid 21/07/2025 | Q48: 3
A49: Ubi | B49: Adidas | C49: 45779 | D49: 10K Village | E49: ADR25 | F49: CLARA-BONVARLET | G49: Delivered | H49: Exe | I49: https://saranistudio.sharepoint.com/:f:/s/SaraniAssets/Em3YG4xNxTBFrbP2hkHg1UgBNpkZhCMwyyIWpdfkKjUV2Q?e=ap3P6n | J49: =IF(SUM(Q49:AW49)=0,"-",SUM(Q49:AW49)) -> 56 | K49: =IF(SUMPRODUCT($Q$5:$AW$5,Q49:AW49)=0,"-",SUMPRODUCT($Q$5:$AW$5,Q49:AW49)) -> 1905 | N49: Envoyée | O49: F2025-0316 | P49: Paid 21/07/2025 | Q49: 1 | R49: 54 | AK49: 1
A50: Ubi | B50: Adidas | C50: 45782 | D50: ADU25 - EXE Adidas 10K | E50: ADU25 | F50: Pauline Drouet | G50: Delivered | H50: Exe | I50: https://saranistudio.sharepoint.com/:f:/s/SaraniAssets/EmmehBNmNfpFrbX-UjTjMBoBAHLNEIt58fWHkijGm1XI7A?e=EHSb33 | J50: =IF(SUM(Q50:AW50)=0,"-",SUM(Q50:AW50)) -> 6 | K50: =IF(SUMPRODUCT($Q$5:$AW$5,Q50:AW50)=0,"-",SUMPRODUCT($Q$5:$AW$5,Q50:AW50)) -> 80 | N50: Envoyée | O50: F2025-0316 | P50: Paid 21/07/2025 | R50: 1 | S50: 5
A51: Ubi | B51: Adidas | C51: 45786 | D51: ADU 25 - EXE Move for the Planet | E51: ADU25 | F51: Pauline Drouet | G51: Delivered | H51: Exe | I51: https://saranistudio.sharepoint.com/:f:/s/SaraniAssets/EqhYmtDug91BuskKLgwXKFYB4DkKHmxvh2q85hPYa7kYIQ?e=hwIzoM | J51: =IF(SUM(Q51:AW51)=0,"-",SUM(Q51:AW51)) -> 10 | K51: =IF(SUMPRODUCT($Q$5:$AW$5,Q51:AW51)=0,"-",SUMPRODUCT($Q$5:$AW$5,Q51:AW51)) -> 180 | N51: Envoyée | O51: F2025-0316 | P51: Paid 21/07/2025 | R51: 4 | S51: 6
A52: Ubi | B52: Adidas | C52: 45789 | D52: ADR25 - Créa brand | E52: ADR25 | F52: Clara BONVARLET | G52: Delivered | H52: Exe | I52: https://saranistudio.sharepoint.com/:f:/s/SaraniAssets/Enc3IfwCvEtGiwm2zkxFlSgBADLJ0L6eq43MYxxNauEGDA?e=z3JYDE | J52: =IF(SUM(Q52:AW52)=0,"-",SUM(Q52:AW52)) -> 9 | K52: =IF(SUMPRODUCT($Q$5:$AW$5,Q52:AW52)=0,"-",SUMPRODUCT($Q$5:$AW$5,Q52:AW52)) -> 210 | N52: Envoyée | O52: F2025-0316 | P52: Paid 21/07/2025 | R52: 6 | S52: 3
A53: Ubi | B53: Adidas | C53: 45790 | D53: RUN CAMP Adidas | E53: ADTPI | F53: Louis Keller | G53: Delivered | H53: Exe | I53: https://saranistudio.sharepoint.com/:f:/s/SaraniAssets/EstWRPSzUoFAlK4xMwcQ6p0BbBoZ-8Mn6vJ5fdx1SGy3pQ?e=3gClB9 | J53: =IF(SUM(Q53:AW53)=0,"-",SUM(Q53:AW53)) -> 4 | K53: =IF(SUMPRODUCT($Q$5:$AW$5,Q53:AW53)=0,"-",SUMPRODUCT($Q$5:$AW$5,Q53:AW53)) -> 540 | N53: Envoyée | O53: F2025-0316 | P53: Paid 21/07/2025 | Q53: 4
A54: Ubi | B54: Adidas | C54: 45791 | D54: ADLDL / Écrans LED | E54: ADLDL | F54: Anouck MOTTIN | G54: Delivered | H54: Exe | I54: 20250514_ADLDL-Écrans LED | J54: =IF(SUM(Q54:AW54)=0,"-",SUM(Q54:AW54)) -> 1 | K54: =IF(SUMPRODUCT($Q$5:$AW$5,Q54:AW54)=0,"-",SUMPRODUCT($Q$5:$AW$5,Q54:AW54)) -> 150 | N54: Envoyée | O54: F2025-0316 | P54: Paid 21/07/2025 | AK54: 1
A55: Ubi | B55: Adidas | C55: 45791 | D55: ADPOE - Banding INSEP | E55: ADPOE | F55: Jérémy LE NILLON | G55: Delivered | H55: Exe | I55: https://saranistudio.sharepoint.com/:f:/s/SaraniAssets/ElVZVfx_c8VIoKtjm6oBzvUBLdjBc45G_xSqqm20iYYMSQ?e=ws8b3h | J55: =IF(SUM(Q55:AW55)=0,"-",SUM(Q55:AW55)) -> 12 | K55: =IF(SUMPRODUCT($Q$5:$AW$5,Q55:AW55)=0,"-",SUMPRODUCT($Q$5:$AW$5,Q55:AW55)) -> 360 | N55: Envoyée | O55: F2025-0316 | P55: Paid 21/07/2025 | R55: 12
A56: Ubi | B56: Adidas | C56: 45793 | D56: ADR25 - Créas Brand | E56: ADR25 | F56: CLARA-BONVARLET | G56: Delivered | H56: Exe | I56: https://saranistudio.sharepoint.com/:f:/s/SaraniAssets/EiUaTdR1OCBAkwCDXWFUvisB0KD7CutMUWX8hxmT-ECZwQ?e=Ggooxa | J56: =IF(SUM(Q56:AW56)=0,"-",SUM(Q56:AW56)) -> 1 | K56: =IF(SUMPRODUCT($Q$5:$AW$5,Q56:AW56)=0,"-",SUMPRODUCT($Q$5:$AW$5,Q56:AW56)) -> 30 | N56: Envoyée | O56: F2025-0316 | P56: Paid 21/07/2025 | R56: 1
A57: Ubi | B57: Adidas | C57: 45797 | D57: ADO25 - Simu Verres | E57: ADO25 | F57: Marie DELGRANGE | G57: Delivered | H57: Exe | I57: https://saranistudio.sharepoint.com/:f:/s/SaraniAssets/EoMNYd3UxKNJlr6MRVURDsMB6tfTIw2A0xQkUCQLl3FHcQ?e=jZQtVM | J57: =IF(SUM(Q57:AW57)=0,"-",SUM(Q57:AW57)) -> 2 | K57: =IF(SUMPRODUCT($Q$5:$AW$5,Q57:AW57)=0,"-",SUMPRODUCT($Q$5:$AW$5,Q57:AW57)) -> 60 | N57: Envoyée | O57: F2025-0316 | P57: Paid 21/07/2025 | R57: 2
A58: Ubi | B58: Perrier | C58: 45797 | D58: Gabarit triporteur et autres assets | E58: PER03 | F58: Clémence VIGNERON | G58: Delivered | H58: Exe | I58: https://saranistudio.sharepoint.com/:f:/s/SaraniAssets/EjQJDnfGDEBNqjHP1wb5kWABnvuq-dHPG0GCgOUEDhzzHQ?e=kruFDD | J58: =IF(SUM(Q58:AW58)=0,"-",SUM(Q58:AW58)) -> 4 | K58: =IF(SUMPRODUCT($Q$5:$AW$5,Q58:AW58)=0,"-",SUMPRODUCT($Q$5:$AW$5,Q58:AW58)) -> 225 | N58: Envoyée | O58: F2025-0316 | P58: Paid 21/07/2025 | Q58: 1 | R58: 3
A59: Ubi | B59: LEGO | C59: 45797 | D59: Leg02 : Wireframe-Le grand tournoi des Champs | E59: LEG02 | F59: Louis KELLER | G59: Delivered | H59: Exe | I59: https://saranistudio.sharepoint.com/:f:/s/SaraniAssets/EvQgxP8syHJEm8wBEUoZfVUBxyGOXMASxo-ZUfOrUUFYog?e=FVehef | J59: =IF(SUM(Q59:AW59)=0,"-",SUM(Q59:AW59)) -> 2 | K59: =IF(SUMPRODUCT($Q$5:$AW$5,Q59:AW59)=0,"-",SUMPRODUCT($Q$5:$AW$5,Q59:AW59)) -> 270 | N59: Envoyée | O59: F2025-0316 | P59: Paid 21/07/2025 | Q59: 2
A60: Ubi | B60: Adidas | C60: 45797 | D60: ADO25 - CAP BAG ART | E60: ADO25 | F60: Marie DELGRANGE | G60: Delivered | H60: Exe | I60: https://saranistudio.sharepoint.com/:f:/s/SaraniAssets/EhlZBNLzcqpFiARLNU-fx1MBSWMgeCX1IeBkcqAD2YbrkQ?e=gPqdbe | J60: =IF(SUM(Q60:AW60)=0,"-",SUM(Q60:AW60)) -> 1 | K60: =IF(SUMPRODUCT($Q$5:$AW$5,Q60:AW60)=0,"-",SUMPRODUCT($Q$5:$AW$5,Q60:AW60)) -> 30 | N60: Envoyée | O60: F2025-0316 | P60: Paid 21/07/2025 | R60: 1
A61: Ubi | B61: Adidas | C61: 45797 | D61: ADR25 - Zone de radars | E61: ADR25 | F61: Jeremy LE NILLON | G61: Delivered | H61: Exe | I61: 20250520_ADR25 - Zone de radars | J61: =IF(SUM(Q61:AW61)=0,"-",SUM(Q61:AW61)) -> 15 | K61: =IF(SUMPRODUCT($Q$5:$AW$5,Q61:AW61)=0,"-",SUMPRODUCT($Q$5:$AW$5,Q61:AW61)) -> 780 | N61: Envoyée | O61: F2025-0316 | P61: Paid 21/07/2025 | Q61: 2 | R61: 12 | AK61: 1
A62: Ubi | B62: Adidas | C62: 45798 | D62: SSTR - urgence déclinaison crea | E62: ADOSS | F62: Hélène | G62: Delivered | H62: Exe | I62: https://saranistudio.sharepoint.com/:f:/s/SaraniAssets/EubDXMXmokJKmJcbTzWzXksBYaDqnuTs-eF5NNogJo2Z7Q?e=KYga9h | J62: =IF(SUM(Q62:AW62)=0,"-",SUM(Q62:AW62)) -> 15 | K62: =IF(SUMPRODUCT($Q$5:$AW$5,Q62:AW62)=0,"-",SUMPRODUCT($Q$5:$AW$5,Q62:AW62)) -> 450 | N62: Envoyée | O62: F2025-0316 | P62: Paid 21/07/2025 | R62: 15
A63: Ubi | B63: Perrier | C63: 45800 | D63: Menu Terrasse Perrier | E63: PER03 | F63: Clémence VIGNERON | G63: Delivered | H63: Exe | I63: https://saranistudio.sharepoint.com/:f:/s/SaraniAssets/EmREgoHdgJxFurb5U2kPbvEBnVcz3LSysKCt3koVf-IfEA?e=57BZwx | J63: =IF(SUM(Q63:AW63)=0,"-",SUM(Q63:AW63)) -> 1 | K63: =IF(SUMPRODUCT($Q$5:$AW$5,Q63:AW63)=0,"-",SUMPRODUCT($Q$5:$AW$5,Q63:AW63)) -> 135 | N63: Envoyée | O63: F2025-0316 | P63: Paid 21/07/2025 | Q63: 1
A64: Ubi | B64: Adidas | C64: 45803 | D64: ADTLD - Adidas Créas | E64: ADTLD | F64: Clara BONVARLET | G64: Delivered | H64: Exe | I64: https://saranistudio.sharepoint.com/:f:/s/SaraniAssets/Esyl6p6nJuRGmt4hceoxI10Bg0bfEX0wmbJIRWD_Nhbbfg?e=4JrjT9 | J64: =IF(SUM(Q64:AW64)=0,"-",SUM(Q64:AW64)) -> 9 | K64: =IF(SUMPRODUCT($Q$5:$AW$5,Q64:AW64)=0,"-",SUMPRODUCT($Q$5:$AW$5,Q64:AW64)) -> 230 | N64: Envoyée | O64: F2025-0316 | P64: Paid 21/07/2025 | R64: 7 | S64: 2
A65: Ubi | B65: Adidas | C65: 45804 | D65: Adidas ISC | E65: ADR25 | F65: Clara BONVARLET | G65: Delivered | H65: Exe | I65: https://saranistudio.sharepoint.com/:f:/s/SaraniAssets/EhkGyghsZf5DnwZHlivUMmYB_5qnJW14hHY5SSIboE939w?e=PCQQLb | J65: =IF(SUM(Q65:AW65)=0,"-",SUM(Q65:AW65)) -> 12 | K65: =IF(SUMPRODUCT($Q$5:$AW$5,Q65:AW65)=0,"-",SUMPRODUCT($Q$5:$AW$5,Q65:AW65)) -> 360 | N65: Envoyée | O65: F2025-0316 | P65: Paid 21/07/2025 | R65: 12
A66: Ubi | B66: Perrier | C66: 45805 | D66: Perrier logos et exe chaises | E66: PER03 | F66: Clémence VIGNERON | G66: Delivered | H66: Exe | J66: =IF(SUM(Q66:AW66)=0,"-",SUM(Q66:AW66)) -> 14 | K66: =IF(SUMPRODUCT($Q$5:$AW$5,Q66:AW66)=0,"-",SUMPRODUCT($Q$5:$AW$5,Q66:AW66)) -> 420 | N66: Envoyée | O66: F2025-0316 | P66: Paid 21/07/2025 | R66: 14
A67: Ubi | B67: Adidas | C67: 45805 | D67: Exe 10K race weekend calendar | E67: ADU25 | F67: Pauline Drouet | G67: Delivered | H67: Exe | I67: https://saranistudio.sharepoint.com/:f:/s/SaraniAssets/Epl8_ZqP5VpArYaqNmgK5vMBJFTEdTr-MluB1y4OHla7VA?e=yr4xOM | J67: =IF(SUM(Q67:AW67)=0,"-",SUM(Q67:AW67)) -> 6 | K67: =IF(SUMPRODUCT($Q$5:$AW$5,Q67:AW67)=0,"-",SUMPRODUCT($Q$5:$AW$5,Q67:AW67)) -> 180 | N67: Envoyée | O67: F2025-0316 | P67: Paid 21/07/2025 | R67: 6
A68: Ubi | B68: Adidas | C68: 45791 | D68: ADR25 - Shake Out Party | E68: ADR25 | F68: Jeremy LE NILLON | G68: Delivered | H68: Exe | I68: 20250514_ADR25 - Shake Out Party | J68: =IF(SUM(Q68:AW68)=0,"-",SUM(Q68:AW68)) -> 66 | K68: =IF(SUMPRODUCT($Q$5:$AW$5,Q68:AW68)=0,"-",SUMPRODUCT($Q$5:$AW$5,Q68:AW68)) -> 2240 | N68: Sent | O68: F2025-0390 | P68: Paid 08/08/2025 | Q68: 4 | R68: 47 | S68: 14 | AK68: 1
A69: Ubi | B69: Adidas | C69: 45796 | D69: ADR25 - Diamond League | E69: ADR25 | F69: Jeremy LE NILLON | G69: Delivered | H69: Exe | I69: https://saranistudio.sharepoint.com/:f:/s/SaraniAssets/Esy3btFmysdEhUyMswG_HiIBLF3MQY3qJ4S2qRv2vEIacg?e=5aVdCD | J69: =IF(SUM(Q69:AW69)=0,"-",SUM(Q69:AW69)) -> 12 | K69: =IF(SUMPRODUCT($Q$5:$AW$5,Q69:AW69)=0,"-",SUMPRODUCT($Q$5:$AW$5,Q69:AW69)) -> 795 | L69: =IF(SUM(S69:AY69)=0,"-",SUM(S69:AY69)) -> 1 | N69: Sent | O69: F2025-0390 | P69: Paid 08/08/2025 | Q69: 3 | R69: 8 | AK69: 1
A70: Ubi | B70: Adidas | C70: 45798 | D70: EXE ADORI25 | E70: ADORI21 | F70: MARIE DELGRANGE | G70: Delivered | H70: Exe | I70: https://saranistudio.sharepoint.com/:f:/s/SaraniAssets/EuZwn3jpLQJIhNUcWlVMz6QBNTNORc2FCfWJ-b3NHQYhQQ?e=Z7Slbi | J70: =IF(SUM(Q70:AW70)=0,"-",SUM(Q70:AW70)) -> 70 | K70: =IF(SUMPRODUCT($Q$5:$AW$5,Q70:AW70)=0,"-",SUMPRODUCT($Q$5:$AW$5,Q70:AW70)) -> 2080 | N70: Sent | O70: F2025-0390 | P70: Paid 08/08/2025 | R70: 69 | S70: 1
A71: Ubi | B71: Adidas | C71: 45811 | D71: ADU25 / Exe adidas 10K - Posters | E71: ADU25 | F71: Pauline Drouet | G71: Delivered | H71: Exe | I71: https://saranistudio.sharepoint.com/:f:/s/SaraniAssets/Et84X0HTvcZEmiBhdZReG4cBmZUAQxHk1tuDEvzRT_hMqw?e=XreuFK | J71: =IF(SUM(Q71:AW71)=0,"-",SUM(Q71:AW71)) -> 7 | K71: =IF(SUMPRODUCT($Q$5:$AW$5,Q71:AW71)=0,"-",SUMPRODUCT($Q$5:$AW$5,Q71:AW71)) -> 360 | N71: Sent | O71: F2025-0390 | P71: Paid 08/08/2025 | Y71: 1 | Z71: 6
A72: Ubi | B72: Adidas | C72: 45812 | D72: Adidas cap customization | E72: ADSDC | F72: Louis KELLER | G72: Delivered | H72: Exe | I72: https://saranistudio.sharepoint.com/:f:/s/SaraniAssets/ErU6GsUyrGFNpyMbkA04fNkB_gFxGgIDGGPlJpn7PR03gg?e=4MLCKA | J72: =IF(SUM(Q72:AW72)=0,"-",SUM(Q72:AW72)) -> 5 | K72: =IF(SUMPRODUCT($Q$5:$AW$5,Q72:AW72)=0,"-",SUMPRODUCT($Q$5:$AW$5,Q72:AW72)) -> 290 | N72: Sent | O72: F2025-0390 | P72: Paid 08/08/2025 | Y72: 1 | Z72: 4
A73: Ubi | B73: LEGO | C73: 45818 | D73: Leg02 : Wireframe Mobile / Tablette / PC + Concepts | E73: LEG02 | F73: Louis KELLER | G73: Delivered | H73: Exe | I73: https://saranistudio.sharepoint.com/:f:/s/SaraniAssets/EvQgxP8syHJEm8wBEUoZfVUBxyGOXMASxo-ZUfOrUUFYog?e=FVehef | J73: =IF(SUM(Q73:AW73)=0,"-",SUM(Q73:AW73)) -> 13 | K73: =IF(SUMPRODUCT($Q$5:$AW$5,Q73:AW73)=0,"-",SUMPRODUCT($Q$5:$AW$5,Q73:AW73)) -> 705 | N73: Sent | O73: F2025-0390 | P73: Paid 08/08/2025 | Q73: 3 | R73: 10
A74: Ubi | B74: LEGO | C74: 45820 | D74: LEGO - Affiches patrimoine & Assets | E74: LEG02 | F74: Louis KELLER | G74: Delivered | H74: Exe | I74: https://saranistudio.sharepoint.com/:f:/s/SaraniAssets/EuiKzOixdoRHj5nnzDUHRw0BXZrvMfCWu4Fdpp_RuGOZ3Q?e=YRyLxt | J74: =IF(SUM(Q74:AW74)=0,"-",SUM(Q74:AW74)) -> 6 | K74: =IF(SUMPRODUCT($Q$5:$AW$5,Q74:AW74)=0,"-",SUMPRODUCT($Q$5:$AW$5,Q74:AW74)) -> 390 | N74: Sent | O74: F2025-0390 | P74: Paid 08/08/2025 | Q74: 2 | R74: 4
A75: ubi | B75: Adidas | C75: 45824 | D75: Adidas ADPOE Branding INSEP | E75: ADPOE | F75: Jérémy LE NILLON | G75: Delivered | H75: Exe | I75: https://saranistudio.sharepoint.com/:f:/s/SaraniAssets/EgCFNLPVa3FHiSuoQhBU05EBPtq7qqU76etCRaC1N8tUjA?e=XBolAI | J75: =IF(SUM(Q75:AW75)=0,"-",SUM(Q75:AW75)) -> 7 | K75: =IF(SUMPRODUCT($Q$5:$AW$5,Q75:AW75)=0,"-",SUMPRODUCT($Q$5:$AW$5,Q75:AW75)) -> 210 | N75: Sent | O75: F2025-0390 | P75: Paid 08/08/2025 | R75: 7
A76: Ubi | B76: Adidas | C76: 45823 | D76: Adidas ADR25 - Diamond League - Image 3D backdrop | E76: ADR25 | F76: Pauline Drouet | G76: Delivered | H76: Exe | J76: =IF(SUM(Q76:AW76)=0,"-",SUM(Q76:AW76)) -> 1 | K76: =IF(SUMPRODUCT($Q$5:$AW$5,Q76:AW76)=0,"-",SUMPRODUCT($Q$5:$AW$5,Q76:AW76)) -> 500 | N76: Sent | O76: F2025-0390 | P76: Paid 08/08/2025 | X76: 1
A77: Ubi | B77: Adidas | C77: 45824 | D77: Adidas - Diamond League Racing bibs | E77: ADR25_09 | F77: Pauline Drouet | G77: Delivered | H77: Exe | I77: https://saranistudio.sharepoint.com/:f:/s/SaraniAssets/EsDCZlBIHItBuomKrCsL1zYBlTRsAC5cHL8IS3VVT62Xeg?e=N1rXoe | J77: =IF(SUM(Q77:AW77)=0,"-",SUM(Q77:AW77)) -> 28 | K77: =IF(SUMPRODUCT($Q$5:$AW$5,Q77:AW77)=0,"-",SUMPRODUCT($Q$5:$AW$5,Q77:AW77)) -> 300 | N77: Sent | O77: F2025-0390 | P77: Paid 08/08/2025 | R77: 1 | S77: 27
A78: Ubi | B78: Adidas | C78: 45824 | D78: ADR25_09 - Exes Diamond League - Packaging & Foodtruck simulation | E78: ADR25_09 | F78: Anouck MOTTIN | G78: Delivered | H78: Exe | I78: https://saranistudio.sharepoint.com/:f:/s/SaraniAssets/Ej1Vkf4vhc1Cr-haaVUdJDQB-aN_xHIO5v8wAz4ooxI5zg?e=bMYIsU | J78: =IF(SUM(Q78:AW78)=0,"-",SUM(Q78:AW78)) -> 15 | K78: =IF(SUMPRODUCT($Q$5:$AW$5,Q78:AW78)=0,"-",SUMPRODUCT($Q$5:$AW$5,Q78:AW78)) -> 660 | N78: Sent | O78: F2025-0390 | P78: Paid 08/08/2025 | Q78: 2 | R78: 13
A79: Ubi | B79: Adidas | C79: 45825 | D79: ADLRA - Led adidas Arena | E79: ADLRA | F79: Jeremy LE NILLON | G79: Delivered | H79: Exe | I79: https://saranistudio.sharepoint.com/:f:/s/SaraniAssets/EmxdCZCacVVJvrQ5aYcu5aoBkdb-gPd1QikjjZ4XqMSwAg?e=flr2P2 | J79: =IF(SUM(Q79:AW79)=0,"-",SUM(Q79:AW79)) -> 9 | K79: =IF(SUMPRODUCT($Q$5:$AW$5,Q79:AW79)=0,"-",SUMPRODUCT($Q$5:$AW$5,Q79:AW79)) -> 930 | L79: - | M79: - | N79: Sent | O79: F2025-0462 | P79: Paid 05/09/2025 | AJ79: 6 | AK79: 3
A80: Ubi | B80: LEGO | C80: 45825 | D80: LEGO - Assets for Winner Contact Platform | E80: LEG02 | F80: Louis KELLER | G80: Delivered | H80: Exe | J80: =IF(SUM(Q80:AW80)=0,"-",SUM(Q80:AW80)) -> 4 | K80: =IF(SUMPRODUCT($Q$5:$AW$5,Q80:AW80)=0,"-",SUMPRODUCT($Q$5:$AW$5,Q80:AW80)) -> 225 | N80: Sent | O80: F2025-0390 | P80: Paid 08/08/2025 | Q80: 1 | R80: 3
A81: Ubi | B81: LEGO | C81: 45826 | D81: Lego Wireframe page 2 | E81: LEG02 | F81: Louis KELLER | G81: Delivered | H81: Exe | J81: =IF(SUM(Q81:AW81)=0,"-",SUM(Q81:AW81)) -> 3 | K81: =IF(SUMPRODUCT($Q$5:$AW$5,Q81:AW81)=0,"-",SUMPRODUCT($Q$5:$AW$5,Q81:AW81)) -> 405 | L81: - | M81: - | N81: Sent | O81: F2025-0462 | P81: Paid 05/09/2025 | Q81: 3
A82: Ubi | B82: Adidas | C82: 45834 | D82: ADU25 - Adidas Pride | E82: ADU 25 | F82: Pauline Drouet | G82: Delivered | H82: Exe | I82: https://saranistudio.sharepoint.com/:f:/s/SaraniAssets/EtnlXTyvXahJjtgg5cPYwhEBgi2bPz4wbfEQxC9QMwjzbg?e=AWO134 | J82: =IF(SUM(Q82:AW82)=0,"-",SUM(Q82:AW82)) -> 4 | K82: =IF(SUMPRODUCT($Q$5:$AW$5,Q82:AW82)=0,"-",SUMPRODUCT($Q$5:$AW$5,Q82:AW82)) -> 40 | N82: Sent | O82: F2025-0390 | P82: Paid 08/08/2025 | S82: 4
A83: Ubi | B83: Adidas | C83: 45834 | D83: ADSBF - Seeding Box FFA adidas (Part 1) | E83: ADSBF | F83: Pauline Drouet | G83: Delivered | H83: Exe | I83: https://saranistudio.sharepoint.com/:f:/r/sites/SaraniAssets/Shared%20Documents/03.%20Customers/17.%20Ubi/02.%20Adidas/02.%20Projects/20250626%20ADSBF%20-%20Seeding%20Box%20FFA?csf=1&web=1&e=wbqGHU | J83: =IF(SUM(Q83:AW83)=0,"-",SUM(Q83:AW83)) -> 10 | K83: =IF(SUMPRODUCT($Q$5:$AW$5,Q83:AW83)=0,"-",SUMPRODUCT($Q$5:$AW$5,Q83:AW83)) -> 800 | L83: - | M83: - | N83: Sent | O83: F2025-0462 | P83: Paid 05/09/2025 | R83: 3 | X83: 1 | Z83: 6
A84: Ubi | B84: LEGO | C84: 45835 | D84: LEGO - Branding Scéno 3D Grand tournoi des champs | E84: LEG02 | F84: Louis Keller | G84: Delivered | H84: Exe | I84: https://saranistudio.sharepoint.com/:f:/s/SaraniAssets/EsF5hgYFleFNsXJ7mzNO9p8B89f7WcfngPHbjWVmfdxzaA?e=Le9HkK | J84: =IF(SUM(Q84:AW84)=0,"-",SUM(Q84:AW84)) -> 4 | K84: =IF(SUMPRODUCT($Q$5:$AW$5,Q84:AW84)=0,"-",SUMPRODUCT($Q$5:$AW$5,Q84:AW84)) -> 120 | L84: - | M84: - | N84: Sent | O84: F2025-0462 | P84: Paid 05/09/2025 | R84: 4
A85: Ubi | B85: IKEA | C85: 45840 | D85: IKEA Cook session | E85: IKE03 | F85: MARIE DELGRANGE | G85: Delivered | H85: Exe | I85: https://saranistudio.sharepoint.com/:f:/s/SaraniAssets/ErF5sbZ715lOlB7H_cWNeR0BngttTKNcHTGX8yZqtpiYpw?e=fndeol | J85: =IF(SUM(Q85:AW85)=0,"-",SUM(Q85:AW85)) -> 53 | K85: =IF(SUMPRODUCT($Q$5:$AW$5,Q85:AW85)=0,"-",SUMPRODUCT($Q$5:$AW$5,Q85:AW85)) -> 1870 | L85: - | M85: - | N85: Sent | O85: F2025-0462 | P85: Paid 05/09/2025 | Q85: 3 | R85: 28 | S85: 15 | Y85: 2 | Z85: 5
A86: Ubi | B86: Adidas | C86: 45841 | D86: ADOSS - Personnalisation F&B Superstar | E86: ADOSS | F86: Inès de Laguiche | G86: Delivered | H86: Exe | I86: https://saranistudio.sharepoint.com/:f:/s/SaraniAssets/EsEx87I6jZJIgeqLrWfLOGcB-KV5RGudNdj_d0vkYUsVuQ?e=SexNVd | J86: =IF(SUM(Q86:AW86)=0,"-",SUM(Q86:AW86)) -> 3 | K86: =IF(SUMPRODUCT($Q$5:$AW$5,Q86:AW86)=0,"-",SUMPRODUCT($Q$5:$AW$5,Q86:AW86)) -> 90 | L86: - | M86: - | N86: Sent | O86: F2025-0462 | P86: Paid 05/09/2025 | R86: 3
A87: Ubi | B87: IKEA | C87: 45845 | D87: IKEA Communiqué de presse | E87: IKE04 | F87: Louis KELLER | G87: Delivered | H87: Exe | I87: https://saranistudio.sharepoint.com/:f:/s/SaraniAssets/EpxT7VzCbbNNmg30vFy95OQB_KBzO3egTv7zTHx_hQGRLA?e=clp2cd | J87: =IF(SUM(Q87:AW87)=0,"-",SUM(Q87:AW87)) -> 1 | K87: =IF(SUMPRODUCT($Q$5:$AW$5,Q87:AW87)=0,"-",SUMPRODUCT($Q$5:$AW$5,Q87:AW87)) -> 135 | L87: - | M87: - | N87: Sent | O87: F2025-0462 | P87: Paid 05/09/2025 | Q87: 1
A88: Ubi | B88: Adidas | C88: 45845 | D88: SSTR - Concert Superstar (Part 1) | E88: ADOSS | F88: Inès de Laguiche | G88: Delivered | H88: Exe | I88: https://saranistudio.sharepoint.com/:f:/s/SaraniAssets/Ehm-_4awGoxFsd7l89wvIHsBc90VPUjoTd0g3EqqIJ6Q4Q?e=lvZUGV | J88: =IF(SUM(Q88:AW88)=0,"-",SUM(Q88:AW88)) -> 123 | K88: =IF(SUMPRODUCT($Q$5:$AW$5,Q88:AW88)=0,"-",SUMPRODUCT($Q$5:$AW$5,Q88:AW88)) -> 4805 | N88: Sent | O88: F2025-0537 | P88: Paid 16/10/2025 | Q88: 10 | R88: 68 | S88: 28 | Y88: 1 | Z88: 15 | AM88: 1
A89: Ubi | B89: IKEA | C89: 45848 | D89: IKEA - BILLYotheque | E89: IKE04 | F89: Louis KELLER | G89: Delivered | H89: Exe | I89: https://saranistudio.sharepoint.com/:f:/s/SaraniAssets/Eqp4A4ubMP9KjLKEg4kP3IoBasriObvfd-PhRMK0FM83bQ?e=H8sEFD | J89: =IF(SUM(Q89:AW89)=0,"-",SUM(Q89:AW89)) -> 20 | K89: =IF(SUMPRODUCT($Q$5:$AW$5,Q89:AW89)=0,"-",SUMPRODUCT($Q$5:$AW$5,Q89:AW89)) -> 590 | L89: - | M89: - | N89: Sent | O89: F2025-0462 | P89: Paid 05/09/2025 | Q89: 2 | R89: 7 | S89: 11
A90: Ubi | B90: Adidas | C90: 45848 | D90: ADU25 - Adidas Runners flocage Tees | E90: ADU25 | F90: Anouck MOTTIN | G90: Delivered | H90: Exe | I90: https://saranistudio.sharepoint.com/:f:/s/SaraniAssets/EqV5xlSAbipNjUwupVK3KvIBHBAhCl-pE6fAHD7lITP-tA?e=dibFOR | J90: =IF(SUM(Q90:AW90)=0,"-",SUM(Q90:AW90)) -> 16 | K90: =IF(SUMPRODUCT($Q$5:$AW$5,Q90:AW90)=0,"-",SUMPRODUCT($Q$5:$AW$5,Q90:AW90)) -> 285 | L90: - | M90: - | N90: Sent | O90: F2025-0462 | P90: Paid 05/09/2025 | Q90: 1 | S90: 15
A91: Ubi | B91: IKEA | C91: 45849 | D91: IKEA - POP UP Tournée | E91: IKE05 | F91: Laure PEYNT | G91: Delivered | H91: Exe | I91: https://saranistudio.sharepoint.com/:f:/s/SaraniAssets/Eiv8AeHE5PRApsx_xd9_V4MBLyHBOb9SpsFr1J2DnkHfBA?e=ozc10b | J91: =IF(SUM(Q91:AW91)=0,"-",SUM(Q91:AW91)) -> 39 | K91: =IF(SUMPRODUCT($Q$5:$AW$5,Q91:AW91)=0,"-",SUMPRODUCT($Q$5:$AW$5,Q91:AW91)) -> 1510 | L91: - | M91: - | N91: Sent | O91: F2025-0462 | P91: Paid 05/09/2025 | Q91: 3 | R91: 4 | S91: 12 | Y91: 2 | Z91: 5 | AE91: 13
A92: Ubi | B92: LEGO | C92: 45853 | D92: LEGO - Affiche Grand tounoi des champs 9:16 / 16/9 A4 | E92: LEG02 | F92: Louis KELLER | G92: Delivered | H92: Exe | I92: https://saranistudio.sharepoint.com/:f:/s/SaraniAssets/Enc3NXf3popLvhLrEwYwp6UBLN5r2UAzmFiMb3Cf7q5UYA?e=8IsmNV | J92: =IF(SUM(Q92:AW92)=0,"-",SUM(Q92:AW92)) -> 5 | K92: =IF(SUMPRODUCT($Q$5:$AW$5,Q92:AW92)=0,"-",SUMPRODUCT($Q$5:$AW$5,Q92:AW92)) -> 150 | L92: - | M92: - | N92: Sent | O92: F2025-0462 | P92: Paid 05/09/2025 | R92: 5
A93: Ubi | B93: Adidas | C93: 45856 | D93: ADSBF - Seeding box FFA adidas (Part 2 - Goodies) | E93: ADSBF | F93: Pauline Drouet | G93: Delivered | H93: Exe | I93: https://saranistudio.sharepoint.com/:f:/s/SaraniAssets/EkN4_O-RGYtJqD6wuri5rLgBiQ2sOoCoFVDf8DWbzoueYg?e=dy8p6G | J93: =IF(SUM(Q93:AW93)=0,"-",SUM(Q93:AW93)) -> 67 | K93: =IF(SUMPRODUCT($Q$5:$AW$5,Q93:AW93)=0,"-",SUMPRODUCT($Q$5:$AW$5,Q93:AW93)) -> 1775 | L93: - | M93: - | N93: Sent | O93: F2025-0462 | P93: Paid 05/09/2025 | Q93: 1 | R93: 35 | S93: 29 | Y93: 2
A94: Ubi | B94: Adidas | C94: 45869 | D94: ADTAT - Kakemonos Test & Run | E94: ADTAT | F94: Anouck MOTTIN | G94: Delivered | H94: Exe | I94: https://saranistudio.sharepoint.com/:f:/s/SaraniAssets/EtCxdz-YcZZJlfQmZMTeDj8BHTsJjQyGQ14yeUG1tpZxeQ?e=7Yhht7 | J94: =IF(SUM(Q94:AW94)=0,"-",SUM(Q94:AW94)) -> 2 | K94: =IF(SUMPRODUCT($Q$5:$AW$5,Q94:AW94)=0,"-",SUMPRODUCT($Q$5:$AW$5,Q94:AW94)) -> 165 | L94: - | M94: - | N94: Sent | O94: F2025-0462 | P94: Paid 05/09/2025 | Q94: 1 | R94: 1
A95: Ubi | B95: Adidas | C95: 45878 | D95: ADSBF - Seeding box FFA adidas (Part 2 - Goodies) suite | E95: ADSBF | F95: Jérémy LE NILLON | G95: Delivered | H95: Exe | I95: https://saranistudio.sharepoint.com/:f:/s/SaraniAssets/EkN4_O-RGYtJqD6wuri5rLgBiQ2sOoCoFVDf8DWbzoueYg?e=dy8p6G | J95: =IF(SUM(Q95:AW95)=0,"-",SUM(Q95:AW95)) -> 33 | K95: =IF(SUMPRODUCT($Q$5:$AW$5,Q95:AW95)=0,"-",SUMPRODUCT($Q$5:$AW$5,Q95:AW95)) -> 1150 | L95: - | M95: - | N95: Sent | O95: F2025-0537 | P95: Paid 16/10/2025 | R95: 16 | S95: 15 | AB95: 2
A96: Ubi | B96: Adidas | C96: 45881 | D96: Mise à jour site FFA | E96: ADR25 | F96: Pauline Drouet | G96: Delivered | H96: Exe | I96: https://saranistudio.sharepoint.com/:f:/s/SaraniAssets/EhickG67KBVOhTh73oHozTQBmbSoTC9WOiJngfCghFrv2Q?e=L2qepT | J96: =IF(SUM(Q96:AW96)=0,"-",SUM(Q96:AW96)) -> 19 | K96: =IF(SUMPRODUCT($Q$5:$AW$5,Q96:AW96)=0,"-",SUMPRODUCT($Q$5:$AW$5,Q96:AW96)) -> 980 | L96: - | M96: - | N96: Sent | O96: F2025-0537 | P96: Paid 16/10/2025 | R96: 15 | S96: 3 | AF96: 1
A97: Ubi | B97: IKEA | C97: 45891 | D97: IKEA Cook session - Part 2 | E97: IKE03 | F97: Laure PEYNT | G97: Delivered | H97: EXE | I97: https://saranistudio.sharepoint.com/:f:/s/SaraniAssets/ErF5sbZ715lOlB7H_cWNeR0BngttTKNcHTGX8yZqtpiYpw?e=fndeol | J97: =IF(SUM(Q97:AW97)=0,"-",SUM(Q97:AW97)) -> 56 | K97: =IF(SUMPRODUCT($Q$5:$AW$5,Q97:AW97)=0,"-",SUMPRODUCT($Q$5:$AW$5,Q97:AW97)) -> 2350 | L97: - | M97: - | N97: Sent | O97: F2025-0537 | P97: Paid 16/10/2025 | Q97: 6 | R97: 38 | S97: 10 | Y97: 2
A98: Ubi | B98: Adidas | C98: 45918 | D98: ADU25 - Carrousel pour post Instagram en 4:5 | E98: ADU25 | F98: Pauline Drouet | G98: Delivered | H98: Exe | I98: 20250918_ADU25_Instagram_Carousel | J98: =IF(SUM(Q98:AW98)=0,"-",SUM(Q98:AW98)) -> 5 | K98: =IF(SUMPRODUCT($Q$5:$AW$5,Q98:AW98)=0,"-",SUMPRODUCT($Q$5:$AW$5,Q98:AW98)) -> 255 | M98: - | N98: Sent | O98: F2025-0595 | P98: Paid 04/11/2025 | Q98: 1 | R98: 4
A99: ubi | B99: Adidas | C99: 45896 | D99: ADLRA - Led adidas Arena (extra versions) | E99: ADLRA | F99: Jérémy | G99: Delivered | H99: Exe | I99: https://saranistudio.sharepoint.com/:f:/s/SaraniAssets/EmxdCZCacVVJvrQ5aYcu5aoBkdb-gPd1QikjjZ4XqMSwAg?e=kazQC4 | J99: =IF(SUM(Q99:AW99)=0,"-",SUM(Q99:AW99)) -> 3 | K99: =IF(SUMPRODUCT($Q$5:$AW$5,Q99:AW99)=0,"-",SUMPRODUCT($Q$5:$AW$5,Q99:AW99)) -> 90 | L99: - | M99: - | N99: Sent | O99: F2025-0537 | P99: Paid 16/10/2025 | R99: 3
A100: Ubi | B100: Adidas | C100: 45896 | D100: ADAML - Run Alice Milliat Scratch Cards | E100: ADAML | F100: Jérémy | G100: Delivered | H100: Exe | I100: https://saranistudio.sharepoint.com/:f:/s/SaraniAssets/Eh8B8wfPqUxBh0I2y0Eq4fwBAu3ZKfrFbmaMy2RsXL7zYQ?e=16d25T | J100: =IF(SUM(Q100:AW100)=0,"-",SUM(Q100:AW100)) -> 7 | K100: =IF(SUMPRODUCT($Q$5:$AW$5,Q100:AW100)=0,"-",SUMPRODUCT($Q$5:$AW$5,Q100:AW100)) -> 360 | L100: - | M100: - | N100: Sent | O100: F2025-0537 | P100: Paid 16/10/2025 | Y100: 1 | Z100: 6
...
