Workbook

Sheet Overview
A1: Performance Dashboard — Sarani / Bose
A3: REVENUS (€) | B3: 2025 | F3: 2026
B4: Q1 | C4: Q2 | D4: Q3 | E4: Q4 | F4: Q1 | G4: Q2 | H4: Q3 | I4: Q4
A5: Bose | B5: =SUMIFS(Bose!$K:$K,Bose!$D:$D,">="&DATE(2025,1,1),Bose!$D:$D,"<="&DATE(2025,3,31)) -> 0 | C5: =SUMIFS(Bose!$K:$K,Bose!$D:$D,">="&DATE(2025,4,1),Bose!$D:$D,"<="&DATE(2025,6,30)) -> 0 | D5: =SUMIFS(Bose!$K:$K,Bose!$D:$D,">="&DATE(2025,7,1),Bose!$D:$D,"<="&DATE(2025,9,30)) -> 1905 | E5: =SUMIFS(Bose!$K:$K,Bose!$D:$D,">="&DATE(2025,10,1),Bose!$D:$D,"<="&DATE(2025,12,31)) -> 13290 | F5: =SUMIFS(Bose!$K:$K,Bose!$D:$D,">="&DATE(2026,1,1),Bose!$D:$D,"<="&DATE(2026,3,31)) -> 25295 | G5: =SUMIFS(Bose!$K:$K,Bose!$D:$D,">="&DATE(2026,4,1),Bose!$D:$D,"<="&DATE(2026,6,30)) -> 1360 | H5: =SUMIFS(Bose!$K:$K,Bose!$D:$D,">="&DATE(2026,7,1),Bose!$D:$D,"<="&DATE(2026,9,30)) -> 0 | I5: =SUMIFS(Bose!$K:$K,Bose!$D:$D,">="&DATE(2026,10,1),Bose!$D:$D,"<="&DATE(2026,12,31)) -> 0
A6: TOTAL | B6: =SUM(B5:B5) -> 0 | C6: =SUM(C5:C5) -> 0 | D6: =SUM(D5:D5) -> 1905 | E6: =SUM(E5:E5) -> 13290 | F6: =SUM(F5:F5) -> 25295 | G6: =SUM(G5:G5) -> 1360 | H6: =SUM(H5:H5) -> 0 | I6: =SUM(I5:I5) -> 0
A8: NOMBRE DE PROJETS | B8: 2025 | F8: 2026
B9: Q1 | C9: Q2 | D9: Q3 | E9: Q4 | F9: Q1 | G9: Q2 | H9: Q3 | I9: Q4
A10: Bose | B10: =COUNTIFS(Bose!$D:$D,">="&DATE(2025,1,1),Bose!$D:$D,"<="&DATE(2025,3,31)) -> 0 | C10: =COUNTIFS(Bose!$D:$D,">="&DATE(2025,4,1),Bose!$D:$D,"<="&DATE(2025,6,30)) -> 0 | D10: =COUNTIFS(Bose!$D:$D,">="&DATE(2025,7,1),Bose!$D:$D,"<="&DATE(2025,9,30)) -> 2 | E10: =COUNTIFS(Bose!$D:$D,">="&DATE(2025,10,1),Bose!$D:$D,"<="&DATE(2025,12,31)) -> 22 | F10: =COUNTIFS(Bose!$D:$D,">="&DATE(2026,1,1),Bose!$D:$D,"<="&DATE(2026,3,31)) -> 37 | G10: =COUNTIFS(Bose!$D:$D,">="&DATE(2026,4,1),Bose!$D:$D,"<="&DATE(2026,6,30)) -> 1 | H10: =COUNTIFS(Bose!$D:$D,">="&DATE(2026,7,1),Bose!$D:$D,"<="&DATE(2026,9,30)) -> 0 | I10: =COUNTIFS(Bose!$D:$D,">="&DATE(2026,10,1),Bose!$D:$D,"<="&DATE(2026,12,31)) -> 0
A11: TOTAL | B11: =SUM(B10:B10) -> 0 | C11: =SUM(C10:C10) -> 0 | D11: =SUM(D10:D10) -> 2 | E11: =SUM(E10:E10) -> 22 | F11: =SUM(F10:F10) -> 37 | G11: =SUM(G10:G10) -> 1 | H11: =SUM(H10:H10) -> 0 | I11: =SUM(I10:I10) -> 0
A13: SYNTHÈSE ANNUELLE | B13: 2025 | C13: 2026
A14: Revenus (€) | B14: =SUM(B6:E6) -> 15195 | C14: =SUM(F6:I6) -> 26655
A15: Projets | B15: =SUM(B11:E11) -> 24 | C15: =SUM(F11:I11) -> 38
A16: Rev. / Projet (€) | B16: =IFERROR(B14/B15,"—") -> 633.125 | C16: =IFERROR(C14/C15,"—") -> 701.44737

Sheet Bose
K1: =SUBTOTAL(2,K6:K19999) -> 62 | Q1: =SUBTOTAL(2,Q6:Q19999) -> 20 | R1: =SUBTOTAL(2,R6:R19999) -> 38 | S1: =SUBTOTAL(2,S6:S19999) -> 2 | T1: =SUBTOTAL(2,T6:T19999) -> 2 | U1: =SUBTOTAL(2,U6:U19999) -> 0 | V1: =SUBTOTAL(2,V6:V19999) -> 0 | W1: =SUBTOTAL(2,W6:W19999) -> 0 | X1: =SUBTOTAL(2,X6:X19999) -> 0 | ... AU1: =SUBTOTAL(2,AU6:AU19999) -> 0
J2: =SUBTOTAL(9,J6:J20000) -> 797 | K2: =SUBTOTAL(9,K6:K20000) -> 41850 | Q2: =SUBTOTAL(9,Q6:Q20000)*Q5 -> 5670 | R2: =SUBTOTAL(9,R6:R20000)*R5 -> 17430 | S2: =SUBTOTAL(9,S6:S20000)*S5 -> 440 | T2: =SUBTOTAL(9,T6:T20000)*T5 -> 450 | U2: =SUBTOTAL(9,U6:U20000)*U5 -> 0 | V2: =SUBTOTAL(9,V6:V20000)*V5 -> 0 | W2: =SUBTOTAL(9,W6:W20000)*W5 -> 0 | X2: =SUBTOTAL(9,X6:X20000)*X5 -> 0 | ... AU2: =SUBTOTAL(9,AU6:AU20000)*AU5 -> 0
A3: Price File | Q3: Online | Y3: Offline | AF3: Presentations | AG3: Web | AK3: Videos | AR3: Virtualization | AT3: Copy
A4: Project | F4: Details PO 4900215137 >> 30 000€ 1 invoice per month at the end of it | Q4: Banner creation (static) | R4: Banner adaptation (static) | S4: Banner creation (animated) | T4: Banner adaptation (animated) | U4: Buttons | V4: Logo | W4: Lifestyle Picture | X4: Wallpapers | Y4: Offline creation (standard) | Z4: Offline creation (adaptation) | AA4: Leaflet (1 page) | AB4: Leaflet (2 pages) | AC4: Roll-up / Wall creation | AD4: Chart | AE4: Brochure (20 pages) | AF4: Slide | AG4: Landing page (design only) | AH4: Landing page (complete) | AI4: Website (design only) | AJ4: Website (complete) | AK4: Video Edition | AL4: Video Subtitles / Adaptations | AM4: Social Media Video (up to 30s) | AN4: Social Media Video (up to 1 min) | AO4: Promotional Video (up to 1 min) | AP4: 2D Video (up to 3mn) | AQ4: 3D Video (up to 3min) | AR4: Virtual space | AS4: Virtual showroom | AT4: Translation (per word) | AU4: Transcription (per word)
A5: Customer | B5: Region | C5: Reseller | D5: Date | E5: Project | F5: Contact | G5: Status | H5: Category | I5: Link | J5: Assets | K5: Total Value | L5: Quote | M5: PO | N5: Invoice | O5: n° Invoice | P5: Statut | Q5: 135 | R5: 35 | S5: 220 | T5: 50 | U5: 15 | V5: 250 | W5: 400 | X5: 85 | Y5: 150 | Z5: 40 | AA5: 180 | AB5: 260 | AC5: 180 | AD5: 400 | AE5: 2200 | AF5: 30 | AG5: 300 | AH5: 700 | AI5: 5000 | AJ5: 7000 | AK5: 80 | AL5: 150 | AM5: 360 | AN5: 460 | AO5: 900 | AP5: 1500 | AQ5: 3000 | AR5: 2500 | AS5: 10000 | AT5: 0.12 | AU5: 0.25
A6: Bose | B6: Germany | C6: Media Markt Saturn | D6: 45927 | E6: Media Markt Saturn Home Theatre Bundle SBA Banner | F6: Daniel Browne | G6: Delivered | H6: EMEA | I6: https://saranistudio.sharepoint.com/:f:/s/SaraniAssets/Ej8JJaDctwVLgXpVrtyzDxwB-8sSy5M2UCWVUtVZRK8dRQ?e=tl8Hdj | J6: =IF(SUM(Q6:AV6)=0,"-",SUM(Q6:AV6)) -> 3 | K6: =IF(SUMPRODUCT($Q$5:$AV$5,Q6:AV6)=0,"-",SUMPRODUCT($Q$5:$AV$5,Q6:AV6)) -> 105 | L6: - | M6: 4900215137 | N6: Submitted to SAP | O6: F2025-0695 | P6: Paid 09/03/2026 | R6: 3
A7: Bose | B7: UK | C7: John Lewis | D7: 45931 | E7: Bose Citrus Managed Service | F7: Daniel Browne | G7: Delivered | H7: EMEA | I7: https://saranistudio.sharepoint.com/:f:/s/SaraniAssets/Enzw3IbgWzdCtNTmIqLTfrMBPvThIDmr7X_7WJNFzBHKQg?e=yRQvdh | J7: =IF(SUM(Q7:AV7)=0,"-",SUM(Q7:AV7)) -> 3 | K7: =IF(SUMPRODUCT($Q$5:$AV$5,Q7:AV7)=0,"-",SUMPRODUCT($Q$5:$AV$5,Q7:AV7)) -> 105 | L7: - | M7: 4900215137 | N7: Submitted to SAP | O7: F2025-0695 | P7: Paid 09/03/2026 | R7: 3
A8: Bose | B8: EU3 | C8: N/A | D8: 45936 | E8: Bose EU Business Cards | F8: Daniel Browne | G8: Delivered | H8: EMEA | I8: 20251006_Bose EU Business Cards | J8: =IF(SUM(Q8:AV8)=0,"-",SUM(Q8:AV8)) -> 2 | K8: =IF(SUMPRODUCT($Q$5:$AV$5,Q8:AV8)=0,"-",SUMPRODUCT($Q$5:$AV$5,Q8:AV8)) -> 190 | L8: - | M8: 4900215137 | N8: Submitted to SAP | O8: F2025-0695 | P8: Paid 09/03/2026 | Y8: 1 | Z8: 1
A9: Bose | B9: UK | C9: Currys | D9: 45930 | E9: Bose Brand Page Project for Currys | F9: Julieta Altamirano | G9: Delivered | H9: EMEA | I9: https://saranistudio.sharepoint.com/:f:/s/SaraniAssets/EqqZ1HFS_ANAkhJ9LuxKyWgB9fEON-90mFPnp0GHRWEOfA?e=ZpgfEf | J9: =IF(SUM(Q9:AV9)=0,"-",SUM(Q9:AV9)) -> 6 | K9: =IF(SUMPRODUCT($Q$5:$AV$5,Q9:AV9)=0,"-",SUMPRODUCT($Q$5:$AV$5,Q9:AV9)) -> 1800 | M9: 4900215137 | N9: Submitted to SAP | O9: F2025-0782 | P9: Waiting payment for 02/04/2026 | AG9: 6
A10: Bose | B10: UK | C10: Argos | D10: 45954 | E10: Bose Holiday Harder Brief UK - ARGOS | F10: Daniel Browne | G10: Delivered | H10: EMEA | I10: 20251024_Bose Holiday Harder Brief UK - ARGOS | J10: =IF(SUM(Q10:AV10)=0,"-",SUM(Q10:AV10)) -> 13 | K10: =IF(SUMPRODUCT($Q$5:$AV$5,Q10:AV10)=0,"-",SUMPRODUCT($Q$5:$AV$5,Q10:AV10)) -> 1590 | M10: 4900215137 | N10: Submitted to SAP | O10: F2025-0782 | P10: Waiting payment for 02/04/2026 | Q10: 10 | AK10: 3
A11: Bose | B11: UK | C11: Currys | D11: 45954 | E11: Bose Holiday Harder brief: Currys | F11: Daniel Browne | G11: Delivered | H11: EMEA | I11: 20251024_Bose Holiday Harder brief Currys | J11: =IF(SUM(Q11:AV11)=0,"-",SUM(Q11:AV11)) -> 18 | K11: =IF(SUMPRODUCT($Q$5:$AV$5,Q11:AV11)=0,"-",SUMPRODUCT($Q$5:$AV$5,Q11:AV11)) -> 1230 | M11: 4900215137 | N11: Submitted to SAP | O11: F2025-0782 | P11: Waiting payment for 02/04/2026 | Q11: 6 | R11: 12
A12: Bose | B12: UK | C12: Currys | D12: 45968 | E12: Brief Currys Speakers media affiliates display | F12: Daniel Browne | G12: Delivered | H12: EMEA | I12: 20251107_Brief Currys Speakers media affiliates display | J12: =IF(SUM(Q12:AV12)=0,"-",SUM(Q12:AV12)) -> 5 | K12: =IF(SUMPRODUCT($Q$5:$AV$5,Q12:AV12)=0,"-",SUMPRODUCT($Q$5:$AV$5,Q12:AV12)) -> 175 | M12: 4900215137 | N12: Submitted to SAP | O12: F2025-0782 | P12: Waiting payment for 02/04/2026 | R12: 5
A13: Bose | B13: SK | C13: Komplett | D13: 45971 | E13: Komplett x BOSE marketing Q4 | F13: Regina Melo | G13: Delivered | H13: EMEA | I13: https://saranistudio.sharepoint.com/:f:/s/SaraniAssets/Ev5illVneQNPnk5vFKuQsHwBa50O58NVGnI8-qsVefCOEA?e=l2TOYp | J13: =IF(SUM(Q13:AV13)=0,"-",SUM(Q13:AV13)) -> 20 | K13: =IF(SUMPRODUCT($Q$5:$AV$5,Q13:AV13)=0,"-",SUMPRODUCT($Q$5:$AV$5,Q13:AV13)) -> 900 | M13: 4900215137 | N13: Submitted to SAP | O13: F2025-0782 | P13: Waiting payment for 02/04/2026 | Q13: 2 | R13: 18
A14: Bose | B14: UK | C14: John Lewis | D14: 45968 | E14: JLP Hang cards_ Artwork request | F14: Ophélie JUCHET | G14: Delivered | H14: EMEA | I14: 20251107_JLP Hang cards - Artwork request | J14: =IF(SUM(Q14:AV14)=0,"-",SUM(Q14:AV14)) -> 44 | K14: =IF(SUMPRODUCT($Q$5:$AV$5,Q14:AV14)=0,"-",SUMPRODUCT($Q$5:$AV$5,Q14:AV14)) -> 2310 | M14: 4900215137 | N14: Submitted to SAP | O14: F2025-0782 | P14: Waiting payment for 02/04/2026 | Y14: 5 | Z14: 39
A15: Bose | B15: UK | C15: John Lewis | D15: 45974 | E15: Bose - resize photo | F15: Daniel Browne | G15: Delivered | H15: EMEA | I15: https://saranistudio.sharepoint.com/:f:/s/SaraniAssets/IgC9s71-q0JsR6kiNaOrlHUcAaLzM4XDqfQlIiXimwmiyd0?e=M4eeXQ | J15: =IF(SUM(Q15:AV15)=0,"-",SUM(Q15:AV15)) -> 4 | K15: =IF(SUMPRODUCT($Q$5:$AV$5,Q15:AV15)=0,"-",SUMPRODUCT($Q$5:$AV$5,Q15:AV15)) -> 140 | M15: 4900215137 | N15: Submitted to SAP | O15: F2025-0782 | P15: Waiting payment for 02/04/2026 | R15: 4
A16: Bose | B16: FR | C16: Boulanger | D16: 45980 | E16: Bose : Creative request for Boulanger | F16: Mehdi Youssfi | G16: Delivered | H16: EMEA | I16: 20251119_Creative request for Boulanger | J16: =IF(SUM(Q16:AV16)=0,"-",SUM(Q16:AV16)) -> 9 | K16: =IF(SUMPRODUCT($Q$5:$AV$5,Q16:AV16)=0,"-",SUMPRODUCT($Q$5:$AV$5,Q16:AV16)) -> 515 | M16: 4900215137 | N16: Submitted to SAP | O16: F2025-0782 | P16: Waiting payment for 02/04/2026 | Q16: 2 | R16: 7
A17: Bose | B17: FR | C17: Boulanger | D17: 45981 | E17: Campagne TV magasins Boulanger | F17: Mehdi Youssfi | G17: Delivered | H17: EMEA | I17: https://saranistudio.sharepoint.com/:f:/s/SaraniAssets/IgAV5aojuKzKQrG3nyEEvxpNAdM7M9gjOK_KWBoVt7qjU4s?e=Iy6JBc | J17: =IF(SUM(Q17:AV17)=0,"-",SUM(Q17:AV17)) -> 1 | K17: =IF(SUMPRODUCT($Q$5:$AV$5,Q17:AV17)=0,"-",SUMPRODUCT($Q$5:$AV$5,Q17:AV17)) -> 150 | M17: 4900215137 | N17: Submitted to SAP | O17: F2025-0782 | P17: Waiting payment for 02/04/2026 | AL17: 1
A18: Bose | B18: EU | C18: MSH | D18: 45981 | E18: A4 Banners for Jet Service | F18: Regina Melo | G18: Delivered | H18: EMEA | I18: https://saranistudio.sharepoint.com/:f:/s/SaraniAssets/IgAMp2DncQF-TpJywobyBjeSAepyfM4Rm51hOwsO6Yh0LAk?e=dfmgzT | J18: =IF(SUM(Q18:AV18)=0,"-",SUM(Q18:AV18)) -> 7 | K18: =IF(SUMPRODUCT($Q$5:$AV$5,Q18:AV18)=0,"-",SUMPRODUCT($Q$5:$AV$5,Q18:AV18)) -> 390 | M18: 4900215137 | N18: Submitted to SAP | O18: F2025-0782 | P18: Waiting payment for 02/04/2026 | Y18: 1 | Z18: 6
A19: Bose | B19: GCD | D19: 45981 | E19: BOSE FY26Q2 | QuietComfort Ultra Headphone 2nd Gen | New Assets | F19: Regina Melo | G19: Delivered | H19: EMEA | I19: https://saranistudio.sharepoint.com/sites/SaraniAssets/Shared%20Documents/Forms/AllItems.aspx?id=%2Fsites%2FSaraniAssets%2FShared%20Documents%2F03%2E%20Customers%2F19%2E%20Bose%2F02%2E%20Projects%2F20251120%5FBOSE%20FY26Q2%20QuietComfort%20Ultra%20Headphone%202nd%20Gen&p=true&ga=1 | J19: =IF(SUM(Q19:AV19)=0,"-",SUM(Q19:AV19)) -> 15 | K19: =IF(SUMPRODUCT($Q$5:$AV$5,Q19:AV19)=0,"-",SUMPRODUCT($Q$5:$AV$5,Q19:AV19)) -> 525 | M19: 4900215137 | N19: Submitted to SAP | O19: F2025-0782 | P19: Waiting payment for 02/04/2026 | R19: 15
A20: Bose | B20: EMEA | C20: N/A | D20: 45985 | E20: Bose EU Music Fest 2026 Save the Date | F20: Daniel Browne | G20: Delivered | H20: EMEA | I20: 20251124_Bose EU Music Fest 2026 Save the Date | J20: =IF(SUM(Q20:AV20)=0,"-",SUM(Q20:AV20)) -> 20 | K20: =IF(SUMPRODUCT($Q$5:$AV$5,Q20:AV20)=0,"-",SUMPRODUCT($Q$5:$AV$5,Q20:AV20)) -> 800 | M20: 4900215137 | N20: Submitted to SAP | O20: F2025-0782 | P20: Waiting payment for 02/04/2026 | Q20: 1 | R20: 19
A21: Bose | B21: ANZ | D21: 45986 | E21: Sarani Brief x ANZ // Holiday Harder social edits | F21: Georgia Lucas | G21: Delivered | H21: ANZ | I21: https://saranistudio.sharepoint.com/:f:/s/SaraniAssets/IgBEKvFdK47HRYVDX2iR-Eo5AW1wC82sA2c7wTePYed7mPk?e=259ht0 | J21: =IF(SUM(Q21:AV21)=0,"-",SUM(Q21:AV21)) -> 47 | K21: =IF(SUMPRODUCT($Q$5:$AV$5,Q21:AV21)=0,"-",SUMPRODUCT($Q$5:$AV$5,Q21:AV21)) -> 1645 | M21: 4900215137 | N21: Submitted to SAP | O21: F2025-0782 | P21: Waiting payment for 02/04/2026 | R21: 47
A22: Bose | B22: Germany | C22: Media Markt | D22: 45992 | E22: MMS December Display Ads DE | F22: Daniel Browne | G22: Delivered | H22: EMEA | I22: https://saranistudio.sharepoint.com/:f:/s/SaraniAssets/IgAym-XhXu8HT6-EMhywfjMEAZZADYNkvQ--X8rRLXHM570?e=2WrDPJ | J22: =IF(SUM(Q22:AV22)=0,"-",SUM(Q22:AV22)) -> 12 | K22: =IF(SUMPRODUCT($Q$5:$AV$5,Q22:AV22)=0,"-",SUMPRODUCT($Q$5:$AV$5,Q22:AV22)) -> 620 | M22: 4900215137 | N22: Submitted to SAP | O22: F2025-0832 | P22: Waiting payment for 29/04/2026 | Q22: 2 | R22: 10
A23: Bose | B23: Germany | C23: Media Markt | D23: 45993 | E23: Media Markt Social Image edits | F23: Daniel Browne | G23: Delivered | H23: EMEA | I23: 20251202_Media Markt Social Image edits | J23: =IF(SUM(Q23:AV23)=0,"-",SUM(Q23:AV23)) -> 8 | K23: =IF(SUMPRODUCT($Q$5:$AV$5,Q23:AV23)=0,"-",SUMPRODUCT($Q$5:$AV$5,Q23:AV23)) -> 380 | M23: 4900215137 | N23: Submitted to SAP | O23: F2025-0832 | P23: Waiting payment for 29/04/2026 | Q23: 1 | R23: 7
A24: Bose | B24: Germany | C24: Media Markt | D24: 45993 | E24: SBA Banners Media Markt | F24: Daniel Browne | G24: Delivered | H24: EMEA | I24: https://saranistudio.sharepoint.com/:f:/s/SaraniAssets/IgDzNmkXWfKbRadZGlZ8BPJMAbzSsrPCHfnfzEvxHZ-9ANg?e=Zctmrz | J24: =IF(SUM(Q24:AV24)=0,"-",SUM(Q24:AV24)) -> 12 | K24: =IF(SUMPRODUCT($Q$5:$AV$5,Q24:AV24)=0,"-",SUMPRODUCT($Q$5:$AV$5,Q24:AV24)) -> 520 | M24: 4900215137 | N24: Submitted to SAP | O24: F2025-0832 | P24: Waiting payment for 29/04/2026 | Q24: 1 | R24: 11
A25: Bose | B25: GCD | D25: 46002 | E25: Resizing Banner - Brack | F25: Regina Melo | G25: Delivered | H25: EMEA | I25: https://saranistudio.sharepoint.com/:f:/s/SaraniAssets/IgCouEcFzS00QYNaWiaUiIiPAST4MFb7M83LAfbJRvbpdTo?e=k1JnaR | J25: =IF(SUM(Q25:AV25)=0,"-",SUM(Q25:AV25)) -> 1 | K25: =IF(SUMPRODUCT($Q$5:$AV$5,Q25:AV25)=0,"-",SUMPRODUCT($Q$5:$AV$5,Q25:AV25)) -> 35 | M25: 4900215137 | N25: Submitted to SAP | O25: F2025-0832 | P25: Waiting payment for 29/04/2026 | R25: 1
A26: Bose | B26: GCD | D26: 46006 | E26: MW IT - IG Story | F26: Regina Melo | G26: Delivered | H26: EMEA | I26: 20251215_MW IT - IG Story | J26: =IF(SUM(Q26:AV26)=0,"-",SUM(Q26:AV26)) -> 2 | K26: =IF(SUMPRODUCT($Q$5:$AV$5,Q26:AV26)=0,"-",SUMPRODUCT($Q$5:$AV$5,Q26:AV26)) -> 70 | M26: 4900215137 | N26: Submitted to SAP | O26: F2025-0832 | P26: Waiting payment for 29/04/2026 | R26: 2
A27: Bose | B27: GCD | D27: 46006 | E27: MW IT - Headphone banners | F27: Regina Melo | G27: Delivered | H27: EMEA | I27: https://saranistudio.sharepoint.com/:f:/s/SaraniAssets/IgCWDBs7oNUzToOxSYSQ8uDzAew_00__P-aRqf9kAqu8ng4?e=CCSvTk | J27: 5 | K27: =IF(SUMPRODUCT($Q$5:$AV$5,Q27:AV27)=0,"-",SUMPRODUCT($Q$5:$AV$5,Q27:AV27)) -> 175 | M27: 4900215137 | N27: Submitted to SAP | O27: F2025-0832 | P27: Waiting payment for 29/04/2026 | R27: 5
A28: Bose | B28: UK | C28: John Lewis | D28: 46014 | E28: JLP Hang cards_ Artwork request | F28: Ophélie JUCHET | G28: Delivered | H28: EMEA | I28: JLP HANG CARDS - FINAL | J28: =IF(SUM(Q28:AV28)=0,"-",SUM(Q28:AV28)) -> 4 | K28: =IF(SUMPRODUCT($Q$5:$AV$5,Q28:AV28)=0,"-",SUMPRODUCT($Q$5:$AV$5,Q28:AV28)) -> 160 | M28: 4900215137 | N28: Submitted to SAP | O28: F2025-0832 | P28: Waiting payment for 29/04/2026 | Z28: 4
A29: Bose | B29: FR | C29: Boulanger | D29: 46013 | E29: Bose Days 2026 creatives request | F29: Mehdi Youssfi | G29: Delivered | H29: EMEA | I29: 20251222_Bose Days 2026 creatives request | J29: =IF(SUM(Q29:AV29)=0,"-",SUM(Q29:AV29)) -> 10 | K29: =IF(SUMPRODUCT($Q$5:$AV$5,Q29:AV29)=0,"-",SUMPRODUCT($Q$5:$AV$5,Q29:AV29)) -> 665 | M29: 4900215137 | N29: Submitted to SAP | O29: F2026-0039 | P29: Waiting payment for 27/05/2026 | Q29: 1 | R29: 6 | S29: 1 | T29: 2
A30: Bose | B30: Germany | C30: Media Markt | D30: 46035 | E30: Q4 Media Markt Saturn DE SBA Banners | F30: Daniel Browne | G30: Delivered | H30: EMEA | I30: https://saranistudio.sharepoint.com/:f:/s/SaraniAssets/IgAQ9EdMR-UTRLsrhw5ux-vtAfi4YKHCCvErufHBix4jmA4?e=u55nKD | J30: =IF(SUM(Q30:AV30)=0,"-",SUM(Q30:AV30)) -> 15 | K30: =IF(SUMPRODUCT($Q$5:$AV$5,Q30:AV30)=0,"-",SUMPRODUCT($Q$5:$AV$5,Q30:AV30)) -> 625 | M30: 4900215137 | N30: Submitted to SAP | O30: F2026-0039 | P30: Waiting payment for 27/05/2026 | Q30: 1 | R30: 14
A31: Bose | B31: UK | C31: Costco | D31: 46036 | E31: Bose - Costco UK New Product Listing | F31: Amaka Onyali | G31: Delivered | H31: EMEA | I31: https://saranistudio.sharepoint.com/:f:/s/SaraniAssets/IgAVoDXokTScS5FtMv7RSCm8ASRJV73e59NvhUWy_5jvgD0?e=BnFU2E | J31: =IF(SUM(Q31:AV31)=0,"-",SUM(Q31:AV31)) -> 2 | K31: =IF(SUMPRODUCT($Q$5:$AV$5,Q31:AV31)=0,"-",SUMPRODUCT($Q$5:$AV$5,Q31:AV31)) -> 70 | M31: 4900215137 | N31: Submitted to SAP | O31: F2026-0039 | P31: Waiting payment for 27/05/2026 | R31: 2
A32: Bose | B32: GCD | C32: Elkjop | D32: 46043 | E32: Elkjop - Banner Resizing | F32: Regina Melo | G32: Delivered | H32: EMEA | I32: https://saranistudio.sharepoint.com/:f:/s/SaraniAssets/IgCRboklNZF2TpGpBEXdLKJcAYuRSlpWHFCIUhfzlSoQMmE?e=5HLbsX | J32: =IF(SUM(Q32:AV32)=0,"-",SUM(Q32:AV32)) -> 48 | K32: =IF(SUMPRODUCT($Q$5:$AV$5,Q32:AV32)=0,"-",SUMPRODUCT($Q$5:$AV$5,Q32:AV32)) -> 1680 | M32: 4900215137 | N32: Submitted to SAP | O32: F2026-0039 | P32: Waiting payment for 27/05/2026 | R32: 48
A33: Bose | B33: EMEA | C33: N/A | D33: 46044 | E33: Bose EU Music Fest 2026 Save the Date - extra | F33: Amaka Onyali | G33: Delivered | H33: EMEA | I33: 20251124_Bose EU Music Fest 2026 Save the Date | J33: =IF(SUM(Q33:AV33)=0,"-",SUM(Q33:AV33)) -> 9 | K33: =IF(SUMPRODUCT($Q$5:$AV$5,Q33:AV33)=0,"-",SUMPRODUCT($Q$5:$AV$5,Q33:AV33)) -> 315 | M33: 4900215137 | N33: Submitted to SAP | O33: F2026-0039 | P33: Waiting payment for 27/05/2026 | R33: 9
A34: Bose | B34: GCD | C34: Elkjop | D34: 46055 | E34: Elkjop - Package KV | F34: Regina Melo | G34: Delivered | H34: EMEA | I34: 20260202_Elkjop - Package KV | J34: =IF(SUM(Q34:AV34)=0,"-",SUM(Q34:AV34)) -> 19 | K34: =IF(SUMPRODUCT($Q$5:$AV$5,Q34:AV34)=0,"-",SUMPRODUCT($Q$5:$AV$5,Q34:AV34)) -> 715 | M34: 4900215137 | N34: Submitted to SAP | O34: F2026-0093 | P34: Waiting payment for 01/07/2026 | R34: 9 | Z34: 10
A35: Bose | B35: Germany | C35: Media Markt | D35: 46056 | E35: Media Markt - Seasonal Flyer | F35: Denis Savchenko | G35: Delivered | H35: EMEA | I35: https://saranistudio.sharepoint.com/:f:/s/SaraniAssets/IgB17_dESIpSRLPeUrkzbcNTASadUySvO2ugYdm4HSgwBc4?e=OtYhth | J35: 4 | K35: =IF(SUMPRODUCT($Q$5:$AV$5,Q35:AV35)=0,"-",SUMPRODUCT($Q$5:$AV$5,Q35:AV35)) -> 270 | M35: 4900215137 | N35: Submitted to SAP | O35: F2026-0093 | P35: Waiting payment for 01/07/2026 | Y35: 1 | Z35: 3
A36: Bose | B36: FR | C36: Boulanger | D36: 46058 | E36: Bose Days 2026 creatives request (missing banners) | F36: Mehdi Youssfi | G36: Delivered | H36: EMEA | I36: 20251222_Bose Days 2026 creatives request | J36: =IF(SUM(Q36:AV36)=0,"-",SUM(Q36:AV36)) -> 5 | K36: =IF(SUMPRODUCT($Q$5:$AV$5,Q36:AV36)=0,"-",SUMPRODUCT($Q$5:$AV$5,Q36:AV36)) -> 175 | M36: 4900215137 | N36: Submitted to SAP | O36: F2026-0093 | P36: Waiting payment for 01/07/2026 | R36: 5
A37: Bose | B37: ANZ | C37: WHSmith Airport Screens | D37: 46063 | E37: Bose - Brief x ANZ // WHSmith Airport Screens | F37: Georgia Lucas | G37: Delivered | H37: ANZ | I37: 20260210_Sarani Brief x ANZ - WHSmith Airport Screens | J37: =IF(SUM(Q37:AV37)=0,"-",SUM(Q37:AV37)) -> 40 | K37: =IF(SUMPRODUCT($Q$5:$AV$5,Q37:AV37)=0,"-",SUMPRODUCT($Q$5:$AV$5,Q37:AV37)) -> 2090 | M37: 4900215137 | N37: Submitted to SAP | O37: F2026-0093 | P37: Waiting payment for 01/07/2026 | Q37: 4 | R37: 28 | S37: 1 | T37: 7
A38: Bose | B38: GCD | C38: Unieuro | D38: 46063 | E38: Bose / Unieuro - Dedicated Page | F38: Regina Melo | G38: Delivered | H38: EMEA | I38: 20260210_Unieuro - Dedicated Page | J38: =IF(SUM(Q38:AV38)=0,"-",SUM(Q38:AV38)) -> 1 | K38: =IF(SUMPRODUCT($Q$5:$AV$5,Q38:AV38)=0,"-",SUMPRODUCT($Q$5:$AV$5,Q38:AV38)) -> 180 | M38: 4900215137 | N38: Submitted to SAP | O38: F2026-0093 | P38: Waiting payment for 01/07/2026 | AA38: 1
A39: Bose | B39: ANZ | D39: 46065 | E39: ANZ 2026 Music Fest Invitations | F39: Georgia Lucas | G39: Delivered | H39: ANZ | I39: 20260212_ANZ 2026 Music Fest Invitations | J39: =IF(SUM(Q39:AV39)=0,"-",SUM(Q39:AV39)) -> 6 | K39: =IF(SUMPRODUCT($Q$5:$AV$5,Q39:AV39)=0,"-",SUMPRODUCT($Q$5:$AV$5,Q39:AV39)) -> 210 | M39: 4900215137 | N39: Submitted to SAP | O39: F2026-0093 | P39: Waiting payment for 01/07/2026 | R39: 6
A40: Bose | B40: UK | D40: 46063 | E40: Bose Posters | F40: Amaka Onyali | G40: Delivered | H40: EMEA | I40: 20260210_Posters | J40: =IF(SUM(Q40:AV40)=0,"-",SUM(Q40:AV40)) -> 9 | K40: 2190 | M40: 4900215137 | N40: Submitted to SAP | O40: F2026-0093 | P40: Waiting payment for 01/07/2026 | Z40: 9
A41: Bose | B41: EMEA | D41: 46066 | E41: Trade Marketing FY27 PPT Template Creation | F41: Daniel Browne | G41: Delivered | H41: EMEA | I41: https://saranistudio.sharepoint.com/:f:/s/SaraniAssets/IgD5DkLWGuMURp0okCP_Q6HUAWT2gQPlhVGzbC5VVJ4-RGg?e=jtfQVM | J41: =IF(SUM(Q41:AV41)=0,"-",SUM(Q41:AV41)) -> 8 | K41: =IF(SUMPRODUCT($Q$5:$AV$5,Q41:AV41)=0,"-",SUMPRODUCT($Q$5:$AV$5,Q41:AV41)) -> 240 | M41: 4900215137 | N41: Submitted to SAP | O41: F2026-0093 | P41: Waiting payment for 01/07/2026 | AF41: 8
A42: Bose | B42: GCD | C42: Media World Italy | D42: 46069 | E42: MW Italy - Banners Headphones / Earbuds 1st Generation | F42: Regina Melo | G42: Delivered | H42: EMEA | I42: 20260216_MW Italy - Banners Headphones Earbuds 1st Generation | J42: =IF(SUM(Q42:AV42)=0,"-",SUM(Q42:AV42)) -> 12 | K42: =IF(SUMPRODUCT($Q$5:$AV$5,Q42:AV42)=0,"-",SUMPRODUCT($Q$5:$AV$5,Q42:AV42)) -> 420 | M42: 4900215137 | N42: Submitted to SAP | O42: F2026-0093 | P42: Waiting payment for 01/07/2026 | R42: 12
A43: Bose | B43: UK | D43: 46070 | E43: Bose UK - Music Fest Badges | F43: Amaka Onyali | G43: Delivered | H43: EMEA | I43: 20260217_Bose UK - Music Fest Badges | J43: =IF(SUM(Q43:AV43)=0,"-",SUM(Q43:AV43)) -> 10 | K43: 1040 | M43: 4900215137 | N43: Submitted to SAP | O43: F2026-0093 | P43: Waiting payment for 01/07/2026 | Z43: 10
A44: Bose | B44: UK | C44: Costco | D44: 46070 | E44: Bose - Costco UK New Product Listing | F44: Amaka Onyali | G44: Delivered | H44: EMEA | I44: 20260217_Costco UK New Product Listing | J44: =IF(SUM(Q44:AV44)=0,"-",SUM(Q44:AV44)) -> 4 | K44: =IF(SUMPRODUCT($Q$5:$AV$5,Q44:AV44)=0,"-",SUMPRODUCT($Q$5:$AV$5,Q44:AV44)) -> 240 | M44: 4900215137 | N44: Submitted to SAP | O44: F2026-0093 | P44: Waiting payment for 01/07/2026 | Q44: 1 | R44: 3
A45: Bose | B45: FR | C45: Boulanger | D45: 46071 | E45: Bose Days 2026 creatives request - extra | F45: Mehdi Youssfi | G45: Delivered | H45: EMEA | I45: https://saranistudio.sharepoint.com/:f:/s/SaraniAssets/IgC8iAKR9jn3TqYpn5MhEeD9ARod6u8jdzrIyfbp0HrCfeI?e=ZTjrT7 | J45: =IF(SUM(Q45:AV45)=0,"-",SUM(Q45:AV45)) -> 3 | K45: =IF(SUMPRODUCT($Q$5:$AV$5,Q45:AV45)=0,"-",SUMPRODUCT($Q$5:$AV$5,Q45:AV45)) -> 105 | M45: 4900215137 | N45: Submitted to SAP | O45: F2026-0093 | P45: Waiting payment for 01/07/2026 | R45: 3
A46: Bose | B46: GCD | C46: Komplett | D46: 46071 | E46: Bose - Norway - Komplett Banners | F46: Regina Melo | G46: Delivered | H46: EMEA | I46: https://saranistudio.sharepoint.com/:f:/s/SaraniAssets/IgCImbSX_BjUSIaC8wupzi44AZ3jnlXn9djeX-IfjtIXgqk?e=Gs3koh | J46: 4 | K46: =IF(SUMPRODUCT($Q$5:$AV$5,Q46:AV46)=0,"-",SUMPRODUCT($Q$5:$AV$5,Q46:AV46)) -> 140 | M46: 4900215137 | N46: Submitted to SAP | O46: F2026-0093 | P46: Waiting payment for 01/07/2026 | R46: 4
A47: Bose | B47: EMEA | D47: 46073 | E47: Trade Marketing FY27 PPT Template - Dan Browne | F47: Daniel Browne | G47: Delivered | H47: EMEA | I47: https://saranistudio.sharepoint.com/:f:/s/SaraniAssets/IgD5DkLWGuMURp0okCP_Q6HUAWT2gQPlhVGzbC5VVJ4-RGg?e=jtfQVM | J47: =IF(SUM(Q47:AV47)=0,"-",SUM(Q47:AV47)) -> 36 | K47: =IF(SUMPRODUCT($Q$5:$AV$5,Q47:AV47)=0,"-",SUMPRODUCT($Q$5:$AV$5,Q47:AV47)) -> 1080 | M47: 4900215137 | N47: Submitted to SAP | O47: F2026-0093 | P47: Waiting payment for 01/07/2026 | AF47: 36
A48: Bose | B48: FR | C48: FNAC | D48: 46077 | E48: Fnac ITH execution rendering request | F48: Mehdi Youssfi | G48: Delivered | H48: EMEA | I48: 20260224_Fnac ITH execution rendering request | J48: =IF(SUM(Q48:AV48)=0,"-",SUM(Q48:AV48)) -> 2 | K48: =IF(SUMPRODUCT($Q$5:$AV$5,Q48:AV48)=0,"-",SUMPRODUCT($Q$5:$AV$5,Q48:AV48)) -> 170 | M48: 4900215137 | N48: Submitted to SAP | O48: F2026-0093 | P48: Waiting payment for 01/07/2026 | Q48: 1 | R48: 1
A49: Bose | B49: EMEA | D49: 46079 | E49: Trade Marketing FY27 PPT Template - Nesrine | F49: Nesrine Khawaja | G49: Delivered | H49: EMEA | I49: https://saranistudio.sharepoint.com/:f:/s/SaraniAssets/IgD5DkLWGuMURp0okCP_Q6HUAWT2gQPlhVGzbC5VVJ4-RGg?e=jtfQVM | J49: =IF(SUM(Q49:AV49)=0,"-",SUM(Q49:AV49)) -> 48 | K49: =IF(SUMPRODUCT($Q$5:$AV$5,Q49:AV49)=0,"-",SUMPRODUCT($Q$5:$AV$5,Q49:AV49)) -> 1440 | M49: 4900215137 | N49: Submitted to SAP | O49: F2026-0093 | P49: Waiting payment for 01/07/2026 | AF49: 48
A50: Bose | B50: ANZ | D50: 46083 | E50: URGENT Bose Brief / JPN ITH Catalogue | F50: Georgia Lucas | G50: Delivered | H50: ANZ | I50: https://saranistudio.sharepoint.com/:f:/s/SaraniAssets/IgDbft-lBXSCSZm_h3GO7oI9AZ0iDdUUfK7mBnfUH4CrtlU?e=C5ghni | J50: =IF(SUM(Q50:AV50)=0,"-",SUM(Q50:AV50)) -> 6 | K50: =IF(SUMPRODUCT($Q$5:$AV$5,Q50:AV50)=0,"-",SUMPRODUCT($Q$5:$AV$5,Q50:AV50)) -> 1560 | AB50: 6
A51: Bose | B51: GCD | C51: Elkjop | D51: 46083 | E51: Elkjop - Package KV (additonal banners) | F51: Regina Melo | G51: Delivered | H51: EMEA | I51: 20260202_Elkjop - Package KV | J51: =IF(SUM(Q51:AV51)=0,"-",SUM(Q51:AV51)) -> 4 | K51: =IF(SUMPRODUCT($Q$5:$AV$5,Q51:AV51)=0,"-",SUMPRODUCT($Q$5:$AV$5,Q51:AV51)) -> 140 | M51: 4900215137 | N51: Submitted to SAP | O51: F2026-0093 | P51: Waiting payment for 01/07/2026 | R51: 4
A52: Bose | B52: GCD | C52: Media Expert | D52: 46083 | E52: Media Expert - KV | F52: Regina Melo | G52: Delivered | H52: EMEA | I52: 20260302_Media Expert - KV | J52: =IF(SUM(Q52:AV52)=0,"-",SUM(Q52:AV52)) -> 2 | K52: =IF(SUMPRODUCT($Q$5:$AV$5,Q52:AV52)=0,"-",SUMPRODUCT($Q$5:$AV$5,Q52:AV52)) -> 70 | M52: 4900215137 | N52: Submitted to SAP | O52: F2026-0093 | P52: Waiting payment for 01/07/2026 | R52: 2
A53: Bose | B53: FR | D53: 46084 | E53: Bose - exclusive Lifestyle content | F53: Mehdi Daile | G53: Delivered | H53: EMEA | I53: 20260303_Bose exclusive Lifestyle content | J53: =IF(SUM(Q53:AV53)=0,"-",SUM(Q53:AV53)) -> 16 | K53: =IF(SUMPRODUCT($Q$5:$AV$5,Q53:AV53)=0,"-",SUMPRODUCT($Q$5:$AV$5,Q53:AV53)) -> 660 | Q53: 1 | R53: 15
A54: Bose | B54: FR | C54: Boulanger | D54: 46084 | E54: New creative request for Boulanger : March promo | F54: Mehdi Daile | G54: Delivered | H54: EMEA | I54: 20260303_New creative request for Boulanger March promo | J54: =IF(SUM(Q54:AV54)=0,"-",SUM(Q54:AV54)) -> 54 | K54: =IF(SUMPRODUCT($Q$5:$AV$5,Q54:AV54)=0,"-",SUMPRODUCT($Q$5:$AV$5,Q54:AV54)) -> 1990 | Q54: 1 | R54: 53
A55: Bose | B55: EMEA | D55: 46086 | E55: Bose - Pop-up creative direction Porsche Tennis Grand Prix | F55: Daniel Browne | G55: Delivered | H55: EMEA | I55: https://saranistudio.sharepoint.com/:f:/s/SaraniAssets/IgCRJy13_QfHRrQfEqKp4k6TAa3Lz5Qn-qRTmyNnAgt87Xs?e=Uc2A8z | J55: =IF(SUM(Q55:AV55)=0,"-",SUM(Q55:AV55)) -> 6 | K55: =IF(SUMPRODUCT($Q$5:$AV$5,Q55:AV55)=0,"-",SUMPRODUCT($Q$5:$AV$5,Q55:AV55)) -> 635 | Q55: 3 | Y55: 1 | Z55: 2
A56: Bose | B56: EMEA | D56: 46086 | E56: Demo Boxes - ITH | F56: Regina Melo | G56: Delivered | H56: EMEA | I56: 20260305_Demo Boxes - ITH | J56: =IF(SUM(Q56:AV56)=0,"-",SUM(Q56:AV56)) -> 6 | K56: =IF(SUMPRODUCT($Q$5:$AV$5,Q56:AV56)=0,"-",SUMPRODUCT($Q$5:$AV$5,Q56:AV56)) -> 240 | Z56: 6
A57: Bose | B57: Germany | C57: Media Markt | D57: 46091 | E57: Bose - MMS DE SBA Video Campaign Opportunity | F57: Daniel Browne | G57: Delivered | H57: EMEA | I57: https://saranistudio.sharepoint.com/:f:/s/SaraniAssets/IgBErnfiOTreS5UBTsybpbbUAdRzraTszh-VCuMpzE8BJfI?e=T5851J | J57: =IF(SUM(Q57:AV57)=0,"-",SUM(Q57:AV57)) -> 3 | K57: =IF(SUMPRODUCT($Q$5:$AV$5,Q57:AV57)=0,"-",SUMPRODUCT($Q$5:$AV$5,Q57:AV57)) -> 240 | AK57: 3
A58: Bose | B58: FR | C58: Boulanger | D58: 46094 | E58: Music Fest PPT | F58: Mehdi Daile | G58: Delivered | H58: EMEA | I58: 20260313_Music Fest PPT | J58: =IF(SUM(Q58:AV58)=0,"-",SUM(Q58:AV58)) -> 21 | K58: =IF(SUMPRODUCT($Q$5:$AV$5,Q58:AV58)=0,"-",SUMPRODUCT($Q$5:$AV$5,Q58:AV58)) -> 630 | AF58: 21
A59: Bose | B59: UK | D59: 46097 | E59: Music Fest Paris Badges & Lanyards | F59: Amaka Onyali | G59: Delivered | H59: EMEA | I59: 20260217_Bose UK - Music Fest Badges | J59: 1 | K59: 590
A60: Bose | B60: FR | D60: 46097 | E60: Contremarques Bose Fnac - Darty | F60: Mehdi Daile | G60: In Progress | H60: EMEA | I60: 20260316_Contremarques Bose Fnac - Darty | J60: =IF(SUM(Q60:AV60)=0,"-",SUM(Q60:AV60)) -> 6 | K60: =IF(SUMPRODUCT($Q$5:$AV$5,Q60:AV60)=0,"-",SUMPRODUCT($Q$5:$AV$5,Q60:AV60)) -> 460 | Y60: 2 | Z60: 4
A61: Bose | B61: FR | D61: 46098 | E61: Request for formatting / FD Exhibition files | F61: Ophélie Juchet | G61: In Progress | H61: EMEA | I61: 20260317_Request for formatting - FD Exhibition files | J61: 8 | K61: =IF(SUMPRODUCT($Q$5:$AV$5,Q61:AV61)=0,"-",SUMPRODUCT($Q$5:$AV$5,Q61:AV61)) -> 280 | R61: 8
A62: Bose | B62: UK | C62: Costco | D62: 46100 | E62: Costco Stickers | F62: Amaka Onyali | G62: Delivered | H62: EMEA | I62: https://saranistudio.sharepoint.com/:f:/s/SaraniAssets/IgDHQ_QBHnGARIKoHr-_2gKaAakG52KuZ-nNk-_DACJYe1s?e=LRzRIt | J62: =IF(SUM(Q62:AV62)=0,"-",SUM(Q62:AV62)) -> 1 | K62: =IF(SUMPRODUCT($Q$5:$AV$5,Q62:AV62)=0,"-",SUMPRODUCT($Q$5:$AV$5,Q62:AV62)) -> 135 | Q62: 1
A63: Bose | B63: FR | C63: Boulanger | D63: 46115 | E63: Boulanger Banners - Jours ++ | F63: Mehdi Daile | G63: In Progress | H63: EMEA | I63: https://saranistudio.sharepoint.com/:f:/s/SaraniAssets/IgCk2ogcu7RxSbB-tGRvULCtARWyS0jXz14QhwZZwa-VwX8?e=ea1AeZ | J63: =IF(SUM(Q63:AV63)=0,"-",SUM(Q63:AV63)) -> 36 | K63: =IF(SUMPRODUCT($Q$5:$AV$5,Q63:AV63)=0,"-",SUMPRODUCT($Q$5:$AV$5,Q63:AV63)) -> 1360 | Q63: 1 | R63: 35
A64: Bose | B64: FR | C64: Boulanger | D64: 46105 | E64: Boulanger Banners - French Days | F64: Mehdi Daile | G64: In Progress | H64: EMEA | I64: https://saranistudio.sharepoint.com/:f:/s/SaraniAssets/IgDwsVdDIxMwRrf3enFo4gaKAfNoBqm1bxo6uW-KHrKNi5s?e=YvdQ9x | J64: =IF(SUM(Q64:AV64)=0,"-",SUM(Q64:AV64)) -> 36 | K64: =IF(SUMPRODUCT($Q$5:$AV$5,Q64:AV64)=0,"-",SUMPRODUCT($Q$5:$AV$5,Q64:AV64)) -> 1360 | Q64: 1 | R64: 35
A65: Bose | B65: FR | C65: Boulanger | D65: 46105 | E65: Boulanger Banners - Les Beaux Jours | F65: Mehdi Daile | G65: In Progress | H65: EMEA | I65: https://saranistudio.sharepoint.com/:f:/s/SaraniAssets/IgD81GAjsqVWQY9oF_sStFphAQiKJIKmWH9uYDoKiXBP1AM?e=RBO3RS | J65: =IF(SUM(Q65:AV65)=0,"-",SUM(Q65:AV65)) -> 28 | K65: =IF(SUMPRODUCT($Q$5:$AV$5,Q65:AV65)=0,"-",SUMPRODUCT($Q$5:$AV$5,Q65:AV65)) -> 1080 | Q65: 1 | R65: 27
A66: Bose | B66: EMEA | D66: 46106 | E66: Slide - Thank you | F66: Regina Melo | G66: In Progress | H66: EMEA | I66: 20260325_Bose - Slide - Thank you | J66: =IF(SUM(Q66:AV66)=0,"-",SUM(Q66:AV66)) -> 1 | K66: =IF(SUMPRODUCT($Q$5:$AV$5,Q66:AV66)=0,"-",SUMPRODUCT($Q$5:$AV$5,Q66:AV66)) -> 30 | AF66: 1
A67: Bose | B67: UK | C67: Currys | D67: 46106 | E67: Bose Brand Page Project for Currys - Reseller ITH brand store | F67: Julieta Altamirano | G67: In Progress | H67: EMEA | I67: 20260325_Bose Brand Page Project for Currys - Reseller ITH brand store | J67: =IF(SUM(Q67:AV67)=0,"-",SUM(Q67:AV67)) -> 6 | K67: =IF(SUMPRODUCT($Q$5:$AV$5,Q67:AV67)=0,"-",SUMPRODUCT($Q$5:$AV$5,Q67:AV67)) -> 1800 | AG67: 6
J68: =IF(SUM(Q68:AV68)=0,"-",SUM(Q68:AV68)) -> - | K68: =IF(SUMPRODUCT($Q$5:$AV$5,Q68:AV68)=0,"-",SUMPRODUCT($Q$5:$AV$5,Q68:AV68)) -> -
J69: =IF(SUM(Q69:AV69)=0,"-",SUM(Q69:AV69)) -> - | K69: =IF(SUMPRODUCT($Q$5:$AV$5,Q69:AV69)=0,"-",SUMPRODUCT($Q$5:$AV$5,Q69:AV69)) -> -
