Workbook

Sheet Overview
A1: Performance Dashboard — Lamarck
A3: REVENUS (€) | B3: 2025 | F3: 2026
B4: Q1 | C4: Q2 | D4: Q3 | E4: Q4 | F4: Q1 | G4: Q2 | H4: Q3 | I4: Q4
A5: Lamarck | B5: =SUMIFS(Lamarck!K:K,Lamarck!D:D,">="&DATE(2025,1,1),Lamarck!D:D,"<="&DATE(2025,3,31)) -> 0 | C5: =SUMIFS(Lamarck!K:K,Lamarck!D:D,">="&DATE(2025,4,1),Lamarck!D:D,"<="&DATE(2025,6,30)) -> 0 | D5: =SUMIFS(Lamarck!K:K,Lamarck!D:D,">="&DATE(2025,7,1),Lamarck!D:D,"<="&DATE(2025,9,30)) -> 0 | E5: =SUMIFS(Lamarck!K:K,Lamarck!D:D,">="&DATE(2025,10,1),Lamarck!D:D,"<="&DATE(2025,12,31)) -> 4730 | F5: =SUMIFS(Lamarck!K:K,Lamarck!D:D,">="&DATE(2026,1,1),Lamarck!D:D,"<="&DATE(2026,3,31)) -> 18595 | G5: =SUMIFS(Lamarck!K:K,Lamarck!D:D,">="&DATE(2026,4,1),Lamarck!D:D,"<="&DATE(2026,6,30)) -> 0 | H5: =SUMIFS(Lamarck!K:K,Lamarck!D:D,">="&DATE(2026,7,1),Lamarck!D:D,"<="&DATE(2026,9,30)) -> 0 | I5: =SUMIFS(Lamarck!K:K,Lamarck!D:D,">="&DATE(2026,10,1),Lamarck!D:D,"<="&DATE(2026,12,31)) -> 0
A6: TOTAL | B6: =SUM(B5:B5) -> 0 | C6: =SUM(C5:C5) -> 0 | D6: =SUM(D5:D5) -> 0 | E6: =SUM(E5:E5) -> 4730 | F6: =SUM(F5:F5) -> 18595 | G6: =SUM(G5:G5) -> 0 | H6: =SUM(H5:H5) -> 0 | I6: =SUM(I5:I5) -> 0
A8: NOMBRE DE PROJETS | B8: 2025 | F8: 2026
B9: Q1 | C9: Q2 | D9: Q3 | E9: Q4 | F9: Q1 | G9: Q2 | H9: Q3 | I9: Q4
A10: Lamarck | B10: =COUNTIFS(Lamarck!D:D,">="&DATE(2025,1,1),Lamarck!D:D,"<="&DATE(2025,3,31)) -> 0 | C10: =COUNTIFS(Lamarck!D:D,">="&DATE(2025,4,1),Lamarck!D:D,"<="&DATE(2025,6,30)) -> 0 | D10: =COUNTIFS(Lamarck!D:D,">="&DATE(2025,7,1),Lamarck!D:D,"<="&DATE(2025,9,30)) -> 0 | E10: =COUNTIFS(Lamarck!D:D,">="&DATE(2025,10,1),Lamarck!D:D,"<="&DATE(2025,12,31)) -> 4 | F10: =COUNTIFS(Lamarck!D:D,">="&DATE(2026,1,1),Lamarck!D:D,"<="&DATE(2026,3,31)) -> 10 | G10: =COUNTIFS(Lamarck!D:D,">="&DATE(2026,4,1),Lamarck!D:D,"<="&DATE(2026,6,30)) -> 0 | H10: =COUNTIFS(Lamarck!D:D,">="&DATE(2026,7,1),Lamarck!D:D,"<="&DATE(2026,9,30)) -> 0 | I10: =COUNTIFS(Lamarck!D:D,">="&DATE(2026,10,1),Lamarck!D:D,"<="&DATE(2026,12,31)) -> 0
A11: TOTAL | B11: =SUM(B10:B10) -> 0 | C11: =SUM(C10:C10) -> 0 | D11: =SUM(D10:D10) -> 0 | E11: =SUM(E10:E10) -> 4 | F11: =SUM(F10:F10) -> 10 | G11: =SUM(G10:G10) -> 0 | H11: =SUM(H10:H10) -> 0 | I11: =SUM(I10:I10) -> 0
A13: SYNTHÈSE ANNUELLE | B13: 2025 | C13: 2026
A14: Revenus (€) | B14: =SUM(B6:E6) -> 4730 | C14: =SUM(F6:I6) -> 18595
A15: Projets | B15: =SUM(B11:E11) -> 4 | C15: =SUM(F11:I11) -> 10
A16: Rev. / Projet (€) | B16: =IFERROR(B14/B15,"—") -> 1182.5 | C16: =IFERROR(C14/C15,"—") -> 1859.5

Sheet TikTok SMB - Content
A1: Price File
A2: Project | E2: Details
A3: Customer | B3: Division | C3: Date | D3: Type of content | E3: Time spent for first upload (minutes) | F3: Time spent on adjustments (minutes) | G3: Description | H3: Assets | I3: Total Time (hours) | J3: Last update | K3: PO | L3: Total
A4: ByteDance | B4: TikTok | C4: - | D4: Case Study (text, images, seo, etc) | E4: 40 | F4: 5 | G4: 10 (Altair, Biolla, Reciclos, Thank you Lab, Elverys, Legend, Mous, Handshake, Party World, Penguin) | H4: 10 | I4: =(E4+F4)*H4/60 -> 7.5 | J4: 18/07/2023
A5: ByteDance | B5: TikTok | C5: - | D5: Blog (text, images, seo, etc) | E5: 40 | F5: 10 | G5: 2 (Newbies) | H5: 2 | I5: =(E5+F5)*H5/60 -> 1.6666667 | J5: 18/07/2023
A6: ByteDance | B6: TikTok | C6: - | D6: Translation (text, images, seo, etc) | E6: 30 | F6: 0 | G6: 32 = 4 blogs x 8 languages (1 pending) | H6: 32 | I6: =(E6+F6)*H6/60 -> 16 | J6: 18/07/2023
A7: ByteDance | B7: TikTok | C7: - | D7: Splash (+ url creation and integration) / language | E7: 20 | F7: 0 | G7: 32 = 4 x 8 languages (1 pending) | H7: 32 | I7: =(E7+F7)*H7/60 -> 10.666667 | J7: 18/07/2023
H8: =IF(SUM(M8:M8)=0,"-",SUM(M8:M8)) -> -
H9: =IF(SUM(M9:M9)=0,"-",SUM(M9:M9)) -> -
H10: =IF(SUM(M10:M10)=0,"-",SUM(M10:M10)) -> -
H11: =IF(SUM(M11:M11)=0,"-",SUM(M11:M11)) -> -
H12: =IF(SUM(M12:M12)=0,"-",SUM(M12:M12)) -> -
H13: =IF(SUM(M13:M13)=0,"-",SUM(M13:M13)) -> -
H14: =IF(SUM(M14:M14)=0,"-",SUM(M14:M14)) -> -
H15: =IF(SUM(M15:M15)=0,"-",SUM(M15:M15)) -> -
H16: =IF(SUM(M16:M16)=0,"-",SUM(M16:M16)) -> -
H17: =IF(SUM(M17:M17)=0,"-",SUM(M17:M17)) -> -
H18: =IF(SUM(M18:M18)=0,"-",SUM(M18:M18)) -> -
H19: =IF(SUM(M19:M19)=0,"-",SUM(M19:M19)) -> -
... H36: =IF(SUM(M36:M36)=0,"-",SUM(M36:M36)) -> -

Sheet Lamarck
K1: =SUBTOTAL(2,K11:K19978) -> 11 | R1: =SUBTOTAL(2,R11:R19978) -> 3 | S1: =SUBTOTAL(2,S11:S19978) -> 2 | T1: =SUBTOTAL(2,T11:T19978) -> 4 | U1: =SUBTOTAL(2,U11:U19978) -> 2 | V1: =SUBTOTAL(2,V11:V19978) -> 0 | W1: =SUBTOTAL(2,W11:W19978) -> 0 | X1: =SUBTOTAL(2,X11:X19978) -> 0 | Y1: =SUBTOTAL(2,Y11:Y19978) -> 0 | ... BC1: =SUBTOTAL(2,BC11:BC19978) -> 0
J2: =SUBTOTAL(9,J11:J19979) -> 249 | K2: =SUBTOTAL(9,K11:K19979) -> 17010 | R2: =SUBTOTAL(9,R11:R19979)*R5 -> 2430 | S2: =SUBTOTAL(9,S11:S19979)*S5 -> 1320 | T2: =SUBTOTAL(9,T11:T19979)*T5 -> 9550 | U2: =SUBTOTAL(9,U11:U19979)*U5 -> 3360 | V2: =SUBTOTAL(9,V11:V19979)*V5 -> 0 | W2: =SUBTOTAL(9,W11:W19979)*W5 -> 0 | X2: =SUBTOTAL(9,X11:X19979)*X5 -> 0 | Y2: =SUBTOTAL(9,Y11:Y19979)*Y5 -> 0 | ... BC2: =SUBTOTAL(9,BC11:BC19979)*BC5 -> 0
A3: Price File | Y3: Online | AG3: Offline | AN3: Presentations | AO3: Web | AS3: Videos | AZ3: Virtualization | BB3: Copy
A4: Project | G4: mylene.pellet@lamarck.fr | R4: Page catalogue (design) | S4: Encodage (par projet) | T4: Montage (par page) | U4: Version adhérents (par version) | V4: Emailing (template) | W4: Emailing (par adhérent) | X4: Banner creation (animated) | Y4: Banner creation (static) | Z4: Banner adaptation (static) | AA4: Banner creation (animated) | AB4: Banner adaptation (animated) | AC4: Buttons | AD4: Logo | AE4: Lifestyle Picture | AF4: Wallpapers | AG4: Offline creation (standard) | AH4: Offline creation (adaptation) | AI4: Leaflet (1 page) | AJ4: Leaflet (2 pages) | AK4: Roll-up / Wall creation | AL4: Chart | AM4: Brochure (20 pages) | AN4: Slide | AO4: Landing page (design only) | AP4: Landing page (complete) | AQ4: Website (design only) | AR4: Website (complete) | AS4: Video Edition | AT4: Video Subtitles / Adaptations | AU4: Social Media Video (up to 30s) | AV4: Social Media Video (up to 1 min) | AW4: Promotional Video (up to 1 min) | AX4: 2D Video (up to 3mn) | AY4: 3D Video (up to 3min) | AZ4: Virtual space | BA4: Virtual showroom | BB4: Translation (per word) | BC4: Transcription (per word)
A5: Customer | B5: Region | C5: Client | D5: Date | F5: Project | G5: Contact | H5: Status | I5: Link | J5: Assets | K5: Total Value | L5: Project total | M5: Quote | N5: PO | O5: Invoice | P5: n° Invoice | Q5: Statut | R5: 90 | S5: 660 | T5: 50 | U5: 120 | V5: 600 | W5: 35 | X5: 220 | Y5: 135 | Z5: 35 | AA5: 220 | AB5: 50 | AC5: 15 | AD5: 250 | AE5: 400 | AF5: 85 | AG5: 150 | AH5: 40 | AI5: 180 | AJ5: 260 | AK5: 180 | AL5: 400 | AM5: 2200 | AN5: 30 | AO5: 300 | AP5: 700 | AQ5: 5000 | AR5: 7000 | AS5: 80 | AT5: 150 | AU5: 360 | AV5: 460 | AW5: 900 | AX5: 1500 | AY5: 3000 | AZ5: 2500 | BA5: 10000 | BB5: 0.12 | BC5: 0.25
A6: Lamarck | B6: France | C6: ROM | D6: 46001 | E6: Italie | F6: Viva Italia - Maquette | G6: Mylène Pellet | H6: Delivered | I6: https://saranistudio.sharepoint.com/:f:/r/sites/SaraniAssets/Shared%20Documents/03.%20Customers/21.Lamarck/20251208%20Catalogue%20Italie?csf=1&web=1&e=1mhtMZ | J6: =IF(SUM(R6:BD6)=0,"-",SUM(R6:BD6)) -> 10 | K6: =IF(SUMPRODUCT($R$5:$BD$5,R6:BD6)=0,"-",SUMPRODUCT($R$5:$BD$5,R6:BD6)) -> 900 | M6: - | N6: - | O6: Sent | P6: F2025-0816 | Q6: Paid 02/01/2026 | R6: 10
A7: Lamarck | B7: France | C7: ROM | D7: 46027 | E7: Italie | F7: 88 pages - Restauration italienne Montage + Encodage | G7: Mylène Pellet | H7: Delivered | I7: https://saranistudio.sharepoint.com/:f:/s/SaraniAssets/IgDb_8Yn6xANRZRPk0epcd-LARAJv9xEQPQqp38tt4PiGZA?e=ADeeO8 | J7: =IF(SUM(R7:BD7)=0,"-",SUM(R7:BD7)) -> 89 | K7: =IF(SUMPRODUCT($R$5:$BD$5,R7:BD7)=0,"-",SUMPRODUCT($R$5:$BD$5,R7:BD7)) -> 5060 | S7: 1 | T7: 88
A8: Lamarck | B8: France | C8: ROM | D8: 46038 | E8: Italie | F8: Catalogue adhérents ITALIE | G8: Mylène Pellet | H8: In Progress | J8: =IF(SUM(R8:BD8)=0,"-",SUM(R8:BD8)) -> 16 | K8: =IF(SUMPRODUCT($R$5:$BD$5,R8:BD8)=0,"-",SUMPRODUCT($R$5:$BD$5,R8:BD8)) -> 1920 | U8: 16
A9: Lamarck | B9: France | C9: ROM | D9: 46084 | E9: Italie | F9: Intégration 196 QR codes | G9: Mylène Pellet | H9: In Progress | J9: 1 | K9: 115
E10: Italie | L10: =SUM(K6:K9) -> 7995
A11: Lamarck | B11: France | C11: ROM | D11: 46009 | E11: PN Mars Avril | F11: 20 pages - Catalogue Promo Nomade- Montage | G11: Mylène Pellet | H11: Delivered | I11: https://saranistudio.sharepoint.com/:f:/s/SaraniAssets/IgAIC_LmDqVJSLrQjN5zu6YZASMgJqX8kZQ9zbzd_RobigY?e=telrOp | J11: =IF(SUM(R11:BD11)=0,"-",SUM(R11:BD11)) -> 20 | K11: =IF(SUMPRODUCT($R$5:$BD$5,R11:BD11)=0,"-",SUMPRODUCT($R$5:$BD$5,R11:BD11)) -> 1000 | M11: - | N11: - | O11: Sent by email to Mylène | P11: F2026-0114 | Q11: Waiting payment for 15/05/2026 | T11: 20
A12: Lamarck | B12: France | C12: ROM | D12: 46048 | E12: PN Mars Avril | F12: Catalogue Promo Nomade- Déroulage Adhérent | G12: Mylène Pellet | H12: Delivered | I12: https://saranistudio.sharepoint.com/:f:/s/SaraniAssets/IgAIC_LmDqVJSLrQjN5zu6YZASMgJqX8kZQ9zbzd_RobigY?e=MiqLly | J12: =IF(SUM(R12:BD12)=0,"-",SUM(R12:BD12)) -> 14 | K12: =IF(SUMPRODUCT($R$5:$BD$5,R12:BD12)=0,"-",SUMPRODUCT($R$5:$BD$5,R12:BD12)) -> 1680 | M12: - | N12: - | O12: Sent by email to Mylène | P12: F2026-0114 | Q12: Waiting payment for 15/05/2026 | U12: 14
A13: Lamarck | B13: France | C13: ROM | D13: 46071 | E13: PN Mars Avril | F13: Encodage du Promo Nomade | G13: Mylène Pellet | H13: Delivered | I13: https://saranistudio.sharepoint.com/:f:/s/SaraniAssets/IgAIC_LmDqVJSLrQjN5zu6YZASMgJqX8kZQ9zbzd_RobigY?e=MiqLly | J13: =IF(SUM(R13:BD13)=0,"-",SUM(R13:BD13)) -> 1 | K13: =IF(SUMPRODUCT($R$5:$BD$5,R13:BD13)=0,"-",SUMPRODUCT($R$5:$BD$5,R13:BD13)) -> 660 | M13: - | N13: - | O13: Sent by email to Mylène | P13: F2026-0114 | Q13: Waiting payment for 15/05/2026 | S13: 1
E14: PN Mars Avril | L14: =SUM(K11:K13) -> 3340
A15: Lamarck | B15: France | C15: ROM | D15: 46048 | E15: RCA | F15: 120 pages - Catalogue A VOS CARTES Montage + Encodage | G15: Mylène Pellet | H15: In Progress | I15: https://saranistudio.sharepoint.com/:f:/s/SaraniAssets/IgCf0BgHWhSMQr2AjpXHM1NpAZly4017ZIhb6bHTmLG4foM?e=qjjVHB | J15: =IF(SUM(R15:BD15)=0,"-",SUM(R15:BD15)) -> 129 | K15: =IF(SUMPRODUCT($R$5:$BD$5,R15:BD15)=0,"-",SUMPRODUCT($R$5:$BD$5,R15:BD15)) -> 7060 | S15: 1 | T15: 128
A16: Lamarck | B16: France | C16: ROM | D16: 46040 | E16: RCA | F16: Catalogue A VOS CARTES Maquette | G16: Mylène Pellet | H16: Delivered | I16: https://saranistudio.sharepoint.com/:f:/s/SaraniAssets/IgCdd4pVvmBrRp4Yz0cT5KJjASRpo4MX9gzK-inYjBEt30s?e=mnuotC | J16: =IF(SUM(R16:BD16)=0,"-",SUM(R16:BD16)) -> 9 | K16: =IF(SUMPRODUCT($R$5:$BD$5,R16:BD16)=0,"-",SUMPRODUCT($R$5:$BD$5,R16:BD16)) -> 810 | M16: - | N16: - | O16: Sent by email to Mylène | P16: F2026-0098 | Q16: Waiting payment 04/04/2026 | R16: 9
E17: RCA | L17: =SUM(K15:K16) -> 7870
A18: Lamarck | B18: France | C18: ROM | D18: 46071 | E18: PN Mai | F18: Catalogue Promo Nomade - Mai | G18: Mylène Pellet | H18: In Progress | I18: https://saranistudio.sharepoint.com/:f:/s/SaraniAssets/IgAzD4s8SINmRouDWm3otpVhAaMNxOBOEaOs_oJjdJQ911s?e=UxVah1 | J18: =IF(SUM(R18:BD18)=0,"-",SUM(R18:BD18)) -> 8 | K18: =IF(SUMPRODUCT($R$5:$BD$5,R18:BD18)=0,"-",SUMPRODUCT($R$5:$BD$5,R18:BD18)) -> 400 | T18: 8
D19: estimation | E19: PN Mai | F19: Catalogue Promo Nomade - Mai | G19: Mylène Pellet | H19: In Progress | I19: https://saranistudio.sharepoint.com/:f:/s/SaraniAssets/IgAzD4s8SINmRouDWm3otpVhAaMNxOBOEaOs_oJjdJQ911s?e=UxVah1 | J19: =IF(SUM(R19:BD19)=0,"-",SUM(R19:BD19)) -> 14 | K19: =IF(SUMPRODUCT($R$5:$BD$5,R19:BD19)=0,"-",SUMPRODUCT($R$5:$BD$5,R19:BD19)) -> 1680 | U19: 14
E20: PN Mai | L20: =SUM(K18:K19) -> 2080
A21: Lamarck | B21: France | C21: ROM | D21: 46009 | E21: Street Life | F21: Pages Concepts - Catalogue Nomade | G21: Mylène Pellet | H21: Delivered | I21: https://saranistudio.sharepoint.com/:f:/s/SaraniAssets/IgCtBflts9yhRK6Qj76BgEO5Ac75dpXaVCUH8iA0iShODQs?e=P62Phn | J21: =IF(SUM(R21:BD21)=0,"-",SUM(R21:BD21)) -> 12 | K21: =IF(SUMPRODUCT($R$5:$BD$5,R21:BD21)=0,"-",SUMPRODUCT($R$5:$BD$5,R21:BD21)) -> 1080 | M21: - | N21: - | O21: Sent | P21: F2025-0817 | Q21: Paid 02/01/2026 | R21: 12
A22: Lamarck | B22: France | C22: ROM | D22: 46009 | E22: Street Life | F22: 15 Pages - Catalogue Guide Nomade Easyfood dessert | G22: Mylène Pellet | H22: Delivered | I22: https://saranistudio.sharepoint.com/:f:/s/SaraniAssets/IgBjSsnS9k_QRKtqboh8bEJ6AbDnRAMSo5VY6LAOGIwlMyA?e=5TEzFk | J22: =IF(SUM(R22:BD22)=0,"-",SUM(R22:BD22)) -> 35 | K22: =IF(SUMPRODUCT($R$5:$BD$5,R22:BD22)=0,"-",SUMPRODUCT($R$5:$BD$5,R22:BD22)) -> 1750 | M22: - | N22: - | O22: Sent by email to Mylène | P22: F2026-0069 | Q22: Waiting payment 17/03/2026 | T22: 35
A23: Lamarck | B23: France | C23: ROM | D23: 46058 | E23: Street Life | F23: Pages Concepts - Catalogue Nomade pages supp | G23: Mylène Pellet | H23: Delivered | I23: https://saranistudio.sharepoint.com/:f:/s/SaraniAssets/IgCtBflts9yhRK6Qj76BgEO5Ac75dpXaVCUH8iA0iShODQs?e=P62Phn | J23: =IF(SUM(R23:BD23)=0,"-",SUM(R23:BD23)) -> 6 | K23: =IF(SUMPRODUCT($R$5:$BD$5,R23:BD23)=0,"-",SUMPRODUCT($R$5:$BD$5,R23:BD23)) -> 540 | M23: - | N23: - | O23: Sent by email to Mylène | P23: F2026-0071 | Q23: Waiting payment 17/03/2026 | R23: 6
A24: Lamarck | B24: France | C24: ROM | D24: 46076 | E24: Street Life | F24: Design Emailing | G24: Mylène Pellet | H24: Delivered | I24: https://saranistudio.sharepoint.com/:f:/s/SaraniAssets/IgB_PXUVnbGiToGk2cqsVNPXAUwhCxjFtIfvXS94TrtQjCQ?e=0kdfBy | J24: 1 | K24: 350 | M24: - | N24: - | O24: Sent by email to Mylène | P24: F2026-0100 | Q24: Waiting payment 04/04/2026
E25: Street Life | L25: =SUM(K21:K24) -> 3720
