Workbook

Sheet Overview
A1: Performance Dashboard — CMC Markets
A3: REVENUS (€) | B3: 2022 | F3: 2023 | J3: 2024 | N3: 2025 | R3: 2026
B4: Q1 | C4: Q2 | D4: Q3 | E4: Q4 | F4: Q1 | G4: Q2 | H4: Q3 | I4: Q4 | J4: Q1 | K4: Q2 | L4: Q3 | M4: Q4 | N4: Q1 | O4: Q2 | P4: Q3 | Q4: Q4 | R4: Q1 | S4: Q2 | T4: Q3 | U4: Q4
A5: CMC Markets | B5: =SUMIFS('CMC Markets'!$I$4:$I$10000,'CMC Markets'!$B$4:$B$10000,">="&DATE(2022,1,1),'CMC Markets'!$B$4:$B$10000,"<="&DATE(2022,3,31)) -> 0 | C5: =SUMIFS('CMC Markets'!$I$4:$I$10000,'CMC Markets'!$B$4:$B$10000,">="&DATE(2022,4,1),'CMC Markets'!$B$4:$B$10000,"<="&DATE(2022,6,30)) -> 0 | D5: =SUMIFS('CMC Markets'!$I$4:$I$10000,'CMC Markets'!$B$4:$B$10000,">="&DATE(2022,7,1),'CMC Markets'!$B$4:$B$10000,"<="&DATE(2022,9,30)) -> 0 | E5: =SUMIFS('CMC Markets'!$I$4:$I$10000,'CMC Markets'!$B$4:$B$10000,">="&DATE(2022,10,1),'CMC Markets'!$B$4:$B$10000,"<="&DATE(2022,12,31)) -> 0 | F5: =SUMIFS('CMC Markets'!$I$4:$I$10000,'CMC Markets'!$B$4:$B$10000,">="&DATE(2023,1,1),'CMC Markets'!$B$4:$B$10000,"<="&DATE(2023,3,31)) -> 0 | G5: =SUMIFS('CMC Markets'!$I$4:$I$10000,'CMC Markets'!$B$4:$B$10000,">="&DATE(2023,4,1),'CMC Markets'!$B$4:$B$10000,"<="&DATE(2023,6,30)) -> 0 | H5: =SUMIFS('CMC Markets'!$I$4:$I$10000,'CMC Markets'!$B$4:$B$10000,">="&DATE(2023,7,1),'CMC Markets'!$B$4:$B$10000,"<="&DATE(2023,9,30)) -> 0 | I5: =SUMIFS('CMC Markets'!$I$4:$I$10000,'CMC Markets'!$B$4:$B$10000,">="&DATE(2023,10,1),'CMC Markets'!$B$4:$B$10000,"<="&DATE(2023,12,31)) -> 0 | J5: =SUMIFS('CMC Markets'!$I$4:$I$10000,'CMC Markets'!$B$4:$B$10000,">="&DATE(2024,1,1),'CMC Markets'!$B$4:$B$10000,"<="&DATE(2024,3,31)) -> 0 | K5: =SUMIFS('CMC Markets'!$I$4:$I$10000,'CMC Markets'!$B$4:$B$10000,">="&DATE(2024,4,1),'CMC Markets'!$B$4:$B$10000,"<="&DATE(2024,6,30)) -> 0 | L5: =SUMIFS('CMC Markets'!$I$4:$I$10000,'CMC Markets'!$B$4:$B$10000,">="&DATE(2024,7,1),'CMC Markets'!$B$4:$B$10000,"<="&DATE(2024,9,30)) -> 0 | M5: =SUMIFS('CMC Markets'!$I$4:$I$10000,'CMC Markets'!$B$4:$B$10000,">="&DATE(2024,10,1),'CMC Markets'!$B$4:$B$10000,"<="&DATE(2024,12,31)) -> 0 | N5: =SUMIFS('CMC Markets'!$I$4:$I$10000,'CMC Markets'!$B$4:$B$10000,">="&DATE(2025,1,1),'CMC Markets'!$B$4:$B$10000,"<="&DATE(2025,3,31)) -> 0 | O5: =SUMIFS('CMC Markets'!$I$4:$I$10000,'CMC Markets'!$B$4:$B$10000,">="&DATE(2025,4,1),'CMC Markets'!$B$4:$B$10000,"<="&DATE(2025,6,30)) -> 0 | P5: =SUMIFS('CMC Markets'!$I$4:$I$10000,'CMC Markets'!$B$4:$B$10000,">="&DATE(2025,7,1),'CMC Markets'!$B$4:$B$10000,"<="&DATE(2025,9,30)) -> 900 | Q5: =SUMIFS('CMC Markets'!$I$4:$I$10000,'CMC Markets'!$B$4:$B$10000,">="&DATE(2025,10,1),'CMC Markets'!$B$4:$B$10000,"<="&DATE(2025,12,31)) -> 5140 | R5: =SUMIFS('CMC Markets'!$I$4:$I$10000,'CMC Markets'!$B$4:$B$10000,">="&DATE(2026,1,1),'CMC Markets'!$B$4:$B$10000,"<="&DATE(2026,3,31)) -> 580 | S5: =SUMIFS('CMC Markets'!$I$4:$I$10000,'CMC Markets'!$B$4:$B$10000,">="&DATE(2026,4,1),'CMC Markets'!$B$4:$B$10000,"<="&DATE(2026,6,30)) -> 0 | T5: =SUMIFS('CMC Markets'!$I$4:$I$10000,'CMC Markets'!$B$4:$B$10000,">="&DATE(2026,7,1),'CMC Markets'!$B$4:$B$10000,"<="&DATE(2026,9,30)) -> 0 | U5: =SUMIFS('CMC Markets'!$I$4:$I$10000,'CMC Markets'!$B$4:$B$10000,">="&DATE(2026,10,1),'CMC Markets'!$B$4:$B$10000,"<="&DATE(2026,12,31)) -> 0
A6: TOTAL | B6: =SUM(B5:B5) -> 0 | C6: =SUM(C5:C5) -> 0 | D6: =SUM(D5:D5) -> 0 | E6: =SUM(E5:E5) -> 0 | F6: =SUM(F5:F5) -> 0 | G6: =SUM(G5:G5) -> 0 | H6: =SUM(H5:H5) -> 0 | I6: =SUM(I5:I5) -> 0 | ... U6: =SUM(U5:U5) -> 0
A8: NOMBRE DE PROJETS | B8: 2022 | F8: 2023 | J8: 2024 | N8: 2025 | R8: 2026
B9: Q1 | C9: Q2 | D9: Q3 | E9: Q4 | F9: Q1 | G9: Q2 | H9: Q3 | I9: Q4 | J9: Q1 | K9: Q2 | L9: Q3 | M9: Q4 | N9: Q1 | O9: Q2 | P9: Q3 | Q9: Q4 | R9: Q1 | S9: Q2 | T9: Q3 | U9: Q4
A10: Feuil1 | B10: =COUNTIFS('CMC Markets'!$B$4:$B$10000,">="&DATE(2022,1,1),'CMC Markets'!$B$4:$B$10000,"<="&DATE(2022,3,31)) -> 0 | C10: =COUNTIFS('CMC Markets'!$B$4:$B$10000,">="&DATE(2022,4,1),'CMC Markets'!$B$4:$B$10000,"<="&DATE(2022,6,30)) -> 0 | D10: =COUNTIFS('CMC Markets'!$B$4:$B$10000,">="&DATE(2022,7,1),'CMC Markets'!$B$4:$B$10000,"<="&DATE(2022,9,30)) -> 0 | E10: =COUNTIFS('CMC Markets'!$B$4:$B$10000,">="&DATE(2022,10,1),'CMC Markets'!$B$4:$B$10000,"<="&DATE(2022,12,31)) -> 0 | F10: =COUNTIFS('CMC Markets'!$B$4:$B$10000,">="&DATE(2023,1,1),'CMC Markets'!$B$4:$B$10000,"<="&DATE(2023,3,31)) -> 0 | G10: =COUNTIFS('CMC Markets'!$B$4:$B$10000,">="&DATE(2023,4,1),'CMC Markets'!$B$4:$B$10000,"<="&DATE(2023,6,30)) -> 0 | H10: =COUNTIFS('CMC Markets'!$B$4:$B$10000,">="&DATE(2023,7,1),'CMC Markets'!$B$4:$B$10000,"<="&DATE(2023,9,30)) -> 0 | I10: =COUNTIFS('CMC Markets'!$B$4:$B$10000,">="&DATE(2023,10,1),'CMC Markets'!$B$4:$B$10000,"<="&DATE(2023,12,31)) -> 0 | J10: =COUNTIFS('CMC Markets'!$B$4:$B$10000,">="&DATE(2024,1,1),'CMC Markets'!$B$4:$B$10000,"<="&DATE(2024,3,31)) -> 0 | K10: =COUNTIFS('CMC Markets'!$B$4:$B$10000,">="&DATE(2024,4,1),'CMC Markets'!$B$4:$B$10000,"<="&DATE(2024,6,30)) -> 0 | L10: =COUNTIFS('CMC Markets'!$B$4:$B$10000,">="&DATE(2024,7,1),'CMC Markets'!$B$4:$B$10000,"<="&DATE(2024,9,30)) -> 0 | M10: =COUNTIFS('CMC Markets'!$B$4:$B$10000,">="&DATE(2024,10,1),'CMC Markets'!$B$4:$B$10000,"<="&DATE(2024,12,31)) -> 0 | N10: =COUNTIFS('CMC Markets'!$B$4:$B$10000,">="&DATE(2025,1,1),'CMC Markets'!$B$4:$B$10000,"<="&DATE(2025,3,31)) -> 0 | O10: =COUNTIFS('CMC Markets'!$B$4:$B$10000,">="&DATE(2025,4,1),'CMC Markets'!$B$4:$B$10000,"<="&DATE(2025,6,30)) -> 0 | P10: =COUNTIFS('CMC Markets'!$B$4:$B$10000,">="&DATE(2025,7,1),'CMC Markets'!$B$4:$B$10000,"<="&DATE(2025,9,30)) -> 1 | Q10: =COUNTIFS('CMC Markets'!$B$4:$B$10000,">="&DATE(2025,10,1),'CMC Markets'!$B$4:$B$10000,"<="&DATE(2025,12,31)) -> 3 | R10: =COUNTIFS('CMC Markets'!$B$4:$B$10000,">="&DATE(2026,1,1),'CMC Markets'!$B$4:$B$10000,"<="&DATE(2026,3,31)) -> 3 | S10: =COUNTIFS('CMC Markets'!$B$4:$B$10000,">="&DATE(2026,4,1),'CMC Markets'!$B$4:$B$10000,"<="&DATE(2026,6,30)) -> 0 | T10: =COUNTIFS('CMC Markets'!$B$4:$B$10000,">="&DATE(2026,7,1),'CMC Markets'!$B$4:$B$10000,"<="&DATE(2026,9,30)) -> 0 | U10: =COUNTIFS('CMC Markets'!$B$4:$B$10000,">="&DATE(2026,10,1),'CMC Markets'!$B$4:$B$10000,"<="&DATE(2026,12,31)) -> 0
A11: TOTAL | B11: =SUM(B10:B10) -> 0 | C11: =SUM(C10:C10) -> 0 | D11: =SUM(D10:D10) -> 0 | E11: =SUM(E10:E10) -> 0 | F11: =SUM(F10:F10) -> 0 | G11: =SUM(G10:G10) -> 0 | H11: =SUM(H10:H10) -> 0 | I11: =SUM(I10:I10) -> 0 | ... U11: =SUM(U10:U10) -> 0
A13: SYNTHÈSE ANNUELLE | B13: 2022 | C13: 2023 | D13: 2024 | E13: 2025 | F13: 2026
A14: Revenus (€) | B14: =SUM(B6:E6) -> 0 | C14: =SUM(F6:I6) -> 0 | D14: =SUM(J6:M6) -> 0 | E14: =SUM(N6:Q6) -> 6040 | F14: =SUM(R6:U6) -> 580
A15: Projets | B15: =SUM(B11:E11) -> 0 | C15: =SUM(F11:I11) -> 0 | D15: =SUM(J11:M11) -> 0 | E15: =SUM(N11:Q11) -> 4 | F15: =SUM(R11:U11) -> 3
A16: Rev. / Projet (€) | B16: =IFERROR(B14/B15,"—") -> — | C16: =IFERROR(C14/C15,"—") -> — | D16: =IFERROR(D14/D15,"—") -> — | E16: =IFERROR(E14/E15,"—") -> 1510 | F16: =IFERROR(F14/F15,"—") -> 193.33333

Sheet CMC Markets
Q1: Video | V1: Online | AD1: Offline | AK1: Presentations | AL1: Web
A2: Customer | B2: Date | C2: Project | D2: Contact | E2: Status | F2: Category | G2: Link | H2: Assets | I2: Total Value | J2: Quote | K2: PO | L2: Invoice | M2: N° invoice | N2: Status inv. | O2: Echéance | P2: Commentaire | Q2: Video Creation (Up to 30 secs) | R2: Video Creation (Up to 30 secs) | S2: Video Version (Up to 30 secs) | T2: Video Adaptation (Up to 30 secs) | U2: Video Animation (per min) | V2: Banner creation (static) | W2: Banner adaptation (static) | X2: Banner creation (animated) | Y2: Banner adaptation (animated) | Z2: Branding pack | AA2: Logo | AB2: Lifestyle Picture | AC2: Wallpapers | AD2: Offline creation (standard) | AE2: Offline creation (adaptation) | AF2: Leaflet (1 page) | AG2: Leaflet (2 pages) | AH2: Roll-up / Wall creation | AI2: Chart | AJ2: Brochure (20 pages) | AK2: Slide | AL2: Landing page (design only) | AM2: Landing page (complete) | AN2: Website (design only) | AO2: Website (complete)
Q3: 900 | R3: 800 | S3: 300 | T3: 80 | U3: 500 | V3: 135 | W3: 30 | X3: 220 | Y3: 50 | Z3: 2000 | AA3: 250 | AB3: 400 | AC3: 85 | AD3: 135 | AE3: 30 | AF3: 180 | AG3: 260 | AH3: 180 | AI3: 400 | AJ3: 2200 | AK3: 40 | AL3: 300 | AM3: 700 | AN3: 5000 | AO3: 7000
A4: CMC Markets | B4: 45950 | C4: Spectre 15 Secs Video | D4: Felix | E4: Delivered | F4: UK | G4: 20251020_CMC Spectre 15 sec Videos | H4: =Q4+R4+S4+T4+U4 -> 1 | I4: =(Q$3*Q4)+(R$3*R4)+(S$3*S4)+(T$3*T4)+(U$3*U4) -> 300 | K4: - | L4: Sent | M4: F2026-0012 | N4: Waiting payment | O4: 46067 | S4: 1
A5: CMC Markets | B5: 45968 | C5: Performance Ads Campaign | D5: A.Catrini@cmcmarkets.com | E5: Delivered | F5: UK | G5: https://saranistudio.sharepoint.com/:f:/s/SaraniAssets/EgndaG9K7UhLsKSyG_JRpD8BjcGM-Ou-doDKO96fc73YOQ?e=6usxdm | H5: =Q5+R5+S5+T5+U5 -> 14 | I5: =(Q$3*Q5)+(R$3*R5)+(S$3*S5)+(T$3*T5)+(U$3*U5) -> 2940 | J5: https://saranistudio.sharepoint.com/:b:/s/SaraniAssets/IQCLl4WYglikR5FTKvVl_xQ-AZCiiCEe5Pl9BioNk9h2abI?e=w1YHoy | K5: - | M5: F2026-0118 | N5: Waiting payment | O5: 46130 | R5: 1 | S5: 5 | T5: 8
A6: CMC Markets | B6: 45929 | C6: Video | D6: Felix | E6: Delivered | F6: UK | G6: CMC Markets | H6: =Q6+R6+S6+T6+U6 -> 1 | I6: =(Q$3*Q6)+(R$3*R6)+(S$3*S6)+(T$3*T6)+(U$3*U6) -> 900 | J6: - | K6: - | L6: Sent via Whatsapp | M6: F2025-0627 | N6: Payée le 04/11/2025 | Q6: 1
A7: CMC Markets | B7: 46003 | C7: Map Video Ads | D7: A.Catrini@cmcmarkets.com | E7: Delivered | F7: UK | G7: https://saranistudio.sharepoint.com/:f:/s/SaraniAssets/IgAchiGm95cqTLZM5iG3JBibAfBbpsw42nQw_zNR6xqxYhE?e=B4a3gw | H7: =Q7+R7+S7+T7+U7 -> 12 | I7: =(Q$3*Q7)+(R$3*R7)+(S$3*S7)+(T$3*T7)+(U$3*U7) -> 1900 | K7: - | M7: F2026-0118 | N7: Waiting payment | O7: 46130 | R7: 1 | S7: 1 | T7: 10
A8: CMC Markets | B8: 46097 | C8: CMC Markets UK Homepage Redesign | D8: Felix | E8: In Progress | G8: https://saranistudio.sharepoint.com/:f:/s/SaraniAssets/IgAG2sbi3pBFSriPxrnwdaVVAZSbgoDXk4mbgChNhsNTEaM?e=IEzQlA | H8: 1 | I8: 500
A9: CMC Markets | B9: 46100 | C9: Norwegian Localisation | D9: Andrea Catrini | E9: In Progress | G9: https://saranistudio.sharepoint.com/:f:/s/SaraniAssets/IgDferjIRvV5TqF9OFXi-KqTAewYbSBnF04HNskKr56BrxQ?e=7FqEU0 | H9: =Q9+R9+S9+T9+U9 -> 1 | I9: =(Q$3*Q9)+(R$3*R9)+(S$3*S9)+(T$3*T9)+(U$3*U9) -> 80 | T9: 1
A10: CMC Markets | B10: 46100 | C10: UGC Video UK | D10: Andrea Catrini | E10: In Progress | I10: =(Q$3*Q10)+(R$3*R10)+(S$3*S10)+(T$3*T10)+(U$3*U10) -> 0
